Workbook
Name Administracion: Listados!$C$2:$C$15
Name Almacen_PC: Listados!#REF!
Name Almacen_PC: Listados!#REF!
Name Almacen_PC: Listados!#REF!
Name Almacen_PC: Listados!#REF!
Name Almacen_PC: Listados!#REF!
Name Almacen_PC: Listados!#REF!
Name Almacen_PC: Listados!#REF!
Name Almacen_PC: Listados!#REF!
Name Almacen_PC: Listados!#REF!
Name Almacen_PC: Listados!#REF!
Name Almacen_PC: Listados!#REF!
Name Almacen_PC: Listados!#REF!
Name Almacen_PC: Listados!#REF!
Name Almacen_PC: Listados!#REF!
Name Almacen_PC: Listados!#REF!
Name Contenedores: Listados!$B$2:$B$15
Name Gasolinera: Listados!$L$2:$L$15
Name Interchange: Listados!$G$2:$G$15
Name Interchange_PC: Listados!$G$2:$G$15
Name Interchange_SL: Listados!$H$2:$H$15
Name Predio_Puerto_Cortes: Listados!$E$2:$E$15
Name Predio_San_Lorenzo: Listados!$F$2:$F$15
Name Servicio_Al_Cliente: Listados!$D$2:$D$15
Name ServicioAlCliente: Listados!$D$2:$D$15
Name Sistemas_Y_Procesos: Listados!$A$2:$A$15
Name SistemasYProcesos: Listados!$A$2:$A$15
Name SLO: Listados!#REF!
Name SLO: Listados!#REF!
Name SLO: Listados!#REF!
Name SLO: Listados!#REF!
Name SLO: Listados!#REF!
Name SLO: Listados!#REF!
Name SLO: Listados!#REF!
Name SLO: Listados!#REF!
Name SLO: Listados!#REF!
Name SLO: Listados!#REF!
Name SLO: Listados!#REF!
Name SLO: Listados!#REF!
Name Taller: Listados!#REF!
Name Taller: Listados!#REF!
Name Taller: Listados!#REF!
Name Taller: Listados!#REF!
Name Taller: Listados!#REF!
Name Taller: Listados!#REF!
Name Taller: Listados!#REF!
Name Taller: Listados!#REF!
Name Taller: Listados!#REF!
Name Taller: Listados!#REF!
Name Taller: Listados!#REF!
Name Taller: Listados!#REF!
Name Taller: Listados!#REF!
Name Taller: Listados!#REF!
Name Taller: Listados!#REF!
Name Taller_PC: Listados!$I$2:$I$15
Name Taller_SL: Listados!$J$2:$J$15
Name Transporte: Listados!$K$2:$K$15

Sheet Contenedores
I1: 0.9
C2: Colaborador: | I2: 80-90%
C3: Departamento: | D3: Contenedores | I3: Menos de 80%
A5: =+Mensual!B5 -> No | B5: =+Mensual!C5 -> Peso | D5: =+Mensual!E5 -> Unidad de medición | E5: =+Mensual!F5 -> Meta | F5: =+Mensual!G5 -> Resultado | G5: =+Mensual!H5 -> Nota | H5: =+Mensual!I5 -> Valor ponderado | I5: =+Mensual!J5 -> 0 | J5: =+Mensual!K5 -> 0.25 | K5: =+Mensual!L5 -> 0.5 | ... Q5: =+Mensual!R5 -> 0 | T5: Nota | U5: Nota
A6: =+Mensual!B6 -> 4 | B6: 0.3 | C6: 1.2 Lograr meta de contenedores | D6: =IF(VLOOKUP($C6,Mensual!$D$6:$G$163,2,0)<0,0,VLOOKUP($C6,Mensual!$D$6:$G$163,2,0)) -> 0 | E6: =IF(VLOOKUP($C6,Mensual!$D$6:$G$163,3,0)<0,0,VLOOKUP($C6,Mensual!$D$6:$G$163,3,0)) -> 15 | F6: =IF(VLOOKUP($C6,Mensual!$D$6:$G$163,4,0)<0,0,VLOOKUP($C6,Mensual!$D$6:$G$163,4,0)) -> 1 | G6: =IF(VLOOKUP($C6,Mensual!$D$6:$H$163,5,0)<0,0,VLOOKUP($C6,Mensual!$D$6:$H$163,5,0)) -> 0.066666667 | H6: =+G6*B6 -> 0.02 | I6: =+Mensual!J6 -> 0 | J6: =+Mensual!K6 -> 0 | K6: =+Mensual!L6 -> 0 | L6: =+Mensual!M6 -> 0
B7: 0.1 | C7: 9. SCORE CARD Grupo EXA | D7: =IF(VLOOKUP($C7,Mensual!$D$6:$G$163,2,0)<0,0,VLOOKUP($C7,Mensual!$D$6:$G$163,2,0)) -> RESULTADO SCORECARD | E7: =IF(VLOOKUP($C7,Mensual!$D$6:$G$163,3,0)<0,0,VLOOKUP($C7,Mensual!$D$6:$G$163,3,0)) -> 1 | F7: =IF(VLOOKUP($C7,Mensual!$D$6:$G$163,4,0)<0,0,VLOOKUP($C7,Mensual!$D$6:$G$163,4,0)) -> 1.0325 | G7: =IF(VLOOKUP($C7,Mensual!$D$6:$H$163,5,0)<0,0,VLOOKUP($C7,Mensual!$D$6:$H$163,5,0)) -> 1.0325 | H7: =+G7*B7 -> 0.10325
B8: 0.05 | C8: 1.6 Alquileres de contenedores secos (solo o en combos CONMOXA) | D8: =IF(VLOOKUP($C8,Mensual!$D$6:$G$163,2,0)<0,0,VLOOKUP($C8,Mensual!$D$6:$G$163,2,0)) -> Porcentaje | E8: =IF(VLOOKUP($C8,Mensual!$D$6:$G$163,3,0)<0,0,VLOOKUP($C8,Mensual!$D$6:$G$163,3,0)) -> 0.2 | F8: =IF(VLOOKUP($C8,Mensual!$D$6:$G$163,4,0)<0,0,VLOOKUP($C8,Mensual!$D$6:$G$163,4,0)) -> 0.45 | G8: =IF(VLOOKUP($C8,Mensual!$D$6:$H$163,5,0)<0,0,VLOOKUP($C8,Mensual!$D$6:$H$163,5,0)) -> 1 | H8: =+G8*B8 -> 0.05
B9: 0.05 | C9: 1.4 Lograr meta de ventas en alquileres de contenedores reefer (solo o en combo) | D9: =IF(VLOOKUP($C9,Mensual!$D$6:$G$163,2,0)<0,0,VLOOKUP($C9,Mensual!$D$6:$G$163,2,0)) -> Dólares | E9: =IF(VLOOKUP($C9,Mensual!$D$6:$G$163,3,0)<0,0,VLOOKUP($C9,Mensual!$D$6:$G$163,3,0)) -> 16000 | F9: =IF(VLOOKUP($C9,Mensual!$D$6:$G$163,4,0)<0,0,VLOOKUP($C9,Mensual!$D$6:$G$163,4,0)) -> 0 | G9: =IF(VLOOKUP($C9,Mensual!$D$6:$H$163,5,0)<0,0,VLOOKUP($C9,Mensual!$D$6:$H$163,5,0)) -> 0 | H9: =+G9*B9 -> 0
B10: 0.05 | C10: 1.3 Lograr meta de ventas contenedores secos y modificados(dolares) | D10: =IF(VLOOKUP($C10,Mensual!$D$6:$G$163,2,0)<0,0,VLOOKUP($C10,Mensual!$D$6:$G$163,2,0)) -> Dólares | E10: =IF(VLOOKUP($C10,Mensual!$D$6:$G$163,3,0)<0,0,VLOOKUP($C10,Mensual!$D$6:$G$163,3,0)) -> 40000 | F10: =IF(VLOOKUP($C10,Mensual!$D$6:$G$163,4,0)<0,0,VLOOKUP($C10,Mensual!$D$6:$G$163,4,0)) -> 1800 | G10: =IF(VLOOKUP($C10,Mensual!$D$6:$H$163,5,0)<0,0,VLOOKUP($C10,Mensual!$D$6:$H$163,5,0)) -> 0.045 | H10: =+G10*B10 -> 0.00225
B11: 0.05 | C11: 2.5 Aumentar Margen neto en venta de contenedores (modificados y secos) | D11: =IF(VLOOKUP($C11,Mensual!$D$6:$G$163,2,0)<0,0,VLOOKUP($C11,Mensual!$D$6:$G$163,2,0)) -> % | E11: =IF(VLOOKUP($C11,Mensual!$D$6:$G$163,3,0)<0,0,VLOOKUP($C11,Mensual!$D$6:$G$163,3,0)) -> 0.1 | F11: =IF(VLOOKUP($C11,Mensual!$D$6:$G$163,4,0)<0,0,VLOOKUP($C11,Mensual!$D$6:$G$163,4,0)) -> 0 | G11: =IF(VLOOKUP($C11,Mensual!$D$6:$H$163,5,0)<0,0,VLOOKUP($C11,Mensual!$D$6:$H$163,5,0)) -> 0 | H11: =+G11*B11 -> 0
B12: 0.05 | C12: 2.6 Aumento en 20% en margen de contribución bruta venta de contenedores | D12: =IF(VLOOKUP($C12,Mensual!$D$6:$G$163,2,0)<0,0,VLOOKUP($C12,Mensual!$D$6:$G$163,2,0)) -> $ | E12: =IF(VLOOKUP($C12,Mensual!$D$6:$G$163,3,0)<0,0,VLOOKUP($C12,Mensual!$D$6:$G$163,3,0)) -> 0.2 | F12: =IF(VLOOKUP($C12,Mensual!$D$6:$G$163,4,0)<0,0,VLOOKUP($C12,Mensual!$D$6:$G$163,4,0)) -> 0 | G12: =IF(VLOOKUP($C12,Mensual!$D$6:$H$163,5,0)<0,0,VLOOKUP($C12,Mensual!$D$6:$H$163,5,0)) -> 0 | H12: =+G12*B12 -> 0
B13: 0.25 | C13: 1.10 Aumentar ventas en articulos Sejue/get504 | D13: =IF(VLOOKUP($C13,Mensual!$D$6:$G$163,2,0)<0,0,VLOOKUP($C13,Mensual!$D$6:$G$163,2,0)) -> Articulos | E13: =IF(VLOOKUP($C13,Mensual!$D$6:$G$163,3,0)<0,0,VLOOKUP($C13,Mensual!$D$6:$G$163,3,0)) -> 10 | F13: =IF(VLOOKUP($C13,Mensual!$D$6:$G$163,4,0)<0,0,VLOOKUP($C13,Mensual!$D$6:$G$163,4,0)) -> 19 | G13: =IF(VLOOKUP($C13,Mensual!$D$6:$H$163,5,0)<0,0,VLOOKUP($C13,Mensual!$D$6:$H$163,5,0)) -> 1 | H13: =+G13*B13 -> 0.25
B14: 0.05 | C14: 2.8 Aumento en 20% en margen de contribución bruta alquiler de reefers. | D14: =IF(VLOOKUP($C14,Mensual!$D$6:$G$163,2,0)<0,0,VLOOKUP($C14,Mensual!$D$6:$G$163,2,0)) -> $ | E14: =IF(VLOOKUP($C14,Mensual!$D$6:$G$163,3,0)<0,0,VLOOKUP($C14,Mensual!$D$6:$G$163,3,0)) -> 0.2 | F14: =IF(VLOOKUP($C14,Mensual!$D$6:$G$163,4,0)<0,0,VLOOKUP($C14,Mensual!$D$6:$G$163,4,0)) -> 0 | G14: =IF(VLOOKUP($C14,Mensual!$D$6:$H$163,5,0)<0,0,VLOOKUP($C14,Mensual!$D$6:$H$163,5,0)) -> 0 | H14: =+G14*B14 -> 0
B15: 0.05 | C15: 2.7 Aumento en 20% en margen de contribución bruta alquiler de bodegas | D15: =IF(VLOOKUP($C15,Mensual!$D$6:$G$163,2,0)<0,0,VLOOKUP($C15,Mensual!$D$6:$G$163,2,0)) -> $ | E15: =IF(VLOOKUP($C15,Mensual!$D$6:$G$163,3,0)<0,0,VLOOKUP($C15,Mensual!$D$6:$G$163,3,0)) -> 0.2 | F15: =IF(VLOOKUP($C15,Mensual!$D$6:$G$163,4,0)<0,0,VLOOKUP($C15,Mensual!$D$6:$G$163,4,0)) -> 0 | G15: =IF(VLOOKUP($C15,Mensual!$D$6:$H$163,5,0)<0,0,VLOOKUP($C15,Mensual!$D$6:$H$163,5,0)) -> 0 | H15: =+G15*B15 -> 0
B16: =SUM(B6:B15) -> 1 | H16: =SUM(H6:H15) -> 0.4255

Sheet Nancy Garcia b (4)
I1: 0.9
C2: Departamento: | D2: Administracion | I2: 80-90%
C3: Colaborador: | D3: Nancy Garcia | I3: Menos de 80%
A5: =+Mensual!B5 -> No | B5: =+Mensual!C5 -> Peso | D5: =+Mensual!E5 -> Unidad de medición | E5: =+Mensual!F5 -> Meta | F5: =+Mensual!G5 -> Resultado | G5: =+Mensual!H5 -> Nota | H5: =+Mensual!I5 -> Valor ponderado | I5: =+Mensual!J5 -> 0 | J5: =+Mensual!K5 -> 0.25 | K5: =+Mensual!L5 -> 0.5 | ... Q5: =+Mensual!R5 -> 0 | T5: Nota | U5: Nota
A6: =+Mensual!B6 -> 4 | B6: 0.38 | C6: 9. SCORE CARD Grupo EXA | D6: =IF(VLOOKUP($C6,Mensual!$D$6:$G$163,2,0)<0,0,VLOOKUP($C6,Mensual!$D$6:$G$163,2,0)) -> RESULTADO SCORECARD | E6: =IF(VLOOKUP($C6,Mensual!$D$6:$G$163,3,0)<0,0,VLOOKUP($C6,Mensual!$D$6:$G$163,3,0)) -> 1 | F6: =IF(VLOOKUP($C6,Mensual!$D$6:$G$163,4,0)<0,0,VLOOKUP($C6,Mensual!$D$6:$G$163,4,0)) -> 1.0325 | G6: =IF(VLOOKUP($C6,Mensual!$D$6:$H$163,5,0)<0,0,VLOOKUP($C6,Mensual!$D$6:$H$163,5,0)) -> 1.0325 | H6: =+G6*B6 -> 0.39235 | I6: =+Mensual!J6 -> 0 | J6: =+Mensual!K6 -> 0 | K6: =+Mensual!L6 -> 0 | L6: =+Mensual!M6 -> 0
B7: 0.03 | C7: 4. Aumentar clima laboral | D7: =IF(VLOOKUP($C7,Mensual!$D$6:$G$163,2,0)<0,0,VLOOKUP($C7,Mensual!$D$6:$G$163,2,0)) -> 0 | E7: =IF(VLOOKUP($C7,Mensual!$D$6:$G$163,3,0)<0,0,VLOOKUP($C7,Mensual!$D$6:$G$163,3,0)) -> 0.1 | F7: =IF(VLOOKUP($C7,Mensual!$D$6:$G$163,4,0)<0,0,VLOOKUP($C7,Mensual!$D$6:$G$163,4,0)) -> 0.1 | G7: =IF(VLOOKUP($C7,Mensual!$D$6:$H$163,5,0)<0,0,VLOOKUP($C7,Mensual!$D$6:$H$163,5,0)) -> 1 | H7: =+G7*B7 -> 0.03
B8: 0.03 | C8: 2.1 Reducir gasto administrativo x% | D8: =IF(VLOOKUP($C8,Mensual!$D$6:$G$163,2,0)<0,0,VLOOKUP($C8,Mensual!$D$6:$G$163,2,0)) -> % | E8: =IF(VLOOKUP($C8,Mensual!$D$6:$G$163,3,0)<0,0,VLOOKUP($C8,Mensual!$D$6:$G$163,3,0)) -> 0.1 | F8: =IF(VLOOKUP($C8,Mensual!$D$6:$G$163,4,0)<0,0,VLOOKUP($C8,Mensual!$D$6:$G$163,4,0)) -> 0.32 | G8: =IF(VLOOKUP($C8,Mensual!$D$6:$H$163,5,0)<0,0,VLOOKUP($C8,Mensual!$D$6:$H$163,5,0)) -> 1 | H8: =+G8*B8 -> 0.03
B9: 0.03 | C9: 3.5 Multas ambientales y fiscales. | D9: =IF(VLOOKUP($C9,Mensual!$D$6:$G$163,2,0)<0,0,VLOOKUP($C9,Mensual!$D$6:$G$163,2,0)) -> 0 | E9: =IF(VLOOKUP($C9,Mensual!$D$6:$G$163,3,0)<0,0,VLOOKUP($C9,Mensual!$D$6:$G$163,3,0)) -> 0 | F9: =IF(VLOOKUP($C9,Mensual!$D$6:$G$163,4,0)<0,0,VLOOKUP($C9,Mensual!$D$6:$G$163,4,0)) -> 0 | G9: =IF(VLOOKUP($C9,Mensual!$D$6:$H$163,5,0)<0,0,VLOOKUP($C9,Mensual!$D$6:$H$163,5,0)) -> 1 | H9: =+G9*B9 -> 0.03
B10: 0.03 | C10: 6.1 Aumentar Rotación de inventario. | D10: =IF(VLOOKUP($C10,Mensual!$D$6:$G$163,2,0)<0,0,VLOOKUP($C10,Mensual!$D$6:$G$163,2,0)) -> 0 | E10: =IF(VLOOKUP($C10,Mensual!$D$6:$G$163,3,0)<0,0,VLOOKUP($C10,Mensual!$D$6:$G$163,3,0)) -> 0.05 | F10: =IF(VLOOKUP($C10,Mensual!$D$6:$G$163,4,0)<0,0,VLOOKUP($C10,Mensual!$D$6:$G$163,4,0)) -> 0 | G10: =IF(VLOOKUP($C10,Mensual!$D$6:$H$163,5,0)<0,0,VLOOKUP($C10,Mensual!$D$6:$H$163,5,0)) -> 0 | H10: =+G10*B10 -> 0
B11: 0.03 | C11: 7.1 Rotación de cuentas por cobrar. | D11: =IF(VLOOKUP($C11,Mensual!$D$6:$G$163,2,0)<0,0,VLOOKUP($C11,Mensual!$D$6:$G$163,2,0)) -> 0 | E11: =IF(VLOOKUP($C11,Mensual!$D$6:$G$163,3,0)<0,0,VLOOKUP($C11,Mensual!$D$6:$G$163,3,0)) -> 0.1 | F11: =IF(VLOOKUP($C11,Mensual!$D$6:$G$163,4,0)<0,0,VLOOKUP($C11,Mensual!$D$6:$G$163,4,0)) -> 0 | G11: =IF(VLOOKUP($C11,Mensual!$D$6:$H$163,5,0)<0,0,VLOOKUP($C11,Mensual!$D$6:$H$163,5,0)) -> 0 | H11: =+G11*B11 -> 0
B12: 0.03 | C12: 7.2 95% de clientes activos dentro del periodo de recuperacion | D12: =IF(VLOOKUP($C12,Mensual!$D$6:$G$163,2,0)<0,0,VLOOKUP($C12,Mensual!$D$6:$G$163,2,0)) -> 0 | E12: =IF(VLOOKUP($C12,Mensual!$D$6:$G$163,3,0)<0,0,VLOOKUP($C12,Mensual!$D$6:$G$163,3,0)) -> 0.2 | F12: =IF(VLOOKUP($C12,Mensual!$D$6:$G$163,4,0)<0,0,VLOOKUP($C12,Mensual!$D$6:$G$163,4,0)) -> 0 | G12: =IF(VLOOKUP($C12,Mensual!$D$6:$H$163,5,0)<0,0,VLOOKUP($C12,Mensual!$D$6:$H$163,5,0)) -> 0 | H12: =+G12*B12 -> 0
B13: 0.03 | C13: 2.3 Reducir Costo por km cabezales propios. | D13: =IF(VLOOKUP($C13,Mensual!$D$6:$G$163,2,0)<0,0,VLOOKUP($C13,Mensual!$D$6:$G$163,2,0)) -> $ | E13: =IF(VLOOKUP($C13,Mensual!$D$6:$G$163,3,0)<0,0,VLOOKUP($C13,Mensual!$D$6:$G$163,3,0)) -> 0.05 | F13: =IF(VLOOKUP($C13,Mensual!$D$6:$G$163,4,0)<0,0,VLOOKUP($C13,Mensual!$D$6:$G$163,4,0)) -> 0.6 | G13: =IF(VLOOKUP($C13,Mensual!$D$6:$H$163,5,0)<0,0,VLOOKUP($C13,Mensual!$D$6:$H$163,5,0)) -> 1 | H13: =+G13*B13 -> 0.03
B14: 0.03 | C14: 5.2 Productividad cabezales Flota Nueva | D14: =IF(VLOOKUP($C14,Mensual!$D$6:$G$163,2,0)<0,0,VLOOKUP($C14,Mensual!$D$6:$G$163,2,0)) -> 0 | E14: =IF(VLOOKUP($C14,Mensual!$D$6:$G$163,3,0)<0,0,VLOOKUP($C14,Mensual!$D$6:$G$163,3,0)) -> 4500 | F14: =IF(VLOOKUP($C14,Mensual!$D$6:$G$163,4,0)<0,0,VLOOKUP($C14,Mensual!$D$6:$G$163,4,0)) -> 4782 | G14: =IF(VLOOKUP($C14,Mensual!$D$6:$H$163,5,0)<0,0,VLOOKUP($C14,Mensual!$D$6:$H$163,5,0)) -> 1 | H14: =+G14*B14 -> 0.03
B15: 0.03 | C15: 6.2 Disminuir a 5% el desuso de los chasis (equipos con mas de 30 dias en las yardas) | D15: =IF(VLOOKUP($C15,Mensual!$D$6:$G$163,2,0)<0,0,VLOOKUP($C15,Mensual!$D$6:$G$163,2,0)) -> % | E15: =IF(VLOOKUP($C15,Mensual!$D$6:$G$163,3,0)<0,0,VLOOKUP($C15,Mensual!$D$6:$G$163,3,0)) -> 0.05 | F15: =IF(VLOOKUP($C15,Mensual!$D$6:$G$163,4,0)<0,0,VLOOKUP($C15,Mensual!$D$6:$G$163,4,0)) -> 0.05 | G15: =IF(VLOOKUP($C15,Mensual!$D$6:$H$163,5,0)<0,0,VLOOKUP($C15,Mensual!$D$6:$H$163,5,0)) -> 1 | H15: =+G15*B15 -> 0.03
B16: 0.03 | C16: 6.5 Disminuir a 0-1 el desuso de cabezales propios | D16: =IF(VLOOKUP($C16,Mensual!$D$6:$G$163,2,0)<0,0,VLOOKUP($C16,Mensual!$D$6:$G$163,2,0)) -> cabezal | E16: =IF(VLOOKUP($C16,Mensual!$D$6:$G$163,3,0)<0,0,VLOOKUP($C16,Mensual!$D$6:$G$163,3,0)) -> 1 | F16: =IF(VLOOKUP($C16,Mensual!$D$6:$G$163,4,0)<0,0,VLOOKUP($C16,Mensual!$D$6:$G$163,4,0)) -> 1 | G16: =IF(VLOOKUP($C16,Mensual!$D$6:$H$163,5,0)<0,0,VLOOKUP($C16,Mensual!$D$6:$H$163,5,0)) -> 0 | H16: =+G16*B16 -> 0
B17: 0.08 | C17: 7. Disminuir el D/E | D17: =IF(VLOOKUP($C17,Mensual!$D$6:$G$163,2,0)<0,0,VLOOKUP($C17,Mensual!$D$6:$G$163,2,0)) -> 0 | E17: =IF(VLOOKUP($C17,Mensual!$D$6:$G$163,3,0)<0,0,VLOOKUP($C17,Mensual!$D$6:$G$163,3,0)) -> 0.05 | F17: =IF(VLOOKUP($C17,Mensual!$D$6:$G$163,4,0)<0,0,VLOOKUP($C17,Mensual!$D$6:$G$163,4,0)) -> 0.05 | G17: =IF(VLOOKUP($C17,Mensual!$D$6:$H$163,5,0)<0,0,VLOOKUP($C17,Mensual!$D$6:$H$163,5,0)) -> 1 | H17: =+G17*B17 -> 0.08
B18: 0.08 | C18: 6. Aumentar el ROA | D18: =IF(VLOOKUP($C18,Mensual!$D$6:$G$163,2,0)<0,0,VLOOKUP($C18,Mensual!$D$6:$G$163,2,0)) -> 0 | E18: =IF(VLOOKUP($C18,Mensual!$D$6:$G$163,3,0)<0,0,VLOOKUP($C18,Mensual!$D$6:$G$163,3,0)) -> 0.05 | F18: =IF(VLOOKUP($C18,Mensual!$D$6:$G$163,4,0)<0,0,VLOOKUP($C18,Mensual!$D$6:$G$163,4,0)) -> 1 | G18: =IF(VLOOKUP($C18,Mensual!$D$6:$H$163,5,0)<0,0,VLOOKUP($C18,Mensual!$D$6:$H$163,5,0)) -> 1 | H18: =+G18*B18 -> 0.08
... B21: 0.03 | C21: 2.3 Reducir Costo por km cabezales propios. | D21: =IF(VLOOKUP($C21,Mensual!$D$6:$G$163,2,0)<0,0,VLOOKUP($C21,Mensual!$D$6:$G$163,2,0)) -> $ | E21: =IF(VLOOKUP($C21,Mensual!$D$6:$G$163,3,0)<0,0,VLOOKUP($C21,Mensual!$D$6:$G$163,3,0)) -> 0.05 | F21: =IF(VLOOKUP($C21,Mensual!$D$6:$G$163,4,0)<0,0,VLOOKUP($C21,Mensual!$D$6:$G$163,4,0)) -> 0.6 | G21: =IF(VLOOKUP($C21,Mensual!$D$6:$H$163,5,0)<0,0,VLOOKUP($C21,Mensual!$D$6:$H$163,5,0)) -> 1 | H21: =+G21*B21 -> 0.03
B22: =SUM(B6:B21) -> 1 | H22: =SUM(H6:H21) -> 0.89235

Sheet David Molina
I1: 0.9
C2: Colaborador: | D2: David Molina | I2: 80-90%
C3: Departamento: | D3: SistemasYProcesos | I3: Menos de 80%
A5: =+Mensual!B5 -> No | B5: =+Mensual!C5 -> Peso | D5: =+Mensual!E5 -> Unidad de medición | E5: =+Mensual!F5 -> Meta | F5: =+Mensual!G5 -> Resultado | G5: =+Mensual!H5 -> Nota | H5: =+Mensual!I5 -> Valor ponderado | I5: =+Mensual!J5 -> 0 | J5: =+Mensual!K5 -> 0.25 | K5: =+Mensual!L5 -> 0.5 | ... Q5: =+Mensual!R5 -> 0 | T5: Nota | U5: Nota
A6: =+Mensual!B6 -> 4 | B6: 0.55 | C6: 9. SCORE CARD Grupo EXA | D6: =IF(VLOOKUP($C6,Mensual!$D$6:$G$163,2,0)<0,0,VLOOKUP($C6,Mensual!$D$6:$G$163,2,0)) -> RESULTADO SCORECARD | E6: =IF(VLOOKUP($C6,Mensual!$D$6:$G$163,3,0)<0,0,VLOOKUP($C6,Mensual!$D$6:$G$163,3,0)) -> 1 | F6: =IF(VLOOKUP($C6,Mensual!$D$6:$G$163,4,0)<0,0,VLOOKUP($C6,Mensual!$D$6:$G$163,4,0)) -> 1.0325 | G6: =IF(VLOOKUP($C6,Mensual!$D$6:$H$163,5,0)<0,0,VLOOKUP($C6,Mensual!$D$6:$H$163,5,0)) -> 1.0325 | H6: =+G6*B6 -> 0.567875 | I6: =+Mensual!J6 -> 0 | J6: =+Mensual!K6 -> 0 | K6: =+Mensual!L6 -> 0 | L6: =+Mensual!M6 -> 0
B7: 0.05 | C7: 3. Cero incidentes mayores de seguridad y sostenibilidad | D7: =IF(VLOOKUP($C7,Mensual!$D$6:$G$163,2,0)<0,0,VLOOKUP($C7,Mensual!$D$6:$G$163,2,0)) -> 0 | E7: =IF(VLOOKUP($C7,Mensual!$D$6:$G$163,3,0)<0,0,VLOOKUP($C7,Mensual!$D$6:$G$163,3,0)) -> 1 | F7: =IF(VLOOKUP($C7,Mensual!$D$6:$G$163,4,0)<0,0,VLOOKUP($C7,Mensual!$D$6:$G$163,4,0)) -> 1 | G7: =IF(VLOOKUP($C7,Mensual!$D$6:$H$163,5,0)<0,0,VLOOKUP($C7,Mensual!$D$6:$H$163,5,0)) -> 1 | H7: =+G7*B7 -> 0.05
B8: 0.25 | C8: 8. Innovaciones estratégicas de sistemas de Impacto recurrente | D8: =IF(VLOOKUP($C8,Mensual!$D$6:$G$163,2,0)<0,0,VLOOKUP($C8,Mensual!$D$6:$G$163,2,0)) -> 0 | E8: =IF(VLOOKUP($C8,Mensual!$D$6:$G$163,3,0)<0,0,VLOOKUP($C8,Mensual!$D$6:$G$163,3,0)) -> 1 | F8: =IF(VLOOKUP($C8,Mensual!$D$6:$G$163,4,0)<0,0,VLOOKUP($C8,Mensual!$D$6:$G$163,4,0)) -> 1 | G8: =IF(VLOOKUP($C8,Mensual!$D$6:$H$163,5,0)<0,0,VLOOKUP($C8,Mensual!$D$6:$H$163,5,0)) -> 1 | H8: =+G8*B8 -> 0.25
B9: 0.05 | C9: 5.6 Aprovechamiento GPS | D9: =IF(VLOOKUP($C9,Mensual!$D$6:$G$163,2,0)<0,0,VLOOKUP($C9,Mensual!$D$6:$G$163,2,0)) -> 0 | E9: =IF(VLOOKUP($C9,Mensual!$D$6:$G$163,3,0)<0,0,VLOOKUP($C9,Mensual!$D$6:$G$163,3,0)) -> 0.9 | F9: =IF(VLOOKUP($C9,Mensual!$D$6:$G$163,4,0)<0,0,VLOOKUP($C9,Mensual!$D$6:$G$163,4,0)) -> 0.82 | G9: =IF(VLOOKUP($C9,Mensual!$D$6:$H$163,5,0)<0,0,VLOOKUP($C9,Mensual!$D$6:$H$163,5,0)) -> 0.91111111 | H9: =+G9*B9 -> 0.045555556
B10: 0.1 | C10: 5. Productividad | D10: =IF(VLOOKUP($C10,Mensual!$D$6:$G$163,2,0)<0,0,VLOOKUP($C10,Mensual!$D$6:$G$163,2,0)) -> 0 | E10: =IF(VLOOKUP($C10,Mensual!$D$6:$G$163,3,0)<0,0,VLOOKUP($C10,Mensual!$D$6:$G$163,3,0)) -> 3700 | F10: =IF(VLOOKUP($C10,Mensual!$D$6:$G$163,4,0)<0,0,VLOOKUP($C10,Mensual!$D$6:$G$163,4,0)) -> 3932 | G10: =IF(VLOOKUP($C10,Mensual!$D$6:$H$163,5,0)<0,0,VLOOKUP($C10,Mensual!$D$6:$H$163,5,0)) -> 1 | H10: =+G10*B10 -> 0.1
B11: =SUM(B6:B10) -> 1 | H11: =SUM(H6:H10) -> 1.0134306
B14: Resultados
B15: =+B5 -> Peso | C15: =+C5 -> 0 | D15: =+D5 -> Unidad de medición | E15: =+E5 -> Meta | F15: ENERO | G15: febrero | H15: marzo | I15: abril | J15: mayo | K15: junio | L15: julio | M15: agosto | N15: septiembre | O15: octubre | P15: noviembre | Q15: diciembre
B16: =+B6 -> 0.55 | C16: =+C6 -> 9. SCORE CARD Grupo EXA | D16: =+D6 -> RESULTADO SCORECARD | E16: =+E6 -> 1 | F16: =+F6 -> 1.0325
B17: =+B7 -> 0.05 | C17: =+C7 -> 3. Cero incidentes mayores de seguridad y sostenibilidad | D17: =+D7 -> 0 | E17: =+E7 -> 1 | F17: =+F7 -> 1
B18: =+B8 -> 0.25 | C18: =+C8 -> 8. Innovaciones estratégicas de sistemas de Impacto recurrente | D18: =+D8 -> 0 | E18: =+E8 -> 1 | F18: =+F8 -> 1
B19: =+B9 -> 0.05 | C19: =+C9 -> 5.6 Aprovechamiento GPS | D19: =+D9 -> 0 | E19: =+E9 -> 0.9 | F19: =+F9 -> 0.82
B20: =+B10 -> 0.1 | C20: =+C10 -> 5. Productividad | D20: =+D10 -> 0 | E20: =+E10 -> 3700 | F20: =+F10 -> 3932
B21: =SUM(B16:B20) -> 1
B24: SCORECARD
B26: Resultados
B27: =+Mensual!C27 -> 0.275 | D27: =+Mensual!E27 -> 0 | F27: enero | G27: febrero | H27: marzo | I27: abril | J27: mayo | K27: junio | L27: julio | M27: agosto | N27: septiembre | O27: octubre | P27: noviembre | Q27: diciembre
B28: 0.55 | C28: 9. SCORE CARD Grupo EXA | D28: =IF(VLOOKUP($C28,Mensual!$D$6:$G$163,2,0)<0,0,VLOOKUP($C28,Mensual!$D$6:$G$163,2,0)) -> RESULTADO SCORECARD | E28: =IF(VLOOKUP($C28,Mensual!$D$6:$G$163,3,0)<0,0,VLOOKUP($C28,Mensual!$D$6:$G$163,3,0)) -> 1 | F28: =IF(VLOOKUP($C28,Mensual!$D$6:$G$163,4,0)<0,0,VLOOKUP($C28,Mensual!$D$6:$G$163,4,0)) -> 1.0325
B29: 0.05 | C29: 3. Cero incidentes mayores de seguridad y sostenibilidad | D29: =IF(VLOOKUP($C29,Mensual!$D$6:$G$163,2,0)<0,0,VLOOKUP($C29,Mensual!$D$6:$G$163,2,0)) -> 0 | E29: =IF(VLOOKUP($C29,Mensual!$D$6:$G$163,3,0)<0,0,VLOOKUP($C29,Mensual!$D$6:$G$163,3,0)) -> 1 | F29: =IF(VLOOKUP($C29,Mensual!$D$6:$G$163,4,0)<0,0,VLOOKUP($C29,Mensual!$D$6:$G$163,4,0)) -> 1
B30: 0.25 | C30: 8. Innovaciones estratégicas de sistemas de Impacto recurrente | D30: =IF(VLOOKUP($C30,Mensual!$D$6:$G$163,2,0)<0,0,VLOOKUP($C30,Mensual!$D$6:$G$163,2,0)) -> 0 | E30: =IF(VLOOKUP($C30,Mensual!$D$6:$G$163,3,0)<0,0,VLOOKUP($C30,Mensual!$D$6:$G$163,3,0)) -> 1 | F30: =IF(VLOOKUP($C30,Mensual!$D$6:$G$163,4,0)<0,0,VLOOKUP($C30,Mensual!$D$6:$G$163,4,0)) -> 1
B31: 0.05 | C31: 5.6 Aprovechamiento GPS | D31: =IF(VLOOKUP($C31,Mensual!$D$6:$G$163,2,0)<0,0,VLOOKUP($C31,Mensual!$D$6:$G$163,2,0)) -> 0 | E31: =IF(VLOOKUP($C31,Mensual!$D$6:$G$163,3,0)<0,0,VLOOKUP($C31,Mensual!$D$6:$G$163,3,0)) -> 0.9 | F31: =IF(VLOOKUP($C31,Mensual!$D$6:$G$163,4,0)<0,0,VLOOKUP($C31,Mensual!$D$6:$G$163,4,0)) -> 0.82
B32: 0.1 | C32: 5. Productividad | D32: =IF(VLOOKUP($C32,Mensual!$D$6:$G$163,2,0)<0,0,VLOOKUP($C32,Mensual!$D$6:$G$163,2,0)) -> 0 | E32: =IF(VLOOKUP($C32,Mensual!$D$6:$G$163,3,0)<0,0,VLOOKUP($C32,Mensual!$D$6:$G$163,3,0)) -> 3700 | F32: =IF(VLOOKUP($C32,Mensual!$D$6:$G$163,4,0)<0,0,VLOOKUP($C32,Mensual!$D$6:$G$163,4,0)) -> 3932
B33: =SUM(B28:B32) -> 1

Sheet Desarrollo
I1: 0.9
I2: 80-90%
C3: Departamento: | D3: Sistemas_Y_Procesos | I3: Menos de 80%
A5: =+Mensual!B5 -> No | B5: =+Mensual!C5 -> Peso | D5: =+Mensual!E5 -> Unidad de medición | E5: =+Mensual!F5 -> Meta | F5: =+Mensual!G5 -> Resultado | G5: =+Mensual!H5 -> Nota | H5: =+Mensual!I5 -> Valor ponderado | I5: =+Mensual!J5 -> 0 | J5: =+Mensual!K5 -> 0.25 | K5: =+Mensual!L5 -> 0.5 | ... Q5: =+Mensual!R5 -> 0 | T5: Nota | U5: Nota
A6: =+Mensual!B6 -> 4 | B6: 0.3 | C6: 9. SCORE CARD Grupo EXA | D6: =IF(VLOOKUP($C6,Mensual!$D$6:$G$163,2,0)<0,0,VLOOKUP($C6,Mensual!$D$6:$G$163,2,0)) -> RESULTADO SCORECARD | E6: =IF(VLOOKUP($C6,Mensual!$D$6:$G$163,3,0)<0,0,VLOOKUP($C6,Mensual!$D$6:$G$163,3,0)) -> 1 | F6: =IF(VLOOKUP($C6,Mensual!$D$6:$G$163,4,0)<0,0,VLOOKUP($C6,Mensual!$D$6:$G$163,4,0)) -> 1.0325 | G6: =IF(VLOOKUP($C6,Mensual!$D$6:$H$163,5,0)<0,0,VLOOKUP($C6,Mensual!$D$6:$H$163,5,0)) -> 1.0325 | H6: =+G6*B6 -> 0.30975 | I6: =+Mensual!J6 -> 0 | J6: =+Mensual!K6 -> 0 | K6: =+Mensual!L6 -> 0 | L6: =+Mensual!M6 -> 0
B7: 0.6 | C7: 8. Innovaciones estratégicas de sistemas de Impacto recurrente | D7: =IF(VLOOKUP($C7,Mensual!$D$6:$G$135,2,0)<0,0,VLOOKUP($C7,Mensual!$D$6:$G$135,2,0)) -> 0 | E7: =IF(VLOOKUP($C7,Mensual!$D$6:$G$163,3,0)<0,0,VLOOKUP($C7,Mensual!$D$6:$G$163,3,0)) -> 1 | F7: =IF(VLOOKUP($C7,Mensual!$D$6:$G$163,4,0)<0,0,VLOOKUP($C7,Mensual!$D$6:$G$163,4,0)) -> 1 | G7: =IF(VLOOKUP($C7,Mensual!$D$6:$H$163,5,0)<0,0,VLOOKUP($C7,Mensual!$D$6:$H$163,5,0)) -> 1 | H7: =+G7*B7 -> 0.6
B8: 0.1 | C8: 5. Productividad | E8: =IF(VLOOKUP($C8,Mensual!$D$6:$G$163,3,0)<0,0,VLOOKUP($C8,Mensual!$D$6:$G$163,3,0)) -> 3700 | F8: =IF(VLOOKUP($C8,Mensual!$D$6:$G$163,4,0)<0,0,VLOOKUP($C8,Mensual!$D$6:$G$163,4,0)) -> 3932 | G8: =IF(VLOOKUP($C8,Mensual!$D$6:$H$163,5,0)<0,0,VLOOKUP($C8,Mensual!$D$6:$H$163,5,0)) -> 1 | H8: =+G8*B8 -> 0.1
B9: =SUM(B6:B8) -> 1 | H9: =SUM(H6:H8) -> 1.00975
C13: Colaboradores
C14: Cristian Hernandez
C15: Oscar Romero

Sheet Yadira
I1: 0.9
C2: Colaborador: | D2: Yadira Reyes | I2: 80-90%
C3: Departamento: | D3: Sistemas_Y_Procesos | I3: Menos de 80%
A5: =+Mensual!B5 -> No | B5: =+Mensual!C5 -> Peso | D5: =+Mensual!E5 -> Unidad de medición | E5: =+Mensual!F5 -> Meta | F5: =+Mensual!G5 -> Resultado | G5: =+Mensual!H5 -> Nota | H5: =+Mensual!I5 -> Valor ponderado | I5: =+Mensual!J5 -> 0 | J5: =+Mensual!K5 -> 0.25 | K5: =+Mensual!L5 -> 0.5 | ... Q5: =+Mensual!R5 -> 0 | T5: Nota | U5: Nota
B6: 0.25 | C6: 9. SCORE CARD Grupo EXA | D6: =IF(VLOOKUP($C6,Mensual!$D$6:$G$163,2,0)<0,0,VLOOKUP($C6,Mensual!$D$6:$G$163,2,0)) -> RESULTADO SCORECARD | E6: =IF(VLOOKUP($C6,Mensual!$D$6:$G$163,3,0)<0,0,VLOOKUP($C6,Mensual!$D$6:$G$163,3,0)) -> 1 | F6: =IF(VLOOKUP($C6,Mensual!$D$6:$G$163,4,0)<0,0,VLOOKUP($C6,Mensual!$D$6:$G$163,4,0)) -> 1.0325 | G6: =IF(VLOOKUP($C6,Mensual!$D$6:$H$163,5,0)<0,0,VLOOKUP($C6,Mensual!$D$6:$H$163,5,0)) -> 1.0325 | H6: =+G6*B6 -> 0.258125 | I6: =+Mensual!J6 -> 0 | J6: =+Mensual!K6 -> 0 | K6: =+Mensual!L6 -> 0 | L6: =+Mensual!M6 -> 0
B7: 0.05 | C7: 3. Cero incidentes mayores de seguridad y sostenibilidad | D7: =IF(VLOOKUP($C7,Mensual!$D$6:$G$135,2,0)<0,0,VLOOKUP($C7,Mensual!$D$6:$G$135,2,0)) -> 0 | E7: =IF(VLOOKUP($C7,Mensual!$D$6:$G$163,3,0)<0,0,VLOOKUP($C7,Mensual!$D$6:$G$163,3,0)) -> 1 | F7: =IF(VLOOKUP($C7,Mensual!$D$6:$G$163,4,0)<0,0,VLOOKUP($C7,Mensual!$D$6:$G$163,4,0)) -> 1 | G7: =IF(VLOOKUP($C7,Mensual!$D$6:$H$163,5,0)<0,0,VLOOKUP($C7,Mensual!$D$6:$H$163,5,0)) -> 1 | H7: =+G7*B7 -> 0.05
B8: 0.05 | C8: 5. Productividad | D8: =IF(VLOOKUP($C8,Mensual!$D$6:$G$135,2,0)<0,0,VLOOKUP($C8,Mensual!$D$6:$G$135,2,0)) -> 0 | E8: =IF(VLOOKUP($C8,Mensual!$D$6:$G$163,3,0)<0,0,VLOOKUP($C8,Mensual!$D$6:$G$163,3,0)) -> 3700 | F8: =IF(VLOOKUP($C8,Mensual!$D$6:$G$163,4,0)<0,0,VLOOKUP($C8,Mensual!$D$6:$G$163,4,0)) -> 3932 | G8: =IF(VLOOKUP($C8,Mensual!$D$6:$H$163,5,0)<0,0,VLOOKUP($C8,Mensual!$D$6:$H$163,5,0)) -> 1 | H8: =+G8*B8 -> 0.05
B9: 0.1 | C9: 2.21 Aumentar % neto del servicio de transporte | D9: =IF(VLOOKUP($C9,Mensual!$D$6:$G$135,2,0)<0,0,VLOOKUP($C9,Mensual!$D$6:$G$135,2,0)) -> 0 | E9: =IF(VLOOKUP($C9,Mensual!$D$6:$G$163,3,0)<0,0,VLOOKUP($C9,Mensual!$D$6:$G$163,3,0)) -> 0.1 | F9: =IF(VLOOKUP($C9,Mensual!$D$6:$G$163,4,0)<0,0,VLOOKUP($C9,Mensual!$D$6:$G$163,4,0)) -> 0.1 | G9: =IF(VLOOKUP($C9,Mensual!$D$6:$H$163,5,0)<0,0,VLOOKUP($C9,Mensual!$D$6:$H$163,5,0)) -> 1 | H9: =+G9*B9 -> 0.1
B10: 0.55 | C10: 5.7 Dias de facturacion | D10: =IF(VLOOKUP($C10,Mensual!$D$6:$G$135,2,0)<0,0,VLOOKUP($C10,Mensual!$D$6:$G$135,2,0)) -> 0 | E10: =IF(VLOOKUP($C10,Mensual!$D$6:$G$163,3,0)<0,0,VLOOKUP($C10,Mensual!$D$6:$G$163,3,0)) -> 4 | F10: =IF(VLOOKUP($C10,Mensual!$D$6:$G$163,4,0)<0,0,VLOOKUP($C10,Mensual!$D$6:$G$163,4,0)) -> 6 | G10: =IF(VLOOKUP($C10,Mensual!$D$6:$H$163,5,0)<0,0,VLOOKUP($C10,Mensual!$D$6:$H$163,5,0)) -> 1 | H10: =+G10*B10 -> 0.55
B11: =SUM(B6:B10) -> 1 | H11: =SUM(H6:H10) -> 1.008125
C21: Agrega el aprovechamiento de dispositivos

Sheet Keila
I1: 0.9
C2: Colaborador: | D2: Keila Rodriguez | I2: 80-90%
C3: Departamento: | D3: Sistemas_Y_Procesos | I3: Menos de 80%
A5: =+Mensual!B5 -> No | B5: =+Mensual!C5 -> Peso | D5: =+Mensual!E5 -> Unidad de medición | E5: =+Mensual!F5 -> Meta | F5: =+Mensual!G5 -> Resultado | G5: =+Mensual!H5 -> Nota | H5: =+Mensual!I5 -> Valor ponderado | I5: =+Mensual!J5 -> 0 | J5: =+Mensual!K5 -> 0.25 | K5: =+Mensual!L5 -> 0.5 | ... Q5: =+Mensual!R5 -> 0 | T5: Nota | U5: Nota
A6: =+Mensual!B6 -> 4 | B6: 0.25 | C6: 9. SCORE CARD Grupo EXA | D6: =IF(VLOOKUP($C6,Mensual!$D$6:$G$163,2,0)<0,0,VLOOKUP($C6,Mensual!$D$6:$G$163,2,0)) -> RESULTADO SCORECARD | E6: =IF(VLOOKUP($C6,Mensual!$D$6:$G$163,3,0)<0,0,VLOOKUP($C6,Mensual!$D$6:$G$163,3,0)) -> 1 | F6: =IF(VLOOKUP($C6,Mensual!$D$6:$G$163,4,0)<0,0,VLOOKUP($C6,Mensual!$D$6:$G$163,4,0)) -> 1.0325 | G6: =IF(VLOOKUP($C6,Mensual!$D$6:$H$163,5,0)<0,0,VLOOKUP($C6,Mensual!$D$6:$H$163,5,0)) -> 1.0325 | H6: =+G6*B6 -> 0.258125 | I6: =+Mensual!J6 -> 0 | J6: =+Mensual!K6 -> 0 | K6: =+Mensual!L6 -> 0 | L6: =+Mensual!M6 -> 0
B7: 0.05 | C7: 3. Cero incidentes mayores de seguridad y sostenibilidad | D7: =IF(VLOOKUP($C7,Mensual!$D$6:$G$135,2,0)<0,0,VLOOKUP($C7,Mensual!$D$6:$G$135,2,0)) -> 0 | E7: =IF(VLOOKUP($C7,Mensual!$D$6:$G$163,3,0)<0,0,VLOOKUP($C7,Mensual!$D$6:$G$163,3,0)) -> 1 | F7: =IF(VLOOKUP($C7,Mensual!$D$6:$G$163,4,0)<0,0,VLOOKUP($C7,Mensual!$D$6:$G$163,4,0)) -> 1 | G7: =IF(VLOOKUP($C7,Mensual!$D$6:$H$163,5,0)<0,0,VLOOKUP($C7,Mensual!$D$6:$H$163,5,0)) -> 1 | H7: =+G7*B7 -> 0.05
B8: 0.1 | C8: 1.9 Aumento en ventas de GPS a terceros (nuevos clientes) | D8: =IF(VLOOKUP($C8,Mensual!$D$6:$G$135,2,0)<0,0,VLOOKUP($C8,Mensual!$D$6:$G$135,2,0)) -> Unidad instaladas / mensuales | E8: =IF(VLOOKUP($C8,Mensual!$D$6:$G$163,3,0)<0,0,VLOOKUP($C8,Mensual!$D$6:$G$163,3,0)) -> 10 | F8: =IF(VLOOKUP($C8,Mensual!$D$6:$G$163,4,0)<0,0,VLOOKUP($C8,Mensual!$D$6:$G$163,4,0)) -> 0 | G8: =IF(VLOOKUP($C8,Mensual!$D$6:$H$163,5,0)<0,0,VLOOKUP($C8,Mensual!$D$6:$H$163,5,0)) -> 0 | H8: =+G8*B8 -> 0
B9: 0.5 | C9: 5.6 Aprovechamiento GPS | D9: =IF(VLOOKUP($C9,Mensual!$D$6:$G$135,2,0)<0,0,VLOOKUP($C9,Mensual!$D$6:$G$135,2,0)) -> 0 | E9: =IF(VLOOKUP($C9,Mensual!$D$6:$G$163,3,0)<0,0,VLOOKUP($C9,Mensual!$D$6:$G$163,3,0)) -> 0.9 | F9: =IF(VLOOKUP($C9,Mensual!$D$6:$G$163,4,0)<0,0,VLOOKUP($C9,Mensual!$D$6:$G$163,4,0)) -> 0.82 | G9: =IF(VLOOKUP($C9,Mensual!$D$6:$H$163,5,0)<0,0,VLOOKUP($C9,Mensual!$D$6:$H$163,5,0)) -> 0.91111111 | H9: =+G9*B9 -> 0.45555556
B10: 0.1 | C10: 2.12 Costo por mes por GPS (Costo de plataforma + Tigo/claro + otros costos) | D10: =IF(VLOOKUP($C10,Mensual!$D$6:$G$135,2,0)<0,0,VLOOKUP($C10,Mensual!$D$6:$G$135,2,0)) -> $ | E10: =IF(VLOOKUP($C10,Mensual!$D$6:$G$163,3,0)<0,0,VLOOKUP($C10,Mensual!$D$6:$G$163,3,0)) -> 8 | F10: =IF(VLOOKUP($C10,Mensual!$D$6:$G$163,4,0)<0,0,VLOOKUP($C10,Mensual!$D$6:$G$163,4,0)) -> 4.71 | G10: =IF(VLOOKUP($C10,Mensual!$D$6:$H$163,5,0)<0,0,VLOOKUP($C10,Mensual!$D$6:$H$163,5,0)) -> 1 | H10: =+G10*B10 -> 0.1
B11: =SUM(B6:B10) -> 1 | H11: =SUM(H6:H10) -> 0.86368056

Sheet Mario
I1: 0.9
C2: Colaborador: | D2: Mario Murillo | I2: 80-90%
C3: Departamento: | D3: Sistemas_Y_Procesos | I3: Menos de 80%
A5: =+Mensual!B5 -> No | B5: =+Mensual!C5 -> Peso | D5: =+Mensual!E5 -> Unidad de medición | E5: =+Mensual!F5 -> Meta | F5: =+Mensual!G5 -> Resultado | G5: =+Mensual!H5 -> Nota | H5: =+Mensual!I5 -> Valor ponderado | I5: =+Mensual!J5 -> 0 | J5: =+Mensual!K5 -> 0.25 | K5: =+Mensual!L5 -> 0.5 | ... Q5: =+Mensual!R5 -> 0 | T5: Nota | U5: Nota
A6: =+Mensual!B6 -> 4 | B6: 0.25 | C6: 9. SCORE CARD Grupo EXA | D6: =IF(VLOOKUP($C6,Mensual!$D$6:$G$163,2,0)<0,0,VLOOKUP($C6,Mensual!$D$6:$G$163,2,0)) -> RESULTADO SCORECARD | E6: =IF(VLOOKUP($C6,Mensual!$D$6:$G$163,3,0)<0,0,VLOOKUP($C6,Mensual!$D$6:$G$163,3,0)) -> 1 | F6: =IF(VLOOKUP($C6,Mensual!$D$6:$G$163,4,0)<0,0,VLOOKUP($C6,Mensual!$D$6:$G$163,4,0)) -> 1.0325 | G6: =IF(VLOOKUP($C6,Mensual!$D$6:$H$163,5,0)<0,0,VLOOKUP($C6,Mensual!$D$6:$H$163,5,0)) -> 1.0325 | H6: =+G6*B6 -> 0.258125 | I6: =+Mensual!J6 -> 0 | J6: =+Mensual!K6 -> 0 | K6: =+Mensual!L6 -> 0 | L6: =+Mensual!M6 -> 0
B7: 0.15 | C7: 4. Aumentar clima laboral | D7: =IF(VLOOKUP($C7,Mensual!$D$6:$G$135,2,0)<0,0,VLOOKUP($C7,Mensual!$D$6:$G$135,2,0)) -> 0 | E7: =IF(VLOOKUP($C7,Mensual!$D$6:$G$163,3,0)<0,0,VLOOKUP($C7,Mensual!$D$6:$G$163,3,0)) -> 0.1 | F7: =IF(VLOOKUP($C7,Mensual!$D$6:$G$163,4,0)<0,0,VLOOKUP($C7,Mensual!$D$6:$G$163,4,0)) -> 0.1 | G7: =IF(VLOOKUP($C7,Mensual!$D$6:$H$163,5,0)<0,0,VLOOKUP($C7,Mensual!$D$6:$H$163,5,0)) -> 1 | H7: =+G7*B7 -> 0.15
B8: 0.6 | C8: 3. Cero incidentes mayores de seguridad y sostenibilidad | D8: =IF(VLOOKUP($C8,Mensual!$D$6:$G$135,2,0)<0,0,VLOOKUP($C8,Mensual!$D$6:$G$135,2,0)) -> 0 | E8: =IF(VLOOKUP($C8,Mensual!$D$6:$G$163,3,0)<0,0,VLOOKUP($C8,Mensual!$D$6:$G$163,3,0)) -> 1 | F8: =IF(VLOOKUP($C8,Mensual!$D$6:$G$163,4,0)<0,0,VLOOKUP($C8,Mensual!$D$6:$G$163,4,0)) -> 1 | G8: =IF(VLOOKUP($C8,Mensual!$D$6:$H$163,5,0)<0,0,VLOOKUP($C8,Mensual!$D$6:$H$163,5,0)) -> 1 | H8: =+G8*B8 -> 0.6
B9: =SUM(B6:B8) -> 1 | H9: =SUM(H6:H8) -> 1.008125

Sheet Luis Madrid
I1: 0.9
C2: Colaborador: | D2: Luis Madrid | I2: 80-90%
C3: Departamento: | D3: Contenedores | I3: Menos de 80%
A5: =+Mensual!B5 -> No | B5: =+Mensual!C5 -> Peso | D5: =+Mensual!E5 -> Unidad de medición | E5: =+Mensual!F5 -> Meta | F5: =+Mensual!G5 -> Resultado | G5: =+Mensual!H5 -> Nota | H5: =+Mensual!I5 -> Valor ponderado | I5: =+Mensual!J5 -> 0 | J5: =+Mensual!K5 -> 0.25 | K5: =+Mensual!L5 -> 0.5 | ... Q5: =+Mensual!R5 -> 0 | T5: Nota | U5: Nota
A6: =+Mensual!B6 -> 4 | B6: 0.3 | C6: 10. CONMOXA | D6: =IF(VLOOKUP($C6,Mensual!$D$6:$G$163,2,0)<0,0,VLOOKUP($C6,Mensual!$D$6:$G$163,2,0)) -> RESULTADO SCORECARD | E6: =IF(VLOOKUP($C6,Mensual!$D$6:$G$163,3,0)<0,0,VLOOKUP($C6,Mensual!$D$6:$G$163,3,0)) -> 1 | F6: =IF(VLOOKUP($C6,Mensual!$D$6:$G$163,4,0)<0,0,VLOOKUP($C6,Mensual!$D$6:$G$163,4,0)) -> 0.4255 | G6: =IF(VLOOKUP($C6,Mensual!$D$6:$H$163,5,0)<0,0,VLOOKUP($C6,Mensual!$D$6:$H$163,5,0)) -> 0.4255 | H6: =+G6*B6 -> 0.12765 | I6: =+Mensual!J6 -> 0 | J6: =+Mensual!K6 -> 0 | K6: =+Mensual!L6 -> 0 | L6: =+Mensual!M6 -> 0
B7: 0.3 | C7: 9. SCORE CARD Grupo EXA | D7: =IF(VLOOKUP($C7,Mensual!$D$6:$G$163,2,0)<0,0,VLOOKUP($C7,Mensual!$D$6:$G$163,2,0)) -> RESULTADO SCORECARD | E7: =IF(VLOOKUP($C7,Mensual!$D$6:$G$163,3,0)<0,0,VLOOKUP($C7,Mensual!$D$6:$G$163,3,0)) -> 1 | F7: =IF(VLOOKUP($C7,Mensual!$D$6:$G$163,4,0)<0,0,VLOOKUP($C7,Mensual!$D$6:$G$163,4,0)) -> 1.0325 | G7: =IF(VLOOKUP($C7,Mensual!$D$6:$H$163,5,0)<0,0,VLOOKUP($C7,Mensual!$D$6:$H$163,5,0)) -> 1.0325 | H7: =+G7*B7 -> 0.30975
B8: 0.1 | C8: 1.10 Aumentar ventas en articulos Sejue/get504 | D8: =IF(VLOOKUP($C8,Mensual!$D$6:$G$163,2,0)<0,0,VLOOKUP($C8,Mensual!$D$6:$G$163,2,0)) -> Articulos | E8: =IF(VLOOKUP($C8,Mensual!$D$6:$G$163,3,0)<0,0,VLOOKUP($C8,Mensual!$D$6:$G$163,3,0)) -> 10 | F8: =IF(VLOOKUP($C8,Mensual!$D$6:$G$163,4,0)<0,0,VLOOKUP($C8,Mensual!$D$6:$G$163,4,0)) -> 19 | G8: =IF(VLOOKUP($C8,Mensual!$D$6:$H$163,5,0)<0,0,VLOOKUP($C8,Mensual!$D$6:$H$163,5,0)) -> 1 | H8: =+G8*B8 -> 0.1
B9: 0.3 | C9: 1.5 Aumentar Rentas bienes y raices | D9: =IF(VLOOKUP($C9,Mensual!$D$6:$G$163,2,0)<0,0,VLOOKUP($C9,Mensual!$D$6:$G$163,2,0)) -> Porcentaje | E9: =IF(VLOOKUP($C9,Mensual!$D$6:$G$163,3,0)<0,0,VLOOKUP($C9,Mensual!$D$6:$G$163,3,0)) -> 0.2 | F9: =IF(VLOOKUP($C9,Mensual!$D$6:$G$163,4,0)<0,0,VLOOKUP($C9,Mensual!$D$6:$G$163,4,0)) -> 0 | G9: =IF(VLOOKUP($C9,Mensual!$D$6:$H$163,5,0)<0,0,VLOOKUP($C9,Mensual!$D$6:$H$163,5,0)) -> 0 | H9: =+G9*B9 -> 0
B10: =SUM(B6:B9) -> 1 | H10: =SUM(H6:H9) -> 0.5374

Sheet Roy Reyes
I1: 0.9
C2: Colaborador: | D2: Roy Reyes | I2: 80-90%
C3: Departamento: | D3: Contenedores | I3: Menos de 80%
A5: =+Mensual!B5 -> No | B5: =+Mensual!C5 -> Peso | D5: =+Mensual!E5 -> Unidad de medición | E5: =+Mensual!F5 -> Meta | F5: =+Mensual!G5 -> Resultado | G5: =+Mensual!H5 -> Nota | H5: =+Mensual!I5 -> Valor ponderado | I5: =+Mensual!J5 -> 0 | J5: =+Mensual!K5 -> 0.25 | K5: =+Mensual!L5 -> 0.5 | ... Q5: =+Mensual!R5 -> 0 | T5: Nota | U5: Nota
A6: =+Mensual!B6 -> 4 | B6: 0.4 | C6: 10. CONMOXA | D6: =IF(VLOOKUP($C6,Mensual!$D$6:$G$163,2,0)<0,0,VLOOKUP($C6,Mensual!$D$6:$G$163,2,0)) -> RESULTADO SCORECARD | E6: =IF(VLOOKUP($C6,Mensual!$D$6:$G$163,3,0)<0,0,VLOOKUP($C6,Mensual!$D$6:$G$163,3,0)) -> 1 | F6: =IF(VLOOKUP($C6,Mensual!$D$6:$G$163,4,0)<0,0,VLOOKUP($C6,Mensual!$D$6:$G$163,4,0)) -> 0.4255 | G6: =IF(VLOOKUP($C6,Mensual!$D$6:$H$163,5,0)<0,0,VLOOKUP($C6,Mensual!$D$6:$H$163,5,0)) -> 0.4255 | H6: =+G6*B6 -> 0.1702 | I6: =+Mensual!J6 -> 0 | J6: =+Mensual!K6 -> 0 | K6: =+Mensual!L6 -> 0 | L6: =+Mensual!M6 -> 0
B7: 0.1 | C7: 9. SCORE CARD Grupo EXA | D7: =IF(VLOOKUP($C7,Mensual!$D$6:$G$135,2,0)<0,0,VLOOKUP($C7,Mensual!$D$6:$G$135,2,0)) -> RESULTADO SCORECARD | E7: =IF(VLOOKUP($C7,Mensual!$D$6:$G$163,3,0)<0,0,VLOOKUP($C7,Mensual!$D$6:$G$163,3,0)) -> 1 | F7: =IF(VLOOKUP($C7,Mensual!$D$6:$G$163,4,0)<0,0,VLOOKUP($C7,Mensual!$D$6:$G$163,4,0)) -> 1.0325 | G7: =IF(VLOOKUP($C7,Mensual!$D$6:$H$163,5,0)<0,0,VLOOKUP($C7,Mensual!$D$6:$H$163,5,0)) -> 1.0325 | H7: =+G7*B7 -> 0.10325
B8: 0.2 | C8: 1.9 Aumento en ventas de GPS a terceros (nuevos clientes) | E8: =IF(VLOOKUP($C8,Mensual!$D$6:$G$163,3,0)<0,0,VLOOKUP($C8,Mensual!$D$6:$G$163,3,0)) -> 10 | F8: =IF(VLOOKUP($C8,Mensual!$D$6:$G$163,4,0)<0,0,VLOOKUP($C8,Mensual!$D$6:$G$163,4,0)) -> 0 | G8: =IF(VLOOKUP($C8,Mensual!$D$6:$H$163,5,0)<0,0,VLOOKUP($C8,Mensual!$D$6:$H$163,5,0)) -> 0 | H8: =+G8*B8 -> 0
B9: 0.3 | C9: 5.11 # de fallas operativas adjudicables al predio (Incluye rescates, rechazos) Puerto Cortes | D9: =IF(VLOOKUP($C9,Mensual!$D$6:$G$135,2,0)<0,0,VLOOKUP($C9,Mensual!$D$6:$G$135,2,0)) -> # de fallas | E9: =IF(VLOOKUP($C9,Mensual!$D$6:$G$163,3,0)<0,0,VLOOKUP($C9,Mensual!$D$6:$G$163,3,0)) -> 1 | F9: =IF(VLOOKUP($C9,Mensual!$D$6:$G$163,4,0)<0,0,VLOOKUP($C9,Mensual!$D$6:$G$163,4,0)) -> 0 | G9: =IF(VLOOKUP($C9,Mensual!$D$6:$H$163,5,0)<0,0,VLOOKUP($C9,Mensual!$D$6:$H$163,5,0)) -> 1 | H9: =+G9*B9 -> 0.3
B10: =SUM(B6:B9) -> 1 | H10: =SUM(H6:H9) -> 0.57345
C24: Agregar aprovechaimiento de gps. Mas que ventas y margen.
C25: Reemplazar el del margen.

Sheet TRANEXPA
I1: 0.9
C2: Departamento: | D2: Transporte | I2: 80-90%
I3: Menos de 80%
A5: =+Mensual!B5 -> No | B5: =+Mensual!C5 -> Peso | D5: =+Mensual!E5 -> Unidad de medición | E5: =+Mensual!F5 -> Meta | F5: =+Mensual!G5 -> Resultado | G5: =+Mensual!H5 -> Nota | H5: =+Mensual!I5 -> Valor ponderado | I5: =+Mensual!J5 -> 0 | J5: =+Mensual!K5 -> 0.25 | K5: =+Mensual!L5 -> 0.5 | ... Q5: =+Mensual!R5 -> 0 | T5: Nota | U5: Nota
A6: =+Mensual!B6 -> 4 | B6: 0.35 | C6: 9. SCORE CARD Grupo EXA | D6: =IF(VLOOKUP($C6,Mensual!$D$6:$G$163,2,0)<0,0,VLOOKUP($C6,Mensual!$D$6:$G$163,2,0)) -> RESULTADO SCORECARD | E6: =IF(VLOOKUP($C6,Mensual!$D$6:$G$163,3,0)<0,0,VLOOKUP($C6,Mensual!$D$6:$G$163,3,0)) -> 1 | F6: =IF(VLOOKUP($C6,Mensual!$D$6:$G$163,4,0)<0,0,VLOOKUP($C6,Mensual!$D$6:$G$163,4,0)) -> 1.0325 | G6: =IF(VLOOKUP($C6,Mensual!$D$6:$H$163,5,0)<0,0,VLOOKUP($C6,Mensual!$D$6:$H$163,5,0)) -> 1.0325 | H6: =+G6*B6 -> 0.361375 | I6: =+Mensual!J6 -> 0 | J6: =+Mensual!K6 -> 0 | K6: =+Mensual!L6 -> 0 | L6: =+Mensual!M6 -> 0
B7: 0.1 | C7: 2.17 Reducir costo por km/cabezal TRANEXPA | D7: =IF(VLOOKUP($C7,Mensual!$D$6:$G$163,2,0)<0,0,VLOOKUP($C7,Mensual!$D$6:$G$163,2,0)) -> 0 | E7: =IF(VLOOKUP($C7,Mensual!$D$6:$G$163,3,0)<0,0,VLOOKUP($C7,Mensual!$D$6:$G$163,3,0)) -> 0 | F7: =IF(VLOOKUP($C7,Mensual!$D$6:$G$163,4,0)<0,0,VLOOKUP($C7,Mensual!$D$6:$G$163,4,0)) -> 0.14 | G7: =IF(VLOOKUP($C7,Mensual!$D$6:$H$163,5,0)<0,0,VLOOKUP($C7,Mensual!$D$6:$H$163,5,0)) -> 0 | H7: =+G7*B7 -> 0
B8: 0.1 | C8: 3. Cero incidentes mayores de seguridad y sostenibilidad | D8: =IF(VLOOKUP($C8,Mensual!$D$6:$G$163,2,0)<0,0,VLOOKUP($C8,Mensual!$D$6:$G$163,2,0)) -> 0 | E8: =IF(VLOOKUP($C8,Mensual!$D$6:$G$163,3,0)<0,0,VLOOKUP($C8,Mensual!$D$6:$G$163,3,0)) -> 1 | F8: =IF(VLOOKUP($C8,Mensual!$D$6:$G$163,4,0)<0,0,VLOOKUP($C8,Mensual!$D$6:$G$163,4,0)) -> 1 | G8: =IF(VLOOKUP($C8,Mensual!$D$6:$H$163,5,0)<0,0,VLOOKUP($C8,Mensual!$D$6:$H$163,5,0)) -> 1 | H8: =+G8*B8 -> 0.1
B9: 0.1 | C9: 3.7 Cero accidente mayores Y/O robos TRANEXPA | D9: =IF(VLOOKUP($C9,Mensual!$D$6:$G$163,2,0)<0,0,VLOOKUP($C9,Mensual!$D$6:$G$163,2,0)) -> 0 | E9: =IF(VLOOKUP($C9,Mensual!$D$6:$G$163,3,0)<0,0,VLOOKUP($C9,Mensual!$D$6:$G$163,3,0)) -> 0 | F9: =IF(VLOOKUP($C9,Mensual!$D$6:$G$163,4,0)<0,0,VLOOKUP($C9,Mensual!$D$6:$G$163,4,0)) -> 0 | G9: =IF(VLOOKUP($C9,Mensual!$D$6:$H$163,5,0)<0,0,VLOOKUP($C9,Mensual!$D$6:$H$163,5,0)) -> 0 | H9: =+G9*B9 -> 0
B10: 0.1 | C10: 5.10 Aumentar kms TRANEXPA | D10: =IF(VLOOKUP($C10,Mensual!$D$6:$G$163,2,0)<0,0,VLOOKUP($C10,Mensual!$D$6:$G$163,2,0)) -> kms | E10: =IF(VLOOKUP($C10,Mensual!$D$6:$G$163,3,0)<0,0,VLOOKUP($C10,Mensual!$D$6:$G$163,3,0)) -> 0.2 | F10: =IF(VLOOKUP($C10,Mensual!$D$6:$G$163,4,0)<0,0,VLOOKUP($C10,Mensual!$D$6:$G$163,4,0)) -> 0 | G10: =IF(VLOOKUP($C10,Mensual!$D$6:$H$163,5,0)<0,0,VLOOKUP($C10,Mensual!$D$6:$H$163,5,0)) -> 0 | H10: =+G10*B10 -> 0
B11: 0.1 | C11: 5.3 Productividad cabezales TRANEXPA | D11: =IF(VLOOKUP($C11,Mensual!$D$6:$G$163,2,0)<0,0,VLOOKUP($C11,Mensual!$D$6:$G$163,2,0)) -> 0 | E11: =IF(VLOOKUP($C11,Mensual!$D$6:$G$163,3,0)<0,0,VLOOKUP($C11,Mensual!$D$6:$G$163,3,0)) -> 4000 | F11: =IF(VLOOKUP($C11,Mensual!$D$6:$G$163,4,0)<0,0,VLOOKUP($C11,Mensual!$D$6:$G$163,4,0)) -> 4268 | G11: =IF(VLOOKUP($C11,Mensual!$D$6:$H$163,5,0)<0,0,VLOOKUP($C11,Mensual!$D$6:$H$163,5,0)) -> 1 | H11: =+G11*B11 -> 0.1
B12: 0.05 | C12: 6.5 Disminuir a 0-1 el desuso de cabezales propios | D12: =IF(VLOOKUP($C12,Mensual!$D$6:$G$163,2,0)<0,0,VLOOKUP($C12,Mensual!$D$6:$G$163,2,0)) -> cabezal | E12: =IF(VLOOKUP($C12,Mensual!$D$6:$G$163,3,0)<0,0,VLOOKUP($C12,Mensual!$D$6:$G$163,3,0)) -> 1 | F12: =IF(VLOOKUP($C12,Mensual!$D$6:$G$163,4,0)<0,0,VLOOKUP($C12,Mensual!$D$6:$G$163,4,0)) -> 1 | G12: =IF(VLOOKUP($C12,Mensual!$D$6:$H$163,5,0)<0,0,VLOOKUP($C12,Mensual!$D$6:$H$163,5,0)) -> 0 | H12: =+G12*B12 -> 0
B13: 0.1 | C13: 2.3 Reducir Costo por km cabezales propios. | D13: =IF(VLOOKUP($C13,Mensual!$D$6:$G$163,2,0)<0,0,VLOOKUP($C13,Mensual!$D$6:$G$163,2,0)) -> $ | E13: =IF(VLOOKUP($C13,Mensual!$D$6:$G$163,3,0)<0,0,VLOOKUP($C13,Mensual!$D$6:$G$163,3,0)) -> 0.05 | F13: =IF(VLOOKUP($C13,Mensual!$D$6:$G$163,4,0)<0,0,VLOOKUP($C13,Mensual!$D$6:$G$163,4,0)) -> 0.6 | G13: =IF(VLOOKUP($C13,Mensual!$D$6:$H$163,5,0)<0,0,VLOOKUP($C13,Mensual!$D$6:$H$163,5,0)) -> 1 | H13: =+G13*B13 -> 0.1
B14: =SUM(B6:B13) -> 1 | H14: =SUM(H6:H13) -> 0.661375
C18: Colaboradores:

Sheet TREXA
I1: 0.9
C2: Departamento: | D2: Administracion | I2: 80-90%
I3: Menos de 80%
A5: =+Mensual!B5 -> No | B5: =+Mensual!C5 -> Peso | D5: =+Mensual!E5 -> Unidad de medición | E5: =+Mensual!F5 -> Meta | F5: =+Mensual!G5 -> Resultado | G5: =+Mensual!H5 -> Nota | H5: =+Mensual!I5 -> Valor ponderado | I5: =+Mensual!J5 -> 0 | J5: =+Mensual!K5 -> 0.25 | K5: =+Mensual!L5 -> 0.5 | ... Q5: =+Mensual!R5 -> 0 | T5: Nota | U5: Nota
A6: =+Mensual!B6 -> 4 | B6: 0.25 | C6: 9. SCORE CARD Grupo EXA | D6: =IF(VLOOKUP($C6,Mensual!$D$6:$G$163,2,0)<0,0,VLOOKUP($C6,Mensual!$D$6:$G$163,2,0)) -> RESULTADO SCORECARD | E6: =IF(VLOOKUP($C6,Mensual!$D$6:$G$163,3,0)<0,0,VLOOKUP($C6,Mensual!$D$6:$G$163,3,0)) -> 1 | F6: =IF(VLOOKUP($C6,Mensual!$D$6:$G$163,4,0)<0,0,VLOOKUP($C6,Mensual!$D$6:$G$163,4,0)) -> 1.0325 | G6: =IF(VLOOKUP($C6,Mensual!$D$6:$H$163,5,0)<0,0,VLOOKUP($C6,Mensual!$D$6:$H$163,5,0)) -> 1.0325 | H6: =+G6*B6 -> 0.258125 | I6: =+Mensual!J6 -> 0 | J6: =+Mensual!K6 -> 0 | K6: =+Mensual!L6 -> 0 | L6: =+Mensual!M6 -> 0
B7: 0.2 | C7: 2.22 Aumentar margen neto alquiler de contenedores secos (solo o en combo) TREXA | D7: =IF(VLOOKUP($C7,Mensual!$D$6:$G$163,2,0)<0,0,VLOOKUP($C7,Mensual!$D$6:$G$163,2,0)) -> 0 | E7: =IF(VLOOKUP($C7,Mensual!$D$6:$G$163,3,0)<0,0,VLOOKUP($C7,Mensual!$D$6:$G$163,3,0)) -> 0.1 | F7: =IF(VLOOKUP($C7,Mensual!$D$6:$G$163,4,0)<0,0,VLOOKUP($C7,Mensual!$D$6:$G$163,4,0)) -> 0.1 | G7: =IF(VLOOKUP($C7,Mensual!$D$6:$H$163,5,0)<0,0,VLOOKUP($C7,Mensual!$D$6:$H$163,5,0)) -> 1 | H7: =+G7*B7 -> 0.2
B8: 0.2 | C8: 1.17 Aumentar el numero de cliente semestralmente | D8: =IF(VLOOKUP($C8,Mensual!$D$6:$G$163,2,0)<0,0,VLOOKUP($C8,Mensual!$D$6:$G$163,2,0)) -> cliente | E8: =IF(VLOOKUP($C8,Mensual!$D$6:$G$163,3,0)<0,0,VLOOKUP($C8,Mensual!$D$6:$G$163,3,0)) -> 1 | F8: =IF(VLOOKUP($C8,Mensual!$D$6:$G$163,4,0)<0,0,VLOOKUP($C8,Mensual!$D$6:$G$163,4,0)) -> 0 | G8: =IF(VLOOKUP($C8,Mensual!$D$6:$H$163,5,0)<0,0,VLOOKUP($C8,Mensual!$D$6:$H$163,5,0)) -> 0 | H8: =+G8*B8 -> 0
B9: 0.1 | C9: 3.6.1 Cierre TREXA | D9: =IF(VLOOKUP($C9,Mensual!$D$6:$G$163,2,0)<0,0,VLOOKUP($C9,Mensual!$D$6:$G$163,2,0)) -> # de cierres a tiempo | E9: =IF(VLOOKUP($C9,Mensual!$D$6:$G$163,3,0)<0,0,VLOOKUP($C9,Mensual!$D$6:$G$163,3,0)) -> 1 | F9: =IF(VLOOKUP($C9,Mensual!$D$6:$G$163,4,0)<0,0,VLOOKUP($C9,Mensual!$D$6:$G$163,4,0)) -> 1 | G9: =IF(VLOOKUP($C9,Mensual!$D$6:$H$163,5,0)<0,0,VLOOKUP($C9,Mensual!$D$6:$H$163,5,0)) -> 1 | H9: =+G9*B9 -> 0.1
B10: 0.25 | C10: 1.8 Aumentar ventas en TREXA | D10: =IF(VLOOKUP($C10,Mensual!$D$6:$G$163,2,0)<0,0,VLOOKUP($C10,Mensual!$D$6:$G$163,2,0)) -> Dólares | E10: =IF(VLOOKUP($C10,Mensual!$D$6:$G$163,3,0)<0,0,VLOOKUP($C10,Mensual!$D$6:$G$163,3,0)) -> 0.2 | F10: =IF(VLOOKUP($C10,Mensual!$D$6:$G$163,4,0)<0,0,VLOOKUP($C10,Mensual!$D$6:$G$163,4,0)) -> 1.03 | G10: =IF(VLOOKUP($C10,Mensual!$D$6:$H$163,5,0)<0,0,VLOOKUP($C10,Mensual!$D$6:$H$163,5,0)) -> 1 | H10: =+G10*B10 -> 0.25
B11: =SUM(B6:B10) -> 1 | H11: =SUM(H6:H10) -> 0.808125
C14: Colaboradores:
C15: Tamara Castro

Sheet Julio - Alejandro
I1: 0.9
C2: Departamento: | D2: Administracion | I2: 80-90%
I3: Menos de 80%
A5: =+Mensual!B5 -> No | B5: =+Mensual!C5 -> Peso | D5: =+Mensual!E5 -> Unidad de medición | E5: =+Mensual!F5 -> Meta | F5: =+Mensual!G5 -> Resultado | G5: =+Mensual!H5 -> Nota | H5: =+Mensual!I5 -> Valor ponderado | I5: =+Mensual!J5 -> 0 | J5: =+Mensual!K5 -> 0.25 | K5: =+Mensual!L5 -> 0.5 | ... Q5: =+Mensual!R5 -> 0 | T5: Nota | U5: Nota
A6: =+Mensual!B6 -> 4 | B6: 0.3 | C6: 9. SCORE CARD Grupo EXA | D6: =IF(VLOOKUP($C6,Mensual!$D$6:$G$163,2,0)<0,0,VLOOKUP($C6,Mensual!$D$6:$G$163,2,0)) -> RESULTADO SCORECARD | E6: =IF(VLOOKUP($C6,Mensual!$D$6:$G$163,3,0)<0,0,VLOOKUP($C6,Mensual!$D$6:$G$163,3,0)) -> 1 | F6: =IF(VLOOKUP($C6,Mensual!$D$6:$G$163,4,0)<0,0,VLOOKUP($C6,Mensual!$D$6:$G$163,4,0)) -> 1.0325 | G6: =IF(VLOOKUP($C6,Mensual!$D$6:$H$163,5,0)<0,0,VLOOKUP($C6,Mensual!$D$6:$H$163,5,0)) -> 1.0325 | H6: =+G6*B6 -> 0.30975 | I6: =+Mensual!J6 -> 0 | J6: =+Mensual!K6 -> 0 | K6: =+Mensual!L6 -> 0 | L6: =+Mensual!M6 -> 0
B7: 0.1 | C7: 2.1 Reducir gasto administrativo x% | D7: =IF(VLOOKUP($C7,Mensual!$D$6:$G$163,2,0)<0,0,VLOOKUP($C7,Mensual!$D$6:$G$163,2,0)) -> % | E7: =IF(VLOOKUP($C7,Mensual!$D$6:$G$163,3,0)<0,0,VLOOKUP($C7,Mensual!$D$6:$G$163,3,0)) -> 0.1 | F7: =IF(VLOOKUP($C7,Mensual!$D$6:$G$163,4,0)<0,0,VLOOKUP($C7,Mensual!$D$6:$G$163,4,0)) -> 0.32 | G7: =IF(VLOOKUP($C7,Mensual!$D$6:$H$163,5,0)<0,0,VLOOKUP($C7,Mensual!$D$6:$H$163,5,0)) -> 1 | H7: =+G7*B7 -> 0.1
B8: 0.05 | C8: 3.5 Multas ambientales y fiscales. | D8: =IF(VLOOKUP($C8,Mensual!$D$6:$G$163,2,0)<0,0,VLOOKUP($C8,Mensual!$D$6:$G$163,2,0)) -> 0 | E8: =IF(VLOOKUP($C8,Mensual!$D$6:$G$163,3,0)<0,0,VLOOKUP($C8,Mensual!$D$6:$G$163,3,0)) -> 0 | F8: =IF(VLOOKUP($C8,Mensual!$D$6:$G$163,4,0)<0,0,VLOOKUP($C8,Mensual!$D$6:$G$163,4,0)) -> 0 | G8: =IF(VLOOKUP($C8,Mensual!$D$6:$H$163,5,0)<0,0,VLOOKUP($C8,Mensual!$D$6:$H$163,5,0)) -> 1 | H8: =+G8*B8 -> 0.05
B9: 0.05 | C9: 7. Disminuir el D/E | D9: =IF(VLOOKUP($C9,Mensual!$D$6:$G$163,2,0)<0,0,VLOOKUP($C9,Mensual!$D$6:$G$163,2,0)) -> 0 | E9: =IF(VLOOKUP($C9,Mensual!$D$6:$G$163,3,0)<0,0,VLOOKUP($C9,Mensual!$D$6:$G$163,3,0)) -> 0.05 | F9: =IF(VLOOKUP($C9,Mensual!$D$6:$G$163,4,0)<0,0,VLOOKUP($C9,Mensual!$D$6:$G$163,4,0)) -> 0.05 | G9: =IF(VLOOKUP($C9,Mensual!$D$6:$H$163,5,0)<0,0,VLOOKUP($C9,Mensual!$D$6:$H$163,5,0)) -> 1 | H9: =+G9*B9 -> 0.05
B10: 0.1 | C10: 6. Aumentar el ROA | D10: =IF(VLOOKUP($C10,Mensual!$D$6:$G$163,2,0)<0,0,VLOOKUP($C10,Mensual!$D$6:$G$163,2,0)) -> 0 | E10: =IF(VLOOKUP($C10,Mensual!$D$6:$G$163,3,0)<0,0,VLOOKUP($C10,Mensual!$D$6:$G$163,3,0)) -> 0.05 | F10: =IF(VLOOKUP($C10,Mensual!$D$6:$G$163,4,0)<0,0,VLOOKUP($C10,Mensual!$D$6:$G$163,4,0)) -> 1 | G10: =IF(VLOOKUP($C10,Mensual!$D$6:$H$163,5,0)<0,0,VLOOKUP($C10,Mensual!$D$6:$H$163,5,0)) -> 1 | H10: =+G10*B10 -> 0.1
B11: 0.1 | C11: 3.6 Cierres contables a mas tardar el 6 de cada mes | D11: =IF(VLOOKUP($C11,Mensual!$D$6:$G$163,2,0)<0,0,VLOOKUP($C11,Mensual!$D$6:$G$163,2,0)) -> # de cierres a tiempo | E11: =IF(VLOOKUP($C11,Mensual!$D$6:$G$163,3,0)<0,0,VLOOKUP($C11,Mensual!$D$6:$G$163,3,0)) -> 6 | F11: =IF(VLOOKUP($C11,Mensual!$D$6:$G$163,4,0)<0,0,VLOOKUP($C11,Mensual!$D$6:$G$163,4,0)) -> 6 | G11: =IF(VLOOKUP($C11,Mensual!$D$6:$H$163,5,0)<0,0,VLOOKUP($C11,Mensual!$D$6:$H$163,5,0)) -> 1 | H11: =+G11*B11 -> 0.1
B12: 0.1 | C12: 6.2 Disminuir a 5% el desuso de los chasis (equipos con mas de 30 dias en las yardas) | D12: =IF(VLOOKUP($C12,Mensual!$D$6:$G$163,2,0)<0,0,VLOOKUP($C12,Mensual!$D$6:$G$163,2,0)) -> % | E12: =IF(VLOOKUP($C12,Mensual!$D$6:$G$163,3,0)<0,0,VLOOKUP($C12,Mensual!$D$6:$G$163,3,0)) -> 0.05 | F12: =IF(VLOOKUP($C12,Mensual!$D$6:$G$163,4,0)<0,0,VLOOKUP($C12,Mensual!$D$6:$G$163,4,0)) -> 0.05 | G12: =IF(VLOOKUP($C12,Mensual!$D$6:$H$163,5,0)<0,0,VLOOKUP($C12,Mensual!$D$6:$H$163,5,0)) -> 1 | H12: =+G12*B12 -> 0.1
B13: 0.1 | C13: 7.1 Rotación de cuentas por cobrar. | D13: =IF(VLOOKUP($C13,Mensual!$D$6:$G$163,2,0)<0,0,VLOOKUP($C13,Mensual!$D$6:$G$163,2,0)) -> 0 | E13: =IF(VLOOKUP($C13,Mensual!$D$6:$G$163,3,0)<0,0,VLOOKUP($C13,Mensual!$D$6:$G$163,3,0)) -> 0.1 | F13: =IF(VLOOKUP($C13,Mensual!$D$6:$G$163,4,0)<0,0,VLOOKUP($C13,Mensual!$D$6:$G$163,4,0)) -> 0 | G13: =IF(VLOOKUP($C13,Mensual!$D$6:$H$163,5,0)<0,0,VLOOKUP($C13,Mensual!$D$6:$H$163,5,0)) -> 0 | H13: =+G13*B13 -> 0
B14: 0.1 | C14: 5.16 # de notas de credito mensuales | D14: =IF(VLOOKUP($C14,Mensual!$D$6:$G$163,2,0)<0,0,VLOOKUP($C14,Mensual!$D$6:$G$163,2,0)) -> # notas de credito | E14: =IF(VLOOKUP($C14,Mensual!$D$6:$G$163,3,0)<0,0,VLOOKUP($C14,Mensual!$D$6:$G$163,3,0)) -> 0 | F14: =IF(VLOOKUP($C14,Mensual!$D$6:$G$163,4,0)<0,0,VLOOKUP($C14,Mensual!$D$6:$G$163,4,0)) -> 0 | G14: =IF(VLOOKUP($C14,Mensual!$D$6:$H$163,5,0)<0,0,VLOOKUP($C14,Mensual!$D$6:$H$163,5,0)) -> 0 | H14: =+G14*B14 -> 0
B15: =SUM(B6:B14) -> 1 | H15: =SUM(H6:H14) -> 0.80975
C18: Colaboradores:
C19: Alejandro Garcia
C20: Julio Estevez

Sheet Cecilia
I1: 0.9
C2: Departamento: | D2: Administracion | I2: 80-90%
I3: Menos de 80%
A5: =+Mensual!B5 -> No | B5: =+Mensual!C5 -> Peso | D5: =+Mensual!E5 -> Unidad de medición | E5: =+Mensual!F5 -> Meta | F5: =+Mensual!G5 -> Resultado | G5: =+Mensual!H5 -> Nota | H5: =+Mensual!I5 -> Valor ponderado | I5: =+Mensual!J5 -> 0 | J5: =+Mensual!K5 -> 0.25 | K5: =+Mensual!L5 -> 0.5 | ... Q5: =+Mensual!R5 -> 0 | T5: Nota | U5: Nota
A6: =+Mensual!B6 -> 4 | B6: 0.25 | C6: 9. SCORE CARD Grupo EXA | D6: =IF(VLOOKUP($C6,Mensual!$D$6:$G$163,2,0)<0,0,VLOOKUP($C6,Mensual!$D$6:$G$163,2,0)) -> RESULTADO SCORECARD | E6: =IF(VLOOKUP($C6,Mensual!$D$6:$G$163,3,0)<0,0,VLOOKUP($C6,Mensual!$D$6:$G$163,3,0)) -> 1 | F6: =IF(VLOOKUP($C6,Mensual!$D$6:$G$163,4,0)<0,0,VLOOKUP($C6,Mensual!$D$6:$G$163,4,0)) -> 1.0325 | G6: =IF(VLOOKUP($C6,Mensual!$D$6:$H$163,5,0)<0,0,VLOOKUP($C6,Mensual!$D$6:$H$163,5,0)) -> 1.0325 | H6: =+G6*B6 -> 0.258125 | I6: =+Mensual!J6 -> 0 | J6: =+Mensual!K6 -> 0 | K6: =+Mensual!L6 -> 0 | L6: =+Mensual!M6 -> 0
B7: 0.05 | C7: 2.1 Reducir gasto administrativo x% | D7: =IF(VLOOKUP($C7,Mensual!$D$6:$G$163,2,0)<0,0,VLOOKUP($C7,Mensual!$D$6:$G$163,2,0)) -> % | E7: =IF(VLOOKUP($C7,Mensual!$D$6:$G$163,3,0)<0,0,VLOOKUP($C7,Mensual!$D$6:$G$163,3,0)) -> 0.1 | F7: =IF(VLOOKUP($C7,Mensual!$D$6:$G$163,4,0)<0,0,VLOOKUP($C7,Mensual!$D$6:$G$163,4,0)) -> 0.32 | G7: =IF(VLOOKUP($C7,Mensual!$D$6:$H$163,5,0)<0,0,VLOOKUP($C7,Mensual!$D$6:$H$163,5,0)) -> 1 | H7: =+G7*B7 -> 0.05
B8: 0.05 | C8: 6.1 Aumentar Rotación de inventario. | D8: =IF(VLOOKUP($C8,Mensual!$D$6:$G$163,2,0)<0,0,VLOOKUP($C8,Mensual!$D$6:$G$163,2,0)) -> 0 | E8: =IF(VLOOKUP($C8,Mensual!$D$6:$G$163,3,0)<0,0,VLOOKUP($C8,Mensual!$D$6:$G$163,3,0)) -> 0.05 | F8: =IF(VLOOKUP($C8,Mensual!$D$6:$G$163,4,0)<0,0,VLOOKUP($C8,Mensual!$D$6:$G$163,4,0)) -> 0 | G8: =IF(VLOOKUP($C8,Mensual!$D$6:$H$163,5,0)<0,0,VLOOKUP($C8,Mensual!$D$6:$H$163,5,0)) -> 0 | H8: =+G8*B8 -> 0
B9: 0.2 | C9: 2.3 Reducir Costo por km cabezales propios. | D9: =IF(VLOOKUP($C9,Mensual!$D$6:$G$163,2,0)<0,0,VLOOKUP($C9,Mensual!$D$6:$G$163,2,0)) -> $ | E9: =IF(VLOOKUP($C9,Mensual!$D$6:$G$163,3,0)<0,0,VLOOKUP($C9,Mensual!$D$6:$G$163,3,0)) -> 0.05 | F9: =IF(VLOOKUP($C9,Mensual!$D$6:$G$163,4,0)<0,0,VLOOKUP($C9,Mensual!$D$6:$G$163,4,0)) -> 0.6 | G9: =IF(VLOOKUP($C9,Mensual!$D$6:$H$163,5,0)<0,0,VLOOKUP($C9,Mensual!$D$6:$H$163,5,0)) -> 1 | H9: =+G9*B9 -> 0.2
B10: 0.2 | C10: 5.2 Productividad cabezales Flota Nueva | D10: =IF(VLOOKUP($C10,Mensual!$D$6:$G$163,2,0)<0,0,VLOOKUP($C10,Mensual!$D$6:$G$163,2,0)) -> 0 | E10: =IF(VLOOKUP($C10,Mensual!$D$6:$G$163,3,0)<0,0,VLOOKUP($C10,Mensual!$D$6:$G$163,3,0)) -> 4500 | F10: =IF(VLOOKUP($C10,Mensual!$D$6:$G$163,4,0)<0,0,VLOOKUP($C10,Mensual!$D$6:$G$163,4,0)) -> 4782 | G10: =IF(VLOOKUP($C10,Mensual!$D$6:$H$163,5,0)<0,0,VLOOKUP($C10,Mensual!$D$6:$H$163,5,0)) -> 1 | H10: =+G10*B10 -> 0.2
B11: 0.1 | C11: 6.5 Disminuir a 0-1 el desuso de cabezales propios | D11: =IF(VLOOKUP($C11,Mensual!$D$6:$G$163,2,0)<0,0,VLOOKUP($C11,Mensual!$D$6:$G$163,2,0)) -> cabezal | E11: =IF(VLOOKUP($C11,Mensual!$D$6:$G$163,3,0)<0,0,VLOOKUP($C11,Mensual!$D$6:$G$163,3,0)) -> 1 | F11: =IF(VLOOKUP($C11,Mensual!$D$6:$G$163,4,0)<0,0,VLOOKUP($C11,Mensual!$D$6:$G$163,4,0)) -> 1 | G11: =IF(VLOOKUP($C11,Mensual!$D$6:$H$163,5,0)<0,0,VLOOKUP($C11,Mensual!$D$6:$H$163,5,0)) -> 0 | H11: =+G11*B11 -> 0
B12: 0.05 | C12: 7. Disminuir el D/E | D12: =IF(VLOOKUP($C12,Mensual!$D$6:$G$163,2,0)<0,0,VLOOKUP($C12,Mensual!$D$6:$G$163,2,0)) -> 0 | E12: =IF(VLOOKUP($C12,Mensual!$D$6:$G$163,3,0)<0,0,VLOOKUP($C12,Mensual!$D$6:$G$163,3,0)) -> 0.05 | F12: =IF(VLOOKUP($C12,Mensual!$D$6:$G$163,4,0)<0,0,VLOOKUP($C12,Mensual!$D$6:$G$163,4,0)) -> 0.05 | G12: =IF(VLOOKUP($C12,Mensual!$D$6:$H$163,5,0)<0,0,VLOOKUP($C12,Mensual!$D$6:$H$163,5,0)) -> 1 | H12: =+G12*B12 -> 0.05
B13: 0.05 | C13: 6. Aumentar el ROA | D13: =IF(VLOOKUP($C13,Mensual!$D$6:$G$163,2,0)<0,0,VLOOKUP($C13,Mensual!$D$6:$G$163,2,0)) -> 0 | E13: =IF(VLOOKUP($C13,Mensual!$D$6:$G$163,3,0)<0,0,VLOOKUP($C13,Mensual!$D$6:$G$163,3,0)) -> 0.05 | F13: =IF(VLOOKUP($C13,Mensual!$D$6:$G$163,4,0)<0,0,VLOOKUP($C13,Mensual!$D$6:$G$163,4,0)) -> 1 | G13: =IF(VLOOKUP($C13,Mensual!$D$6:$H$163,5,0)<0,0,VLOOKUP($C13,Mensual!$D$6:$H$163,5,0)) -> 1 | H13: =+G13*B13 -> 0.05
B14: 0.05 | C14: 3.6 Cierres contables a mas tardar el 6 de cada mes | D14: =IF(VLOOKUP($C14,Mensual!$D$6:$G$163,2,0)<0,0,VLOOKUP($C14,Mensual!$D$6:$G$163,2,0)) -> # de cierres a tiempo | E14: =IF(VLOOKUP($C14,Mensual!$D$6:$G$163,3,0)<0,0,VLOOKUP($C14,Mensual!$D$6:$G$163,3,0)) -> 6 | F14: =IF(VLOOKUP($C14,Mensual!$D$6:$G$163,4,0)<0,0,VLOOKUP($C14,Mensual!$D$6:$G$163,4,0)) -> 6 | G14: =IF(VLOOKUP($C14,Mensual!$D$6:$H$163,5,0)<0,0,VLOOKUP($C14,Mensual!$D$6:$H$163,5,0)) -> 1 | H14: =+G14*B14 -> 0.05
B15: =SUM(B6:B14) -> 1 | H15: =SUM(H6:H14) -> 0.858125
C18: Colaboradores:
C19: Cecilia Galeano

Sheet Compras
I1: 0.9
C2: Departamento: | D2: Administracion | I2: 80-90%
I3: Menos de 80%
A5: =+Mensual!B5 -> No | B5: =+Mensual!C5 -> Peso | D5: =+Mensual!E5 -> Unidad de medición | E5: =+Mensual!F5 -> Meta | F5: =+Mensual!G5 -> Resultado | G5: =+Mensual!H5 -> Nota | H5: =+Mensual!I5 -> Valor ponderado | I5: =+Mensual!J5 -> 0 | J5: =+Mensual!K5 -> 0.25 | K5: =+Mensual!L5 -> 0.5 | ... Q5: =+Mensual!R5 -> 0 | T5: Nota | U5: Nota
A6: =+Mensual!B6 -> 4 | B6: 0.25 | C6: 9. SCORE CARD Grupo EXA | D6: =IF(VLOOKUP($C6,Mensual!$D$6:$G$163,2,0)<0,0,VLOOKUP($C6,Mensual!$D$6:$G$163,2,0)) -> RESULTADO SCORECARD | E6: =IF(VLOOKUP($C6,Mensual!$D$6:$G$163,3,0)<0,0,VLOOKUP($C6,Mensual!$D$6:$G$163,3,0)) -> 1 | F6: =IF(VLOOKUP($C6,Mensual!$D$6:$G$163,4,0)<0,0,VLOOKUP($C6,Mensual!$D$6:$G$163,4,0)) -> 1.0325 | G6: =IF(VLOOKUP($C6,Mensual!$D$6:$H$163,5,0)<0,0,VLOOKUP($C6,Mensual!$D$6:$H$163,5,0)) -> 1.0325 | H6: =+G6*B6 -> 0.258125 | I6: =+Mensual!J6 -> 0 | J6: =+Mensual!K6 -> 0 | K6: =+Mensual!L6 -> 0 | L6: =+Mensual!M6 -> 0
B7: 0.1 | C7: 2.1 Reducir gasto administrativo x% | D7: =IF(VLOOKUP($C7,Mensual!$D$6:$G$163,2,0)<0,0,VLOOKUP($C7,Mensual!$D$6:$G$163,2,0)) -> % | E7: =IF(VLOOKUP($C7,Mensual!$D$6:$G$163,3,0)<0,0,VLOOKUP($C7,Mensual!$D$6:$G$163,3,0)) -> 0.1 | F7: =IF(VLOOKUP($C7,Mensual!$D$6:$G$163,4,0)<0,0,VLOOKUP($C7,Mensual!$D$6:$G$163,4,0)) -> 0.32 | G7: =IF(VLOOKUP($C7,Mensual!$D$6:$H$163,5,0)<0,0,VLOOKUP($C7,Mensual!$D$6:$H$163,5,0)) -> 1 | H7: =+G7*B7 -> 0.1
B8: 0.2 | C8: 6.1 Aumentar Rotación de inventario. | D8: =IF(VLOOKUP($C8,Mensual!$D$6:$G$163,2,0)<0,0,VLOOKUP($C8,Mensual!$D$6:$G$163,2,0)) -> 0 | E8: =IF(VLOOKUP($C8,Mensual!$D$6:$G$163,3,0)<0,0,VLOOKUP($C8,Mensual!$D$6:$G$163,3,0)) -> 0.05 | F8: =IF(VLOOKUP($C8,Mensual!$D$6:$G$163,4,0)<0,0,VLOOKUP($C8,Mensual!$D$6:$G$163,4,0)) -> 0 | G8: =IF(VLOOKUP($C8,Mensual!$D$6:$H$163,5,0)<0,0,VLOOKUP($C8,Mensual!$D$6:$H$163,5,0)) -> 0 | H8: =+G8*B8 -> 0
B9: 0.1 | C9: 2.3 Reducir Costo por km cabezales propios. | D9: =IF(VLOOKUP($C9,Mensual!$D$6:$G$163,2,0)<0,0,VLOOKUP($C9,Mensual!$D$6:$G$163,2,0)) -> $ | E9: =IF(VLOOKUP($C9,Mensual!$D$6:$G$163,3,0)<0,0,VLOOKUP($C9,Mensual!$D$6:$G$163,3,0)) -> 0.05 | F9: =IF(VLOOKUP($C9,Mensual!$D$6:$G$163,4,0)<0,0,VLOOKUP($C9,Mensual!$D$6:$G$163,4,0)) -> 0.6 | G9: =IF(VLOOKUP($C9,Mensual!$D$6:$H$163,5,0)<0,0,VLOOKUP($C9,Mensual!$D$6:$H$163,5,0)) -> 1 | H9: =+G9*B9 -> 0.1
B10: 0.05 | C10: 5.2 Productividad cabezales Flota Nueva | D10: =IF(VLOOKUP($C10,Mensual!$D$6:$G$163,2,0)<0,0,VLOOKUP($C10,Mensual!$D$6:$G$163,2,0)) -> 0 | E10: =IF(VLOOKUP($C10,Mensual!$D$6:$G$163,3,0)<0,0,VLOOKUP($C10,Mensual!$D$6:$G$163,3,0)) -> 4500 | F10: =IF(VLOOKUP($C10,Mensual!$D$6:$G$163,4,0)<0,0,VLOOKUP($C10,Mensual!$D$6:$G$163,4,0)) -> 4782 | G10: =IF(VLOOKUP($C10,Mensual!$D$6:$H$163,5,0)<0,0,VLOOKUP($C10,Mensual!$D$6:$H$163,5,0)) -> 1 | H10: =+G10*B10 -> 0.05
B11: 0.05 | C11: 6.5 Disminuir a 0-1 el desuso de cabezales propios | D11: =IF(VLOOKUP($C11,Mensual!$D$6:$G$163,2,0)<0,0,VLOOKUP($C11,Mensual!$D$6:$G$163,2,0)) -> cabezal | E11: =IF(VLOOKUP($C11,Mensual!$D$6:$G$163,3,0)<0,0,VLOOKUP($C11,Mensual!$D$6:$G$163,3,0)) -> 1 | F11: =IF(VLOOKUP($C11,Mensual!$D$6:$G$163,4,0)<0,0,VLOOKUP($C11,Mensual!$D$6:$G$163,4,0)) -> 1 | G11: =IF(VLOOKUP($C11,Mensual!$D$6:$H$163,5,0)<0,0,VLOOKUP($C11,Mensual!$D$6:$H$163,5,0)) -> 0 | H11: =+G11*B11 -> 0
B12: 0.025 | C12: 7. Disminuir el D/E | D12: =IF(VLOOKUP($C12,Mensual!$D$6:$G$163,2,0)<0,0,VLOOKUP($C12,Mensual!$D$6:$G$163,2,0)) -> 0 | E12: =IF(VLOOKUP($C12,Mensual!$D$6:$G$163,3,0)<0,0,VLOOKUP($C12,Mensual!$D$6:$G$163,3,0)) -> 0.05 | F12: =IF(VLOOKUP($C12,Mensual!$D$6:$G$163,4,0)<0,0,VLOOKUP($C12,Mensual!$D$6:$G$163,4,0)) -> 0.05 | G12: =IF(VLOOKUP($C12,Mensual!$D$6:$H$163,5,0)<0,0,VLOOKUP($C12,Mensual!$D$6:$H$163,5,0)) -> 1 | H12: =+G12*B12 -> 0.025
B13: 0.1 | C13: 2.2 Reducir costo de M&R de chasis propios | D13: =IF(VLOOKUP($C13,Mensual!$D$6:$G$163,2,0)<0,0,VLOOKUP($C13,Mensual!$D$6:$G$163,2,0)) -> $/km | E13: =IF(VLOOKUP($C13,Mensual!$D$6:$G$163,3,0)<0,0,VLOOKUP($C13,Mensual!$D$6:$G$163,3,0)) -> 0.05 | F13: =IF(VLOOKUP($C13,Mensual!$D$6:$G$163,4,0)<0,0,VLOOKUP($C13,Mensual!$D$6:$G$163,4,0)) -> 0.09 | G13: =IF(VLOOKUP($C13,Mensual!$D$6:$H$163,5,0)<0,0,VLOOKUP($C13,Mensual!$D$6:$H$163,5,0)) -> 0 | H13: =+G13*B13 -> 0
B14: 0.025 | C14: 6. Aumentar el ROA | D14: =IF(VLOOKUP($C14,Mensual!$D$6:$G$163,2,0)<0,0,VLOOKUP($C14,Mensual!$D$6:$G$163,2,0)) -> 0 | E14: =IF(VLOOKUP($C14,Mensual!$D$6:$G$163,3,0)<0,0,VLOOKUP($C14,Mensual!$D$6:$G$163,3,0)) -> 0.05 | F14: =IF(VLOOKUP($C14,Mensual!$D$6:$G$163,4,0)<0,0,VLOOKUP($C14,Mensual!$D$6:$G$163,4,0)) -> 1 | G14: =IF(VLOOKUP($C14,Mensual!$D$6:$H$163,5,0)<0,0,VLOOKUP($C14,Mensual!$D$6:$H$163,5,0)) -> 1 | H14: =+G14*B14 -> 0.025
B15: 0.1 | C15: 3.6 Cierres contables a mas tardar el 6 de cada mes | D15: =IF(VLOOKUP($C15,Mensual!$D$6:$G$163,2,0)<0,0,VLOOKUP($C15,Mensual!$D$6:$G$163,2,0)) -> # de cierres a tiempo | E15: =IF(VLOOKUP($C15,Mensual!$D$6:$G$163,3,0)<0,0,VLOOKUP($C15,Mensual!$D$6:$G$163,3,0)) -> 6 | F15: =IF(VLOOKUP($C15,Mensual!$D$6:$G$163,4,0)<0,0,VLOOKUP($C15,Mensual!$D$6:$G$163,4,0)) -> 6 | G15: =IF(VLOOKUP($C15,Mensual!$D$6:$H$163,5,0)<0,0,VLOOKUP($C15,Mensual!$D$6:$H$163,5,0)) -> 1 | H15: =+G15*B15 -> 0.1
B16: =SUM(B6:B15) -> 1 | H16: =SUM(H6:H15) -> 0.658125
C19: Colaboradores:
C20: Emilia Pineda
C21: Juan Manuel

Sheet Tesoreria
I1: 0.9
C2: Departamento: | D2: Administracion | I2: 80-90%
I3: Menos de 80%
A5: =+Mensual!B5 -> No | B5: =+Mensual!C5 -> Peso | D5: =+Mensual!E5 -> Unidad de medición | E5: =+Mensual!F5 -> Meta | F5: =+Mensual!G5 -> Resultado | G5: =+Mensual!H5 -> Nota | H5: =+Mensual!I5 -> Valor ponderado | I5: =+Mensual!J5 -> 0 | J5: =+Mensual!K5 -> 0.25 | K5: =+Mensual!L5 -> 0.5 | ... Q5: =+Mensual!R5 -> 0 | T5: Nota | U5: Nota
A6: =+Mensual!B6 -> 4 | B6: 0.3 | C6: 9. SCORE CARD Grupo EXA | D6: =IF(VLOOKUP($C6,Mensual!$D$6:$G$163,2,0)<0,0,VLOOKUP($C6,Mensual!$D$6:$G$163,2,0)) -> RESULTADO SCORECARD | E6: =IF(VLOOKUP($C6,Mensual!$D$6:$G$163,3,0)<0,0,VLOOKUP($C6,Mensual!$D$6:$G$163,3,0)) -> 1 | F6: =IF(VLOOKUP($C6,Mensual!$D$6:$G$163,4,0)<0,0,VLOOKUP($C6,Mensual!$D$6:$G$163,4,0)) -> 1.0325 | G6: =IF(VLOOKUP($C6,Mensual!$D$6:$H$163,5,0)<0,0,VLOOKUP($C6,Mensual!$D$6:$H$163,5,0)) -> 1.0325 | H6: =+G6*B6 -> 0.30975 | I6: =+Mensual!J6 -> 0 | J6: =+Mensual!K6 -> 0 | K6: =+Mensual!L6 -> 0 | L6: =+Mensual!M6 -> 0
B7: 0.1 | C7: 2.1 Reducir gasto administrativo x% | D7: =IF(VLOOKUP($C7,Mensual!$D$6:$G$163,2,0)<0,0,VLOOKUP($C7,Mensual!$D$6:$G$163,2,0)) -> % | E7: =IF(VLOOKUP($C7,Mensual!$D$6:$G$163,3,0)<0,0,VLOOKUP($C7,Mensual!$D$6:$G$163,3,0)) -> 0.1 | F7: =IF(VLOOKUP($C7,Mensual!$D$6:$G$163,4,0)<0,0,VLOOKUP($C7,Mensual!$D$6:$G$163,4,0)) -> 0.32 | G7: =IF(VLOOKUP($C7,Mensual!$D$6:$H$163,5,0)<0,0,VLOOKUP($C7,Mensual!$D$6:$H$163,5,0)) -> 1 | H7: =+G7*B7 -> 0.1
B8: 0.05 | C8: 3.5 Multas ambientales y fiscales. | D8: =IF(VLOOKUP($C8,Mensual!$D$6:$G$163,2,0)<0,0,VLOOKUP($C8,Mensual!$D$6:$G$163,2,0)) -> 0 | E8: =IF(VLOOKUP($C8,Mensual!$D$6:$G$163,3,0)<0,0,VLOOKUP($C8,Mensual!$D$6:$G$163,3,0)) -> 0 | F8: =IF(VLOOKUP($C8,Mensual!$D$6:$G$163,4,0)<0,0,VLOOKUP($C8,Mensual!$D$6:$G$163,4,0)) -> 0 | G8: =IF(VLOOKUP($C8,Mensual!$D$6:$H$163,5,0)<0,0,VLOOKUP($C8,Mensual!$D$6:$H$163,5,0)) -> 1 | H8: =+G8*B8 -> 0.05
B9: 0.05 | C9: 6.1 Aumentar Rotación de inventario. | D9: =IF(VLOOKUP($C9,Mensual!$D$6:$G$163,2,0)<0,0,VLOOKUP($C9,Mensual!$D$6:$G$163,2,0)) -> 0 | E9: =IF(VLOOKUP($C9,Mensual!$D$6:$G$163,3,0)<0,0,VLOOKUP($C9,Mensual!$D$6:$G$163,3,0)) -> 0.05 | F9: =IF(VLOOKUP($C9,Mensual!$D$6:$G$163,4,0)<0,0,VLOOKUP($C9,Mensual!$D$6:$G$163,4,0)) -> 0 | G9: =IF(VLOOKUP($C9,Mensual!$D$6:$H$163,5,0)<0,0,VLOOKUP($C9,Mensual!$D$6:$H$163,5,0)) -> 0 | H9: =+G9*B9 -> 0
B10: 0.15 | C10: 7.1 Rotación de cuentas por cobrar. | D10: =IF(VLOOKUP($C10,Mensual!$D$6:$G$163,2,0)<0,0,VLOOKUP($C10,Mensual!$D$6:$G$163,2,0)) -> 0 | E10: =IF(VLOOKUP($C10,Mensual!$D$6:$G$163,3,0)<0,0,VLOOKUP($C10,Mensual!$D$6:$G$163,3,0)) -> 0.1 | F10: =IF(VLOOKUP($C10,Mensual!$D$6:$G$163,4,0)<0,0,VLOOKUP($C10,Mensual!$D$6:$G$163,4,0)) -> 0 | G10: =IF(VLOOKUP($C10,Mensual!$D$6:$H$163,5,0)<0,0,VLOOKUP($C10,Mensual!$D$6:$H$163,5,0)) -> 0 | H10: =+G10*B10 -> 0
B11: 0.1 | C11: 7. Disminuir el D/E | D11: =IF(VLOOKUP($C11,Mensual!$D$6:$G$163,2,0)<0,0,VLOOKUP($C11,Mensual!$D$6:$G$163,2,0)) -> 0 | E11: =IF(VLOOKUP($C11,Mensual!$D$6:$G$163,3,0)<0,0,VLOOKUP($C11,Mensual!$D$6:$G$163,3,0)) -> 0.05 | F11: =IF(VLOOKUP($C11,Mensual!$D$6:$G$163,4,0)<0,0,VLOOKUP($C11,Mensual!$D$6:$G$163,4,0)) -> 0.05 | G11: =IF(VLOOKUP($C11,Mensual!$D$6:$H$163,5,0)<0,0,VLOOKUP($C11,Mensual!$D$6:$H$163,5,0)) -> 1 | H11: =+G11*B11 -> 0.1
B12: 0.1 | C12: 6. Aumentar el ROA | D12: =IF(VLOOKUP($C12,Mensual!$D$6:$G$163,2,0)<0,0,VLOOKUP($C12,Mensual!$D$6:$G$163,2,0)) -> 0 | E12: =IF(VLOOKUP($C12,Mensual!$D$6:$G$163,3,0)<0,0,VLOOKUP($C12,Mensual!$D$6:$G$163,3,0)) -> 0.05 | F12: =IF(VLOOKUP($C12,Mensual!$D$6:$G$163,4,0)<0,0,VLOOKUP($C12,Mensual!$D$6:$G$163,4,0)) -> 1 | G12: =IF(VLOOKUP($C12,Mensual!$D$6:$H$163,5,0)<0,0,VLOOKUP($C12,Mensual!$D$6:$H$163,5,0)) -> 1 | H12: =+G12*B12 -> 0.1
B13: 0.15 | C13: 3.6 Cierres contables a mas tardar el 6 de cada mes | D13: =IF(VLOOKUP($C13,Mensual!$D$6:$G$163,2,0)<0,0,VLOOKUP($C13,Mensual!$D$6:$G$163,2,0)) -> # de cierres a tiempo | E13: =IF(VLOOKUP($C13,Mensual!$D$6:$G$163,3,0)<0,0,VLOOKUP($C13,Mensual!$D$6:$G$163,3,0)) -> 6 | F13: =IF(VLOOKUP($C13,Mensual!$D$6:$G$163,4,0)<0,0,VLOOKUP($C13,Mensual!$D$6:$G$163,4,0)) -> 6 | G13: =IF(VLOOKUP($C13,Mensual!$D$6:$H$163,5,0)<0,0,VLOOKUP($C13,Mensual!$D$6:$H$163,5,0)) -> 1 | H13: =+G13*B13 -> 0.15
B14: =SUM(B6:B13) -> 1 | H14: =SUM(H6:H13) -> 0.80975
C17: Colaboradores:
C18: Suley Canales
C19: Bryan Lopez
C20: Carolina Vargas

Sheet Lorenzo Varela
I1: 0.9
C2: Colaborador: | D2: Lorenzo Varela | I2: 80-90%
C3: Departamento: | D3: Predio_Puerto_Cortes | I3: Menos de 80%
A5: =+Mensual!B5 -> No | B5: =+Mensual!C5 -> Peso | D5: =+Mensual!E5 -> Unidad de medición | E5: =+Mensual!F5 -> Meta | F5: =+Mensual!G5 -> Resultado | G5: =+Mensual!H5 -> Nota | H5: =+Mensual!I5 -> Valor ponderado | I5: =+Mensual!J5 -> 0 | J5: =+Mensual!K5 -> 0.25 | K5: =+Mensual!L5 -> 0.5 | ... Q5: =+Mensual!R5 -> 0 | T5: Nota | U5: Nota
A6: =+Mensual!B6 -> 4 | B6: 0.4 | C6: 9. SCORE CARD Grupo EXA | D6: =IF(VLOOKUP($C6,Mensual!$D$6:$G$163,2,0)<0,0,VLOOKUP($C6,Mensual!$D$6:$G$163,2,0)) -> RESULTADO SCORECARD | E6: =IF(VLOOKUP($C6,Mensual!$D$6:$G$163,3,0)<0,0,VLOOKUP($C6,Mensual!$D$6:$G$163,3,0)) -> 1 | F6: =IF(VLOOKUP($C6,Mensual!$D$6:$G$163,4,0)<0,0,VLOOKUP($C6,Mensual!$D$6:$G$163,4,0)) -> 1.0325 | G6: =IF(VLOOKUP($C6,Mensual!$D$6:$H$163,5,0)<0,0,VLOOKUP($C6,Mensual!$D$6:$H$163,5,0)) -> 1.0325 | H6: =+G6*B6 -> 0.413 | I6: =+Mensual!J6 -> 0 | J6: =+Mensual!K6 -> 0 | K6: =+Mensual!L6 -> 0 | L6: =+Mensual!M6 -> 0
B7: 0.05 | C7: 1.14 Incrementar gate out de contenedores Puerto Cortés | D7: =IF(VLOOKUP($C7,Mensual!$D$6:$G$135,2,0)<0,0,VLOOKUP($C7,Mensual!$D$6:$G$135,2,0)) -> Gate | E7: =IF(VLOOKUP($C7,Mensual!$D$6:$G$163,3,0)<0,0,VLOOKUP($C7,Mensual!$D$6:$G$163,3,0)) -> 0.2 | F7: =IF(VLOOKUP($C7,Mensual!$D$6:$G$163,4,0)<0,0,VLOOKUP($C7,Mensual!$D$6:$G$163,4,0)) -> 0 | G7: =IF(VLOOKUP($C7,Mensual!$D$6:$H$163,5,0)<0,0,VLOOKUP($C7,Mensual!$D$6:$H$163,5,0)) -> 0 | H7: =+G7*B7 -> 0
B8: 0.1 | C8: 2.9 Reducir Costo administrativo Puerto Cortés con relacion al año anterior | D8: =IF(VLOOKUP($C8,Mensual!$D$6:$G$135,2,0)<0,0,VLOOKUP($C8,Mensual!$D$6:$G$135,2,0)) -> 0 | E8: =IF(VLOOKUP($C8,Mensual!$D$6:$G$163,3,0)<0,0,VLOOKUP($C8,Mensual!$D$6:$G$163,3,0)) -> 0.05 | F8: =IF(VLOOKUP($C8,Mensual!$D$6:$G$163,4,0)<0,0,VLOOKUP($C8,Mensual!$D$6:$G$163,4,0)) -> 0 | G8: =IF(VLOOKUP($C8,Mensual!$D$6:$H$163,5,0)<0,0,VLOOKUP($C8,Mensual!$D$6:$H$163,5,0)) -> 0 | H8: =+G8*B8 -> 0
B9: 0.05 | C9: 2.13 Reducir Costo de M&R por contenedor Puerto Cortes | D9: =IF(VLOOKUP($C9,Mensual!$D$6:$G$135,2,0)<0,0,VLOOKUP($C9,Mensual!$D$6:$G$135,2,0)) -> $/contenedor | E9: =IF(VLOOKUP($C9,Mensual!$D$6:$G$163,3,0)<0,0,VLOOKUP($C9,Mensual!$D$6:$G$163,3,0)) -> 0.1 | F9: =IF(VLOOKUP($C9,Mensual!$D$6:$G$163,4,0)<0,0,VLOOKUP($C9,Mensual!$D$6:$G$163,4,0)) -> 0 | G9: =IF(VLOOKUP($C9,Mensual!$D$6:$H$163,5,0)<0,0,VLOOKUP($C9,Mensual!$D$6:$H$163,5,0)) -> 0 | H9: =+G9*B9 -> 0
B10: 0.05 | C10: 2.14 Reducir costo máquinas (incluye mulita y containers handler) Puerto Cortes | D10: =IF(VLOOKUP($C10,Mensual!$D$6:$G$135,2,0)<0,0,VLOOKUP($C10,Mensual!$D$6:$G$135,2,0)) -> $/contenedor | E10: =IF(VLOOKUP($C10,Mensual!$D$6:$G$163,3,0)<0,0,VLOOKUP($C10,Mensual!$D$6:$G$163,3,0)) -> 0.1 | F10: =IF(VLOOKUP($C10,Mensual!$D$6:$G$163,4,0)<0,0,VLOOKUP($C10,Mensual!$D$6:$G$163,4,0)) -> 0 | G10: =IF(VLOOKUP($C10,Mensual!$D$6:$H$163,5,0)<0,0,VLOOKUP($C10,Mensual!$D$6:$H$163,5,0)) -> 0 | H10: =+G10*B10 -> 0
B11: 0.05 | C11: 2.18 Reducir M&R gensets $ /genset activo 10% | D11: =IF(VLOOKUP($C11,Mensual!$D$6:$G$135,2,0)<0,0,VLOOKUP($C11,Mensual!$D$6:$G$135,2,0)) -> dolares | E11: =IF(VLOOKUP($C11,Mensual!$D$6:$G$163,3,0)<0,0,VLOOKUP($C11,Mensual!$D$6:$G$163,3,0)) -> 0.1 | F11: =IF(VLOOKUP($C11,Mensual!$D$6:$G$163,4,0)<0,0,VLOOKUP($C11,Mensual!$D$6:$G$163,4,0)) -> 4.66 | G11: =IF(VLOOKUP($C11,Mensual!$D$6:$H$163,5,0)<0,0,VLOOKUP($C11,Mensual!$D$6:$H$163,5,0)) -> 0 | H11: =+G11*B11 -> 0
B12: 0.05 | C12: 3. Cero incidentes mayores de seguridad y sostenibilidad | D12: =IF(VLOOKUP($C12,Mensual!$D$6:$G$135,2,0)<0,0,VLOOKUP($C12,Mensual!$D$6:$G$135,2,0)) -> 0 | E12: =IF(VLOOKUP($C12,Mensual!$D$6:$G$163,3,0)<0,0,VLOOKUP($C12,Mensual!$D$6:$G$163,3,0)) -> 1 | F12: =IF(VLOOKUP($C12,Mensual!$D$6:$G$163,4,0)<0,0,VLOOKUP($C12,Mensual!$D$6:$G$163,4,0)) -> 1 | G12: =IF(VLOOKUP($C12,Mensual!$D$6:$H$163,5,0)<0,0,VLOOKUP($C12,Mensual!$D$6:$H$163,5,0)) -> 1 | H12: =+G12*B12 -> 0.05
B13: 0.05 | C13: 5.11 # de fallas operativas adjudicables al predio (Incluye rescates, rechazos) Puerto Cortes | D13: =IF(VLOOKUP($C13,Mensual!$D$6:$G$135,2,0)<0,0,VLOOKUP($C13,Mensual!$D$6:$G$135,2,0)) -> # de fallas | E13: =IF(VLOOKUP($C13,Mensual!$D$6:$G$163,3,0)<0,0,VLOOKUP($C13,Mensual!$D$6:$G$163,3,0)) -> 1 | F13: =IF(VLOOKUP($C13,Mensual!$D$6:$G$163,4,0)<0,0,VLOOKUP($C13,Mensual!$D$6:$G$163,4,0)) -> 0 | G13: =IF(VLOOKUP($C13,Mensual!$D$6:$H$163,5,0)<0,0,VLOOKUP($C13,Mensual!$D$6:$H$163,5,0)) -> 1 | H13: =+G13*B13 -> 0.05
B14: 0.05 | C14: 6.2.1 Disminuir a 5% el desuso de los equipos Puerto Cortés (equipos con mas de 30 dias en yarda) | D14: =IF(VLOOKUP($C14,Mensual!$D$6:$G$135,2,0)<0,0,VLOOKUP($C14,Mensual!$D$6:$G$135,2,0)) -> Equipos | E14: =IF(VLOOKUP($C14,Mensual!$D$6:$G$163,3,0)<0,0,VLOOKUP($C14,Mensual!$D$6:$G$163,3,0)) -> 30 | F14: =IF(VLOOKUP($C14,Mensual!$D$6:$G$163,4,0)<0,0,VLOOKUP($C14,Mensual!$D$6:$G$163,4,0)) -> 45 | G14: =IF(VLOOKUP($C14,Mensual!$D$6:$H$163,5,0)<0,0,VLOOKUP($C14,Mensual!$D$6:$H$163,5,0)) -> 0 | H14: =+G14*B14 -> 0
B15: 0.05 | C15: 6.4 No exceder a 5 equipos en desuso generadores | D15: =IF(VLOOKUP($C15,Mensual!$D$6:$G$135,2,0)<0,0,VLOOKUP($C15,Mensual!$D$6:$G$135,2,0)) -> generadores | E15: =IF(VLOOKUP($C15,Mensual!$D$6:$G$163,3,0)<0,0,VLOOKUP($C15,Mensual!$D$6:$G$163,3,0)) -> 1 | F15: =IF(VLOOKUP($C15,Mensual!$D$6:$G$163,4,0)<0,0,VLOOKUP($C15,Mensual!$D$6:$G$163,4,0)) -> 44 | G15: =IF(VLOOKUP($C15,Mensual!$D$6:$H$163,5,0)<0,0,VLOOKUP($C15,Mensual!$D$6:$H$163,5,0)) -> 0 | H15: =+G15*B15 -> 0
B16: 0.1 | C16: 2.2 Reducir costo de M&R de chasis propios | D16: =IF(VLOOKUP($C16,Mensual!$D$6:$G$135,2,0)<0,0,VLOOKUP($C16,Mensual!$D$6:$G$135,2,0)) -> $/km | E16: =IF(VLOOKUP($C16,Mensual!$D$6:$G$163,3,0)<0,0,VLOOKUP($C16,Mensual!$D$6:$G$163,3,0)) -> 0.05 | F16: =IF(VLOOKUP($C16,Mensual!$D$6:$G$163,4,0)<0,0,VLOOKUP($C16,Mensual!$D$6:$G$163,4,0)) -> 0.09 | G16: =IF(VLOOKUP($C16,Mensual!$D$6:$H$163,5,0)<0,0,VLOOKUP($C16,Mensual!$D$6:$H$163,5,0)) -> 0 | H16: =+G16*B16 -> 0
B17: =SUM(B6:B16) -> 1 | H17: =SUM(H6:H16) -> 0.513 | I17: =+B17-B18 -> 0.85
B18: =+B8+B10 -> 0.15 | F18: Nota ponderada. | H18: =+H17/I17 -> 0.60352941

Sheet Puerto Cortes
I1: 0.9
C2: Colaborador: | D2: Lorenzo Varela | I2: 80-90%
C3: Departamento: | D3: Predio_Puerto_Cortes | I3: Menos de 80%
A5: =+Mensual!B5 -> No | B5: =+Mensual!C5 -> Peso | D5: =+Mensual!E5 -> Unidad de medición | E5: =+Mensual!F5 -> Meta | F5: =+Mensual!G5 -> Resultado | G5: =+Mensual!H5 -> Nota | H5: =+Mensual!I5 -> Valor ponderado | I5: =+Mensual!J5 -> 0 | J5: =+Mensual!K5 -> 0.25 | K5: =+Mensual!L5 -> 0.5 | ... Q5: =+Mensual!R5 -> 0 | T5: Nota | U5: Nota
A6: =+Mensual!B6 -> 4 | B6: 0.1 | C6: 9. SCORE CARD Grupo EXA | D6: =IF(VLOOKUP($C6,Mensual!$D$6:$G$163,2,0)<0,0,VLOOKUP($C6,Mensual!$D$6:$G$163,2,0)) -> RESULTADO SCORECARD | E6: =IF(VLOOKUP($C6,Mensual!$D$6:$G$163,3,0)<0,0,VLOOKUP($C6,Mensual!$D$6:$G$163,3,0)) -> 1 | F6: =IF(VLOOKUP($C6,Mensual!$D$6:$G$163,4,0)<0,0,VLOOKUP($C6,Mensual!$D$6:$G$163,4,0)) -> 1.0325 | G6: =IF(VLOOKUP($C6,Mensual!$D$6:$H$163,5,0)<0,0,VLOOKUP($C6,Mensual!$D$6:$H$163,5,0)) -> 1.0325 | H6: =+G6*B6 -> 0.10325 | I6: =+Mensual!J6 -> 0 | J6: =+Mensual!K6 -> 0 | K6: =+Mensual!L6 -> 0 | L6: =+Mensual!M6 -> 0
B7: 0.08 | C7: 1.14 Incrementar gate out de contenedores Puerto Cortés | D7: =IF(VLOOKUP($C7,Mensual!$D$6:$G$135,2,0)<0,0,VLOOKUP($C7,Mensual!$D$6:$G$135,2,0)) -> Gate | E7: =IF(VLOOKUP($C7,Mensual!$D$6:$G$163,3,0)<0,0,VLOOKUP($C7,Mensual!$D$6:$G$163,3,0)) -> 0.2 | F7: =IF(VLOOKUP($C7,Mensual!$D$6:$G$163,4,0)<0,0,VLOOKUP($C7,Mensual!$D$6:$G$163,4,0)) -> 0 | G7: =IF(VLOOKUP($C7,Mensual!$D$6:$H$163,5,0)<0,0,VLOOKUP($C7,Mensual!$D$6:$H$163,5,0)) -> 0 | H7: =+G7*B7 -> 0
B8: 0.13 | C8: 2.9 Reducir Costo administrativo Puerto Cortés con relacion al año anterior | D8: =IF(VLOOKUP($C8,Mensual!$D$6:$G$135,2,0)<0,0,VLOOKUP($C8,Mensual!$D$6:$G$135,2,0)) -> 0 | E8: =IF(VLOOKUP($C8,Mensual!$D$6:$G$163,3,0)<0,0,VLOOKUP($C8,Mensual!$D$6:$G$163,3,0)) -> 0.05 | F8: =IF(VLOOKUP($C8,Mensual!$D$6:$G$163,4,0)<0,0,VLOOKUP($C8,Mensual!$D$6:$G$163,4,0)) -> 0 | G8: =IF(VLOOKUP($C8,Mensual!$D$6:$H$163,5,0)<0,0,VLOOKUP($C8,Mensual!$D$6:$H$163,5,0)) -> 0 | H8: =+G8*B8 -> 0
B9: 0.08 | C9: 2.13 Reducir Costo de M&R por contenedor Puerto Cortes | D9: =IF(VLOOKUP($C9,Mensual!$D$6:$G$135,2,0)<0,0,VLOOKUP($C9,Mensual!$D$6:$G$135,2,0)) -> $/contenedor | E9: =IF(VLOOKUP($C9,Mensual!$D$6:$G$163,3,0)<0,0,VLOOKUP($C9,Mensual!$D$6:$G$163,3,0)) -> 0.1 | F9: =IF(VLOOKUP($C9,Mensual!$D$6:$G$163,4,0)<0,0,VLOOKUP($C9,Mensual!$D$6:$G$163,4,0)) -> 0 | G9: =IF(VLOOKUP($C9,Mensual!$D$6:$H$163,5,0)<0,0,VLOOKUP($C9,Mensual!$D$6:$H$163,5,0)) -> 0 | H9: =+G9*B9 -> 0
B10: 0.05 | C10: 2.14 Reducir costo máquinas (incluye mulita y containers handler) Puerto Cortes | D10: =IF(VLOOKUP($C10,Mensual!$D$6:$G$135,2,0)<0,0,VLOOKUP($C10,Mensual!$D$6:$G$135,2,0)) -> $/contenedor | E10: =IF(VLOOKUP($C10,Mensual!$D$6:$G$163,3,0)<0,0,VLOOKUP($C10,Mensual!$D$6:$G$163,3,0)) -> 0.1 | F10: =IF(VLOOKUP($C10,Mensual!$D$6:$G$163,4,0)<0,0,VLOOKUP($C10,Mensual!$D$6:$G$163,4,0)) -> 0 | G10: =IF(VLOOKUP($C10,Mensual!$D$6:$H$163,5,0)<0,0,VLOOKUP($C10,Mensual!$D$6:$H$163,5,0)) -> 0 | H10: =+G10*B10 -> 0
B11: 0.08 | C11: 2.18 Reducir M&R gensets $ /genset activo 10% | D11: =IF(VLOOKUP($C11,Mensual!$D$6:$G$135,2,0)<0,0,VLOOKUP($C11,Mensual!$D$6:$G$135,2,0)) -> dolares | E11: =IF(VLOOKUP($C11,Mensual!$D$6:$G$163,3,0)<0,0,VLOOKUP($C11,Mensual!$D$6:$G$163,3,0)) -> 0.1 | F11: =IF(VLOOKUP($C11,Mensual!$D$6:$G$163,4,0)<0,0,VLOOKUP($C11,Mensual!$D$6:$G$163,4,0)) -> 4.66 | G11: =IF(VLOOKUP($C11,Mensual!$D$6:$H$163,5,0)<0,0,VLOOKUP($C11,Mensual!$D$6:$H$163,5,0)) -> 0 | H11: =+G11*B11 -> 0
B12: 0.08 | C12: 3. Cero incidentes mayores de seguridad y sostenibilidad | D12: =IF(VLOOKUP($C12,Mensual!$D$6:$G$135,2,0)<0,0,VLOOKUP($C12,Mensual!$D$6:$G$135,2,0)) -> 0 | E12: =IF(VLOOKUP($C12,Mensual!$D$6:$G$163,3,0)<0,0,VLOOKUP($C12,Mensual!$D$6:$G$163,3,0)) -> 1 | F12: =IF(VLOOKUP($C12,Mensual!$D$6:$G$163,4,0)<0,0,VLOOKUP($C12,Mensual!$D$6:$G$163,4,0)) -> 1 | G12: =IF(VLOOKUP($C12,Mensual!$D$6:$H$163,5,0)<0,0,VLOOKUP($C12,Mensual!$D$6:$H$163,5,0)) -> 1 | H12: =+G12*B12 -> 0.08
B13: 0.13 | C13: 5.11 # de fallas operativas adjudicables al predio (Incluye rescates, rechazos) Puerto Cortes | D13: =IF(VLOOKUP($C13,Mensual!$D$6:$G$135,2,0)<0,0,VLOOKUP($C13,Mensual!$D$6:$G$135,2,0)) -> # de fallas | E13: =IF(VLOOKUP($C13,Mensual!$D$6:$G$163,3,0)<0,0,VLOOKUP($C13,Mensual!$D$6:$G$163,3,0)) -> 1 | F13: =IF(VLOOKUP($C13,Mensual!$D$6:$G$163,4,0)<0,0,VLOOKUP($C13,Mensual!$D$6:$G$163,4,0)) -> 0 | G13: =IF(VLOOKUP($C13,Mensual!$D$6:$H$163,5,0)<0,0,VLOOKUP($C13,Mensual!$D$6:$H$163,5,0)) -> 1 | H13: =+G13*B13 -> 0.13
B14: 0.08 | C14: 6.2.1 Disminuir a 5% el desuso de los equipos Puerto Cortés (equipos con mas de 30 dias en yarda) | D14: =IF(VLOOKUP($C14,Mensual!$D$6:$G$135,2,0)<0,0,VLOOKUP($C14,Mensual!$D$6:$G$135,2,0)) -> Equipos | E14: =IF(VLOOKUP($C14,Mensual!$D$6:$G$163,3,0)<0,0,VLOOKUP($C14,Mensual!$D$6:$G$163,3,0)) -> 30 | F14: =IF(VLOOKUP($C14,Mensual!$D$6:$G$163,4,0)<0,0,VLOOKUP($C14,Mensual!$D$6:$G$163,4,0)) -> 45 | G14: =IF(VLOOKUP($C14,Mensual!$D$6:$H$163,5,0)<0,0,VLOOKUP($C14,Mensual!$D$6:$H$163,5,0)) -> 0 | H14: =+G14*B14 -> 0
B15: 0.06 | C15: 6.4 No exceder a 5 equipos en desuso generadores | D15: =IF(VLOOKUP($C15,Mensual!$D$6:$G$135,2,0)<0,0,VLOOKUP($C15,Mensual!$D$6:$G$135,2,0)) -> generadores | E15: =IF(VLOOKUP($C15,Mensual!$D$6:$G$163,3,0)<0,0,VLOOKUP($C15,Mensual!$D$6:$G$163,3,0)) -> 1 | F15: =IF(VLOOKUP($C15,Mensual!$D$6:$G$163,4,0)<0,0,VLOOKUP($C15,Mensual!$D$6:$G$163,4,0)) -> 44 | G15: =IF(VLOOKUP($C15,Mensual!$D$6:$H$163,5,0)<0,0,VLOOKUP($C15,Mensual!$D$6:$H$163,5,0)) -> 0 | H15: =+G15*B15 -> 0
B16: 0.13 | C16: 2.2 Reducir costo de M&R de chasis propios | D16: =IF(VLOOKUP($C16,Mensual!$D$6:$G$135,2,0)<0,0,VLOOKUP($C16,Mensual!$D$6:$G$135,2,0)) -> $/km | E16: =IF(VLOOKUP($C16,Mensual!$D$6:$G$163,3,0)<0,0,VLOOKUP($C16,Mensual!$D$6:$G$163,3,0)) -> 0.05 | F16: =IF(VLOOKUP($C16,Mensual!$D$6:$G$163,4,0)<0,0,VLOOKUP($C16,Mensual!$D$6:$G$163,4,0)) -> 0.09 | G16: =IF(VLOOKUP($C16,Mensual!$D$6:$H$163,5,0)<0,0,VLOOKUP($C16,Mensual!$D$6:$H$163,5,0)) -> 0 | H16: =+G16*B16 -> 0
B17: =SUM(B6:B16) -> 1 | H17: =SUM(H6:H16) -> 0.31325 | I17: =+B17-B18 -> 0.82
B18: =+B8+B10 -> 0.18 | F18: Nota ponderada menos azules | H18: =+H17/I17 -> 0.3820122
B21: .
B22: ..

Sheet Cubillo
I1: 0.9
C2: Colaborador: | D2: Juan Cubillo | I2: 80-90%
C3: Departamento: | D3: Predio_San_Lorenzo | I3: Menos de 80%
A5: =+Mensual!B5 -> No | B5: =+Mensual!C5 -> Peso | D5: =+Mensual!E5 -> Unidad de medición | E5: =+Mensual!F5 -> Meta | F5: =+Mensual!G5 -> Resultado | G5: =+Mensual!H5 -> Nota | H5: =+Mensual!I5 -> Valor ponderado | I5: =+Mensual!J5 -> 0 | J5: =+Mensual!K5 -> 0.25 | K5: =+Mensual!L5 -> 0.5 | ... Q5: =+Mensual!R5 -> 0 | T5: Nota | U5: Nota
A6: =+Mensual!B6 -> 4 | B6: 0.35 | C6: 9. SCORE CARD Grupo EXA | D6: =IF(VLOOKUP($C6,Mensual!$D$6:$G$163,2,0)<0,0,VLOOKUP($C6,Mensual!$D$6:$G$163,2,0)) -> RESULTADO SCORECARD | E6: =IF(VLOOKUP($C6,Mensual!$D$6:$G$163,3,0)<0,0,VLOOKUP($C6,Mensual!$D$6:$G$163,3,0)) -> 1 | F6: =IF(VLOOKUP($C6,Mensual!$D$6:$G$163,4,0)<0,0,VLOOKUP($C6,Mensual!$D$6:$G$163,4,0)) -> 1.0325 | G6: =IF(VLOOKUP($C6,Mensual!$D$6:$H$163,5,0)<0,0,VLOOKUP($C6,Mensual!$D$6:$H$163,5,0)) -> 1.0325 | H6: =+G6*B6 -> 0.361375 | I6: =+Mensual!J6 -> 0 | J6: =+Mensual!K6 -> 0 | K6: =+Mensual!L6 -> 0 | L6: =+Mensual!M6 -> 0
B7: 0.1 | C7: 1.13 Aumentar servicio de almacenamiento y M&R San Lorenzo | D7: =IF(VLOOKUP($C7,Mensual!$D$6:$G$135,2,0)<0,0,VLOOKUP($C7,Mensual!$D$6:$G$135,2,0)) -> 0 | E7: =IF(VLOOKUP($C7,Mensual!$D$6:$G$163,3,0)<0,0,VLOOKUP($C7,Mensual!$D$6:$G$163,3,0)) -> 0.2 | F7: =IF(VLOOKUP($C7,Mensual!$D$6:$G$163,4,0)<0,0,VLOOKUP($C7,Mensual!$D$6:$G$163,4,0)) -> 0.3 | G7: =IF(VLOOKUP($C7,Mensual!$D$6:$H$163,5,0)<0,0,VLOOKUP($C7,Mensual!$D$6:$H$163,5,0)) -> 1 | H7: =+G7*B7 -> 0.1
B8: 0.1 | C8: 2.11 Gasto administrativo San Lorenzo | D8: =IF(VLOOKUP($C8,Mensual!$D$6:$G$135,2,0)<0,0,VLOOKUP($C8,Mensual!$D$6:$G$135,2,0)) -> 0 | E8: =IF(VLOOKUP($C8,Mensual!$D$6:$G$163,3,0)<0,0,VLOOKUP($C8,Mensual!$D$6:$G$163,3,0)) -> 0.1 | F8: =IF(VLOOKUP($C8,Mensual!$D$6:$G$163,4,0)<0,0,VLOOKUP($C8,Mensual!$D$6:$G$163,4,0)) -> 0 | G8: =IF(VLOOKUP($C8,Mensual!$D$6:$H$163,5,0)<0,0,VLOOKUP($C8,Mensual!$D$6:$H$163,5,0)) -> 0 | H8: =+G8*B8 -> 0
B9: 0.05 | C9: 2.15 Aumentar margen de M&R por contenedor San Lorenzo | D9: =IF(VLOOKUP($C9,Mensual!$D$6:$G$135,2,0)<0,0,VLOOKUP($C9,Mensual!$D$6:$G$135,2,0)) -> 0 | E9: =IF(VLOOKUP($C9,Mensual!$D$6:$G$163,3,0)<0,0,VLOOKUP($C9,Mensual!$D$6:$G$163,3,0)) -> 0 | F9: =IF(VLOOKUP($C9,Mensual!$D$6:$G$163,4,0)<0,0,VLOOKUP($C9,Mensual!$D$6:$G$163,4,0)) -> 0 | G9: =IF(VLOOKUP($C9,Mensual!$D$6:$H$163,5,0)<0,0,VLOOKUP($C9,Mensual!$D$6:$H$163,5,0)) -> 0 | H9: =+G9*B9 -> 0
B10: 0.05 | C10: 5.15 # de fallas operativas adjudicables al predio (Incluye rescates, rechazos) San Lorenzo | D10: =IF(VLOOKUP($C10,Mensual!$D$6:$G$135,2,0)<0,0,VLOOKUP($C10,Mensual!$D$6:$G$135,2,0)) -> 0 | E10: =IF(VLOOKUP($C10,Mensual!$D$6:$G$163,3,0)<0,0,VLOOKUP($C10,Mensual!$D$6:$G$163,3,0)) -> 0 | F10: =IF(VLOOKUP($C10,Mensual!$D$6:$G$163,4,0)<0,0,VLOOKUP($C10,Mensual!$D$6:$G$163,4,0)) -> 0 | G10: =IF(VLOOKUP($C10,Mensual!$D$6:$H$163,5,0)<0,0,VLOOKUP($C10,Mensual!$D$6:$H$163,5,0)) -> 1 | H10: =+G10*B10 -> 0.05
B11: 0.05 | C11: 2.16 Reducir costo máquinas (incluye mulita y containers handler) San Lorenzo | D11: =IF(VLOOKUP($C11,Mensual!$D$6:$G$135,2,0)<0,0,VLOOKUP($C11,Mensual!$D$6:$G$135,2,0)) -> 0 | E11: =IF(VLOOKUP($C11,Mensual!$D$6:$G$163,3,0)<0,0,VLOOKUP($C11,Mensual!$D$6:$G$163,3,0)) -> 0 | F11: =IF(VLOOKUP($C11,Mensual!$D$6:$G$163,4,0)<0,0,VLOOKUP($C11,Mensual!$D$6:$G$163,4,0)) -> 0 | G11: =IF(VLOOKUP($C11,Mensual!$D$6:$H$163,5,0)<0,0,VLOOKUP($C11,Mensual!$D$6:$H$163,5,0)) -> 0 | H11: =+G11*B11 -> 0
B12: 0.05 | C12: 2.18 Reducir M&R gensets $ /genset activo 10% | D12: =IF(VLOOKUP($C12,Mensual!$D$6:$G$135,2,0)<0,0,VLOOKUP($C12,Mensual!$D$6:$G$135,2,0)) -> dolares | E12: =IF(VLOOKUP($C12,Mensual!$D$6:$G$163,3,0)<0,0,VLOOKUP($C12,Mensual!$D$6:$G$163,3,0)) -> 0.1 | F12: =IF(VLOOKUP($C12,Mensual!$D$6:$G$163,4,0)<0,0,VLOOKUP($C12,Mensual!$D$6:$G$163,4,0)) -> 4.66 | G12: =IF(VLOOKUP($C12,Mensual!$D$6:$H$163,5,0)<0,0,VLOOKUP($C12,Mensual!$D$6:$H$163,5,0)) -> 0 | H12: =+G12*B12 -> 0
B13: 0.05 | C13: 3. Cero incidentes mayores de seguridad y sostenibilidad | D13: =IF(VLOOKUP($C13,Mensual!$D$6:$G$135,2,0)<0,0,VLOOKUP($C13,Mensual!$D$6:$G$135,2,0)) -> 0 | E13: =IF(VLOOKUP($C13,Mensual!$D$6:$G$163,3,0)<0,0,VLOOKUP($C13,Mensual!$D$6:$G$163,3,0)) -> 1 | F13: =IF(VLOOKUP($C13,Mensual!$D$6:$G$163,4,0)<0,0,VLOOKUP($C13,Mensual!$D$6:$G$163,4,0)) -> 1 | G13: =IF(VLOOKUP($C13,Mensual!$D$6:$H$163,5,0)<0,0,VLOOKUP($C13,Mensual!$D$6:$H$163,5,0)) -> 1 | H13: =+G13*B13 -> 0.05
B14: 0.05 | C14: 6.2.2 Disminuir a 1% el desuso de los equipos San Lorenzo (equipos con mas de 30 dias en yarda) | D14: =IF(VLOOKUP($C14,Mensual!$D$6:$G$135,2,0)<0,0,VLOOKUP($C14,Mensual!$D$6:$G$135,2,0)) -> Equipos | E14: =IF(VLOOKUP($C14,Mensual!$D$6:$G$163,3,0)<0,0,VLOOKUP($C14,Mensual!$D$6:$G$163,3,0)) -> 6 | F14: =IF(VLOOKUP($C14,Mensual!$D$6:$G$163,4,0)<0,0,VLOOKUP($C14,Mensual!$D$6:$G$163,4,0)) -> 7 | G14: =IF(VLOOKUP($C14,Mensual!$D$6:$H$163,5,0)<0,0,VLOOKUP($C14,Mensual!$D$6:$H$163,5,0)) -> 0 | H14: =+G14*B14 -> 0
B15: 0.05 | C15: 6.4 No exceder a 5 equipos en desuso generadores | D15: =IF(VLOOKUP($C15,Mensual!$D$6:$G$135,2,0)<0,0,VLOOKUP($C15,Mensual!$D$6:$G$135,2,0)) -> generadores | E15: =IF(VLOOKUP($C15,Mensual!$D$6:$G$163,3,0)<0,0,VLOOKUP($C15,Mensual!$D$6:$G$163,3,0)) -> 1 | F15: =IF(VLOOKUP($C15,Mensual!$D$6:$G$163,4,0)<0,0,VLOOKUP($C15,Mensual!$D$6:$G$163,4,0)) -> 44 | G15: =IF(VLOOKUP($C15,Mensual!$D$6:$H$163,5,0)<0,0,VLOOKUP($C15,Mensual!$D$6:$H$163,5,0)) -> 0 | H15: =+G15*B15 -> 0
B16: 0.1 | C16: 2.2 Reducir costo de M&R de chasis propios | D16: =IF(VLOOKUP($C16,Mensual!$D$6:$G$135,2,0)<0,0,VLOOKUP($C16,Mensual!$D$6:$G$135,2,0)) -> $/km | E16: =IF(VLOOKUP($C16,Mensual!$D$6:$G$163,3,0)<0,0,VLOOKUP($C16,Mensual!$D$6:$G$163,3,0)) -> 0.05 | F16: =IF(VLOOKUP($C16,Mensual!$D$6:$G$163,4,0)<0,0,VLOOKUP($C16,Mensual!$D$6:$G$163,4,0)) -> 0.09 | G16: =IF(VLOOKUP($C16,Mensual!$D$6:$H$163,5,0)<0,0,VLOOKUP($C16,Mensual!$D$6:$H$163,5,0)) -> 0 | H16: =+G16*B16 -> 0
B17: =SUM(B6:B16) -> 1 | H17: =SUM(H6:H16) -> 0.561375
F18: Nota podera. | H18: =+H17/85% -> 0.66044118

Sheet San Lorenzo b
I1: 0.9
C2: Colaborador: | D2: Juan Cubillo | I2: 80-90%
C3: Departamento: | D3: Predio_San_Lorenzo | I3: Menos de 80%
A5: =+Mensual!B5 -> No | B5: =+Mensual!C5 -> Peso | D5: =+Mensual!E5 -> Unidad de medición | E5: =+Mensual!F5 -> Meta | F5: =+Mensual!G5 -> Resultado | G5: =+Mensual!H5 -> Nota | H5: =+Mensual!I5 -> Valor ponderado | I5: =+Mensual!J5 -> 0 | J5: =+Mensual!K5 -> 0.25 | K5: =+Mensual!L5 -> 0.5 | ... Q5: =+Mensual!R5 -> 0 | T5: Nota | U5: Nota
A6: =+Mensual!B6 -> 4 | B6: 0.1 | C6: 9. SCORE CARD Grupo EXA | D6: =IF(VLOOKUP($C6,Mensual!$D$6:$G$163,2,0)<0,0,VLOOKUP($C6,Mensual!$D$6:$G$163,2,0)) -> RESULTADO SCORECARD | E6: =IF(VLOOKUP($C6,Mensual!$D$6:$G$163,3,0)<0,0,VLOOKUP($C6,Mensual!$D$6:$G$163,3,0)) -> 1 | F6: =IF(VLOOKUP($C6,Mensual!$D$6:$G$163,4,0)<0,0,VLOOKUP($C6,Mensual!$D$6:$G$163,4,0)) -> 1.0325 | G6: =+F6*A6 -> 4.13 | H6: =+G6*B6 -> 0.413 | I6: =+Mensual!J6 -> 0 | J6: =+Mensual!K6 -> 0 | K6: =+Mensual!L6 -> 0 | L6: =+Mensual!M6 -> 0
B7: 0.11 | C7: 1.13 Aumentar servicio de almacenamiento y M&R San Lorenzo | D7: =IF(VLOOKUP($C7,Mensual!$D$6:$G$135,2,0)<0,0,VLOOKUP($C7,Mensual!$D$6:$G$135,2,0)) -> 0 | E7: =IF(VLOOKUP($C7,Mensual!$D$6:$G$163,3,0)<0,0,VLOOKUP($C7,Mensual!$D$6:$G$163,3,0)) -> 0.2 | F7: =IF(VLOOKUP($C7,Mensual!$D$6:$G$163,4,0)<0,0,VLOOKUP($C7,Mensual!$D$6:$G$163,4,0)) -> 0.3 | G7: =IF(VLOOKUP($C7,Mensual!$D$6:$H$163,5,0)<0,0,VLOOKUP($C7,Mensual!$D$6:$H$163,5,0)) -> 1 | H7: =+G7*B7 -> 0.11
B8: 0.12 | C8: 2.11 Gasto administrativo San Lorenzo | D8: =IF(VLOOKUP($C8,Mensual!$D$6:$G$135,2,0)<0,0,VLOOKUP($C8,Mensual!$D$6:$G$135,2,0)) -> 0 | E8: =IF(VLOOKUP($C8,Mensual!$D$6:$G$163,3,0)<0,0,VLOOKUP($C8,Mensual!$D$6:$G$163,3,0)) -> 0.1 | F8: =IF(VLOOKUP($C8,Mensual!$D$6:$G$163,4,0)<0,0,VLOOKUP($C8,Mensual!$D$6:$G$163,4,0)) -> 0 | G8: =IF(VLOOKUP($C8,Mensual!$D$6:$H$163,5,0)<0,0,VLOOKUP($C8,Mensual!$D$6:$H$163,5,0)) -> 0 | H8: =+G8*B8 -> 0
B9: 0.08 | C9: 2.15 Aumentar margen de M&R por contenedor San Lorenzo | D9: =IF(VLOOKUP($C9,Mensual!$D$6:$G$135,2,0)<0,0,VLOOKUP($C9,Mensual!$D$6:$G$135,2,0)) -> 0 | E9: =IF(VLOOKUP($C9,Mensual!$D$6:$G$163,3,0)<0,0,VLOOKUP($C9,Mensual!$D$6:$G$163,3,0)) -> 0 | F9: =IF(VLOOKUP($C9,Mensual!$D$6:$G$163,4,0)<0,0,VLOOKUP($C9,Mensual!$D$6:$G$163,4,0)) -> 0 | G9: =IF(VLOOKUP($C9,Mensual!$D$6:$H$163,5,0)<0,0,VLOOKUP($C9,Mensual!$D$6:$H$163,5,0)) -> 0 | H9: =+G9*B9 -> 0
B10: 0.08 | C10: 5.15 # de fallas operativas adjudicables al predio (Incluye rescates, rechazos) San Lorenzo | D10: =IF(VLOOKUP($C10,Mensual!$D$6:$G$135,2,0)<0,0,VLOOKUP($C10,Mensual!$D$6:$G$135,2,0)) -> 0 | E10: =IF(VLOOKUP($C10,Mensual!$D$6:$G$163,3,0)<0,0,VLOOKUP($C10,Mensual!$D$6:$G$163,3,0)) -> 0 | F10: =IF(VLOOKUP($C10,Mensual!$D$6:$G$163,4,0)<0,0,VLOOKUP($C10,Mensual!$D$6:$G$163,4,0)) -> 0 | G10: =IF(VLOOKUP($C10,Mensual!$D$6:$H$163,5,0)<0,0,VLOOKUP($C10,Mensual!$D$6:$H$163,5,0)) -> 1 | H10: =+G10*B10 -> 0.08
B11: 0.08 | C11: 2.16 Reducir costo máquinas (incluye mulita y containers handler) San Lorenzo | D11: =IF(VLOOKUP($C11,Mensual!$D$6:$G$135,2,0)<0,0,VLOOKUP($C11,Mensual!$D$6:$G$135,2,0)) -> 0 | E11: =IF(VLOOKUP($C11,Mensual!$D$6:$G$163,3,0)<0,0,VLOOKUP($C11,Mensual!$D$6:$G$163,3,0)) -> 0 | F11: =IF(VLOOKUP($C11,Mensual!$D$6:$G$163,4,0)<0,0,VLOOKUP($C11,Mensual!$D$6:$G$163,4,0)) -> 0 | G11: =IF(VLOOKUP($C11,Mensual!$D$6:$H$163,5,0)<0,0,VLOOKUP($C11,Mensual!$D$6:$H$163,5,0)) -> 0 | H11: =+G11*B11 -> 0
B12: 0.08 | C12: 2.18 Reducir M&R gensets $ /genset activo 10% | D12: =IF(VLOOKUP($C12,Mensual!$D$6:$G$135,2,0)<0,0,VLOOKUP($C12,Mensual!$D$6:$G$135,2,0)) -> dolares | E12: =IF(VLOOKUP($C12,Mensual!$D$6:$G$163,3,0)<0,0,VLOOKUP($C12,Mensual!$D$6:$G$163,3,0)) -> 0.1 | F12: =IF(VLOOKUP($C12,Mensual!$D$6:$G$163,4,0)<0,0,VLOOKUP($C12,Mensual!$D$6:$G$163,4,0)) -> 4.66 | G12: =IF(VLOOKUP($C12,Mensual!$D$6:$H$163,5,0)<0,0,VLOOKUP($C12,Mensual!$D$6:$H$163,5,0)) -> 0 | H12: =+G12*B12 -> 0
B13: 0.08 | C13: 3. Cero incidentes mayores de seguridad y sostenibilidad | D13: =IF(VLOOKUP($C13,Mensual!$D$6:$G$135,2,0)<0,0,VLOOKUP($C13,Mensual!$D$6:$G$135,2,0)) -> 0 | E13: =IF(VLOOKUP($C13,Mensual!$D$6:$G$163,3,0)<0,0,VLOOKUP($C13,Mensual!$D$6:$G$163,3,0)) -> 1 | F13: =IF(VLOOKUP($C13,Mensual!$D$6:$G$163,4,0)<0,0,VLOOKUP($C13,Mensual!$D$6:$G$163,4,0)) -> 1 | G13: =IF(VLOOKUP($C13,Mensual!$D$6:$H$163,5,0)<0,0,VLOOKUP($C13,Mensual!$D$6:$H$163,5,0)) -> 1 | H13: =+G13*B13 -> 0.08
B14: 0.08 | C14: 6.2.2 Disminuir a 1% el desuso de los equipos San Lorenzo (equipos con mas de 30 dias en yarda) | D14: =IF(VLOOKUP($C14,Mensual!$D$6:$G$135,2,0)<0,0,VLOOKUP($C14,Mensual!$D$6:$G$135,2,0)) -> Equipos | E14: =IF(VLOOKUP($C14,Mensual!$D$6:$G$163,3,0)<0,0,VLOOKUP($C14,Mensual!$D$6:$G$163,3,0)) -> 6 | F14: =IF(VLOOKUP($C14,Mensual!$D$6:$G$163,4,0)<0,0,VLOOKUP($C14,Mensual!$D$6:$G$163,4,0)) -> 7 | G14: =IF(VLOOKUP($C14,Mensual!$D$6:$H$163,5,0)<0,0,VLOOKUP($C14,Mensual!$D$6:$H$163,5,0)) -> 0 | H14: =+G14*B14 -> 0
B15: 0.08 | C15: 6.4 No exceder a 5 equipos en desuso generadores | D15: =IF(VLOOKUP($C15,Mensual!$D$6:$G$135,2,0)<0,0,VLOOKUP($C15,Mensual!$D$6:$G$135,2,0)) -> generadores | E15: =IF(VLOOKUP($C15,Mensual!$D$6:$G$163,3,0)<0,0,VLOOKUP($C15,Mensual!$D$6:$G$163,3,0)) -> 1 | F15: =IF(VLOOKUP($C15,Mensual!$D$6:$G$163,4,0)<0,0,VLOOKUP($C15,Mensual!$D$6:$G$163,4,0)) -> 44 | G15: =IF(VLOOKUP($C15,Mensual!$D$6:$H$163,5,0)<0,0,VLOOKUP($C15,Mensual!$D$6:$H$163,5,0)) -> 0 | H15: =+G15*B15 -> 0
B16: 0.11 | C16: 2.2 Reducir costo de M&R de chasis propios | D16: =IF(VLOOKUP($C16,Mensual!$D$6:$G$135,2,0)<0,0,VLOOKUP($C16,Mensual!$D$6:$G$135,2,0)) -> $/km | E16: =IF(VLOOKUP($C16,Mensual!$D$6:$G$163,3,0)<0,0,VLOOKUP($C16,Mensual!$D$6:$G$163,3,0)) -> 0.05 | F16: =IF(VLOOKUP($C16,Mensual!$D$6:$G$163,4,0)<0,0,VLOOKUP($C16,Mensual!$D$6:$G$163,4,0)) -> 0.09 | G16: =IF(VLOOKUP($C16,Mensual!$D$6:$H$163,5,0)<0,0,VLOOKUP($C16,Mensual!$D$6:$H$163,5,0)) -> 0 | H16: =+G16*B16 -> 0
B17: =SUM(B6:B16) -> 1 | H17: =SUM(H6:H16) -> 0.683 | I17: =+B17-B19 -> 0.8
F18: Nota quitando celestes. | H18: =+H17/I17 -> 0.85375
B19: =+B8+B11 -> 0.2

Sheet Gasolinera
I1: 0.9
C2: Colaborador: | D2: Abner Urbina | I2: 80-90%
C3: Departamento: | D3: Gasolinera | I3: Menos de 80%
A5: =+Mensual!B5 -> No | B5: =+Mensual!C5 -> Peso | D5: =+Mensual!E5 -> Unidad de medición | E5: =+Mensual!F5 -> Meta | F5: =+Mensual!G5 -> Resultado | G5: =+Mensual!H5 -> Nota | H5: =+Mensual!I5 -> Valor ponderado | I5: =+Mensual!J5 -> 0 | J5: =+Mensual!K5 -> 0.25 | K5: =+Mensual!L5 -> 0.5 | ... Q5: =+Mensual!R5 -> 0 | T5: Nota | U5: Nota
A6: =+Mensual!B6 -> 4 | B6: 0.1 | C6: 9. SCORE CARD Grupo EXA | D6: =IF(VLOOKUP($C6,Mensual!$D$6:$G$163,2,0)<0,0,VLOOKUP($C6,Mensual!$D$6:$G$163,2,0)) -> RESULTADO SCORECARD | E6: =IF(VLOOKUP($C6,Mensual!$D$6:$G$163,3,0)<0,0,VLOOKUP($C6,Mensual!$D$6:$G$163,3,0)) -> 1 | F6: =IF(VLOOKUP($C6,Mensual!$D$6:$G$163,4,0)<0,0,VLOOKUP($C6,Mensual!$D$6:$G$163,4,0)) -> 1.0325 | G6: =IF(VLOOKUP($C6,Mensual!$D$6:$H$163,5,0)<0,0,VLOOKUP($C6,Mensual!$D$6:$H$163,5,0)) -> 1.0325 | H6: =+G6*B6 -> 0.10325 | I6: =+Mensual!J6 -> 0 | J6: =+Mensual!K6 -> 0 | K6: =+Mensual!L6 -> 0 | L6: =+Mensual!M6 -> 0
B7: 0.3 | C7: 1.7 Lograr ventas de gasolinera de galones | D7: =IF(VLOOKUP($C7,Mensual!$D$6:$G$135,2,0)<0,0,VLOOKUP($C7,Mensual!$D$6:$G$135,2,0)) -> Galones | E7: =IF(VLOOKUP($C7,Mensual!$D$6:$G$163,3,0)<0,0,VLOOKUP($C7,Mensual!$D$6:$G$163,3,0)) -> 100000 | F7: =IF(VLOOKUP($C7,Mensual!$D$6:$G$163,4,0)<0,0,VLOOKUP($C7,Mensual!$D$6:$G$163,4,0)) -> 112588 | G7: =IF(VLOOKUP($C7,Mensual!$D$6:$H$163,5,0)<0,0,VLOOKUP($C7,Mensual!$D$6:$H$163,5,0)) -> 1 | H7: =+G7*B7 -> 0.3
B8: 0.2 | C8: 1.11 Tienda de conveniencia (Primeros 4 meses 15k usd y 25k usd) | D8: =IF(VLOOKUP($C8,Mensual!$D$6:$G$135,2,0)<0,0,VLOOKUP($C8,Mensual!$D$6:$G$135,2,0)) -> Dólares | E8: =IF(VLOOKUP($C8,Mensual!$D$6:$G$163,3,0)<0,0,VLOOKUP($C8,Mensual!$D$6:$G$163,3,0)) -> 25000 | F8: =IF(VLOOKUP($C8,Mensual!$D$6:$G$163,4,0)<0,0,VLOOKUP($C8,Mensual!$D$6:$G$163,4,0)) -> 20092.4 | G8: =IF(VLOOKUP($C8,Mensual!$D$6:$H$163,5,0)<0,0,VLOOKUP($C8,Mensual!$D$6:$H$163,5,0)) -> 0.803696 | H8: =+G8*B8 -> 0.1607392
B9: 0.05 | C9: 3.5 Multas ambientales y fiscales. | D9: =IF(VLOOKUP($C9,Mensual!$D$6:$G$135,2,0)<0,0,VLOOKUP($C9,Mensual!$D$6:$G$135,2,0)) -> 0 | E9: =IF(VLOOKUP($C9,Mensual!$D$6:$G$163,3,0)<0,0,VLOOKUP($C9,Mensual!$D$6:$G$163,3,0)) -> 0 | F9: =IF(VLOOKUP($C9,Mensual!$D$6:$G$163,4,0)<0,0,VLOOKUP($C9,Mensual!$D$6:$G$163,4,0)) -> 0 | G9: =IF(VLOOKUP($C9,Mensual!$D$6:$H$163,5,0)<0,0,VLOOKUP($C9,Mensual!$D$6:$H$163,5,0)) -> 1 | H9: =+G9*B9 -> 0.05
B10: 0.12 | C10: 2.19 Gasto administrativo gasolinera 3%/ventas | D10: =IF(VLOOKUP($C10,Mensual!$D$6:$G$135,2,0)<0,0,VLOOKUP($C10,Mensual!$D$6:$G$135,2,0)) -> dolares | E10: =IF(VLOOKUP($C10,Mensual!$D$6:$G$163,3,0)<0,0,VLOOKUP($C10,Mensual!$D$6:$G$163,3,0)) -> 0.03 | F10: =IF(VLOOKUP($C10,Mensual!$D$6:$G$163,4,0)<0,0,VLOOKUP($C10,Mensual!$D$6:$G$163,4,0)) -> 0.07 | G10: =IF(VLOOKUP($C10,Mensual!$D$6:$H$163,5,0)<0,0,VLOOKUP($C10,Mensual!$D$6:$H$163,5,0)) -> 0 | H10: =+G10*B10 -> 0
B11: 0.12 | C11: 2.21 Margen operativo de la gasolinera | D11: =IF(VLOOKUP($C11,Mensual!$D$6:$G$135,2,0)<0,0,VLOOKUP($C11,Mensual!$D$6:$G$135,2,0)) -> dolares | E11: =IF(VLOOKUP($C11,Mensual!$D$6:$G$163,3,0)<0,0,VLOOKUP($C11,Mensual!$D$6:$G$163,3,0)) -> 0.1 | F11: =IF(VLOOKUP($C11,Mensual!$D$6:$G$163,4,0)<0,0,VLOOKUP($C11,Mensual!$D$6:$G$163,4,0)) -> 0.06 | G11: =IF(VLOOKUP($C11,Mensual!$D$6:$H$163,5,0)<0,0,VLOOKUP($C11,Mensual!$D$6:$H$163,5,0)) -> 0 | H11: =+G11*B11 -> 0
B12: 0.11 | C12: 2.20 Margen operativo de tienda | D12: =IF(VLOOKUP($C12,Mensual!$D$6:$G$135,2,0)<0,0,VLOOKUP($C12,Mensual!$D$6:$G$135,2,0)) -> 0 | E12: =IF(VLOOKUP($C12,Mensual!$D$6:$G$163,3,0)<0,0,VLOOKUP($C12,Mensual!$D$6:$G$163,3,0)) -> 0.1 | F12: =IF(VLOOKUP($C12,Mensual!$D$6:$G$163,4,0)<0,0,VLOOKUP($C12,Mensual!$D$6:$G$163,4,0)) -> 0 | G12: =IF(VLOOKUP($C12,Mensual!$D$6:$H$163,5,0)<0,0,VLOOKUP($C12,Mensual!$D$6:$H$163,5,0)) -> 0 | H12: =+G12*B12 -> 0
B13: =SUM(B6:B12) -> 1 | H13: =SUM(H6:H12) -> 0.6139892

Sheet Abner U b
I1: 0.9
C2: Colaborador: | D2: Abner Urbina | I2: 80-90%
C3: Departamento: | D3: Gasolinera | I3: Menos de 80%
A5: =+Mensual!B5 -> No | B5: =+Mensual!C5 -> Peso | D5: =+Mensual!E5 -> Unidad de medición | E5: =+Mensual!F5 -> Meta | F5: =+Mensual!G5 -> Resultado | G5: =+Mensual!H5 -> Nota | H5: =+Mensual!I5 -> Valor ponderado | I5: =+Mensual!J5 -> 0 | J5: =+Mensual!K5 -> 0.25 | K5: =+Mensual!L5 -> 0.5 | ... Q5: =+Mensual!R5 -> 0 | T5: Nota | U5: Nota
A6: =+Mensual!B6 -> 4 | B6: 0.2 | C6: 9. SCORE CARD Grupo EXA | D6: =IF(VLOOKUP($C6,Mensual!$D$6:$G$163,2,0)<0,0,VLOOKUP($C6,Mensual!$D$6:$G$163,2,0)) -> RESULTADO SCORECARD | E6: =IF(VLOOKUP($C6,Mensual!$D$6:$G$163,3,0)<0,0,VLOOKUP($C6,Mensual!$D$6:$G$163,3,0)) -> 1 | F6: =IF(VLOOKUP($C6,Mensual!$D$6:$G$163,4,0)<0,0,VLOOKUP($C6,Mensual!$D$6:$G$163,4,0)) -> 1.0325 | G6: =IF(VLOOKUP($C6,Mensual!$D$6:$H$163,5,0)<0,0,VLOOKUP($C6,Mensual!$D$6:$H$163,5,0)) -> 1.0325 | H6: =+G6*B6 -> 0.2065 | I6: =+Mensual!J6 -> 0 | J6: =+Mensual!K6 -> 0 | K6: =+Mensual!L6 -> 0 | L6: =+Mensual!M6 -> 0
B7: 0.25 | C7: 1.7 Lograr ventas de gasolinera de galones | D7: =IF(VLOOKUP($C7,Mensual!$D$6:$G$135,2,0)<0,0,VLOOKUP($C7,Mensual!$D$6:$G$135,2,0)) -> Galones | E7: =IF(VLOOKUP($C7,Mensual!$D$6:$G$163,3,0)<0,0,VLOOKUP($C7,Mensual!$D$6:$G$163,3,0)) -> 100000 | F7: =IF(VLOOKUP($C7,Mensual!$D$6:$G$163,4,0)<0,0,VLOOKUP($C7,Mensual!$D$6:$G$163,4,0)) -> 112588 | G7: =IF(VLOOKUP($C7,Mensual!$D$6:$H$163,5,0)<0,0,VLOOKUP($C7,Mensual!$D$6:$H$163,5,0)) -> 1 | H7: =+G7*B7 -> 0.25
B8: 0.15 | C8: 1.11 Tienda de conveniencia (Primeros 4 meses 15k usd y 25k usd) | D8: =IF(VLOOKUP($C8,Mensual!$D$6:$G$135,2,0)<0,0,VLOOKUP($C8,Mensual!$D$6:$G$135,2,0)) -> Dólares | E8: =IF(VLOOKUP($C8,Mensual!$D$6:$G$163,3,0)<0,0,VLOOKUP($C8,Mensual!$D$6:$G$163,3,0)) -> 25000 | F8: =IF(VLOOKUP($C8,Mensual!$D$6:$G$163,4,0)<0,0,VLOOKUP($C8,Mensual!$D$6:$G$163,4,0)) -> 20092.4 | G8: =IF(VLOOKUP($C8,Mensual!$D$6:$H$163,5,0)<0,0,VLOOKUP($C8,Mensual!$D$6:$H$163,5,0)) -> 0.803696 | H8: =+G8*B8 -> 0.1205544
B9: 0.1 | C9: 3.5 Multas ambientales y fiscales. | D9: =IF(VLOOKUP($C9,Mensual!$D$6:$G$135,2,0)<0,0,VLOOKUP($C9,Mensual!$D$6:$G$135,2,0)) -> 0 | E9: =IF(VLOOKUP($C9,Mensual!$D$6:$G$163,3,0)<0,0,VLOOKUP($C9,Mensual!$D$6:$G$163,3,0)) -> 0 | F9: =IF(VLOOKUP($C9,Mensual!$D$6:$G$163,4,0)<0,0,VLOOKUP($C9,Mensual!$D$6:$G$163,4,0)) -> 0 | G9: =IF(VLOOKUP($C9,Mensual!$D$6:$H$163,5,0)<0,0,VLOOKUP($C9,Mensual!$D$6:$H$163,5,0)) -> 1 | H9: =+G9*B9 -> 0.1
B10: 0.1 | C10: 2.19 Gasto administrativo gasolinera 3%/ventas | D10: =IF(VLOOKUP($C10,Mensual!$D$6:$G$135,2,0)<0,0,VLOOKUP($C10,Mensual!$D$6:$G$135,2,0)) -> dolares | E10: =IF(VLOOKUP($C10,Mensual!$D$6:$G$163,3,0)<0,0,VLOOKUP($C10,Mensual!$D$6:$G$163,3,0)) -> 0.03 | F10: =IF(VLOOKUP($C10,Mensual!$D$6:$G$163,4,0)<0,0,VLOOKUP($C10,Mensual!$D$6:$G$163,4,0)) -> 0.07 | G10: =IF(VLOOKUP($C10,Mensual!$D$6:$H$163,5,0)<0,0,VLOOKUP($C10,Mensual!$D$6:$H$163,5,0)) -> 0 | H10: =+G10*B10 -> 0
B11: 0.1 | C11: 2.21 Margen operativo de la gasolinera | D11: =IF(VLOOKUP($C11,Mensual!$D$6:$G$135,2,0)<0,0,VLOOKUP($C11,Mensual!$D$6:$G$135,2,0)) -> dolares | E11: =IF(VLOOKUP($C11,Mensual!$D$6:$G$163,3,0)<0,0,VLOOKUP($C11,Mensual!$D$6:$G$163,3,0)) -> 0.1 | F11: =IF(VLOOKUP($C11,Mensual!$D$6:$G$163,4,0)<0,0,VLOOKUP($C11,Mensual!$D$6:$G$163,4,0)) -> 0.06 | G11: =IF(VLOOKUP($C11,Mensual!$D$6:$H$163,5,0)<0,0,VLOOKUP($C11,Mensual!$D$6:$H$163,5,0)) -> 0 | H11: =+G11*B11 -> 0
B12: 0.1 | C12: 2.20 Margen operativo de tienda | D12: =IF(VLOOKUP($C12,Mensual!$D$6:$G$135,2,0)<0,0,VLOOKUP($C12,Mensual!$D$6:$G$135,2,0)) -> 0 | E12: =IF(VLOOKUP($C12,Mensual!$D$6:$G$163,3,0)<0,0,VLOOKUP($C12,Mensual!$D$6:$G$163,3,0)) -> 0.1 | F12: =IF(VLOOKUP($C12,Mensual!$D$6:$G$163,4,0)<0,0,VLOOKUP($C12,Mensual!$D$6:$G$163,4,0)) -> 0 | G12: =IF(VLOOKUP($C12,Mensual!$D$6:$H$163,5,0)<0,0,VLOOKUP($C12,Mensual!$D$6:$H$163,5,0)) -> 0 | H12: =+G12*B12 -> 0
B13: =SUM(B6:B12) -> 1 | H13: =SUM(H6:H12) -> 0.6770544

Sheet Jacky
I1: 0.9
C2: Colaborador: | D2: Jacky Mena | I2: 80-90%
C3: Departamento: | D3: Servicio_Al_Cliente | I3: Menos de 80%
A5: =+Mensual!B5 -> No | B5: =+Mensual!C5 -> Peso | D5: =+Mensual!E5 -> Unidad de medición | E5: =+Mensual!F5 -> Meta | F5: =+Mensual!G5 -> Resultado | G5: =+Mensual!H5 -> Nota | H5: =+Mensual!I5 -> Valor ponderado | I5: =+Mensual!J5 -> 0 | J5: =+Mensual!K5 -> 0.25 | K5: =+Mensual!L5 -> 0.5 | ... Q5: =+Mensual!R5 -> 0 | T5: Nota | U5: Nota
A6: =+Mensual!B6 -> 4 | B6: 0.25 | C6: 9. SCORE CARD Grupo EXA | D6: =IF(VLOOKUP($C6,Mensual!$D$6:$G$163,2,0)<0,0,VLOOKUP($C6,Mensual!$D$6:$G$163,2,0)) -> RESULTADO SCORECARD | E6: =IF(VLOOKUP($C6,Mensual!$D$6:$G$163,3,0)<0,0,VLOOKUP($C6,Mensual!$D$6:$G$163,3,0)) -> 1 | F6: =IF(VLOOKUP($C6,Mensual!$D$6:$G$163,4,0)<0,0,VLOOKUP($C6,Mensual!$D$6:$G$163,4,0)) -> 1.0325 | G6: =IF(VLOOKUP($C6,Mensual!$D$6:$H$163,5,0)<0,0,VLOOKUP($C6,Mensual!$D$6:$H$163,5,0)) -> 1.0325 | H6: =+G6*B6 -> 0.258125 | I6: =+Mensual!J6 -> 0 | J6: =+Mensual!K6 -> 0 | K6: =+Mensual!L6 -> 0 | L6: =+Mensual!M6 -> 0
B7: 0.1 | C7: 3.9 On time delivery without sevice incidents | D7: =IF(VLOOKUP($C7,Mensual!$D$6:$G$135,2,0)<0,0,VLOOKUP($C7,Mensual!$D$6:$G$135,2,0)) -> 0 | E7: =IF(VLOOKUP($C7,Mensual!$D$6:$G$163,3,0)<0,0,VLOOKUP($C7,Mensual!$D$6:$G$163,3,0)) -> 0.995 | F7: =IF(VLOOKUP($C7,Mensual!$D$6:$G$163,4,0)<0,0,VLOOKUP($C7,Mensual!$D$6:$G$163,4,0)) -> 1 | G7: =IF(VLOOKUP($C7,Mensual!$D$6:$H$163,5,0)<0,0,VLOOKUP($C7,Mensual!$D$6:$H$163,5,0)) -> 1 | H7: =+G7*B7 -> 0.1
B8: 0.05 | C8: 5.12 Aumentar # de viajes de EXA | D8: =IF(VLOOKUP($C8,Mensual!$D$6:$G$135,2,0)<0,0,VLOOKUP($C8,Mensual!$D$6:$G$135,2,0)) -> # de viajes | E8: =IF(VLOOKUP($C8,Mensual!$D$6:$G$163,3,0)<0,0,VLOOKUP($C8,Mensual!$D$6:$G$163,3,0)) -> 0.2 | F8: =IF(VLOOKUP($C8,Mensual!$D$6:$G$163,4,0)<0,0,VLOOKUP($C8,Mensual!$D$6:$G$163,4,0)) -> 0 | G8: =IF(VLOOKUP($C8,Mensual!$D$6:$H$163,5,0)<0,0,VLOOKUP($C8,Mensual!$D$6:$H$163,5,0)) -> 0 | H8: =+G8*B8 -> 0
B9: 0.1 | C9: 3. Cero incidentes mayores de seguridad y sostenibilidad | D9: =IF(VLOOKUP($C9,Mensual!$D$6:$G$135,2,0)<0,0,VLOOKUP($C9,Mensual!$D$6:$G$135,2,0)) -> 0 | E9: =IF(VLOOKUP($C9,Mensual!$D$6:$G$163,3,0)<0,0,VLOOKUP($C9,Mensual!$D$6:$G$163,3,0)) -> 1 | F9: =IF(VLOOKUP($C9,Mensual!$D$6:$G$163,4,0)<0,0,VLOOKUP($C9,Mensual!$D$6:$G$163,4,0)) -> 1 | G9: =IF(VLOOKUP($C9,Mensual!$D$6:$H$163,5,0)<0,0,VLOOKUP($C9,Mensual!$D$6:$H$163,5,0)) -> 1 | H9: =+G9*B9 -> 0.1
B10: 0.05 | C10: 5.1 Productividad kms/cabezal/mes. | D10: =IF(VLOOKUP($C10,Mensual!$D$6:$G$135,2,0)<0,0,VLOOKUP($C10,Mensual!$D$6:$G$135,2,0)) -> 0 | E10: =IF(VLOOKUP($C10,Mensual!$D$6:$G$163,3,0)<0,0,VLOOKUP($C10,Mensual!$D$6:$G$163,3,0)) -> 3700 | F10: =IF(VLOOKUP($C10,Mensual!$D$6:$G$163,4,0)<0,0,VLOOKUP($C10,Mensual!$D$6:$G$163,4,0)) -> 3932 | G10: =IF(VLOOKUP($C10,Mensual!$D$6:$H$163,5,0)<0,0,VLOOKUP($C10,Mensual!$D$6:$H$163,5,0)) -> 1 | H10: =+G10*B10 -> 0.05
B11: 0.04 | C11: 5.2 Productividad cabezales Flota Nueva | D11: =IF(VLOOKUP($C11,Mensual!$D$6:$G$135,2,0)<0,0,VLOOKUP($C11,Mensual!$D$6:$G$135,2,0)) -> 0 | E11: =IF(VLOOKUP($C11,Mensual!$D$6:$G$163,3,0)<0,0,VLOOKUP($C11,Mensual!$D$6:$G$163,3,0)) -> 4500 | F11: =IF(VLOOKUP($C11,Mensual!$D$6:$G$163,4,0)<0,0,VLOOKUP($C11,Mensual!$D$6:$G$163,4,0)) -> 4782 | G11: =IF(VLOOKUP($C11,Mensual!$D$6:$H$163,5,0)<0,0,VLOOKUP($C11,Mensual!$D$6:$H$163,5,0)) -> 1 | H11: =+G11*B11 -> 0.04
B12: 0.03 | C12: 5.3 Productividad cabezales TRANEXPA | D12: =IF(VLOOKUP($C12,Mensual!$D$6:$G$135,2,0)<0,0,VLOOKUP($C12,Mensual!$D$6:$G$135,2,0)) -> 0 | E12: =IF(VLOOKUP($C12,Mensual!$D$6:$G$163,3,0)<0,0,VLOOKUP($C12,Mensual!$D$6:$G$163,3,0)) -> 4000 | F12: =IF(VLOOKUP($C12,Mensual!$D$6:$G$163,4,0)<0,0,VLOOKUP($C12,Mensual!$D$6:$G$163,4,0)) -> 4268 | G12: =IF(VLOOKUP($C12,Mensual!$D$6:$H$163,5,0)<0,0,VLOOKUP($C12,Mensual!$D$6:$H$163,5,0)) -> 1 | H12: =+G12*B12 -> 0.03
B13: 0.03 | C13: 5.4 Productividad cabezales IPH | D13: =IF(VLOOKUP($C13,Mensual!$D$6:$G$135,2,0)<0,0,VLOOKUP($C13,Mensual!$D$6:$G$135,2,0)) -> 0 | E13: =IF(VLOOKUP($C13,Mensual!$D$6:$G$163,3,0)<0,0,VLOOKUP($C13,Mensual!$D$6:$G$163,3,0)) -> 3800 | F13: =IF(VLOOKUP($C13,Mensual!$D$6:$G$163,4,0)<0,0,VLOOKUP($C13,Mensual!$D$6:$G$163,4,0)) -> 3501 | G13: =IF(VLOOKUP($C13,Mensual!$D$6:$H$163,5,0)<0,0,VLOOKUP($C13,Mensual!$D$6:$H$163,5,0)) -> 0 | H13: =+G13*B13 -> 0
B14: 0.02 | C14: 5.5.1 Productividad cabezales Tranexpa Particulares. | D14: =IF(VLOOKUP($C14,Mensual!$D$6:$G$135,2,0)<0,0,VLOOKUP($C14,Mensual!$D$6:$G$135,2,0)) -> 0 | E14: =IF(VLOOKUP($C14,Mensual!$D$6:$G$163,3,0)<0,0,VLOOKUP($C14,Mensual!$D$6:$G$163,3,0)) -> 3500 | F14: =IF(VLOOKUP($C14,Mensual!$D$6:$G$163,4,0)<0,0,VLOOKUP($C14,Mensual!$D$6:$G$163,4,0)) -> 2144 | G14: =IF(VLOOKUP($C14,Mensual!$D$6:$H$163,5,0)<0,0,VLOOKUP($C14,Mensual!$D$6:$H$163,5,0)) -> 0 | H14: =+G14*B14 -> 0
B15: 0.02 | C15: 5.5.2 Productividad cabezales Ponce | D15: =IF(VLOOKUP($C15,Mensual!$D$6:$G$135,2,0)<0,0,VLOOKUP($C15,Mensual!$D$6:$G$135,2,0)) -> 0 | E15: =IF(VLOOKUP($C15,Mensual!$D$6:$G$163,3,0)<0,0,VLOOKUP($C15,Mensual!$D$6:$G$163,3,0)) -> 3500 | F15: =IF(VLOOKUP($C15,Mensual!$D$6:$G$163,4,0)<0,0,VLOOKUP($C15,Mensual!$D$6:$G$163,4,0)) -> 2560 | G15: =IF(VLOOKUP($C15,Mensual!$D$6:$H$163,5,0)<0,0,VLOOKUP($C15,Mensual!$D$6:$H$163,5,0)) -> 0 | H15: =+G15*B15 -> 0
B16: 0.02 | C16: 5.5.4 Productividad cabezales Obregon | D16: =IF(VLOOKUP($C16,Mensual!$D$6:$G$135,2,0)<0,0,VLOOKUP($C16,Mensual!$D$6:$G$135,2,0)) -> 0 | E16: =IF(VLOOKUP($C16,Mensual!$D$6:$G$163,3,0)<0,0,VLOOKUP($C16,Mensual!$D$6:$G$163,3,0)) -> 3500 | F16: =IF(VLOOKUP($C16,Mensual!$D$6:$G$163,4,0)<0,0,VLOOKUP($C16,Mensual!$D$6:$G$163,4,0)) -> 3165 | G16: =IF(VLOOKUP($C16,Mensual!$D$6:$H$163,5,0)<0,0,VLOOKUP($C16,Mensual!$D$6:$H$163,5,0)) -> 0 | H16: =+G16*B16 -> 0
B17: 0.02 | C17: 5.5.3 Productividad cabezales Moreno | D17: =IF(VLOOKUP($C17,Mensual!$D$6:$G$135,2,0)<0,0,VLOOKUP($C17,Mensual!$D$6:$G$135,2,0)) -> 0 | E17: =IF(VLOOKUP($C17,Mensual!$D$6:$G$163,3,0)<0,0,VLOOKUP($C17,Mensual!$D$6:$G$163,3,0)) -> 3500 | F17: =IF(VLOOKUP($C17,Mensual!$D$6:$G$163,4,0)<0,0,VLOOKUP($C17,Mensual!$D$6:$G$163,4,0)) -> 2923 | G17: =IF(VLOOKUP($C17,Mensual!$D$6:$H$163,5,0)<0,0,VLOOKUP($C17,Mensual!$D$6:$H$163,5,0)) -> 0 | H17: =+G17*B17 -> 0
B18: 0.02 | C18: 5.5.5 Productividad cabezales San Lorenzo | D18: =IF(VLOOKUP($C18,Mensual!$D$6:$G$135,2,0)<0,0,VLOOKUP($C18,Mensual!$D$6:$G$135,2,0)) -> 0 | E18: =IF(VLOOKUP($C18,Mensual!$D$6:$G$163,3,0)<0,0,VLOOKUP($C18,Mensual!$D$6:$G$163,3,0)) -> 3500 | F18: =IF(VLOOKUP($C18,Mensual!$D$6:$G$163,4,0)<0,0,VLOOKUP($C18,Mensual!$D$6:$G$163,4,0)) -> 2234 | G18: =IF(VLOOKUP($C18,Mensual!$D$6:$H$163,5,0)<0,0,VLOOKUP($C18,Mensual!$D$6:$H$163,5,0)) -> 0 | H18: =+G18*B18 -> 0
... B23: 0.08 | C23: 5.8 Aumentar kms EXA | D23: =IF(VLOOKUP($C23,Mensual!$D$6:$G$135,2,0)<0,0,VLOOKUP($C23,Mensual!$D$6:$G$135,2,0)) -> kms | E23: =IF(VLOOKUP($C23,Mensual!$D$6:$G$163,3,0)<0,0,VLOOKUP($C23,Mensual!$D$6:$G$163,3,0)) -> 506974.68 | F23: =IF(VLOOKUP($C23,Mensual!$D$6:$G$163,4,0)<0,0,VLOOKUP($C23,Mensual!$D$6:$G$163,4,0)) -> 485973.6 | G23: =IF(VLOOKUP($C23,Mensual!$D$6:$H$163,5,0)<0,0,VLOOKUP($C23,Mensual!$D$6:$H$163,5,0)) -> 0 | H23: =+G23*B23 -> 0
B24: =SUM(B6:B23) -> 1 | H24: =SUM(H6:H23) -> 0.728125

Sheet Servicio al cliente b
I1: 0.9
I2: 80-90%
C3: Departamento: | D3: Servicio_Al_Cliente | I3: Menos de 80%
A5: =+Mensual!B5 -> No | B5: =+Mensual!C5 -> Peso | D5: =+Mensual!E5 -> Unidad de medición | E5: =+Mensual!F5 -> Meta | F5: =+Mensual!G5 -> Resultado | G5: =+Mensual!H5 -> Nota | H5: =+Mensual!I5 -> Valor ponderado | I5: =+Mensual!J5 -> 0 | J5: =+Mensual!K5 -> 0.25 | K5: =+Mensual!L5 -> 0.5 | ... Q5: =+Mensual!R5 -> 0 | T5: Nota | U5: Nota
A6: =+Mensual!B6 -> 4 | B6: 0.1 | C6: 9. SCORE CARD Grupo EXA | D6: =IF(VLOOKUP($C6,Mensual!$D$6:$G$163,2,0)<0,0,VLOOKUP($C6,Mensual!$D$6:$G$163,2,0)) -> RESULTADO SCORECARD | E6: =IF(VLOOKUP($C6,Mensual!$D$6:$G$163,3,0)<0,0,VLOOKUP($C6,Mensual!$D$6:$G$163,3,0)) -> 1 | F6: =IF(VLOOKUP($C6,Mensual!$D$6:$G$163,4,0)<0,0,VLOOKUP($C6,Mensual!$D$6:$G$163,4,0)) -> 1.0325 | G6: =IF(VLOOKUP($C6,Mensual!$D$6:$H$163,5,0)<0,0,VLOOKUP($C6,Mensual!$D$6:$H$163,5,0)) -> 1.0325 | H6: =+G6*B6 -> 0.10325 | I6: =+Mensual!J6 -> 0 | J6: =+Mensual!K6 -> 0 | K6: =+Mensual!L6 -> 0 | L6: =+Mensual!M6 -> 0
B7: 0.11 | C7: 3.9 On time delivery without sevice incidents | D7: =IF(VLOOKUP($C7,Mensual!$D$6:$G$135,2,0)<0,0,VLOOKUP($C7,Mensual!$D$6:$G$135,2,0)) -> 0 | E7: =IF(VLOOKUP($C7,Mensual!$D$6:$G$163,3,0)<0,0,VLOOKUP($C7,Mensual!$D$6:$G$163,3,0)) -> 0.995 | F7: =IF(VLOOKUP($C7,Mensual!$D$6:$G$163,4,0)<0,0,VLOOKUP($C7,Mensual!$D$6:$G$163,4,0)) -> 1 | G7: =IF(VLOOKUP($C7,Mensual!$D$6:$H$163,5,0)<0,0,VLOOKUP($C7,Mensual!$D$6:$H$163,5,0)) -> 1 | H7: =+G7*B7 -> 0.11
B8: 0.06 | C8: 5.12 Aumentar # de viajes de EXA | D8: =IF(VLOOKUP($C8,Mensual!$D$6:$G$135,2,0)<0,0,VLOOKUP($C8,Mensual!$D$6:$G$135,2,0)) -> # de viajes | E8: =IF(VLOOKUP($C8,Mensual!$D$6:$G$163,3,0)<0,0,VLOOKUP($C8,Mensual!$D$6:$G$163,3,0)) -> 0.2 | F8: =IF(VLOOKUP($C8,Mensual!$D$6:$G$163,4,0)<0,0,VLOOKUP($C8,Mensual!$D$6:$G$163,4,0)) -> 0 | G8: =IF(VLOOKUP($C8,Mensual!$D$6:$H$163,5,0)<0,0,VLOOKUP($C8,Mensual!$D$6:$H$163,5,0)) -> 0 | H8: =+G8*B8 -> 0
B9: 0.1 | C9: 3. Cero incidentes mayores de seguridad y sostenibilidad | D9: =IF(VLOOKUP($C9,Mensual!$D$6:$G$135,2,0)<0,0,VLOOKUP($C9,Mensual!$D$6:$G$135,2,0)) -> 0 | E9: =IF(VLOOKUP($C9,Mensual!$D$6:$G$163,3,0)<0,0,VLOOKUP($C9,Mensual!$D$6:$G$163,3,0)) -> 1 | F9: =IF(VLOOKUP($C9,Mensual!$D$6:$G$163,4,0)<0,0,VLOOKUP($C9,Mensual!$D$6:$G$163,4,0)) -> 1 | G9: =IF(VLOOKUP($C9,Mensual!$D$6:$H$163,5,0)<0,0,VLOOKUP($C9,Mensual!$D$6:$H$163,5,0)) -> 1 | H9: =+G9*B9 -> 0.1
B10: 0.06 | C10: 5.1 Productividad kms/cabezal/mes. | D10: =IF(VLOOKUP($C10,Mensual!$D$6:$G$135,2,0)<0,0,VLOOKUP($C10,Mensual!$D$6:$G$135,2,0)) -> 0 | E10: =IF(VLOOKUP($C10,Mensual!$D$6:$G$163,3,0)<0,0,VLOOKUP($C10,Mensual!$D$6:$G$163,3,0)) -> 3700 | F10: =IF(VLOOKUP($C10,Mensual!$D$6:$G$163,4,0)<0,0,VLOOKUP($C10,Mensual!$D$6:$G$163,4,0)) -> 3932 | G10: =IF(VLOOKUP($C10,Mensual!$D$6:$H$163,5,0)<0,0,VLOOKUP($C10,Mensual!$D$6:$H$163,5,0)) -> 1 | H10: =+G10*B10 -> 0.06
B11: 0.05 | C11: 5.2 Productividad cabezales Flota Nueva | D11: =IF(VLOOKUP($C11,Mensual!$D$6:$G$135,2,0)<0,0,VLOOKUP($C11,Mensual!$D$6:$G$135,2,0)) -> 0 | E11: =IF(VLOOKUP($C11,Mensual!$D$6:$G$163,3,0)<0,0,VLOOKUP($C11,Mensual!$D$6:$G$163,3,0)) -> 4500 | F11: =IF(VLOOKUP($C11,Mensual!$D$6:$G$163,4,0)<0,0,VLOOKUP($C11,Mensual!$D$6:$G$163,4,0)) -> 4782 | G11: =IF(VLOOKUP($C11,Mensual!$D$6:$H$163,5,0)<0,0,VLOOKUP($C11,Mensual!$D$6:$H$163,5,0)) -> 1 | H11: =+G11*B11 -> 0.05
B12: 0.04 | C12: 5.3 Productividad cabezales TRANEXPA | D12: =IF(VLOOKUP($C12,Mensual!$D$6:$G$135,2,0)<0,0,VLOOKUP($C12,Mensual!$D$6:$G$135,2,0)) -> 0 | E12: =IF(VLOOKUP($C12,Mensual!$D$6:$G$163,3,0)<0,0,VLOOKUP($C12,Mensual!$D$6:$G$163,3,0)) -> 4000 | F12: =IF(VLOOKUP($C12,Mensual!$D$6:$G$163,4,0)<0,0,VLOOKUP($C12,Mensual!$D$6:$G$163,4,0)) -> 4268 | G12: =IF(VLOOKUP($C12,Mensual!$D$6:$H$163,5,0)<0,0,VLOOKUP($C12,Mensual!$D$6:$H$163,5,0)) -> 1 | H12: =+G12*B12 -> 0.04
B13: 0.04 | C13: 5.4 Productividad cabezales IPH | D13: =IF(VLOOKUP($C13,Mensual!$D$6:$G$135,2,0)<0,0,VLOOKUP($C13,Mensual!$D$6:$G$135,2,0)) -> 0 | E13: =IF(VLOOKUP($C13,Mensual!$D$6:$G$163,3,0)<0,0,VLOOKUP($C13,Mensual!$D$6:$G$163,3,0)) -> 3800 | F13: =IF(VLOOKUP($C13,Mensual!$D$6:$G$163,4,0)<0,0,VLOOKUP($C13,Mensual!$D$6:$G$163,4,0)) -> 3501 | G13: =IF(VLOOKUP($C13,Mensual!$D$6:$H$163,5,0)<0,0,VLOOKUP($C13,Mensual!$D$6:$H$163,5,0)) -> 0 | H13: =+G13*B13 -> 0
B14: 0.03 | C14: 5.5.1 Productividad cabezales Tranexpa Particulares. | D14: =IF(VLOOKUP($C14,Mensual!$D$6:$G$135,2,0)<0,0,VLOOKUP($C14,Mensual!$D$6:$G$135,2,0)) -> 0 | E14: =IF(VLOOKUP($C14,Mensual!$D$6:$G$163,3,0)<0,0,VLOOKUP($C14,Mensual!$D$6:$G$163,3,0)) -> 3500 | F14: =IF(VLOOKUP($C14,Mensual!$D$6:$G$163,4,0)<0,0,VLOOKUP($C14,Mensual!$D$6:$G$163,4,0)) -> 2144 | G14: =IF(VLOOKUP($C14,Mensual!$D$6:$H$163,5,0)<0,0,VLOOKUP($C14,Mensual!$D$6:$H$163,5,0)) -> 0 | H14: =+G14*B14 -> 0
B15: 0.03 | C15: 5.5.2 Productividad cabezales Ponce | D15: =IF(VLOOKUP($C15,Mensual!$D$6:$G$135,2,0)<0,0,VLOOKUP($C15,Mensual!$D$6:$G$135,2,0)) -> 0 | E15: =IF(VLOOKUP($C15,Mensual!$D$6:$G$163,3,0)<0,0,VLOOKUP($C15,Mensual!$D$6:$G$163,3,0)) -> 3500 | F15: =IF(VLOOKUP($C15,Mensual!$D$6:$G$163,4,0)<0,0,VLOOKUP($C15,Mensual!$D$6:$G$163,4,0)) -> 2560 | G15: =IF(VLOOKUP($C15,Mensual!$D$6:$H$163,5,0)<0,0,VLOOKUP($C15,Mensual!$D$6:$H$163,5,0)) -> 0 | H15: =+G15*B15 -> 0
B16: 0.03 | C16: 5.5.4 Productividad cabezales Obregon | D16: =IF(VLOOKUP($C16,Mensual!$D$6:$G$135,2,0)<0,0,VLOOKUP($C16,Mensual!$D$6:$G$135,2,0)) -> 0 | E16: =IF(VLOOKUP($C16,Mensual!$D$6:$G$163,3,0)<0,0,VLOOKUP($C16,Mensual!$D$6:$G$163,3,0)) -> 3500 | F16: =IF(VLOOKUP($C16,Mensual!$D$6:$G$163,4,0)<0,0,VLOOKUP($C16,Mensual!$D$6:$G$163,4,0)) -> 3165 | G16: =IF(VLOOKUP($C16,Mensual!$D$6:$H$163,5,0)<0,0,VLOOKUP($C16,Mensual!$D$6:$H$163,5,0)) -> 0 | H16: =+G16*B16 -> 0
B17: 0.03 | C17: 5.5.3 Productividad cabezales Moreno | D17: =IF(VLOOKUP($C17,Mensual!$D$6:$G$135,2,0)<0,0,VLOOKUP($C17,Mensual!$D$6:$G$135,2,0)) -> 0 | E17: =IF(VLOOKUP($C17,Mensual!$D$6:$G$163,3,0)<0,0,VLOOKUP($C17,Mensual!$D$6:$G$163,3,0)) -> 3500 | F17: =IF(VLOOKUP($C17,Mensual!$D$6:$G$163,4,0)<0,0,VLOOKUP($C17,Mensual!$D$6:$G$163,4,0)) -> 2923 | G17: =IF(VLOOKUP($C17,Mensual!$D$6:$H$163,5,0)<0,0,VLOOKUP($C17,Mensual!$D$6:$H$163,5,0)) -> 0 | H17: =+G17*B17 -> 0
B18: 0.03 | C18: 5.5.5 Productividad cabezales San Lorenzo | D18: =IF(VLOOKUP($C18,Mensual!$D$6:$G$135,2,0)<0,0,VLOOKUP($C18,Mensual!$D$6:$G$135,2,0)) -> 0 | E18: =IF(VLOOKUP($C18,Mensual!$D$6:$G$163,3,0)<0,0,VLOOKUP($C18,Mensual!$D$6:$G$163,3,0)) -> 3500 | F18: =IF(VLOOKUP($C18,Mensual!$D$6:$G$163,4,0)<0,0,VLOOKUP($C18,Mensual!$D$6:$G$163,4,0)) -> 2234 | G18: =IF(VLOOKUP($C18,Mensual!$D$6:$H$163,5,0)<0,0,VLOOKUP($C18,Mensual!$D$6:$H$163,5,0)) -> 0 | H18: =+G18*B18 -> 0
... B23: 0.09 | C23: 5.8 Aumentar kms EXA | D23: =IF(VLOOKUP($C23,Mensual!$D$6:$G$135,2,0)<0,0,VLOOKUP($C23,Mensual!$D$6:$G$135,2,0)) -> kms | E23: =IF(VLOOKUP($C23,Mensual!$D$6:$G$163,3,0)<0,0,VLOOKUP($C23,Mensual!$D$6:$G$163,3,0)) -> 506974.68 | F23: =IF(VLOOKUP($C23,Mensual!$D$6:$G$163,4,0)<0,0,VLOOKUP($C23,Mensual!$D$6:$G$163,4,0)) -> 485973.6 | G23: =IF(VLOOKUP($C23,Mensual!$D$6:$H$163,5,0)<0,0,VLOOKUP($C23,Mensual!$D$6:$H$163,5,0)) -> 0 | H23: =+G23*B23 -> 0
B24: =SUM(B6:B23) -> 1 | H24: =SUM(H6:H23) -> 0.63325
C27: Colaboradores:
C28: Sinia Murillo
C29: Josseline Chavarria
C30: Edgardo Hernandez

Sheet Mensual (2)
A1: hola | B1: Fechas comparables
B2: Inicio | F2: 44197 | G2: Fin | I2: 31/01/2021
B3: Periodo inicial | F3: 2021 | G3: vs | I3: 2022
G4: L=$ | I4: 1 | J4: 25
A5: Empresa | B5: Cuenta contable | C5: Fuente | E5: FÓRMULA | F5: Peso | G5: Descripción | I5: Unidad de medición | J5: Meta | K5: Resultado | L5: Nota | M5: Valor ponderado | N5: 0 | O5: 0.25 | P5: 0.5 | Q5: 1
A6: (EXA, CONMOXA, AXA, TREXA, SAN JORGE) | B6: 41 | C6: SAP | E6: SUMA DE LA CUENTA 41 DEL PERÍODO ACTUAL ENTRE LA SUMA DE LA CUENTA 41 DEL AÑO ANTERIO | F6: 0.325 | G6: 1. Aumentar ventas en el año 2023 del Grupo EXA (EXA, CONMOXA, AXA, TREXA, SAN JORGE) en 10% en USD vs año 2022. | H6: Utillizar saldo en dólares | I6: Porcentaje | J6: 0.1 | K6: 0.2 | L6: =IF(K6>(J6*1.1),1.1,IF(K6<0,0,K6/J6)) -> 1.1 | M6: =+L6*F6 -> 0.3575
A7: (EXA, CONMOXA, AXA, TREXA, SAN JORGE) | B7: 410101 | C7: SAP | E7: SUMA DE LA CUENTA 410101 DEL PERÍODO ACTUAL ENTRE LA SUMA DE LA CUENTA 410101 DEL AÑO ANTERIO | G7: 1. Aumentar ventas en el año 2023 del Grupo EXA las ventas de transporte en 10% en USD vs año 2022. | J7: 0.2 | K7: -0.15 | L7: =IF(K7>J7,1,IF(K7<0,0,K7/J7)) -> 0 | M7: =+L7*F7 -> 0
A8: (EXA, CONMOXA, AXA, TREXA, SAN JORGE) | B8: ANÁLISIS DE VENTAS POR ARTÍCULO, | C8: SAP | E8: PENDIENTE Anàlisis de venta de contenedores | F8: NANCY | G8: Vender 10 contenedores / mes en el 2023 en el Grupo EXA | J8: 15 | K8: 1 | L8: =IF(K8>J8,1,IF(K8<0,0,K8/J8)) -> 0.066666667 | M8: =+L8*F8 -> #VALUE!
A9: (EXA, CONMOXA, AXA, TREXA, SAN JORGE) | B9: 410202 | C9: SAP | E9: SUMA DE LA CUENTA 410202 al final del mes | G9: Vender $ 40,000 / mes por concepto de contenedores secos, reefer, nor, proyectos, el 2023 en el grupo EXA | I9: Dólares | J9: =1000000/$J$4 -> 40000 | K9: 1800 | L9: =IF(K9>J9,1,IF(K9<0,0,K9/J9)) -> 0.045
A10: (EXA, CONMOXA, AXA, TREXA, SAN JORGE) | B10: 410108002 | C10: SAP | E10: SALDO de la cuenta 410108002 al final de mes o período | G10: Vender $ 16,000 / mes por concepto de alquileres de contenedores reefer (solo o en combo) | I10: Dólares | J10: =400000/$J$4 -> 16000 | K10: 0 | L10: =IF(K10>J10,1,IF(K10<0,0,K10/J10)) -> 0
A11: ( AXA, SAN JORGE) | B11: 410107001 | C11: sap | E11: SALDO DE LA CUENTA 410107001 AL FINAL DEL MES | G11: Aumentar ventas por concepto de biens y raíces (EXA, CONMOXA, AXA, TREXA, SAN JORGE) en 20% en USD vs año 2022. | I11: Porcentaje | J11: 0.2 | K11: -0.37 | L11: =IF(K11>J11,1,IF(K11<0,0,K11/J11)) -> 0
A12: (EXA, CONMOXA, AXA, TREXA, SAN JORGE) | B12: SA -000046 | C12: SAP | E12: SUMA DE los ingresos del artículo SA -000046 al final del mes | G12: Aumentar ventas por concepto de alquiler de contenedores secos (EXA, CONMOXA, AXA, TREXA, SAN JORGE) en 20% en USD vs año 2022. | I12: Porcentaje | J12: 0.2 | K12: 0.45 | L12: =IF(K12>J12,1,IF(K12<0,0,K12/J12)) -> 1 | N12: Se consideró solo 2019
A13: CONMOXA | B13: 410203 | C13: SAP | E13: ANÁLISIS DE ventas por artículo / grupo combustible / mes * revisar si se rebajan las notas de crédito | G13: Aumentar ventas en el año 2023 de CONMOXA en 5% en GALONES vs año 2022. | I13: % | J13: 0.05 | K13: 112588 | L13: =IF(K13>J13,1,IF(K13<0,0,K13/J13)) -> 1 | M13: =+L13*F13 -> 0
A14: TREXA | B14: 41 | C14: SAP | E14: SUMA DE LA CUENTA 41 DEL PERÍODO ACTUAL ENTRE LA SUMA DE LA CUENTA 41 DEL AÑO ANTERIO | G14: Aumentar ventas en el año 2023 de TREXA en 15% en DÓLARES vs año 2022. | I14: Dólares | J14: 0.15 | K14: 1.03 | L14: =IF(K14>J14,1,IF(K14<0,0,K14/J14)) -> 1 | M14: =+L14*F14 -> 0
A15: CONMOXA | B15: ARTÍCULOS SAP | C15: SAP | E15: sUMA DE LA CANTIDAD DE EQUIPOS VENDIDOS, DE LOS ARTÍCULOS GPS MC - 0000027,28,36,61 ** POSIBILIDAD DE AGREGAR OTRO ARTÍCULO | G15: Vender10 GPS a terceros / mes vs año 2022 | I15: Unidad instaladas / mensuales | J15: 10 | K15: 0 | L15: =IF(K15>J15,1,IF(K15<0,0,K15/J15)) -> 0 | M15: =+L15*F15 -> 0
A16: INTERNATIONAL CONSULTING | B16: 410201 International C. | C16: SAP | E16: SUMA DE LAS CANTIDADES DE LOS ARTÍCULOS DEL GRUPO VENDIDOS EN EL MES | G16: Vender10 artículos de Sejue/get504 / mes vs año 2022 | I16: Articulos | J16: 10 | K16: 19 | L16: =IF(K16>J16,1,IF(K16<0,0,K16/J16)) -> 1 | M16: =+L16*F16 -> 0
A17: CONMOXA | B17: 410201001 | C17: SAP | E17: SUMA DE LOS INGRESOS DE LA CUENTA 41021001 AL FINAL DEL MES | G17: Aumentar ventas en 15% / mes por concepto de TIENDA DE CONVENIENCIA MEGA, el 2023 en CONMOXA en relación al 2022 | I17: Dólares | J17: 25000 | K17: 20092.4 | L17: =IF(K17>J17,1,IF(K17<0,0,K17/J17)) -> 0.803696
A18: (EXA, CONMOXA, AXA, TREXA, SAN JORGE) | B18: 410102001 y 410103001 | C18: SAP | E18: SUMA DE LOS SALDOS DE LAS CUENTAS 410102001 Y 410103001 AL FINAL DEL MES VS AÑO ANTERIOR | G18: Aumentar renta de chasis y/o genset sin contenedor EN 20% DEL GRUPO EN USD VS AÑO 2022 | I18: Chasis rentados | J18: 0.2 | K18: -0.39 | L18: =IF(K18>J18,1,IF(K18<0,0,K18/J18)) -> 0
A19: (EXA, CONMOXA, TREXA) | B19: 4101105001 | C19: SAP | E19: SUMA DE LOS INGRESOS DE LA CUENTA 4101105001 AL FINAL DE MES | G19: Aumentar 20% $ servicio de almacenamiento y M&R San Lorenzo vs año 2022 | J19: 0.2 | K19: 0.3 | L19: =IF(K19>J19,1,IF(K19<0,0,K19/J19)) -> 1 | N19: sin considerar enp
A20: (EXA, CONMOXA, TREXA) | C20: DEPOT | E20: # DE GATES DEPOT | G20: Aumentar 20% LOS GATE OUTS Puerto Cortés vs año 2022 | I20: Gate | J20: 0.2 | K20: -0.5 | L20: =IF(K20>J20,1,IF(K20<0,0,K20/J20)) -> 0
A21: (EXA, CONMOXA, TREXA) | B21: 4101105002 | G21: Aumentar 20% $ servicio de almacenamiento y M&R Puerto Cortés vs año 2022
A22: (EXA, CONMOXA, TREXA) | C22: SAP | G22: Aumentar el numero de clientes en transporte semestralmente (1) (no cuenta clientes con ventas inferiores a $10,000.00 mensuales | I22: cliente | J22: 1
A23: CONMOXA | C23: SAP | E23: ANÁLISIS DE ventas por artículo por propiedad | G23: Aumentar ventas en 25% / mes por concepto de Xcafé y YommyYommy, el 2023 en CONMOXA en relación al 202
A24: CONMOXA | C24: SAP | E24: ANÁLISIS DE ventas por artículo por propiedad | G24: Aumentar ventas en Mega Part´s en 25% en $ vs año 2022
A26: (EXA, CONMOXA, AXA, TREXA, SAN JORGE) | C26: SAP | E26: utilidad periodo actual entre utilidad periodo año anterior menos 1 | F26: 0.275 | G26: 2. Aumentar margen neto vrs año anterior | J26: 0.1 | K26: 0.1 | L26: =IF(K26>J26,1,IF(K26<0,0,K26/J26)) -> 1 | M26: =+L26*F26 -> 0.275 | N26: 0
A27: (EXA, CONMOXA, AXA, TREXA, SAN JORGE) | B27: 61/41 | C27: SAP | E27: suma de total cta 61/41 | G27: 2.1 Reducir gasto administrativo x% | I27: % | J27: 0.1 | K27: 0.32 | L27: =IF(K27>J27,1,IF(K27<0,0,K27/J27)) -> 1
A28: EXA, CONMOXA, TREXA | B28: 510102 | C28: SAP/EMS/DEPOT | E28: SE NECESITAN DOS CAMPOS UNO % PONDERACIÓN ALQUILADOS VS EN USO, OTRO CAMPO PARA AGREGAR CANTIDAD DE KILÓMETROS EL RESULTADO SERÁ CENTAVOS $ /KM (SUMA DE TODAS LAS EMPRESAS 510102*%CHASISENUSO/KMSDELMES) | G28: 2.2 Reducir costo de M&R de chasis propios | I28: $/km | J28: 0.05 | K28: 0.09 | L28: =IF(K28>J28,0,IF(K28<0,0,K28/J28)) -> 0
A29: EXA, CONMOXA, TREXA | B29: 510105005+510105006+510105007 | E29: SE NECESITA UN CAMPO PARA AGREGAR KILOMETROS POR MES EL RESULTADO SERÁ CENTAVOS EN DÓLARES (SUMA DE TODAS LAS EMPRESAS 510105005+510105006+510105007/KMSDELMES) | G29: 2.3 Reducir Costo por DE MYR y otros POR km de cabezales propios. | I29: $ | J29: 0.25 | K29: 0.6 | L29: =IF(K29>J29,1,IF(K29<0,0,K29/J29)) -> 1
E30: ems | G30: 2.4 Mantener Costo por km otras subdivisiones. | I30: $ | J30: 0.05 | K30: 0.0319 | L30: =IF(K30>J30,1,IF(K30<0,0,K30/J30)) -> 0.638
A31: EXA, CONMOXA, TREXA | C31: SAP | E31: Total de la cuenta 410202001+410202003 me nos costos por venta de contenedores modificadosa(510107001+510107003+510107006+510107009+5101070011+5101070012) año actual vs año anterior | G31: 2.5 Aumentar Margen BRUTO en venta de contenedores (modificados y secos) | I31: % | J31: 0.1 | K31: -2.92 | L31: =IF(K31>J31,1,IF(K31<0,0,K31/J31)) -> 0
A32: ELIMINAR | G32: 2.6 Aumento en 20% en margen de contribución bruta venta de contenedores | I32: $ | J32: 0.2 | K32: 0 | L32: =IF(K32>J32,1,IF(K32<0,0,K32/J32)) -> 0
A33: EXA, CONMOXA, TREXA | C33: SAP | E33: 410108001-(510107004+510107007) mes año actual vs año anterior | G33: 2.7 Aumento en 20% en margen de contribución bruta alquiler de secos | I33: $ | J33: 0.2 | L33: =IF(K33>J33,1,IF(K33<0,0,K33/J33)) -> 0
A34: EXA, CONMOXA, TREXA | C34: SAP | E34: 410108002-(510107005+510107008) MES AÑO ACTUAL VS AÑO ANTERIOR VALOR DEBE SER DADO EN PORCENTAJE | G34: 2.8 Aumento en 20% en margen de contribución bruta alquiler de reefers. | I34: $ | J34: 0.2 | L34: =IF(K34>J34,1,IF(K34<0,0,K34/J34)) -> 0
A35: (EXA, CONMOXA, AXA, TREXA, SAN JORGE) | E35: obtener dato del centro de costo por zona Puerto Cortés PCO-COR vs el año anterior | G35: 2.9 Reducir Costo administrativo Puerto Cortés con relacion al año anterior | J35: 0.05 | L35: =IF(K35>J35,1,IF(K35<0,0,K35/J35)) -> 0 | N35: No se puede generar por falta de centro de uso de centro de costo en 2019
A36: (EXA, CONMOXA, AXA, TREXA, SAN JORGE) | E36: 6101/41 MES ACTUAL | G36: 2.10 Mantener el Gasto administrativo San Pedro Sula (APLICA GLOBAL) | I36: dolares | J36: 0.135 | L36: =IF(K36>J36,1,IF(K36<0,0,K36/J36)) -> 0 | M36: =+L36*F36 -> 0 | N36: No se puede generar por falta de centro de uso de centro de costo en 2020
A37: (EXA, CONMOXA, AXA, TREXA, SAN JORGE) | E37: obtener dato del centro de costo por zona Puerto Cortés PCO-SLO vs el año anterior | G37: 2.11 Gasto administrativo San Lorenzo | J37: 0.1 | L37: =IF(K37>J37,1,IF(K37<0,0,K37/J37)) -> 0 | M37: =+L37*F37 -> 0 | N37: No se puede generar por falta de centro de uso de centro de costo en 2021
E38: CENTRO DE COSTOS DE GPS ENTRE CANTIDAD DE EQUIPOS QUE REPORTAN AGREGAR UN CAMPO PARA PONER EL NUMERO DE EQUIPOS | G38: 2.12 Costo por mes por GPS (Costo de plataforma + Tigo/claro + otros costos) | I38: $ | J38: 8 | K38: 4.71 | L38: =IF(K38<J38,1,IF(K38<0,0,K38/J38)) -> 1 | M38: 1
E39: 510104001 +510104002 +510104002 MES ACTUAL VS AÑO ANTERIOR PORCENTAJE | G39: 2.13 Reducir Costo de M&R por contenedor Puerto Cortes | I39: $/contenedor | J39: 0.1 | L39: =IF(K39>J39,1,IF(K39<0,0,K39/J39)) -> 0
A40: (EXA, CONMOXA, AXA, TREXA, SAN JORGE) | C40: SAP | E40: 510103 ENTRE LOS GATE IN CONTENEDORES VS AÑO ANTERIOR, DOS CAMPOS PARA AGREGAR LOS GATE IN AÑO ACTUAL Y AÑO ANTERIOR Y LUEGO DIVIDIR Y SACAR EL PORCENTAJE | G40: 2.14 Reducir costo máquinas (incluye mulita y containers handler) Puerto Cortes | I40: $/contenedor | J40: 0.1 | L40: =IF(K40>J40,1,IF(K40<0,0,K40/J40)) -> 0 | M40: Se estan yendo a una sola cuenta
A41: (EXA, CONMOXA, AXA, TREXA, SAN JORGE) | C41: SAP | G41: 2.15 Aumentar margen de M&R por contenedor San Lorenzo | I41: Porcentaje | J41: 0.1
G42: 2.16 Reducir costo máquinas (incluye mulita y containers handler) San Lorenzo | M42: Se estan yendo a una sola cuenta
A43: TRANEXPA | B43: 510105 | C43: EMS | E43: 510105 + Total deducciones ems entre el total de kilómetros del mes tranexpa, dos campos que se deben agregar divididos entre el valor del año anterior | G43: 2.17 Reducir costo por km/cabezal TRANEXPA | J43: -0.1 | K43: 0.14 | L43: =IF(K43<J43,1,IF(K43<0,0,0)) -> 0
A44: EXA, CONMOXA, TREXA | E44: Total de la cuenta 510106002+510106003+510106004 entre la cantidad de gensets activos del mes año actual vs año anterior | G44: 2.18 Reducir M&R gensets $ /genset activo 10% | I44: dolares | J44: 0.1 | K44: 4.66 | L44: =IF(K44<J44,1,IF(K44<0,0,0)) -> 0
E45: (6101-610108)+(8101+520101+ 510108+510110) dividido entre (410201+410203) mes actual año actual vs año anterior | G45: 2.19 Margen neto gasolinera superior a 3% en relación a las ventas | I45: dolares | J45: 0.04 | K45: 0.07 | L45: =IF(K45<J45,1,IF(K45<0,0,0)) -> 0
A46: conmoxa | E46: 410201-510108-(35%x510110004)-520101 mes año actual vs año de comparación | G46: 2.20 Margen operativo de tienda | J46: 0.1 | K46: -0.0005 | L46: =IF(K46>J46,1,IF(K46<0,0,0)) -> 0
A47: exa | E47: Agregar campo para ponderación del porcentaje de los chasis Suma de la cuentas 410101 menos 510101*(porcentaje de ponderación * 510102)-510103-510104-510105-510106-510108-6101-8101+610105004-5201 vs año anterior EXA | G47: 2.21 Aumentar % neto del servicio de transporte | J47: 0.1 | K47: 0.1 | L47: 1
A48: trexa | E48: 410108-5101-5201-6101-8101 | G48: 2.22 Aumentar margen neto alquiler de contenedores secos (solo o en combo) TREXA | J48: 0.1 | K48: 0.1 | L48: 1
B49: 3 | F49: 0.05 | G49: 3. Cero incidentes mayores de seguridad y sostenibilidad | J49: 1 | K49: 1 | L49: =IF(K49>J49,1,IF(K49<0,0,K49/J49)) -> 1 | M49: =+L49*F49 -> 0.05 | N49: >0 | Q49: 0
G50: 3.1 Robos. | J50: 0 | K50: 0 | L50: 1 | M50: =+L50*F50 -> 0
G51: 3.2 Accidentes. | J51: 0 | K51: 0 | L51: 1 | M51: =+L51*F51 -> 0
G52: 3.3 No conformidades mayores. | J52: 0 | K52: 0 | L52: 1 | M52: =+L52*F52 -> 0
J53: 0 | K53: 0 | L53: 1 | M53: =+L53*F53 -> 0
J54: 0 | L54: 1 | M54: =+L54*F54 -> 0
G55: 3.6 Cierres contables a mas tardar el 6 de cada mes | I55: # de cierres a tiempo | J55: 6 | K55: 6 | L55: =IF(K55>J55,1,IF(K55<0,0,K55/J55)) -> 1
G56: 3.6.1 Cierre TREXA | I56: # de cierres a tiempo | J56: 1 | K56: 1 | L56: =IF(K56>J56,1,IF(K56<0,0,K56/J56)) -> 1
G57: 3.7 Cero accidente mayores Y/O robos TRANEXPA
G58: 2.21 Margen operativo de la gasolinera | I58: dolares | J58: 0.1 | K58: 0.06 | L58: 0
G59: 3.8 Aumentar satisfaccion al cliente | J59: 0.1 | K59: 1 | L59: 1
G60: 3.9 On time delivery without sevice incidents | J60: 0.995 | K60: 1 | L60: 1
B61: 4 | F61: 0.1 | G61: 4. Aumentar clima laboral | J61: 0.1 | K61: 0.1 | L61: =IF(K61>J61,1,IF(K61<0,0,K61/J61)) -> 1 | M61: =+L61*F61 -> 0.1
G63: 0.5
B66: 5 | F66: 0.1 | G66: 5. Productividad | J66: 3700 | K66: 3932 | L66: =IF(K66>J66,1,IF(K66<0,0,K66/J66)) -> 1 | M66: =+L66*F66 -> 0.1 | N66: Ninguna o Tranexpa | O66: General o tranexpa o EXA | P66: General+ EXA | Q66: # general+ EXA + Tranexpa
G67: 5.1 Productividad kms/cabezal/mes. | J67: =+J66 -> 3700 | K67: =+K66 -> 3932 | L67: =IF(K67>J67,1,IF(K67<0,0,K67/J67)) -> 1
F68: 0.08 | G68: 5.2 Productividad cabezales Flota Nueva | J68: 4500 | K68: 4782 | L68: =IF(K68>J68,1,IF(K68<0,0,K68/J68)) -> 1 | M68: =+L68*F68 -> 0.08
F69: 0.12 | G69: 5.3 Productividad cabezales TRANEXPA | J69: 4000 | K69: 4268 | L69: =IF(K69>J69,1,0) -> 1 | M69: =+L69*F69 -> 0.12
F70: 0.1 | G70: 5.4 Productividad cabezales IPH | J70: 3800 | K70: 3501 | L70: =IF(K70>J70,1,0) -> 0 | M70: =+L70*F70 -> 0
F71: 0.7 | G71: 5.5 Productividad cabezales Particulares. | J71: 3500 | K71: 2429 | L71: =IF(K71>J71,1,0) -> 0 | M71: =+L71*F71 -> 0 | N71: 4/6 transportes
G72: 5.5.1 Productividad cabezales Tranexpa Particulares. | J72: =+J71 -> 3500 | K72: 2144 | L72: =IF(K72>J72,1,0) -> 0
G73: 5.5.2 Productividad cabezales Ponce | J73: =+J71 -> 3500 | K73: 2560 | L73: =IF(K73>J73,1,0) -> 0
G74: 5.5.3 Productividad cabezales Moreno | J74: =+J71 -> 3500 | K74: 2923 | L74: =IF(K74>J74,1,0) -> 0
G75: 5.5.4 Productividad cabezales Obregon | J75: =+J71 -> 3500 | K75: 3165 | L75: =IF(K75>J75,1,0) -> 0
G76: 5.5.5 Productividad cabezales San Lorenzo | J76: =+J71 -> 3500 | K76: 2234 | L76: =IF(K76>J76,1,0) -> 0
G77: 5.5.6 Productividad cabezales Sinai | J77: =+J72 -> 3500 | K77: 1551 | L77: =IF(K77>J77,1,0) -> 0
G78: 5.6 Aprovechamiento GPS | J78: 0.9 | K78: 0.82 | L78: =IF(K78>J78,1,K78/J78) -> 0.91111111
G79: 5.7 Dias de facturacion | J79: 4 | K79: 6 | L79: =IF(K79>J79,1,0) -> 1
G80: 5.8 Aumentar kms EXA | I80: kms | J80: =(410915.3+434042.5)/2*1.2 -> 506974.68 | K80: 485973.6 | L80: =IF(K80>J80,1,IF(K80<0,0,K80/J80-1)) -> -0.041424317
G81: 5.8.1 Aumentar kms clientes Jacky Mena (Rango110-90) | J81: 100000
G82: 5.8.2 Aumentar kms clientes Honoria Rodriguez (Rango 110-90) | I82: kms/mes | J82: 100000
G83: 5.8.3 Aumentar kms clientes Sinia Murillo (Rango 110-90) | J83: 100000
G84: 5.8.4 Aumentar kms clientes Josselyn Chavarria (Rango 110-90) | J84: 100000
G85: 5.8.5 Aumentar kms clientes Edgardo Hernandez (Rango 150-115) | J85: 100000
G86: 5.9 Aumentar Total kms cabezales propios | I86: kms | J86: 0.2
G87: 5.10 Aumentar kms TRANEXPA | I87: kms | J87: 0.2 | K87: 0 | L87: =IF(K87>J87,0,IF(K87<0,0,K87/J87)) -> 0
G88: 5.11 # de fallas operativas adjudicables al predio (Incluye rescates, rechazos) Puerto Cortes | I88: # de fallas | J88: 1 | K88: 0 | L88: 1
G89: 5.12 Aumentar # de viajes de EXA | I89: # de viajes | J89: 0.2 | K89: -0.32 | L89: 0 | M89: =+J89/1.2 -> 0.16666667 | N89: 0.2
G90: 5.9.1 Aumentar numero de viajes Jacky | I90: # de viajes
G91: 5.9.2 Aumentar numero de viajes Honoria | I91: # de viajes
G92: 5.9.3 Aumentar numero de viajes Sinia | I92: # de viajes
G93: 5.9.4 Aumentar numero de viajes Josselyn | I93: # de viajes
G94: 5.9.5 Aumentar numero de viajes Edgardo | I94: # de viajes
G95: 5.13 Aumenar promedio de kms/viaje | I95: kms/viaje | J95: 0.1 | K95: =+(1.25182481751825)-1 -> 0.25182482 | L95: =IF(K95>J95,1,IF(K95<0,0,K95/J95)) -> 1
G96: 5.14 90% de cabezales dentro de un +-10% del promedio de kms cabezal/mes | I96: Porcentaje | J96: 0.9
G97: 5.15 # de fallas operativas adjudicables al predio (Incluye rescates, rechazos) San Lorenzo | J97: 0 | K97: 0 | L97: 1
G98: 5.16 # de notas de credito mensuales | I98: # notas de credito
A100: (EXA, CONMOXA, AXA, TREXA, SAN JORGE) | B100: 6 | E100: Utilidad neta del mes y periodo actual entre Total de activos vs el año anterior (cada año la cuenta de pérdidas y utilidades cambia) | F100: 0.05 | G100: 6. Aumentar el ROA | J100: 0.05 | K100: 1 | L100: =IF(K100>J100,1,IF(K100<0,0,K100/J100)) -> 1 | M100: =+L100*F100 -> 0.05
G101: 6.1 Aumentar Rotación de inventario. | J101: 0.05 | L101: =IF(K101>J101,1,IF(K101<0,0,K101/J101)) -> 0 | M101: =+L101*F101 -> 0
G102: 6.2 Disminuir a 5% el desuso de los chasis (equipos con mas de 30 dias en las yardas) | I102: % | J102: 0.05 | K102: 0.05 | L102: =IF(K102>J102,1,IF(K102<0,0,K102/J102)) -> 1 | M102: =+L102*F102 -> 0
G103: 6.2.1 Disminuir a 5% el desuso de los equipos Puerto Cortés (equipos con mas de 30 dias en yarda) | I103: Equipos | J103: 30 | K103: 45 | L103: =IF(K103>J103,0,IF(K103<0,0,K103/J103)) -> 0
G104: 6.2.2 Disminuir a 1% el desuso de los equipos San Lorenzo (equipos con mas de 30 dias en yarda) | I104: Equipos | J104: 6 | K104: 7 | L104: =IF(K104>J104,0,IF(K104<0,0,K104/J104)) -> 0
G105: 6. 3 Disminuir a 0-1 los cabezales TRANEXPA | J105: 1 | K105: 2 | L105: =IF(K105>J105,0,IF(K105<0,0,K105/J105)) -> 0
...

Sheet Hoja3
A1: Peso | B1: Descripción | C1: Unidad de medición | D1: Meta | E1: Resultado | F1: Nota | G1: Valor ponderado | H1: 0 | I1: 0.25 | J1: 0.5 | K1: 1 | L1: Empresa | M1: Cuenta contable | N1: Fuente | O1: FÓRMULA
A2: 0.325 | B2: 1. Aumentar ventas en el año 2023 del Grupo EXA (EXA, CONMOXA, AXA, TREXA, SAN JORGE) en 10% en USD vs año 2022. | C2: Porcentaje | D2: 0.1 | E2: 0.2 | F2: =IF(E2>(D2*1.1),1.1,IF(E2<0,0,E2/D2)) -> 1.1 | G2: =+F2*A2 -> 0.3575 | L2: (EXA, CONMOXA, AXA, TREXA, SAN JORGE) | M2: 41 | N2: SAP | O2: SUMA DE LA CUENTA 41 DEL PERÍODO ACTUAL ENTRE LA SUMA DE LA CUENTA 41 DEL AÑO ANTERIO
A3: 0.275 | B3: 2. Aumentar margen neto vrs año anterior | D3: 0.1 | E3: 0.1 | F3: =IF(E3>D3,1,IF(E3<0,0,E3/D3)) -> 1 | G3: =+F3*A3 -> 0.275 | H3: 0 | L3: (EXA, CONMOXA, AXA, TREXA, SAN JORGE) | N3: SAP | O3: utilidad periodo actual entre utilidad periodo año anterior menos 1
A4: 0.05 | B4: 3. Cero incidentes mayores de seguridad y sostenibilidad | D4: 1 | E4: 1 | F4: =IF(E4>D4,1,IF(E4<0,0,E4/D4)) -> 1 | G4: =+F4*A4 -> 0.05 | H4: >0 | K4: 0 | M4: 3
A5: 0.1 | B5: 4. Aumentar clima laboral | D5: 0.1 | E5: 0.1 | F5: =IF(E5>D5,1,IF(E5<0,0,E5/D5)) -> 1 | G5: =+F5*A5 -> 0.1 | M5: 4
A6: 0.1 | B6: 5. Productividad | D6: 3700 | E6: 3932 | F6: =IF(E6>D6,1,IF(E6<0,0,E6/D6)) -> 1 | G6: =+F6*A6 -> 0.1 | H6: Ninguna o Tranexpa | I6: General o tranexpa o EXA | J6: General+ EXA | K6: # general+ EXA + Tranexpa | M6: 5
A7: 0.05 | B7: 6. Aumentar el ROA | D7: 0.05 | E7: 1 | F7: =IF(E7>D7,1,IF(E7<0,0,E7/D7)) -> 1 | G7: =+F7*A7 -> 0.05 | L7: (EXA, CONMOXA, AXA, TREXA, SAN JORGE) | M7: 6 | O7: Utilidad neta del mes y periodo actual entre Total de activos vs el año anterior (cada año la cuenta de pérdidas y utilidades cambia)
A8: 0.05 | B8: 7. Disminuir el D/E | D8: 0.05 | E8: 0.05 | F8: =IF(E8>D8,1,IF(E8<0,0,E8/D8)) -> 1 | G8: =+F8*A8 -> 0.05 | L8: (EXA, CONMOXA, AXA, TREXA, SAN JORGE) | M8: 7 | O8: (21+22)/(31 + utilidad a la fech la fecha) mes actual y año actual vs año anterior
A9: 0.05 | B9: 8. Innovaciones estratégicas de sistemas de Impacto recurrente | D9: 1 | E9: 1 | F9: =IF(E9>D9,1,IF(E9<0,0,E9/D9)) -> 1 | G9: =+F9*A9 -> 0.05 | M9: 8
A11: RESULTADOS | C11: META | E11: ENERO | F11: FEBRERO | G11: MARZO | H11: ABRIL | I11: MAYO | J11: JUNIO | K11: JULIO | L11: AGOSTO | M11: SEPTIEMBRE | N11: OCTUBRE | O11: NOVIEMBRE | P11: DICIEMBRE
A12: =+B2 -> 1. Aumentar ventas en el año 2023 del Grupo EXA (EXA, CONMOXA, AXA, TREXA, SAN JORGE) en 10% en USD vs año 2022. | B12: =+C2 -> Porcentaje | C12: =+D2 -> 0.1
A13: =+B3 -> 2. Aumentar margen neto vrs año anterior | B13: =+C3 -> 0 | C13: =+D3 -> 0.1
A14: =+B4 -> 3. Cero incidentes mayores de seguridad y sostenibilidad | B14: =+C4 -> 0 | C14: =+D4 -> 1
A15: =+B5 -> 4. Aumentar clima laboral | B15: =+C5 -> 0 | C15: =+D5 -> 0.1
A16: =+B6 -> 5. Productividad | B16: =+C6 -> 0 | C16: =+D6 -> 3700
A17: =+B7 -> 6. Aumentar el ROA | B17: =+C7 -> 0 | C17: =+D7 -> 0.05
A18: =+B8 -> 7. Disminuir el D/E | B18: =+C8 -> 0 | C18: =+D8 -> 0.05
A20: NOTA | E20: ENERO | F20: FEBRERO | G20: MARZO | H20: ABRIL | I20: MAYO | J20: JUNIO | K20: JULIO | L20: AGOSTO | M20: SEPTIEMBRE | N20: OCTUBRE | O20: NOVIEMBRE | P20: DICIEMBRE
A21: =+A2 -> 0.325 | B21: =+A12 -> 1. Aumentar ventas en el año 2023 del Grupo EXA (EXA, CONMOXA, AXA, TREXA, SAN JORGE) en 10% en USD vs año 2022. | C21: =+B12 -> Porcentaje | D21: =+C12 -> 0.1 | E21: =IF(D21>(C21*1.1),1.1,IF(D21<0,0,D21/C21)) -> #VALUE!
A22: =+A3 -> 0.275 | B22: =+A13 -> 2. Aumentar margen neto vrs año anterior
A23: =+A4 -> 0.05 | B23: =+A14 -> 3. Cero incidentes mayores de seguridad y sostenibilidad
A24: =+A5 -> 0.1 | B24: =+A15 -> 4. Aumentar clima laboral
A25: =+A6 -> 0.1 | B25: =+A16 -> 5. Productividad
A26: =+A7 -> 0.05 | B26: =+A17 -> 6. Aumentar el ROA
A27: =+A8 -> 0.05 | B27: =+A18 -> 7. Disminuir el D/E
A29: NOTAS PONDERADAS

Sheet Mensual
A1: hola | B1: Fechas comparables
B2: Inicio | C2: 44197 | D2: Fin | E2: 31/01/2021
B3: Periodo inicial | C3: 2021 | D3: vs | E3: 2022
D4: L=$ | E4: 1 | F4: 25
A5: Empresa | B5: No | C5: Peso | D5: Descripción | E5: Unidad de medición | F5: Meta | G5: Resultado | H5: Nota | I5: Valor ponderado | J5: 0 | K5: 0.25 | L5: 0.5 | M5: 1
A6: Todas | B6: 4 | C6: 0.325 | D6: 1. Aumentar ventas en: | F6: 0.2 | G6: 0.2491 | H6: =IF(G6>(F6*1.1),1.1,IF(G6<0,0,G6/F6)) -> 1.1 | I6: =+H6*C6 -> 0.3575
B7: 410101 | D7: 1.1 Aumentar ventas de transporte | F7: 0.2 | G7: -0.15 | H7: =IF(G7>F7,1,IF(G7<0,0,G7/F7)) -> 0 | I7: =+H7*C7 -> 0
D8: 1.2 Lograr meta de contenedores | F8: 15 | G8: 1 | H8: =IF(G8>F8,1,IF(G8<0,0,G8/F8)) -> 0.066666667 | I8: =+H8*C8 -> 0
B9: 410202 | D9: 1.3 Lograr meta de ventas contenedores secos y modificados(dolares) | E9: Dólares | F9: =1000000/$F$4 -> 40000 | G9: 1800 | H9: =IF(G9>F9,1,IF(G9<0,0,G9/F9)) -> 0.045
B10: 410108002 | D10: 1.4 Lograr meta de ventas en alquileres de contenedores reefer (solo o en combo) | E10: Dólares | F10: =400000/$F$4 -> 16000 | G10: 0 | H10: =IF(G10>F10,1,IF(G10<0,0,G10/F10)) -> 0
B11: 410107 | D11: 1.5 Aumentar Rentas bienes y raices | E11: Porcentaje | F11: 0.2 | G11: -0.37 | H11: =IF(G11>F11,1,IF(G11<0,0,G11/F11)) -> 0
B12: 410108001 y 410108003 | D12: 1.6 Alquileres de contenedores secos (solo o en combos CONMOXA) | E12: Porcentaje | F12: 0.2 | G12: 0.45 | H12: =IF(G12>F12,1,IF(G12<0,0,G12/F12)) -> 1 | J12: Se consideró solo 2019
B13: 410203 | D13: 1.7 Lograr ventas de gasolinera de galones | E13: Galones | F13: 100000 | G13: 112588 | H13: =IF(G13>F13,1,IF(G13<0,0,G13/F13)) -> 1 | I13: =+H13*C13 -> 0
B14: 41 TREXA | D14: 1.8 Aumentar ventas en TREXA | E14: Dólares | F14: 0.2 | G14: 1.03 | H14: =IF(G14>F14,1,IF(G14<0,0,G14/F14)) -> 1 | I14: =+H14*C14 -> 0
D15: 1.9 Aumento en ventas de GPS a terceros (nuevos clientes) | E15: Unidad instaladas / mensuales | F15: 10 | G15: 0 | H15: =IF(G15>F15,1,IF(G15<0,0,G15/F15)) -> 0 | I15: =+H15*C15 -> 0
B16: 410201 International C. | D16: 1.10 Aumentar ventas en articulos Sejue/get504 | E16: Articulos | F16: 10 | G16: 19 | H16: =IF(G16>F16,1,IF(G16<0,0,G16/F16)) -> 1 | I16: =+H16*C16 -> 0
B17: 410201 | D17: 1.11 Tienda de conveniencia (Primeros 4 meses 15k usd y 25k usd) | E17: Dólares | F17: 25000 | G17: 20092.4 | H17: =IF(G17>F17,1,IF(G17<0,0,G17/F17)) -> 0.803696
B18: 410102 y 410103 | D18: 1.12 Aumentar renta de chasis y/o genset sin contenedor 410102 + 410103 | E18: Chasis rentados | F18: 0.2 | G18: -0.39 | H18: =IF(G18>F18,1,IF(G18<0,0,G18/F18)) -> 0
B19: 4101105001 | D19: 1.13 Aumentar servicio de almacenamiento y M&R San Lorenzo | F19: 0.2 | G19: 0.3 | H19: =IF(G19>F19,1,IF(G19<0,0,G19/F19)) -> 1 | J19: sin considerar enp
B20: 4101105002 | D20: 1.14 Incrementar gate out de contenedores Puerto Cortés | E20: Gate | F20: 0.2 | G20: -0.5 | H20: =IF(G20>F20,1,IF(G20<0,0,G20/F20)) -> 0
B21: 410201 | D21: 1.15 Aumento de ventas EXA Part´s (Interno + externo) | F21: 0.2 | G21: 0 | H21: =IF(G21>F21,1,IF(G21<0,0,G21/F21)) -> 0
B22: 4101105 | D22: 1.16 Aumentar servicio de almacenamiento y m&r
D23: 1.17 Aumentar el numero de cliente semestralmente | E23: cliente | F23: 1
B27: 2 | C27: 0.275 | D27: 2. Aumentar margen neto | F27: 0.1 | G27: 0.1 | H27: =IF(G27>F27,1,IF(G27<0,0,G27/F27)) -> 1 | I27: =+H27*C27 -> 0.275 | J27: 0
D28: 2.1 Reducir gasto administrativo x% | E28: % | F28: 0.1 | G28: 0.32 | H28: =IF(G28>F28,1,IF(G28<0,0,G28/F28)) -> 1
D29: 2.2 Reducir costo de M&R de chasis propios | E29: $/km | F29: 0.05 | G29: 0.09 | H29: =IF(G29>F29,0,IF(G29<0,0,G29/F29)) -> 0
D30: 2.3 Reducir Costo por km cabezales propios. | E30: $ | F30: 0.05 | G30: 0.6 | H30: =IF(G30>F30,1,IF(G30<0,0,G30/F30)) -> 1
D31: 2.4 Reducir Costo por km otros EXA. | E31: $ | F31: 0.05 | G31: 0.0319 | H31: =IF(G31>F31,1,IF(G31<0,0,G31/F31)) -> 0.638
D32: 2.5 Aumentar Margen neto en venta de contenedores (modificados y secos) | E32: % | F32: 0.1 | G32: -2.92 | H32: =IF(G32>F32,1,IF(G32<0,0,G32/F32)) -> 0
D33: 2.6 Aumento en 20% en margen de contribución bruta venta de contenedores | E33: $ | F33: 0.2 | G33: 0 | H33: =IF(G33>F33,1,IF(G33<0,0,G33/F33)) -> 0
D34: 2.7 Aumento en 20% en margen de contribución bruta alquiler de bodegas | E34: $ | F34: 0.2 | H34: =IF(G34>F34,1,IF(G34<0,0,G34/F34)) -> 0
D35: 2.8 Aumento en 20% en margen de contribución bruta alquiler de reefers. | E35: $ | F35: 0.2 | H35: =IF(G35>F35,1,IF(G35<0,0,G35/F35)) -> 0
D36: 2.9 Reducir Costo administrativo Puerto Cortés con relacion al año anterior | F36: 0.05 | H36: =IF(G36>F36,1,IF(G36<0,0,G36/F36)) -> 0 | J36: No se puede generar por falta de centro de uso de centro de costo en 2019
D37: 2.10 Mantener el Gasto administrativo San Pedro Sula | E37: dolares | F37: 0.135 | H37: =IF(G37>F37,1,IF(G37<0,0,G37/F37)) -> 0 | I37: =+H37*C37 -> 0 | J37: No se puede generar por falta de centro de uso de centro de costo en 2020
D38: 2.11 Gasto administrativo San Lorenzo | F38: 0.1 | H38: =IF(G38>F38,1,IF(G38<0,0,G38/F38)) -> 0 | I38: =+H38*C38 -> 0 | J38: No se puede generar por falta de centro de uso de centro de costo en 2021
D39: 2.12 Costo por mes por GPS (Costo de plataforma + Tigo/claro + otros costos) | E39: $ | F39: 8 | G39: 4.71 | H39: =IF(G39<F39,1,IF(G39<0,0,G39/F39)) -> 1 | I39: 1
D40: 2.13 Reducir Costo de M&R por contenedor Puerto Cortes | E40: $/contenedor | F40: 0.1 | H40: =IF(G40>F40,1,IF(G40<0,0,G40/F40)) -> 0
D41: 2.14 Reducir costo máquinas (incluye mulita y containers handler) Puerto Cortes | E41: $/contenedor | F41: 0.1 | H41: =IF(G41>F41,1,IF(G41<0,0,G41/F41)) -> 0 | I41: Se estan yendo a una sola cuenta
D42: 2.15 Aumentar margen de M&R por contenedor San Lorenzo
D43: 2.16 Reducir costo máquinas (incluye mulita y containers handler) San Lorenzo | I43: Se estan yendo a una sola cuenta
D44: 2.17 Reducir costo por km/cabezal TRANEXPA | F44: -0.1 | G44: 0.14 | H44: =IF(G44<F44,1,IF(G44<0,0,0)) -> 0
D45: 2.18 Reducir M&R gensets $ /genset activo 10% | E45: dolares | F45: 0.1 | G45: 4.66 | H45: =IF(G45<F45,1,IF(G45<0,0,0)) -> 0
D46: 2.19 Gasto administrativo gasolinera 3%/ventas | E46: dolares | F46: 0.03 | G46: 0.07 | H46: =IF(G46<F46,1,IF(G46<0,0,0)) -> 0
D47: 2.20 Margen operativo de tienda | F47: 0.1 | G47: -0.0005 | H47: =IF(G47>F47,1,IF(G47<0,0,0)) -> 0
D48: 2.21 Aumentar % neto del servicio de transporte | F48: 0.1 | G48: 0.1 | H48: 1
D49: 2.22 Aumentar margen neto alquiler de contenedores secos (solo o en combo) TREXA | F49: 0.1 | G49: 0.1 | H49: 1
B50: 3 | C50: 0.05 | D50: 3. Cero incidentes mayores de seguridad y sostenibilidad | F50: 1 | G50: 1 | H50: =IF(G50>F50,1,IF(G50<0,0,G50/F50)) -> 1 | I50: =+H50*C50 -> 0.05 | J50: >0 | M50: 0
D51: 3.1 Robos. | F51: 0 | G51: 0 | H51: 1 | I51: =+H51*C51 -> 0
D52: 3.2 Accidentes. | F52: 0 | G52: 0 | H52: 1 | I52: =+H52*C52 -> 0
D53: 3.3 No conformidades mayores. | F53: 0 | G53: 0 | H53: 1 | I53: =+H53*C53 -> 0
D54: 3.4 Pérdida de clientes estratégicos, | F54: 0 | G54: 0 | H54: 1 | I54: =+H54*C54 -> 0
D55: 3.5 Multas ambientales y fiscales. | F55: 0 | H55: 1 | I55: =+H55*C55 -> 0
D56: 3.6 Cierres contables a mas tardar el 6 de cada mes | E56: # de cierres a tiempo | F56: 6 | G56: 6 | H56: =IF(G56>F56,1,IF(G56<0,0,G56/F56)) -> 1
D57: 3.6.1 Cierre TREXA | E57: # de cierres a tiempo | F57: 1 | G57: 1 | H57: =IF(G57>F57,1,IF(G57<0,0,G57/F57)) -> 1
D58: 3.7 Cero accidente mayores Y/O robos TRANEXPA
D59: 2.21 Margen operativo de la gasolinera | E59: dolares | F59: 0.1 | G59: 0.06 | H59: 0
D60: 3.8 Aumentar satisfaccion al cliente | F60: 0.1 | G60: 1 | H60: 1
D61: 3.9 On time delivery without sevice incidents | F61: 0.995 | G61: 1 | H61: 1
B62: 4 | C62: 0.1 | D62: 4. Aumentar clima laboral | F62: 0.1 | G62: 0.1 | H62: =IF(G62>F62,1,IF(G62<0,0,G62/F62)) -> 1 | I62: =+H62*C62 -> 0.1
D64: 0.5
B67: 5 | C67: 0.1 | D67: 5. Productividad | F67: 3700 | G67: 3932 | H67: =IF(G67>F67,1,IF(G67<0,0,G67/F67)) -> 1 | I67: =+H67*C67 -> 0.1 | J67: Ninguna o Tranexpa | K67: General o tranexpa o EXA | L67: General+ EXA | M67: # general+ EXA + Tranexpa
D68: 5.1 Productividad kms/cabezal/mes. | F68: =+F67 -> 3700 | G68: =+G67 -> 3932 | H68: =IF(G68>F68,1,IF(G68<0,0,G68/F68)) -> 1
C69: 0.08 | D69: 5.2 Productividad cabezales Flota Nueva | F69: 4500 | G69: 4782 | H69: =IF(G69>F69,1,IF(G69<0,0,G69/F69)) -> 1 | I69: =+H69*C69 -> 0.08
C70: 0.12 | D70: 5.3 Productividad cabezales TRANEXPA | F70: 4000 | G70: 4268 | H70: =IF(G70>F70,1,0) -> 1 | I70: =+H70*C70 -> 0.12
C71: 0.1 | D71: 5.4 Productividad cabezales IPH | F71: 3800 | G71: 3501 | H71: =IF(G71>F71,1,0) -> 0 | I71: =+H71*C71 -> 0
C72: 0.7 | D72: 5.5 Productividad cabezales Particulares. | F72: 3500 | G72: 2429 | H72: =IF(G72>F72,1,0) -> 0 | I72: =+H72*C72 -> 0 | J72: 4/6 transportes
D73: 5.5.1 Productividad cabezales Tranexpa Particulares. | F73: =+F72 -> 3500 | G73: 2144 | H73: =IF(G73>F73,1,0) -> 0
D74: 5.5.2 Productividad cabezales Ponce | F74: =+F72 -> 3500 | G74: 2560 | H74: =IF(G74>F74,1,0) -> 0
D75: 5.5.3 Productividad cabezales Moreno | F75: =+F72 -> 3500 | G75: 2923 | H75: =IF(G75>F75,1,0) -> 0
D76: 5.5.4 Productividad cabezales Obregon | F76: =+F72 -> 3500 | G76: 3165 | H76: =IF(G76>F76,1,0) -> 0
D77: 5.5.5 Productividad cabezales San Lorenzo | F77: =+F72 -> 3500 | G77: 2234 | H77: =IF(G77>F77,1,0) -> 0
D78: 5.5.6 Productividad cabezales Sinai | F78: =+F73 -> 3500 | G78: 1551 | H78: =IF(G78>F78,1,0) -> 0
D79: 5.6 Aprovechamiento GPS | F79: 0.9 | G79: 0.82 | H79: =IF(G79>F79,1,G79/F79) -> 0.91111111
D80: 5.7 Dias de facturacion | F80: 4 | G80: 6 | H80: =IF(G80>F80,1,0) -> 1
D81: 5.8 Aumentar kms EXA | E81: kms | F81: =(410915.3+434042.5)/2*1.2 -> 506974.68 | G81: 485973.6 | H81: =IF(G81>F81,1,IF(G81<0,0,G81/F81-1)) -> -0.041424317
D82: 5.8.1 Aumentar kms clientes Jacky Mena (Rango110-90) | F82: 100000
D83: 5.8.2 Aumentar kms clientes Honoria Rodriguez (Rango 110-90) | E83: kms/mes | F83: 100000
D84: 5.8.3 Aumentar kms clientes Sinia Murillo (Rango 110-90) | F84: 100000
D85: 5.8.4 Aumentar kms clientes Josselyn Chavarria (Rango 110-90) | F85: 100000
D86: 5.8.5 Aumentar kms clientes Edgardo Hernandez (Rango 150-115) | F86: 100000
D87: 5.9 Aumentar Total kms cabezales propios | E87: kms | F87: 0.2
D88: 5.10 Aumentar kms TRANEXPA | E88: kms | F88: 0.2 | G88: 0 | H88: =IF(G88>F88,0,IF(G88<0,0,G88/F88)) -> 0
D89: 5.11 # de fallas operativas adjudicables al predio (Incluye rescates, rechazos) Puerto Cortes | E89: # de fallas | F89: 1 | G89: 0 | H89: 1
D90: 5.12 Aumentar # de viajes de EXA | E90: # de viajes | F90: 0.2 | G90: -0.32 | H90: 0 | I90: =+F90/1.2 -> 0.16666667 | J90: 0.2
D91: 5.9.1 Aumentar numero de viajes Jacky | E91: # de viajes
D92: 5.9.2 Aumentar numero de viajes Honoria | E92: # de viajes
D93: 5.9.3 Aumentar numero de viajes Sinia | E93: # de viajes
D94: 5.9.4 Aumentar numero de viajes Josselyn | E94: # de viajes
D95: 5.9.5 Aumentar numero de viajes Edgardo | E95: # de viajes
D96: 5.13 Aumenar promedio de kms/viaje | E96: kms/viaje | F96: 0.1 | G96: =+(1.25182481751825)-1 -> 0.25182482 | H96: =IF(G96>F96,1,IF(G96<0,0,G96/F96)) -> 1
D97: 5.14 90% de cabezales dentro de un +-10% del promedio de kms cabezal/mes | E97: Porcentaje | F97: 0.9
D98: 5.15 # de fallas operativas adjudicables al predio (Incluye rescates, rechazos) San Lorenzo | F98: 0 | G98: 0 | H98: 1
D99: 5.16 # de notas de credito mensuales | E99: # notas de credito
B101: 6 | C101: 0.05 | D101: 6. Aumentar el ROA | F101: 0.05 | G101: 1 | H101: =IF(G101>F101,1,IF(G101<0,0,G101/F101)) -> 1 | I101: =+H101*C101 -> 0.05
D102: 6.1 Aumentar Rotación de inventario. | F102: 0.05 | H102: =IF(G102>F102,1,IF(G102<0,0,G102/F102)) -> 0 | I102: =+H102*C102 -> 0
D103: 6.2 Disminuir a 5% el desuso de los chasis (equipos con mas de 30 dias en las yardas) | E103: % | F103: 0.05 | G103: 0.05 | H103: =IF(G103>F103,1,IF(G103<0,0,G103/F103)) -> 1 | I103: =+H103*C103 -> 0
D104: 6.2.1 Disminuir a 5% el desuso de los equipos Puerto Cortés (equipos con mas de 30 dias en yarda) | E104: Equipos | F104: 30 | G104: 45 | H104: =IF(G104>F104,0,IF(G104<0,0,G104/F104)) -> 0
D105: 6.2.2 Disminuir a 1% el desuso de los equipos San Lorenzo (equipos con mas de 30 dias en yarda) | E105: Equipos | F105: 6 | G105: 7 | H105: =IF(G105>F105,0,IF(G105<0,0,G105/F105)) -> 0
D106: 6. 3 Disminuir a 0-1 los cabezales TRANEXPA | F106: 1 | G106: 2 | H106: =IF(G106>F106,0,IF(G106<0,0,G106/F106)) -> 0
D107: 6.4 No exceder a 5 equipos en desuso generadores | E107: generadores | F107: 1 | G107: 44 | H107: =IF(G107>F107,0,IF(G107<0,0,G107/F107)) -> 0 | I107: % | J107: 1 en san lorenzo
...

Sheet Hoja2

Sheet Hoja1
B3: No | C3: Peso | D3: Descripción | E3: Unidad de medición | F3: Meta
B4: 1 | C4: 0.325 | D4: 1. Aumentar ventas en: | E4: Dólares | F4: 0.2
B5: 2 | C5: 0.275 | D5: 2. Aumentar margen neto | E5: Porcentaje | F5: 0.1
B6: 3 | C6: 0.05 | D6: 3. Cero incidentes mayores de seguridad y sostenibilidad | E6: # Incidente | F6: 1
B7: 4 | C7: 0.1 | D7: 4. Aumentar clima laboral | E7: Porcentaje | F7: 0.1
B8: 5 | C8: 0.1 | D8: 5. Productividad | F8: 3670
B9: 6 | C9: 0.05 | D9: 6. Aumentar el ROA | E9: Porcentaje | F9: 0.05
B10: 7 | C10: 0.05 | D10: 7. Disminuir el D/E | E10: Porcentaje | F10: 0.05
B11: 8 | C11: 0.05 | D11: 8. Innovaciones estratégicas de sistemas de Impacto recurrente | E11: SW Implementado | F11: 1
D12: 8.1 Integracion EMS - Hapag-Lloyd
D13: 8.2 Integracion EMS - GPS
D14: 8.3 Integracion EMS - SAP
D15: 8.4 Integracion EMS - Gasolinera
D16: 8.5 Planilla de motorista
D17: 8.6 Reset Module
D18: 8.7 Add on SAP
D19: 8.8 Multilanguage
D20: 8.9 Multicompany
D21: 8.10 Depot - EMS
D22: 8.11 Multireport
D28: 9. SCORE CARD Grupo EXA | E28: RESULTADO SCORECARD | F28: 1

Sheet Acumulado
A2: =+Mensual!B5 -> No | B2: =+Mensual!C5 -> Peso | C2: =+Mensual!D5 -> Descripción | D2: =+Mensual!E5 -> Unidad de medición | E2: =+Mensual!F5 -> Meta | F2: =+Mensual!G5 -> Resultado | G2: =+Mensual!H5 -> Nota | H2: =+Mensual!I5 -> Valor ponderado | ... K2: =+Mensual!L5 -> 0.5 | L2: 1
A3: =+Mensual!B6 -> 4 | B3: =+Mensual!C6 -> 0.325 | C3: =+Mensual!D6 -> 1. Aumentar ventas en: | D3: =+Mensual!E6 -> 0 | E3: =+Mensual!F6 -> 0.2 | F3: -0.1146 | G3: =IF(F3>(E3*1.1),1.1,IF(F3<0,0,F3/E3)) -> 0 | H3: =+G3*B3 -> 0
A4: =+Mensual!B7 -> 410101 | B4: =+Mensual!C7 -> 0 | C4: =+Mensual!D7 -> 1.1 Aumentar ventas de transporte | D4: =+Mensual!E7 -> 0 | E4: =+Mensual!F7 -> 0.2 | F4: -0.14 | G4: =IF(F4>E4,1,IF(F4<0,0,F4/E4)) -> 0 | H4: =+G4*B4 -> 0
A5: =+Mensual!B8 -> 0 | B5: =+Mensual!C8 -> 0 | C5: =+Mensual!D8 -> 1.2 Lograr meta de contenedores | D5: =+Mensual!E8 -> 0 | E5: 15 | F5: 1 | G5: 0.066666667 | H5: =+G5*B5 -> 0
A6: =+Mensual!B9 -> 410202 | B6: =+Mensual!C9 -> 0 | C6: =+Mensual!D9 -> 1.3 Lograr meta de ventas contenedores secos y modificados(dolares) | D6: =+Mensual!E9 -> Dólares | E6: 4000000 | F6: 70537.5 | G6: =IF(F6>E6,1,IF(F6<0,0,F6/E6)) -> 0.017634375
A7: =+Mensual!B10 -> 410108002 | B7: =+Mensual!C10 -> 0 | C7: =+Mensual!D10 -> 1.4 Lograr meta de ventas en alquileres de contenedores reefer (solo o en combo) | D7: =+Mensual!E10 -> Dólares | E7: =+Mensual!F10 -> 16000 | F7: 200000 | G7: =IF(F7>E7,1,IF(F7<0,0,F7/E7)) -> 1
A8: =+Mensual!B11 -> 410107 | B8: =+Mensual!C11 -> 0 | C8: =+Mensual!D11 -> 1.5 Aumentar Rentas bienes y raices | D8: =+Mensual!E11 -> Porcentaje | E8: =+Mensual!F11 -> 0.2 | F8: 400000 | G8: =IF(F8>E8,1,IF(F8<0,0,F8/E8)) -> 1
B9: =+Mensual!C12 -> 0 | C9: =+Mensual!D12 -> 1.6 Alquileres de contenedores secos (solo o en combos CONMOXA) | D9: =+Mensual!E12 -> Porcentaje | E9: =+Mensual!F12 -> 0.2 | F9: 200000 | G9: =IF(F9>E9,1,IF(F9<0,0,F9/E9)) -> 1
A10: =+Mensual!B13 -> 410203 | B10: =+Mensual!C13 -> 0 | C10: =+Mensual!D13 -> 1.7 Lograr ventas de gasolinera de galones | D10: =+Mensual!E13 -> Galones | E10: =+Mensual!F13 -> 100000 | F10: 0 | G10: =IF(F10>E10,1,IF(F10<0,0,F10/E10)) -> 0 | H10: =+G10*B10 -> 0
A11: =+Mensual!B14 -> 41 TREXA | B11: =+Mensual!C14 -> 0 | C11: =+Mensual!D14 -> 1.8 Aumentar ventas en TREXA | D11: =+Mensual!E14 -> Dólares | E11: =+Mensual!F14 -> 0.2 | F11: 0.01 | G11: =IF(F11>E11,1,IF(F11<0,0,F11/E11)) -> 0.05 | H11: =+G11*B11 -> 0
A12: =+Mensual!B15 -> 0 | B12: =+Mensual!C15 -> 0 | C12: =+Mensual!D15 -> 1.9 Aumento en ventas de GPS a terceros (nuevos clientes) | D12: =+Mensual!E15 -> Unidad instaladas / mensuales | E12: =+Mensual!F15 -> 10 | F12: 0 | G12: =IF(F12>E12,1,IF(F12<0,0,F12/E12)) -> 0 | H12: =+G12*B12 -> 0
A13: =+Mensual!B16 -> 410201 International C. | B13: =+Mensual!C16 -> 0 | C13: =+Mensual!D16 -> 1.10 Aumentar ventas en articulos Sejue/get504 | D13: =+Mensual!E16 -> Articulos | E13: =+Mensual!F16 -> 10 | F13: 0 | G13: =IF(F13>E13,1,IF(F13<0,0,F13/E13)) -> 0 | H13: =+G13*B13 -> 0
A14: =+Mensual!B17 -> 410201 | B14: =+Mensual!C17 -> 0 | C14: =+Mensual!D17 -> 1.11 Tienda de conveniencia (Primeros 4 meses 15k usd y 25k usd) | D14: =+Mensual!E17 -> Dólares | E14: =+Mensual!F17 -> 25000 | F14: 1 | G14: =IF(F14>E14,1,IF(F14<0,0,F14/E14)) -> 4e-05 | H14: =+G14*B14 -> 0
A15: =+Mensual!B18 -> 410102 y 410103 | B15: =+Mensual!C18 -> 0 | C15: =+Mensual!D18 -> 1.12 Aumentar renta de chasis y/o genset sin contenedor 410102 + 410103 | D15: =+Mensual!E18 -> Chasis rentados | E15: =+Mensual!F18 -> 0.2 | F15: 2 | G15: =IF(F15>E15,1,IF(F15<0,0,F15/E15)) -> 1 | H15: =+G15*B15 -> 0
A16: =+Mensual!B19 -> 4101105001 | B16: =+Mensual!C19 -> 0 | C16: =+Mensual!D19 -> 1.13 Aumentar servicio de almacenamiento y M&R San Lorenzo | D16: =+Mensual!E19 -> 0 | E16: =+Mensual!F19 -> 0.2 | F16: 3 | G16: =IF(F16>E16,1,IF(F16<0,0,F16/E16)) -> 1 | H16: =+G16*B16 -> 0
A17: =+Mensual!B20 -> 4101105002 | B17: =+Mensual!C20 -> 0 | C17: =+Mensual!D20 -> 1.14 Incrementar gate out de contenedores Puerto Cortés | D17: =+Mensual!E20 -> Gate | E17: =+Mensual!F20 -> 0.2 | F17: 4 | G17: =IF(F17>E17,1,IF(F17<0,0,F17/E17)) -> 1 | H17: =+G17*B17 -> 0
A18: =+Mensual!B21 -> 410201 | B18: =+Mensual!C21 -> 0 | C18: =+Mensual!D21 -> 1.15 Aumento de ventas EXA Part´s (Interno + externo) | D18: =+Mensual!E21 -> 0 | E18: =+Mensual!F21 -> 0.2 | F18: 5 | G18: =IF(F18>E18,1,IF(F18<0,0,F18/E18)) -> 1 | H18: =+G18*B18 -> 0
A19: =+Mensual!B22 -> 4101105 | B19: =+Mensual!C22 -> 0 | C19: =+Mensual!D22 -> 1.16 Aumentar servicio de almacenamiento y m&r | D19: =+Mensual!E22 -> 0 | E19: =+Mensual!F22 -> 0 | F19: 6 | G19: =IF(F19>E19,1,IF(F19<0,0,F19/E19)) -> 1 | H19: =+G19*B19 -> 0
A20: =+Mensual!B23 -> 0 | B20: =+Mensual!C23 -> 0 | C20: =+Mensual!D23 -> 1.17 Aumentar el numero de cliente semestralmente | D20: =+Mensual!E23 -> cliente | E20: =+Mensual!F23 -> 1 | F20: 7 | G20: =IF(F20>E20,1,IF(F20<0,0,F20/E20)) -> 1 | H20: =+G20*B20 -> 0
A21: =+Mensual!B24 -> 0 | B21: =+Mensual!C24 -> 0 | C21: =+Mensual!D24 -> 0 | D21: =+Mensual!E24 -> 0 | E21: =+Mensual!F24 -> 0 | F21: 8 | G21: =IF(F21>E21,1,IF(F21<0,0,F21/E21)) -> 1 | H21: =+G21*B21 -> 0
... A23: =+Mensual!B26 -> 0 | B23: =+Mensual!C26 -> 0 | C23: =+Mensual!D26 -> 0 | D23: =+Mensual!E26 -> 0 | E23: =+Mensual!F26 -> 0 | F23: 10 | G23: =IF(F23>E23,1,IF(F23<0,0,F23/E23)) -> 1 | H23: =+G23*B23 -> 0
A24: =+Mensual!B27 -> 2 | B24: =+Mensual!C27 -> 0.275 | C24: =+Mensual!D27 -> 2. Aumentar margen neto | D24: =+Mensual!E27 -> 0 | E24: =+Mensual!F27 -> 0.1 | F24: 0.1 | G24: =IF(F24>E24,1,IF(F24<0,0,F24/E24)) -> 1 | H24: =+G24*B24 -> 0.275 | I24: 0
A25: =+Mensual!B28 -> 0 | B25: =+Mensual!C28 -> 0 | C25: =+Mensual!D28 -> 2.1 Reducir gasto administrativo x% | D25: =+Mensual!E28 -> % | E25: =+Mensual!F28 -> 0.1 | G25: =IF(F25>E25,1,IF(F25<0,0,F25/E25)) -> 0 | H25: =+G25*B25 -> 0
A26: =+Mensual!B29 -> 0 | B26: =+Mensual!C29 -> 0 | C26: =+Mensual!D29 -> 2.2 Reducir costo de M&R de chasis propios | D26: =+Mensual!E29 -> $/km | E26: =+Mensual!F29 -> 0.05 | G26: =IF(F26>E26,1,IF(F26<0,0,F26/E26)) -> 0 | H26: =+G26*B26 -> 0
A27: =+Mensual!B30 -> 0 | B27: =+Mensual!C30 -> 0 | C27: =+Mensual!D30 -> 2.3 Reducir Costo por km cabezales propios. | D27: =+Mensual!E30 -> $ | E27: =+Mensual!F30 -> 0.05 | G27: =IF(F27>E27,1,IF(F27<0,0,F27/E27)) -> 0 | H27: =+G27*B27 -> 0
A28: =+Mensual!B31 -> 0 | B28: =+Mensual!C31 -> 0 | C28: =+Mensual!D31 -> 2.4 Reducir Costo por km otros EXA. | D28: =+Mensual!E31 -> $ | E28: =+Mensual!F31 -> 0.05 | G28: =IF(F28>E28,1,IF(F28<0,0,F28/E28)) -> 0 | H28: =+G28*B28 -> 0
A29: =+Mensual!B32 -> 0 | B29: =+Mensual!C32 -> 0 | C29: =+Mensual!D32 -> 2.5 Aumentar Margen neto en venta de contenedores (modificados y secos) | D29: =+Mensual!E32 -> % | E29: =+Mensual!F32 -> 0.1 | G29: =IF(F29>E29,1,IF(F29<0,0,F29/E29)) -> 0 | H29: =+G29*B29 -> 0
A30: =+Mensual!B33 -> 0 | B30: =+Mensual!C33 -> 0 | C30: =+Mensual!D33 -> 2.6 Aumento en 20% en margen de contribución bruta venta de contenedores | D30: =+Mensual!E33 -> $ | E30: =+Mensual!F33 -> 0.2 | G30: =IF(F30>E30,1,IF(F30<0,0,F30/E30)) -> 0 | H30: =+G30*B30 -> 0
A31: =+Mensual!B34 -> 0 | B31: =+Mensual!C34 -> 0 | C31: =+Mensual!D34 -> 2.7 Aumento en 20% en margen de contribución bruta alquiler de bodegas | D31: =+Mensual!E34 -> $ | E31: =+Mensual!F34 -> 0.2 | G31: =IF(F31>E31,1,IF(F31<0,0,F31/E31)) -> 0 | H31: =+G31*B31 -> 0
A32: =+Mensual!B35 -> 0 | B32: =+Mensual!C35 -> 0 | C32: =+Mensual!D35 -> 2.8 Aumento en 20% en margen de contribución bruta alquiler de reefers. | D32: =+Mensual!E35 -> $ | E32: =+Mensual!F35 -> 0.2 | G32: =IF(F32>E32,1,IF(F32<0,0,F32/E32)) -> 0 | H32: =+G32*B32 -> 0
A33: =+Mensual!B36 -> 0 | B33: =+Mensual!C36 -> 0 | C33: =+Mensual!D36 -> 2.9 Reducir Costo administrativo Puerto Cortés con relacion al año anterior | D33: =+Mensual!E36 -> 0 | E33: =+Mensual!F36 -> 0.05 | G33: =IF(F33>E33,1,IF(F33<0,0,F33/E33)) -> 0 | H33: =+G33*B33 -> 0
A34: =+Mensual!B37 -> 0 | B34: =+Mensual!C37 -> 0 | C34: =+Mensual!D37 -> 2.10 Mantener el Gasto administrativo San Pedro Sula | D34: =+Mensual!E37 -> dolares | E34: =+Mensual!F37 -> 0.135 | G34: =IF(F34>E34,1,IF(F34<0,0,F34/E34)) -> 0 | H34: =+G34*B34 -> 0
A35: =+Mensual!B38 -> 0 | B35: =+Mensual!C38 -> 0 | C35: =+Mensual!D38 -> 2.11 Gasto administrativo San Lorenzo | D35: =+Mensual!E38 -> 0 | E35: =+Mensual!F38 -> 0.1 | G35: =IF(F35>E35,1,IF(F35<0,0,F35/E35)) -> 0 | H35: =+G35*B35 -> 0
A36: =+Mensual!B39 -> 0 | B36: =+Mensual!C39 -> 0 | C36: =+Mensual!D39 -> 2.12 Costo por mes por GPS (Costo de plataforma + Tigo/claro + otros costos) | D36: =+Mensual!E39 -> $ | E36: =+Mensual!F39 -> 8 | G36: =IF(F36>E36,1,IF(F36<0,0,F36/E36)) -> 0 | H36: =+G36*B36 -> 0
... A44: =+Mensual!B47 -> 0 | B44: =+Mensual!C47 -> 0 | C44: =+Mensual!D47 -> 2.20 Margen operativo de tienda | D44: =+Mensual!E47 -> 0 | E44: =+Mensual!F47 -> 0.1 | G44: =IF(F44>E44,1,IF(F44<0,0,F44/E44)) -> 0 | H44: =+G44*B44 -> 0
C45: =+Mensual!D48 -> 2.21 Aumentar % neto del servicio de transporte | D45: =+Mensual!E48 -> 0 | E45: =+Mensual!F48 -> 0.1 | G45: =IF(F45>E45,1,IF(F45<0,0,F45/E45)) -> 0 | H45: =+G45*B45 -> 0
C46: =+Mensual!D49 -> 2.22 Aumentar margen neto alquiler de contenedores secos (solo o en combo) TREXA | D46: =+Mensual!E49 -> 0 | E46: =+Mensual!F49 -> 0.1 | G46: =IF(F46>E46,1,IF(F46<0,0,F46/E46)) -> 0 | H46: =+G46*B46 -> 0
A47: =+Mensual!B50 -> 3 | B47: =+Mensual!C50 -> 0.05 | C47: =+Mensual!D50 -> 3. Cero incidentes mayores de seguridad y sostenibilidad | D47: =+Mensual!E50 -> 0 | E47: =+Mensual!F50 -> 1 | F47: 1 | G47: =IF(F47>E47,1,IF(F47<0,0,F47/E47)) -> 1 | H47: =+G47*B47 -> 0.05 | I47: >0 | L47: 0
A48: =+Mensual!B51 -> 0 | B48: =+Mensual!C51 -> 0 | C48: =+Mensual!D51 -> 3.1 Robos. | D48: =+Mensual!E51 -> 0 | E48: =+Mensual!F51 -> 0 | G48: =IF(F48>E48,1,IF(F48<0,0,F48/E48)) -> #DIV/0! | H48: =+G48*B48 -> #DIV/0!
A49: =+Mensual!B52 -> 0 | B49: =+Mensual!C52 -> 0 | C49: =+Mensual!D52 -> 3.2 Accidentes. | D49: =+Mensual!E52 -> 0 | E49: =+Mensual!F52 -> 0 | G49: =IF(F49>E49,1,IF(F49<0,0,F49/E49)) -> #DIV/0! | H49: =+G49*B49 -> #DIV/0!
A50: =+Mensual!B53 -> 0 | B50: =+Mensual!C53 -> 0 | C50: =+Mensual!D53 -> 3.3 No conformidades mayores. | D50: =+Mensual!E53 -> 0 | E50: =+Mensual!F53 -> 0 | G50: =IF(F50>E50,1,IF(F50<0,0,F50/E50)) -> #DIV/0! | H50: =+G50*B50 -> #DIV/0!
A51: =+Mensual!B54 -> 0 | B51: =+Mensual!C54 -> 0 | C51: =+Mensual!D54 -> 3.4 Pérdida de clientes estratégicos, | D51: =+Mensual!E54 -> 0 | E51: =+Mensual!F54 -> 0 | G51: =IF(F51>E51,1,IF(F51<0,0,F51/E51)) -> #DIV/0! | H51: =+G51*B51 -> #DIV/0!
A52: =+Mensual!B55 -> 0 | B52: =+Mensual!C55 -> 0 | C52: =+Mensual!D55 -> 3.5 Multas ambientales y fiscales. | D52: =+Mensual!E55 -> 0 | E52: =+Mensual!F55 -> 0 | G52: =IF(F52>E52,1,IF(F52<0,0,F52/E52)) -> #DIV/0! | H52: =+G52*B52 -> #DIV/0!
A53: =+Mensual!B56 -> 0 | B53: =+Mensual!C56 -> 0 | C53: =+Mensual!D56 -> 3.6 Cierres contables a mas tardar el 6 de cada mes | D53: =+Mensual!E56 -> # de cierres a tiempo | E53: =+Mensual!F56 -> 6 | G53: =IF(F53>E53,1,IF(F53<0,0,F53/E53)) -> 0 | H53: =+G53*B53 -> 0
B54: =+Mensual!C57 -> 0 | C54: =+Mensual!D57 -> 3.6.1 Cierre TREXA | D54: =+Mensual!E57 -> # de cierres a tiempo | E54: =+Mensual!F57 -> 1 | G54: =IF(F54>E54,1,IF(F54<0,0,F54/E54)) -> 0 | H54: =+G54*B54 -> 0
A55: =+Mensual!B58 -> 0 | B55: =+Mensual!C58 -> 0 | C55: =+Mensual!D58 -> 3.7 Cero accidente mayores Y/O robos TRANEXPA | D55: =+Mensual!E58 -> 0 | E55: =+Mensual!F58 -> 0 | G55: =IF(F55>E55,1,IF(F55<0,0,F55/E55)) -> #DIV/0! | H55: =+G55*B55 -> #DIV/0!
A56: =+Mensual!B59 -> 0 | B56: =+Mensual!C59 -> 0 | C56: =+Mensual!D59 -> 2.21 Margen operativo de la gasolinera | D56: =+Mensual!E59 -> dolares | E56: =+Mensual!F59 -> 0.1 | G56: =IF(F56>E56,1,IF(F56<0,0,F56/E56)) -> 0 | H56: =+G56*B56 -> 0
A57: =+Mensual!B60 -> 0 | B57: =+Mensual!C60 -> 0 | C57: =+Mensual!D60 -> 3.8 Aumentar satisfaccion al cliente | D57: =+Mensual!E60 -> 0 | E57: =+Mensual!F60 -> 0.1 | G57: =IF(F57>E57,1,IF(F57<0,0,F57/E57)) -> 0 | H57: =+G57*B57 -> 0
A58: =+Mensual!B61 -> 0 | B58: =+Mensual!C61 -> 0 | C58: =+Mensual!D61 -> 3.9 On time delivery without sevice incidents | D58: =+Mensual!E61 -> 0 | E58: =+Mensual!F61 -> 0.995 | G58: =IF(F58>E58,1,IF(F58<0,0,F58/E58)) -> 0 | H58: =+G58*B58 -> 0
A59: =+Mensual!B62 -> 4 | B59: =+Mensual!C62 -> 0.1 | C59: =+Mensual!D62 -> 4. Aumentar clima laboral | D59: =+Mensual!E62 -> 0 | E59: =+Mensual!F62 -> 0.1 | F59: 0.1 | G59: =IF(F59>E59,1,IF(F59<0,0,F59/E59)) -> 1 | H59: =+G59*B59 -> 0.1
A60: =+Mensual!B63 -> 0 | B60: =+Mensual!C63 -> 0 | C60: =+Mensual!D63 -> 0 | D60: =+Mensual!E63 -> 0 | E60: =+Mensual!F63 -> 0 | F60: 1.1 | G60: =IF(F60>E60,1,IF(F60<0,0,F60/E60)) -> 1 | H60: =+G60*B60 -> 0
A61: =+Mensual!B64 -> 0 | B61: =+Mensual!C64 -> 0 | C61: =+Mensual!D64 -> 0.5 | D61: =+Mensual!E64 -> 0 | E61: =+Mensual!F64 -> 0 | F61: 2.1 | G61: =IF(F61>E61,1,IF(F61<0,0,F61/E61)) -> 1 | H61: =+G61*B61 -> 0
A62: =+Mensual!B65 -> 0 | B62: =+Mensual!C65 -> 0 | C62: =+Mensual!D65 -> 0 | D62: =+Mensual!E65 -> 0 | E62: =+Mensual!F65 -> 0 | F62: 3.1 | G62: =IF(F62>E62,1,IF(F62<0,0,F62/E62)) -> 1 | H62: =+G62*B62 -> 0
A63: =+Mensual!B66 -> 0 | B63: =+Mensual!C66 -> 0 | C63: =+Mensual!D66 -> 0 | D63: =+Mensual!E66 -> 0 | E63: =+Mensual!F66 -> 0 | F63: 4.1 | G63: =IF(F63>E63,1,IF(F63<0,0,F63/E63)) -> 1 | H63: =+G63*B63 -> 0
A64: =+Mensual!B67 -> 5 | B64: =+Mensual!C67 -> 0.1 | C64: =+Mensual!D67 -> 5. Productividad | D64: =+Mensual!E67 -> 0 | E64: =+Mensual!F67 -> 3700 | F64: 3457 | G64: =IF(F64>E64,1,IF(F64<0,0,F64/E64)) -> 0.93432432 | H64: =+G64*B64 -> 0.093432432 | I64: Ninguna o Tranexpa | J64: General o tranexpa o EXA | K64: General+ EXA | L64: # general+ EXA + Tranexpa
A65: =+Mensual!B68 -> 0 | B65: =+Mensual!C68 -> 0 | C65: =+Mensual!D68 -> 5.1 Productividad kms/cabezal/mes. | D65: =+Mensual!E68 -> 0 | E65: =+Mensual!F68 -> 3700 | F65: 3457 | G65: =IF(F65>E65,1,IF(F65<0,0,F65/E65)) -> 0.93432432 | H65: =+G65*B65 -> 0
A66: =+Mensual!B69 -> 0 | B66: =+Mensual!C69 -> 0.08 | C66: =+Mensual!D69 -> 5.2 Productividad cabezales Flota Nueva | D66: =+Mensual!E69 -> 0 | E66: =+Mensual!F69 -> 4500 | F66: 5167 | G66: =IF(F66>E66,1,IF(F66<0,0,F66/E66)) -> 1 | H66: =+G66*B66 -> 0.08
A67: =+Mensual!B70 -> 0 | B67: =+Mensual!C70 -> 0.12 | C67: =+Mensual!D70 -> 5.3 Productividad cabezales TRANEXPA | D67: =+Mensual!E70 -> 0 | E67: =+Mensual!F70 -> 4000 | F67: 3619 | G67: =IF(F67>E67,1,IF(F67<0,0,F67/E67)) -> 0.90475 | H67: =+G67*B67 -> 0.10857
A68: =+Mensual!B71 -> 0 | B68: =+Mensual!C71 -> 0.1 | C68: =+Mensual!D71 -> 5.4 Productividad cabezales IPH | D68: =+Mensual!E71 -> 0 | E68: =+Mensual!F71 -> 3800 | F68: 5278 | G68: =IF(F68>E68,1,IF(F68<0,0,F68/E68)) -> 1 | H68: =+G68*B68 -> 0.1
A69: =+Mensual!B72 -> 0 | B69: =+Mensual!C72 -> 0.7 | C69: =+Mensual!D72 -> 5.5 Productividad cabezales Particulares. | D69: =+Mensual!E72 -> 0 | E69: =+Mensual!F72 -> 3500 | F69: 3020 | G69: =IF(F69>E69,1,IF(F69<0,0,F69/E69)) -> 0.86285714 | H69: =+G69*B69 -> 0.604
C70: =+Mensual!D73 -> 5.5.1 Productividad cabezales Tranexpa Particulares. | D70: =+Mensual!E73 -> 0 | E70: =+Mensual!F73 -> 3500 | F70: 3021 | G70: =IF(F70>E70,1,IF(F70<0,0,F70/E70)) -> 0.86314286 | H70: =+G70*B70 -> 0
C71: =+Mensual!D74 -> 5.5.2 Productividad cabezales Ponce | D71: =+Mensual!E74 -> 0 | E71: =+Mensual!F74 -> 3500 | F71: 3022 | G71: =IF(F71>E71,1,IF(F71<0,0,F71/E71)) -> 0.86342857 | H71: =+G71*B71 -> 0
C72: =+Mensual!D75 -> 5.5.3 Productividad cabezales Moreno | D72: =+Mensual!E75 -> 0 | E72: =+Mensual!F75 -> 3500 | F72: 3023 | G72: =IF(F72>E72,1,IF(F72<0,0,F72/E72)) -> 0.86371429 | H72: =+G72*B72 -> 0
C73: =+Mensual!D76 -> 5.5.4 Productividad cabezales Obregon | D73: =+Mensual!E76 -> 0 | E73: =+Mensual!F76 -> 3500 | F73: 3024 | G73: =IF(F73>E73,1,IF(F73<0,0,F73/E73)) -> 0.864 | H73: =+G73*B73 -> 0
C74: =+Mensual!D77 -> 5.5.5 Productividad cabezales San Lorenzo | D74: =+Mensual!E77 -> 0 | E74: =+Mensual!F77 -> 3500 | F74: 3025 | G74: =IF(F74>E74,1,IF(F74<0,0,F74/E74)) -> 0.86428571 | H74: =+G74*B74 -> 0
C75: =+Mensual!D78 -> 5.5.6 Productividad cabezales Sinai | D75: =+Mensual!E78 -> 0 | E75: =+Mensual!F78 -> 3500 | F75: 3026
A76: =+Mensual!B79 -> 0 | B76: =+Mensual!C79 -> 0 | C76: =+Mensual!D79 -> 5.6 Aprovechamiento GPS | D76: =+Mensual!E79 -> 0 | E76: =+Mensual!F79 -> 0.9 | F76: 3021 | G76: =IF(F76>E76,1,IF(F76<0,0,F76/E76)) -> 1 | H76: =+G76*B76 -> 0
A77: =+Mensual!B80 -> 0 | B77: =+Mensual!C80 -> 0 | C77: =+Mensual!D80 -> 5.7 Dias de facturacion | D77: =+Mensual!E80 -> 0 | E77: =+Mensual!F80 -> 4 | F77: 3022 | G77: =IF(F77>E77,1,IF(F77<0,0,F77/E77)) -> 1 | H77: =+G77*B77 -> 0
A78: =+Mensual!B81 -> 0 | B78: =+Mensual!C81 -> 0 | C78: =+Mensual!D81 -> 5.8 Aumentar kms EXA | D78: =+Mensual!E81 -> kms | E78: =+Mensual!F81 -> 506974.68 | F78: 3023 | G78: =IF(F78>E78,1,IF(F78<0,0,F78/E78)) -> 0.0059628224 | H78: =+G78*B78 -> 0
A79: =+Mensual!B82 -> 0 | B79: =+Mensual!C82 -> 0 | C79: =+Mensual!D82 -> 5.8.1 Aumentar kms clientes Jacky Mena (Rango110-90) | D79: =+Mensual!E82 -> 0 | E79: =+Mensual!F82 -> 100000 | F79: 3024 | G79: =IF(F79>E79,1,IF(F79<0,0,F79/E79)) -> 0.03024 | H79: =+G79*B79 -> 0
A80: =+Mensual!B83 -> 0 | B80: =+Mensual!C83 -> 0 | C80: =+Mensual!D83 -> 5.8.2 Aumentar kms clientes Honoria Rodriguez (Rango 110-90) | D80: =+Mensual!E83 -> kms/mes | E80: =+Mensual!F83 -> 100000 | F80: 3025 | G80: =IF(F80>E80,1,IF(F80<0,0,F80/E80)) -> 0.03025 | H80: =+G80*B80 -> 0
A81: =+Mensual!B84 -> 0 | B81: =+Mensual!C84 -> 0 | C81: =+Mensual!D84 -> 5.8.3 Aumentar kms clientes Sinia Murillo (Rango 110-90) | D81: =+Mensual!E84 -> 0 | E81: =+Mensual!F84 -> 100000 | F81: 3026 | G81: =IF(F81>E81,1,IF(F81<0,0,F81/E81)) -> 0.03026 | H81: =+G81*B81 -> 0
A82: =+Mensual!B85 -> 0 | B82: =+Mensual!C85 -> 0 | C82: =+Mensual!D85 -> 5.8.4 Aumentar kms clientes Josselyn Chavarria (Rango 110-90) | D82: =+Mensual!E85 -> 0 | E82: =+Mensual!F85 -> 100000 | F82: 3027 | G82: =IF(F82>E82,1,IF(F82<0,0,F82/E82)) -> 0.03027 | H82: =+G82*B82 -> 0
A83: =+Mensual!B86 -> 0 | B83: =+Mensual!C86 -> 0 | C83: =+Mensual!D86 -> 5.8.5 Aumentar kms clientes Edgardo Hernandez (Rango 150-115) | D83: =+Mensual!E86 -> 0 | E83: =+Mensual!F86 -> 100000 | F83: 3028 | G83: =IF(F83>E83,1,IF(F83<0,0,F83/E83)) -> 0.03028 | H83: =+G83*B83 -> 0
A84: =+Mensual!B87 -> 0 | B84: =+Mensual!C87 -> 0 | C84: =+Mensual!D87 -> 5.9 Aumentar Total kms cabezales propios | D84: =+Mensual!E87 -> kms | E84: =+Mensual!F87 -> 0.2 | F84: 3029 | G84: =IF(F84>E84,1,IF(F84<0,0,F84/E84)) -> 1 | H84: =+G84*B84 -> 0
A85: =+Mensual!B88 -> 0 | B85: =+Mensual!C88 -> 0 | C85: =+Mensual!D88 -> 5.10 Aumentar kms TRANEXPA | D85: =+Mensual!E88 -> kms | E85: =+Mensual!F88 -> 0.2 | F85: 3030 | G85: =IF(F85>E85,1,IF(F85<0,0,F85/E85)) -> 1 | H85: =+G85*B85 -> 0
A86: =+Mensual!B89 -> 0 | B86: =+Mensual!C89 -> 0 | C86: =+Mensual!D89 -> 5.11 # de fallas operativas adjudicables al predio (Incluye rescates, rechazos) Puerto Cortes | D86: =+Mensual!E89 -> # de fallas | E86: =+Mensual!F89 -> 1 | F86: 3031 | G86: =IF(F86>E86,1,IF(F86<0,0,F86/E86)) -> 1 | H86: =+G86*B86 -> 0
A87: =+Mensual!B90 -> 0 | B87: =+Mensual!C90 -> 0 | C87: =+Mensual!D90 -> 5.12 Aumentar # de viajes de EXA | D87: =+Mensual!E90 -> # de viajes | E87: =+Mensual!F90 -> 0.2 | F87: 3032 | G87: =IF(F87>E87,1,IF(F87<0,0,F87/E87)) -> 1 | H87: =+G87*B87 -> 0
... A98: =+Mensual!B101 -> 6 | B98: =+Mensual!C101 -> 0.05 | C98: =+Mensual!D101 -> 6. Aumentar el ROA | D98: =+Mensual!E101 -> 0 | E98: =+Mensual!F101 -> 0.05 | F98: 5 | G98: =IF(F98>E98,1,IF(F98<0,0,F98/E98)) -> 1 | H98: =+G98*B98 -> 0.05
A99: =+Mensual!B102 -> 0 | B99: =+Mensual!C102 -> 0 | C99: =+Mensual!D102 -> 6.1 Aumentar Rotación de inventario. | D99: =+Mensual!E102 -> 0 | E99: =+Mensual!F102 -> 0.05 | G99: =IF(F99>E99,1,IF(F99<0,0,F99/E99)) -> 0 | H99: =+G99*B99 -> 0
A100: =+Mensual!B103 -> 0 | B100: =+Mensual!C103 -> 0 | C100: =+Mensual!D103 -> 6.2 Disminuir a 5% el desuso de los chasis (equipos con mas de 30 dias en las yardas) | D100: =+Mensual!E103 -> % | E100: =+Mensual!F103 -> 0.05 | G100: =IF(F100>E100,1,IF(F100<0,0,F100/E100)) -> 0 | H100: =+G100*B100 -> 0
A101: =+Mensual!B104 -> 0 | B101: =+Mensual!C104 -> 0 | C101: =+Mensual!D104 -> 6.2.1 Disminuir a 5% el desuso de los equipos Puerto Cortés (equipos con mas de 30 dias en yarda) | D101: =+Mensual!E104 -> Equipos | E101: =+Mensual!F104 -> 30 | G101: =IF(F101>E101,1,IF(F101<0,0,F101/E101)) -> 0 | H101: =+G101*B101 -> 0
A102: =+Mensual!B105 -> 0 | B102: =+Mensual!C105 -> 0 | C102: =+Mensual!D105 -> 6.2.2 Disminuir a 1% el desuso de los equipos San Lorenzo (equipos con mas de 30 dias en yarda) | D102: =+Mensual!E105 -> Equipos | E102: =+Mensual!F105 -> 6 | G102: =IF(F102>E102,1,IF(F102<0,0,F102/E102)) -> 0 | H102: =+G102*B102 -> 0
A103: =+Mensual!B106 -> 0 | B103: =+Mensual!C106 -> 0 | C103: =+Mensual!D106 -> 6. 3 Disminuir a 0-1 los cabezales TRANEXPA | D103: =+Mensual!E106 -> 0 | E103: =+Mensual!F106 -> 1 | G103: =IF(F103>E103,1,IF(F103<0,0,F103/E103)) -> 0 | H103: =+G103*B103 -> 0
A104: =+Mensual!B107 -> 0 | B104: =+Mensual!C107 -> 0 | C104: =+Mensual!D107 -> 6.4 No exceder a 5 equipos en desuso generadores | D104: =+Mensual!E107 -> generadores | E104: =+Mensual!F107 -> 1 | G104: =IF(F104>E104,1,IF(F104<0,0,F104/E104)) -> 0 | H104: =+G104*B104 -> 0
A105: =+Mensual!B108 -> 0 | B105: =+Mensual!C108 -> 0 | C105: =+Mensual!D108 -> 6.5 Disminuir a 0-1 el desuso de cabezales propios | D105: =+Mensual!E108 -> cabezal | E105: =+Mensual!F108 -> 1 | G105: =IF(F105>E105,1,IF(F105<0,0,F105/E105)) -> 0 | H105: =+G105*B105 -> 0
A106: =+Mensual!B109 -> 7 | B106: =+Mensual!C109 -> 0.05 | C106: =+Mensual!D109 -> 7. Disminuir el D/E | D106: =+Mensual!E109 -> 0 | E106: =+Mensual!F109 -> 0.05 | F106: 5 | G106: =IF(F106>E106,1,IF(F106<0,0,F106/E106)) -> 1 | H106: =+G106*B106 -> 0.05
A107: =+Mensual!B110 -> 0 | B107: =+Mensual!C110 -> 0 | C107: =+Mensual!D110 -> 7.1 Rotación de cuentas por cobrar. | D107: =+Mensual!E110 -> 0 | E107: =+Mensual!F110 -> 0.1 | G107: =IF(F107>E107,1,IF(F107<0,0,F107/E107)) -> 0 | H107: =+G107*B107 -> 0
A108: =+Mensual!B111 -> 0 | B108: =+Mensual!C111 -> 0 | C108: =+Mensual!D111 -> 7.2 95% de clientes activos dentro del periodo de recuperacion | D108: =+Mensual!E111 -> 0 | E108: =+Mensual!F111 -> 0.2 | G108: =IF(F108>E108,1,IF(F108<0,0,F108/E108)) -> 0 | H108: =+G108*B108 -> 0
A109: =+Mensual!B112 -> 0 | B109: =+Mensual!C112 -> 0 | C109: =+Mensual!D112 -> 7.3 | D109: =+Mensual!E112 -> 0 | E109: =+Mensual!F112 -> 0 | G109: =IF(F109>E109,1,IF(F109<0,0,F109/E109)) -> #DIV/0! | H109: =+G109*B109 -> #DIV/0!
A110: =+Mensual!B113 -> 0 | B110: =+Mensual!C113 -> 0 | C110: =+Mensual!D113 -> 0 | D110: =+Mensual!E113 -> 0 | E110: =+Mensual!F113 -> 0 | G110: =IF(F110>E110,1,IF(F110<0,0,F110/E110)) -> #DIV/0! | H110: =+G110*B110 -> #DIV/0!
A111: =+Mensual!B114 -> 0 | B111: =+Mensual!C114 -> 0 | C111: =+Mensual!D114 -> 0 | D111: =+Mensual!E114 -> 0 | E111: =+Mensual!F114 -> 0 | G111: =IF(F111>E111,1,IF(F111<0,0,F111/E111)) -> #DIV/0! | H111: =+G111*B111 -> #DIV/0!
A112: =+Mensual!B115 -> 0 | B112: =+Mensual!C115 -> 0 | C112: =+Mensual!D115 -> 0 | D112: =+Mensual!E115 -> 0 | E112: =+Mensual!F115 -> 0 | G112: =IF(F112>E112,1,IF(F112<0,0,F112/E112)) -> #DIV/0! | H112: =+G112*B112 -> #DIV/0!
A113: =+Mensual!B116 -> 0 | B113: =+Mensual!C116 -> 0 | C113: =+Mensual!D116 -> 0 | D113: =+Mensual!E116 -> 0 | E113: =+Mensual!F116 -> 0 | G113: =IF(F113>E113,1,IF(F113<0,0,F113/E113)) -> #DIV/0! | H113: =+G113*B113 -> #DIV/0!
A114: =+Mensual!B118 -> 8 | B114: =+Mensual!C118 -> 0.05 | C114: =+Mensual!D118 -> 8. Innovaciones estratégicas de sistemas de Impacto recurrente | D114: =+Mensual!E118 -> 0 | E114: =+Mensual!F118 -> 1 | F114: 0 | G114: =IF(F114>E114,1,IF(F114<0,0,F114/E114)) -> 0 | H114: =+G114*B114 -> 0
A115: =+Mensual!B119 -> 0 | B115: =+Mensual!C119 -> 0 | C115: =+Mensual!D119 -> 8.1 Integracion EMS - Hapag-Lloyd | D115: =+Mensual!E119 -> 0 | E115: =+Mensual!F119 -> 0 | G115: =IF(F115>B115,1,F115/B115) -> #DIV/0! | H115: =+G115*B115 -> #DIV/0!
A116: =+Mensual!B120 -> 0 | B116: =+Mensual!C120 -> 0 | C116: =+Mensual!D120 -> 8.2 Integracion EMS - GPS | D116: =+Mensual!E120 -> 0 | E116: =+Mensual!F120 -> 0 | G116: =IF(F116>B116,1,F116/B116) -> #DIV/0! | H116: =+G116*B116 -> #DIV/0!
A117: =+Mensual!B121 -> 0 | B117: =+Mensual!C121 -> 0 | C117: =+Mensual!D121 -> 8.3 Integracion EMS - SAP | D117: =+Mensual!E121 -> 0 | E117: =+Mensual!F121 -> 0 | G117: =IF(F117>B117,1,F117/B117) -> #DIV/0! | H117: =+G117*B117 -> #DIV/0!
A118: =+Mensual!B122 -> 0 | B118: =+Mensual!C122 -> 0 | C118: =+Mensual!D122 -> 8.4 Integracion EMS - Gasolinera | D118: =+Mensual!E122 -> 0 | E118: =+Mensual!F122 -> 0 | G118: =IF(F118>B118,1,F118/B118) -> #DIV/0! | H118: =+G118*B118 -> #DIV/0!
A119: =+Mensual!B123 -> 0 | B119: =+Mensual!C123 -> 0 | C119: =+Mensual!D123 -> 8.5 Planilla de motorista | D119: =+Mensual!E123 -> 0 | E119: =+Mensual!F123 -> 0 | G119: =IF(F119>B119,1,F119/B119) -> #DIV/0! | H119: =+G119*B119 -> #DIV/0!
...

Sheet EJ,. CXMA acumulado
C3: Departamento: | D3: Contenedores
A5: =+Mensual!B5 -> No | B5: =+Mensual!C5 -> Peso | D5: =+Mensual!E5 -> Unidad de medición | E5: =+Mensual!F5 -> Meta | F5: =+Mensual!G5 -> Resultado | G5: =+Mensual!H5 -> Nota | H5: =+Mensual!I5 -> Valor ponderado | I5: =+Mensual!J5 -> 0 | J5: =+Mensual!K5 -> 0.25 | K5: =+Mensual!L5 -> 0.5 | ... Q5: =+Mensual!R5 -> 0 | T5: Nota | U5: Nota
A6: =+Mensual!B6 -> 4 | B6: 0.3 | C6: 1.2 Lograr meta de contenedores | D6: =IF(VLOOKUP($C6,Acumulado!$C$3:$G$161,2,0)<0,0,VLOOKUP($C6,Acumulado!$C$3:$G$161,2,0)) -> #N/A | E6: =IF(VLOOKUP($C6,Acumulado!$C$3:$G$161,3,0)<0,0,VLOOKUP($C6,Acumulado!$C$3:$G$161,3,0)) -> #N/A | F6: =IF(VLOOKUP($C6,Acumulado!$C$3:$G$161,3,0)<0,0,VLOOKUP($C6,Acumulado!$C$3:$G$161,4,0)) -> #N/A | G6: =IF(VLOOKUP($C6,Acumulado!$C$3:$G$161,5,0)<0,0,VLOOKUP($C6,Acumulado!$C$3:$G$161,5,0)) -> #N/A | H6: =+G6*B6 -> #N/A | I6: =+Mensual!J6 -> 0 | J6: =+Mensual!K6 -> 0 | K6: =+Mensual!L6 -> 0 | L6: =+Mensual!M6 -> 0
B7: 0.1 | C7: 1.4 Lograr meta de ventas en alquileres de contenedores reefer (solo o en combo) | D7: =IF(VLOOKUP($C7,Acumulado!$C$3:$G$161,2,0)<0,0,VLOOKUP($C7,Acumulado!$C$3:$G$161,2,0)) -> Dólares | E7: =IF(VLOOKUP($C7,Acumulado!$C$3:$G$161,3,0)<0,0,VLOOKUP($C7,Acumulado!$C$3:$G$161,3,0)) -> 16000 | F7: =IF(VLOOKUP($C7,Acumulado!$C$3:$G$161,3,0)<0,0,VLOOKUP($C7,Acumulado!$C$3:$G$161,4,0)) -> 200000 | G7: =IF(VLOOKUP($C7,Acumulado!$C$3:$G$161,5,0)<0,0,VLOOKUP($C7,Acumulado!$C$3:$G$161,5,0)) -> 1 | H7: =+G7*B7 -> 0.1
A8: =+Mensual!B7 -> 410101 | B8: 0.3 | C8: 1.4 Lograr meta de ventas en alquileres de contenedores reefer (solo o en combo) | D8: =IF(VLOOKUP($C8,Acumulado!$C$3:$G$161,2,0)<0,0,VLOOKUP($C8,Acumulado!$C$3:$G$161,2,0)) -> Dólares | E8: =IF(VLOOKUP($C8,Acumulado!$C$3:$G$161,3,0)<0,0,VLOOKUP($C8,Acumulado!$C$3:$G$161,3,0)) -> 16000 | F8: =IF(VLOOKUP($C8,Acumulado!$C$3:$G$161,3,0)<0,0,VLOOKUP($C8,Acumulado!$C$3:$G$161,4,0)) -> 200000 | G8: =IF(VLOOKUP($C8,Acumulado!$C$3:$G$161,5,0)<0,0,VLOOKUP($C8,Acumulado!$C$3:$G$161,5,0)) -> 1 | H8: =+G8*B8 -> 0.3 | I8: =+Mensual!J7 -> 0 | J8: =+Mensual!K7 -> 0 | K8: =+Mensual!L7 -> 0 | L8: =+Mensual!M7 -> 0
A9: =+Mensual!B8 -> 0 | B9: 0.3 | C9: 1.6 Alquileres de contenedores secos (solo o en combos CONMOXA) | D9: =IF(VLOOKUP($C9,Acumulado!$C$3:$G$161,2,0)<0,0,VLOOKUP($C9,Acumulado!$C$3:$G$161,2,0)) -> Porcentaje | E9: =IF(VLOOKUP($C9,Acumulado!$C$3:$G$161,3,0)<0,0,VLOOKUP($C9,Acumulado!$C$3:$G$161,3,0)) -> 0.2 | F9: =IF(VLOOKUP($C9,Acumulado!$C$3:$G$161,3,0)<0,0,VLOOKUP($C9,Acumulado!$C$3:$G$161,4,0)) -> 200000 | G9: =IF(VLOOKUP($C9,Acumulado!$C$3:$G$161,5,0)<0,0,VLOOKUP($C9,Acumulado!$C$3:$G$161,5,0)) -> 1 | H9: =+G9*B9 -> 0.3 | I9: =+Mensual!J8 -> 0 | J9: =+Mensual!K8 -> 0 | K9: =+Mensual!L8 -> 0 | L9: =+Mensual!M8 -> 0
B10: =SUM(B6:B9) -> 1 | H10: =SUM(H6:H9) -> #N/A

Sheet EJ,. CXMA MENSUAL
C3: Departamento: | D3: Contenedores
A5: =+Mensual!B5 -> No | B5: =+Mensual!C5 -> Peso | D5: =+Mensual!E5 -> Unidad de medición | E5: =+Mensual!F5 -> Meta | F5: =+Mensual!G5 -> Resultado | G5: =+Mensual!H5 -> Nota | H5: =+Mensual!I5 -> Valor ponderado | I5: =+Mensual!J5 -> 0 | J5: =+Mensual!K5 -> 0.25 | K5: =+Mensual!L5 -> 0.5 | ... Q5: =+Mensual!R5 -> 0 | T5: Nota | U5: Nota
A6: =+Mensual!B6 -> 4 | B6: 0.3 | C6: 1.2 Lograr meta de contenedores | D6: =IF(VLOOKUP($C6,Mensual!$D$6:$G$163,2,0)<0,0,VLOOKUP($C6,Mensual!$D$6:$G$163,2,0)) -> 0 | E6: =IF(VLOOKUP($C6,Mensual!$D$6:$G$163,3,0)<0,0,VLOOKUP($C6,Mensual!$D$6:$G$163,3,0)) -> 15 | F6: =IF(VLOOKUP($C6,Mensual!$D$6:$G$163,4,0)<0,0,VLOOKUP($C6,Mensual!$D$6:$G$163,4,0)) -> 1 | G6: =IF(VLOOKUP($C6,Mensual!$D$6:$H$163,5,0)<0,0,VLOOKUP($C6,Mensual!$D$6:$H$163,5,0)) -> 0.066666667 | H6: =+G6*B6 -> 0.02 | I6: =+Mensual!J6 -> 0 | J6: =+Mensual!K6 -> 0 | K6: =+Mensual!L6 -> 0 | L6: =+Mensual!M6 -> 0
C7: 1.2 Lograr meta de contenedores | D7: =IF(VLOOKUP($C7,Mensual!$D$6:$G$163,2,0)<0,0,VLOOKUP($C7,Mensual!$D$6:$G$163,2,0)) -> 0 | E7: =IF(VLOOKUP($C7,Mensual!$D$6:$G$163,3,0)<0,0,VLOOKUP($C7,Mensual!$D$6:$G$163,3,0)) -> 15 | F7: =IF(VLOOKUP($C7,Mensual!$D$6:$G$163,4,0)<0,0,VLOOKUP($C7,Mensual!$D$6:$G$163,4,0)) -> 1 | G7: =IF(VLOOKUP($C7,Mensual!$D$6:$H$163,5,0)<0,0,VLOOKUP($C7,Mensual!$D$6:$H$163,5,0)) -> 0.066666667 | H7: =+G7*B7 -> 0
C8: 1.2 Lograr meta de contenedores | D8: =IF(VLOOKUP($C8,Mensual!$D$6:$G$163,2,0)<0,0,VLOOKUP($C8,Mensual!$D$6:$G$163,2,0)) -> 0 | E8: =IF(VLOOKUP($C8,Mensual!$D$6:$G$163,3,0)<0,0,VLOOKUP($C8,Mensual!$D$6:$G$163,3,0)) -> 15 | F8: =IF(VLOOKUP($C8,Mensual!$D$6:$G$163,4,0)<0,0,VLOOKUP($C8,Mensual!$D$6:$G$163,4,0)) -> 1 | G8: =IF(VLOOKUP($C8,Mensual!$D$6:$H$163,5,0)<0,0,VLOOKUP($C8,Mensual!$D$6:$H$163,5,0)) -> 0.066666667 | H8: =+G8*B8 -> 0
C9: 1.2 Lograr meta de contenedores | D9: =IF(VLOOKUP($C9,Mensual!$D$6:$G$163,2,0)<0,0,VLOOKUP($C9,Mensual!$D$6:$G$163,2,0)) -> 0 | E9: =IF(VLOOKUP($C9,Mensual!$D$6:$G$163,3,0)<0,0,VLOOKUP($C9,Mensual!$D$6:$G$163,3,0)) -> 15 | F9: =IF(VLOOKUP($C9,Mensual!$D$6:$G$163,4,0)<0,0,VLOOKUP($C9,Mensual!$D$6:$G$163,4,0)) -> 1 | G9: =IF(VLOOKUP($C9,Mensual!$D$6:$H$163,5,0)<0,0,VLOOKUP($C9,Mensual!$D$6:$H$163,5,0)) -> 0.066666667 | H9: =+G9*B9 -> 0
C10: 1.2 Lograr meta de contenedores | D10: =IF(VLOOKUP($C10,Mensual!$D$6:$G$163,2,0)<0,0,VLOOKUP($C10,Mensual!$D$6:$G$163,2,0)) -> 0 | E10: =IF(VLOOKUP($C10,Mensual!$D$6:$G$163,3,0)<0,0,VLOOKUP($C10,Mensual!$D$6:$G$163,3,0)) -> 15 | F10: =IF(VLOOKUP($C10,Mensual!$D$6:$G$163,4,0)<0,0,VLOOKUP($C10,Mensual!$D$6:$G$163,4,0)) -> 1 | G10: =IF(VLOOKUP($C10,Mensual!$D$6:$H$163,5,0)<0,0,VLOOKUP($C10,Mensual!$D$6:$H$163,5,0)) -> 0.066666667 | H10: =+G10*B10 -> 0
C11: 1.2 Lograr meta de contenedores | D11: =IF(VLOOKUP($C11,Mensual!$D$6:$G$163,2,0)<0,0,VLOOKUP($C11,Mensual!$D$6:$G$163,2,0)) -> 0 | E11: =IF(VLOOKUP($C11,Mensual!$D$6:$G$163,3,0)<0,0,VLOOKUP($C11,Mensual!$D$6:$G$163,3,0)) -> 15 | F11: =IF(VLOOKUP($C11,Mensual!$D$6:$G$163,4,0)<0,0,VLOOKUP($C11,Mensual!$D$6:$G$163,4,0)) -> 1 | G11: =IF(VLOOKUP($C11,Mensual!$D$6:$H$163,5,0)<0,0,VLOOKUP($C11,Mensual!$D$6:$H$163,5,0)) -> 0.066666667 | H11: =+G11*B11 -> 0
C12: 1.2 Lograr meta de contenedores | D12: =IF(VLOOKUP($C12,Mensual!$D$6:$G$163,2,0)<0,0,VLOOKUP($C12,Mensual!$D$6:$G$163,2,0)) -> 0 | E12: =IF(VLOOKUP($C12,Mensual!$D$6:$G$163,3,0)<0,0,VLOOKUP($C12,Mensual!$D$6:$G$163,3,0)) -> 15 | F12: =IF(VLOOKUP($C12,Mensual!$D$6:$G$163,4,0)<0,0,VLOOKUP($C12,Mensual!$D$6:$G$163,4,0)) -> 1 | G12: =IF(VLOOKUP($C12,Mensual!$D$6:$H$163,5,0)<0,0,VLOOKUP($C12,Mensual!$D$6:$H$163,5,0)) -> 0.066666667 | H12: =+G12*B12 -> 0
C13: 1.2 Lograr meta de contenedores | D13: =IF(VLOOKUP($C13,Mensual!$D$6:$G$163,2,0)<0,0,VLOOKUP($C13,Mensual!$D$6:$G$163,2,0)) -> 0 | E13: =IF(VLOOKUP($C13,Mensual!$D$6:$G$163,3,0)<0,0,VLOOKUP($C13,Mensual!$D$6:$G$163,3,0)) -> 15 | F13: =IF(VLOOKUP($C13,Mensual!$D$6:$G$163,4,0)<0,0,VLOOKUP($C13,Mensual!$D$6:$G$163,4,0)) -> 1 | G13: =IF(VLOOKUP($C13,Mensual!$D$6:$H$163,5,0)<0,0,VLOOKUP($C13,Mensual!$D$6:$H$163,5,0)) -> 0.066666667 | H13: =+G13*B13 -> 0
C14: 1.2 Lograr meta de contenedores | D14: =IF(VLOOKUP($C14,Mensual!$D$6:$G$163,2,0)<0,0,VLOOKUP($C14,Mensual!$D$6:$G$163,2,0)) -> 0 | E14: =IF(VLOOKUP($C14,Mensual!$D$6:$G$163,3,0)<0,0,VLOOKUP($C14,Mensual!$D$6:$G$163,3,0)) -> 15 | F14: =IF(VLOOKUP($C14,Mensual!$D$6:$G$163,4,0)<0,0,VLOOKUP($C14,Mensual!$D$6:$G$163,4,0)) -> 1 | G14: =IF(VLOOKUP($C14,Mensual!$D$6:$H$163,5,0)<0,0,VLOOKUP($C14,Mensual!$D$6:$H$163,5,0)) -> 0.066666667 | H14: =+G14*B14 -> 0
B15: 0.1 | C15: 1.6 Alquileres de bodegas | D15: =IF(VLOOKUP($C15,Mensual!$D$6:$G$163,2,0)<0,0,VLOOKUP($C15,Mensual!$D$6:$G$163,2,0)) -> #N/A | E15: =IF(VLOOKUP($C15,Mensual!$D$6:$G$163,3,0)<0,0,VLOOKUP($C15,Mensual!$D$6:$G$163,3,0)) -> #N/A | F15: =IF(VLOOKUP($C15,Mensual!$D$6:$G$163,4,0)<0,0,VLOOKUP($C15,Mensual!$D$6:$G$163,4,0)) -> #N/A | G15: =IF(VLOOKUP($C15,Mensual!$D$6:$H$163,5,0)<0,0,VLOOKUP($C15,Mensual!$D$6:$H$163,5,0)) -> #N/A | H15: =+G15*B15 -> #N/A
A16: =+Mensual!B7 -> 410101 | B16: 0.3 | C16: 1.3 Lograr venta meta de ventas contenedores secos y modificados(lps) | D16: =IF(VLOOKUP($C16,Mensual!$D$6:$G$163,2,0)<0,0,VLOOKUP($C16,Mensual!$D$6:$G$163,2,0)) -> #N/A | E16: =IF(VLOOKUP($C16,Mensual!$D$6:$G$163,3,0)<0,0,VLOOKUP($C16,Mensual!$D$6:$G$163,3,0)) -> #N/A | F16: =IF(VLOOKUP($C16,Mensual!$D$6:$G$163,4,0)<0,0,VLOOKUP($C16,Mensual!$D$6:$G$163,4,0)) -> #N/A | G16: =IF(VLOOKUP($C16,Mensual!$D$6:$H$163,5,0)<0,0,VLOOKUP($C16,Mensual!$D$6:$H$163,5,0)) -> #N/A | H16: =+G16*B16 -> #N/A | I16: =+Mensual!J7 -> 0 | J16: =+Mensual!K7 -> 0 | K16: =+Mensual!L7 -> 0 | L16: =+Mensual!M7 -> 0
A17: =+Mensual!B8 -> 0 | B17: 0.3 | C17: 1.4 Lograr meta de ventas en alquileres de contenedores reefer | D17: =IF(VLOOKUP($C17,Mensual!$D$6:$G$163,2,0)<0,0,VLOOKUP($C17,Mensual!$D$6:$G$163,2,0)) -> #N/A | E17: =IF(VLOOKUP($C17,Mensual!$D$6:$G$163,3,0)<0,0,VLOOKUP($C17,Mensual!$D$6:$G$163,3,0)) -> #N/A | F17: =IF(VLOOKUP($C17,Mensual!$D$6:$G$163,4,0)<0,0,VLOOKUP($C17,Mensual!$D$6:$G$163,4,0)) -> #N/A | G17: =IF(VLOOKUP($C17,Mensual!$D$6:$H$163,5,0)<0,0,VLOOKUP($C17,Mensual!$D$6:$H$163,5,0)) -> #N/A | H17: =+G17*B17 -> #N/A | I17: =+Mensual!J8 -> 0 | J17: =+Mensual!K8 -> 0 | K17: =+Mensual!L8 -> 0 | L17: =+Mensual!M8 -> 0
B18: =SUM(B6:B17) -> 1 | H18: =SUM(H6:H17) -> #N/A

Sheet Listados
A1: Sistemas_Y_Procesos | B1: Contenedores | C1: Administracion | D1: Servicio_Al_Cliente | E1: Predio_Puerto_Cortes | F1: Predio_San_Lorenzo | G1: Interchange_PC | H1: Interchange_SL | I1: Taller_PC | J1: Taller_SL | K1: Transporte | L1: Gasolinera
A2: David Molina | B2: Luis Madrid | C2: Nancy Garcia | D2: Jacky Mena | E2: Lorenzo Varela | F2: Juan Cubillo | G2: Jose Rivera | H2: Jose Borjas | I2: Alicia Castro | J2: Brayan Valdez | K2: Gelsy Pineda | L2: Abner Urbina
A3: Oscar Romero | B3: Paola Pineda | C3: Bryan Lopez | D3: Sinia Murillo | E3: Honoria Rodriguez | F3: Danahara Castillo | G3: Denis Mejia | I3: Miguel Oviedo | K3: Vilna Murcia | L3: Angie Licona
A4: Keila Rodriguez | B4: Roy Reyes | C4: Suley Canales | D4: Josseline Chavarria | E4: Dennis Pereira | F4: Oscar Urbina | G4: Victor Escobar | I4: Jose Carballo | L4: Brenda Reyes
A5: Yadira Reyes | B5: Valeria Mena | C5: Alejandro Garcia | D5: Edgardo Hernandez | E5: Oneida Reyes | F5: Bayron Sierra | I5: Oscar Castellanos | L5: Dairy Coello
A6: Mario Murillo | C6: Juan Manuel | E6: Kelvin Garcia | F6: Cristino Umanzaor | I6: Osman Zeron | L6: Doris Murillo
A7: Cristian Hernandez | C7: Elder Perdomo | E7: Carlos Sanchez | F7: Cristian Gonzales | I7: Adrian Rivas | L7: Irma Bonilla
C8: Emilia Pineda | E8: Erika Sanchez | I8: Denis Rivera | L8: Jeimy Lopez
C9: Carolina Vargas | E9: Jairo Bueso | I9: Eduardo Muñoz | L9: Jose Bertrand
C10: Cecilia Galeano | E10: Kimberly Orellana | I10: Fredy Ortiz | L10: Joselin Reyes
C11: Julio Estevez | E11: Marvin Ortiz | I11: Marvin Mendez | L11: Kenia Reyes
C12: Tamara Castro | I12: Abner Orellana | L12: Maria López
I13: Josue Castro | L13: Sandra Alvarenga
I14: Orlin Mejia | L14: Wendy Munguia
I15: Victor Maradiaga | L15: Gasolinera General
