Workbook

Sheet Summary
A1: KPI Evaluation Catalog — Working Classification
A3: Metric | B3: Value | D3: Evaluation Type | E3: Count | G3: Catalog Status | H3: Count
A4: Catalog records | B4: =COUNTA('KPI Catalog'!A2:A200) -> 89 | D4: GREATER_IS_BETTER | E4: =COUNTIF('KPI Catalog'!J2:J200,"GREATER_IS_BETTER") -> 48 | G4: PROPOSED | H4: =COUNTIF('KPI Catalog'!Q2:Q200,"PROPOSED") -> 56
A5: Atomic KPIs | B5: =COUNTIF('KPI Catalog'!D2:D200,"ATOMIC KPI") -> 73 | D5: LOWER_IS_BETTER | E5: =COUNTIF('KPI Catalog'!J2:J200,"LOWER_IS_BETTER") -> 21 | G5: BLOCKED | H5: =COUNTIF('KPI Catalog'!Q2:Q200,"BLOCKED") -> 28
A6: Feature / Milestone | B6: =COUNTIF('KPI Catalog'!D2:D200,"FEATURE / MILESTONE") -> 11 | D6: BINARY / MILESTONE | E6: =COUNTIF('KPI Catalog'!J2:J200,"BINARY / MILESTONE") -> 12 | G6: EXCLUDE / REVIEW | H6: =COUNTIF('KPI Catalog'!Q2:Q200,"EXCLUDE / REVIEW") -> 5
A7: Blocked / needs decision | B7: =COUNTIF('KPI Catalog'!Q2:Q200,"BLOCKED") -> 28 | D7: EQUAL_OR_LOWER_REVIEW | E7: =COUNTIF('KPI Catalog'!J2:J200,"EQUAL_OR_LOWER_REVIEW") -> 0
A8: Excluded / aggregates | B8: =COUNTIF('KPI Catalog'!Q2:Q200,"EXCLUDE / REVIEW") -> 5 | D8: NEEDS_REVIEW | E8: =COUNTIF('KPI Catalog'!J2:J200,"NEEDS_REVIEW") -> 8
A11: Category | B11: Count | D11: How to use this workbook
A12: Operational Productivity | B12: =COUNTIF('KPI Catalog'!E2:E200,"Operational Productivity") -> 15 | D12: 1. This is a proposed working classification, not an approved business rulebook.
A13: Commercial Growth | B13: =COUNTIF('KPI Catalog'!E2:E200,"Commercial Growth") -> 13 | D13: 2. Review BLOCKED items first; many have ambiguous result semantics, zero goals, or inconsistent legacy units/goals.
A14: Financial Performance | B14: =COUNTIF('KPI Catalog'!E2:E200,"Financial Performance") -> 13 | D14: 3. Evaluation Type answers whether higher/lower/equal/range is better; Scoring Method answers how Goal + Result becomes Compliance.
A15: Innovation & Digitalization | B15: =COUNTIF('KPI Catalog'!E2:E200,"Innovation & Digitalization") -> 12 | D15: 4. Result Semantics is critical: e.g. “reduce cost 10%” can mean lower actual cost OR higher achieved reduction percentage.
A16: Cost Efficiency | B16: =COUNTIF('KPI Catalog'!E2:E200,"Cost Efficiency") -> 11 | D16: 5. Source Occurrences preserves traceability back to the original workbook and shows where the same KPI was reused.
A17: Needs Business Review | B17: =COUNTIF('KPI Catalog'!E2:E200,"Needs Business Review") -> 10
A18: Asset Utilization | B18: =COUNTIF('KPI Catalog'!E2:E200,"Asset Utilization") -> 6
A19: Process & Service Quality | B19: =COUNTIF('KPI Catalog'!E2:E200,"Process & Service Quality") -> 4
A20: Safety & Risk | B20: =COUNTIF('KPI Catalog'!E2:E200,"Safety & Risk") -> 2
A21: Customer Experience | B21: =COUNTIF('KPI Catalog'!E2:E200,"Customer Experience") -> 1
A22: Financial Health | B22: =COUNTIF('KPI Catalog'!E2:E200,"Financial Health") -> 1
A23: People & Culture | B23: =COUNTIF('KPI Catalog'!E2:E200,"People & Culture") -> 1

Sheet KPI Catalog
A1: Catalog ID | B1: Legacy Code | C1: KPI Name / Original | D1: Row Type | E1: Category (Proposed) | F1: Primary Owner (Proposed) | G1: Result Semantics | H1: Measurement Unit (Proposed) | I1: Goal Example | J1: Evaluation Type (Proposed) | K1: Scoring Method (Proposed) | L1: Special Rule / Rationale | M1: Example Result (Source) | N1: Illustrative Raw Achievement % | O1: Illustrative Compliance % (cap 100) | P1: Classification Confidence | Q1: Catalog Status | R1: Business Review Required | S1: Review Reason | T1: KPI Family | U1: Source Department(s) | V1: Source Sheet(s) | W1: Occurrences | X1: Original Unit Variant(s) | Y1: Goal Variant(s) | Z1: Calculation Note | AA1: Action Priority | AB1: What Must Change / Confirm | AC1: Business Question / Decision | AD1: Recommended Next Status | AE1: Blocks Production Scoring for This KPI?
A2: CAT-001 | B2: 1 | C2: Aumentar ventas en el año 2023 del Grupo EXA (EXA, CONMOXA, AXA, TREXA, SAN JORGE) en 10% en USD vs año 2022. | D2: ATOMIC KPI | E2: Commercial Growth | F2: Contenedores / Ventas | G2: CHANGE_PERCENT | H2: % | I2: 0.1 | J2: GREATER_IS_BETTER | K2: PROPORTIONAL | L2: Mayor resultado = mejor; usar Result/Goal si el Goal es comparable. | M2: 0.2 | N2: 200 | O2: 100 | P2: MEDIUM | Q2: PROPOSED | R2: YES | S2: Confirmar que Result es porcentaje de cambio logrado y no valor absoluto. | T2: Sales & Commercial | V2: Hoja3 | W2: 2 | X2: Porcentaje | Y2: 0.1 | AA2: P1 - BUSINESS CONFIRMATION | AB2: Confirm Result Semantics and Goal interpretation; the current Greater/Lower proposal is plausible but not safe enough to approve automatically. | AC2: Confirmar que Result es porcentaje de cambio logrado y no valor absoluto. | AD2: APPROVED | AE2: YES for production
A3: CAT-002 | B3: 1 | C3: Aumentar ventas en: | D3: PARENT / AGGREGATE | E3: Commercial Growth | F3: Contenedores / Ventas | G3: CHANGE_PERCENT | H3: USD | I3: 0.2 | J3: GREATER_IS_BETTER | K3: PROPORTIONAL | L3: Mayor resultado = mejor; usar Result/Goal si el Goal es comparable. | P3: LOW | Q3: EXCLUDE / REVIEW | R3: YES | S3: No es un KPI atómico confiable para scoring. | T3: Sales & Commercial | V3: Hoja1 | W3: 1 | X3: Dólares | Y3: 0.2 | AA3: P3 - EXCLUDE/STRUCTURE | AB3: Do not score this row as an atomic KPI. Keep it only as a parent/group/Scorecard aggregate if the business still needs it. | AC3: Confirm that this row is an aggregate/header and should not generate an independent KPI result. | AD3: EXCLUDE / REVIEW | AE3: NO - exclude from atomic scoring
A4: CAT-003 | B4: 1.10 | C4: Aumentar ventas en articulos Sejue/get504 | D4: ATOMIC KPI | E4: Commercial Growth | F4: Contenedores / Ventas | G4: ABSOLUTE_VALUE | H4: artículos | I4: 10 | J4: GREATER_IS_BETTER | K4: PROPORTIONAL | L4: Mayor resultado = mejor; usar Result/Goal si el Goal es comparable. | M4: 19 | N4: 190 | O4: 100 | P4: HIGH | Q4: PROPOSED | R4: YES | S4: Clasificación propuesta con señales consistentes; requiere aprobación formal. | T4: Sales & Commercial | U4: Contenedores | V4: Contenedores, Luis Madrid | W4: 2 | X4: Articulos | Y4: 10 | AA4: P2 - APPROVAL | AB4: No formula change is currently suggested; obtain formal business approval and normalize any naming/unit variants. | AC4: Confirm KPI meaning, Goal, Unit, Evaluation Type and Scoring Method as proposed. | AD4: APPROVED | AE4: NO - formula can be tested
A5: CAT-004 | B5: 1.11 | C5: Tienda de conveniencia (Primeros 4 meses 15k usd y 25k usd) | D5: ATOMIC KPI | E5: Commercial Growth | F5: Gasolinera | G5: NEEDS_REVIEW | H5: USD | I5: 25000 | J5: NEEDS_REVIEW | K5: NEEDS_REVIEW | L5: No hay suficiente información inequívoca para decidir la fórmula. | M5: 20092.4 | P5: LOW | Q5: BLOCKED | R5: YES | S5: Semántica o dirección de evaluación ambigua. | T5: Other | U5: Gasolinera | V5: Abner U b, Gasolinera | W5: 2 | X5: Dólares | Y5: 25000 | AA5: P0 - BLOCKING | AB5: Must clarify what the Result actually represents; choose the Evaluation Type; define the Scoring Method before this KPI can be scored safely. | AC5: What does Result represent: absolute value, percentage change, compliance %, count, rate, duration, cost, ratio, or another value? Is higher better, lower better, exact target, range, or milestone/binary? How should Goal + Result be converted to Compliance %? | AD5: BLOCKED | AE5: YES
A6: CAT-005 | B6: 1.13 | C6: Aumentar servicio de almacenamiento y M&R San Lorenzo | D6: ATOMIC KPI | E6: Needs Business Review | F6: Predio San Lorenzo / Taller | G6: NEEDS_REVIEW | H6: REVIEW | I6: 0.2 | J6: GREATER_IS_BETTER | K6: PROPORTIONAL | L6: Mayor resultado = mejor; usar Result/Goal si el Goal es comparable. | M6: 0.3 | N6: 150 | O6: 100 | P6: LOW | Q6: BLOCKED | R6: YES | S6: Semántica o dirección de evaluación ambigua. | T6: Other | U6: Predio San Lorenzo | V6: Cubillo, San Lorenzo b | W6: 2 | X6: 0 | Y6: 0.2 | AA6: P0 - BLOCKING | AB6: Must clarify what the Result actually represents; normalize the Measurement Unit before this KPI can be scored safely. | AC6: What does Result represent: absolute value, percentage change, compliance %, count, rate, duration, cost, ratio, or another value? What exact unit should be stored and displayed for Result? | AD6: BLOCKED | AE6: YES
A7: CAT-006 | B7: 1.14 | C7: Incrementar gate out de contenedores Puerto Cortés | D7: ATOMIC KPI | E7: Commercial Growth | F7: Predio Puerto Cortés | G7: CHANGE_PERCENT | H7: gate-outs | I7: 0.2 | J7: GREATER_IS_BETTER | K7: PROPORTIONAL | L7: Mayor resultado = mejor; usar Result/Goal si el Goal es comparable. | M7: 0 | N7: 0 | O7: 0 | P7: MEDIUM | Q7: PROPOSED | R7: YES | S7: Confirmar que Result es porcentaje de cambio logrado y no valor absoluto. | T7: Sales & Commercial | U7: Predio Puerto Cortes | V7: Lorenzo Varela, Puerto Cortes | W7: 2 | X7: Gate | Y7: 0.2 | AA7: P1 - BUSINESS CONFIRMATION | AB7: Confirm Result Semantics and Goal interpretation; the current Greater/Lower proposal is plausible but not safe enough to approve automatically. | AC7: Confirmar que Result es porcentaje de cambio logrado y no valor absoluto. | AD7: APPROVED | AE7: YES for production
A8: CAT-007 | B8: 1.17 | C8: Aumentar el numero de cliente semestralmente | D8: ATOMIC KPI | E8: Commercial Growth | F8: Administracion | G8: CHANGE_PERCENT | H8: clientes | I8: 1 | J8: GREATER_IS_BETTER | K8: PROPORTIONAL | L8: Mayor resultado = mejor; usar Result/Goal si el Goal es comparable. | M8: 0 | N8: 0 | O8: 0 | P8: MEDIUM | Q8: PROPOSED | R8: YES | S8: Confirmar que Result es porcentaje de cambio logrado y no valor absoluto. | T8: Sales & Commercial | U8: Administracion | V8: TREXA | W8: 1 | X8: cliente | Y8: 1 | AA8: P1 - BUSINESS CONFIRMATION | AB8: Confirm Result Semantics and Goal interpretation; the current Greater/Lower proposal is plausible but not safe enough to approve automatically. | AC8: Confirmar que Result es porcentaje de cambio logrado y no valor absoluto. | AD8: APPROVED | AE8: YES for production
A9: CAT-008 | B9: 1.2 | C9: Lograr meta de contenedores | D9: ATOMIC KPI | E9: Needs Business Review | F9: Contenedores / Ventas | G9: NEEDS_REVIEW | H9: REVIEW | I9: 15 | J9: GREATER_IS_BETTER | K9: PROPORTIONAL | L9: Mayor resultado = mejor; usar Result/Goal si el Goal es comparable. | M9: 1 | N9: 6.6666667 | O9: 6.6666667 | P9: LOW | Q9: BLOCKED | R9: YES | S9: Semántica o dirección de evaluación ambigua. | T9: Other | U9: Contenedores | V9: Contenedores | W9: 1 | X9: 0 | Y9: 15 | AA9: P0 - BLOCKING | AB9: Must clarify what the Result actually represents; normalize the Measurement Unit before this KPI can be scored safely. | AC9: What does Result represent: absolute value, percentage change, compliance %, count, rate, duration, cost, ratio, or another value? What exact unit should be stored and displayed for Result? | AD9: BLOCKED | AE9: YES
A10: CAT-009 | B10: 1.3 | C10: Lograr meta de ventas contenedores secos y modificados(dolares) | D10: ATOMIC KPI | E10: Commercial Growth | F10: Contenedores / Ventas | G10: ABSOLUTE_VALUE | H10: USD | I10: 40000 | J10: GREATER_IS_BETTER | K10: PROPORTIONAL | L10: Mayor resultado = mejor; usar Result/Goal si el Goal es comparable. | M10: 1800 | N10: 4.5 | O10: 4.5 | P10: HIGH | Q10: PROPOSED | R10: YES | S10: Clasificación propuesta con señales consistentes; requiere aprobación formal. | T10: Sales & Commercial | U10: Contenedores | V10: Contenedores | W10: 1 | X10: Dólares | Y10: 40000 | AA10: P2 - APPROVAL | AB10: No formula change is currently suggested; obtain formal business approval and normalize any naming/unit variants. | AC10: Confirm KPI meaning, Goal, Unit, Evaluation Type and Scoring Method as proposed. | AD10: APPROVED | AE10: NO - formula can be tested
A11: CAT-010 | B11: 1.4 | C11: Lograr meta de ventas en alquileres de contenedores reefer (solo o en combo) | D11: ATOMIC KPI | E11: Commercial Growth | F11: Contenedores / Ventas | G11: ABSOLUTE_VALUE | H11: USD | I11: 16000 | J11: GREATER_IS_BETTER | K11: PROPORTIONAL | L11: Mayor resultado = mejor; usar Result/Goal si el Goal es comparable. | M11: 0 | N11: 0 | O11: 0 | P11: HIGH | Q11: PROPOSED | R11: YES | S11: Clasificación propuesta con señales consistentes; requiere aprobación formal. | T11: Sales & Commercial | U11: Contenedores | V11: Contenedores | W11: 1 | X11: Dólares | Y11: 16000 | AA11: P2 - APPROVAL | AB11: No formula change is currently suggested; obtain formal business approval and normalize any naming/unit variants. | AC11: Confirm KPI meaning, Goal, Unit, Evaluation Type and Scoring Method as proposed. | AD11: APPROVED | AE11: NO - formula can be tested
A12: CAT-011 | B12: 1.5 | C12: Aumentar Rentas bienes y raices | D12: ATOMIC KPI | E12: Commercial Growth | F12: Contenedores / Ventas | G12: CHANGE_PERCENT | H12: % | I12: 0.2 | J12: GREATER_IS_BETTER | K12: PROPORTIONAL | L12: Mayor resultado = mejor; usar Result/Goal si el Goal es comparable. | M12: 0 | N12: 0 | O12: 0 | P12: MEDIUM | Q12: PROPOSED | R12: YES | S12: Confirmar que Result es porcentaje de cambio logrado y no valor absoluto. | T12: Sales & Commercial | U12: Contenedores | V12: Luis Madrid | W12: 1 | X12: Porcentaje | Y12: 0.2 | AA12: P1 - BUSINESS CONFIRMATION | AB12: Confirm Result Semantics and Goal interpretation; the current Greater/Lower proposal is plausible but not safe enough to approve automatically. | AC12: Confirmar que Result es porcentaje de cambio logrado y no valor absoluto. | AD12: APPROVED | AE12: YES for production
A13: CAT-012 | B13: 1.6 | C13: Alquileres de contenedores secos (solo o en combos CONMOXA) | D13: ATOMIC KPI | E13: Commercial Growth | F13: Contenedores / Ventas | G13: CHANGE_PERCENT | H13: % | I13: 0.2 | J13: NEEDS_REVIEW | K13: NEEDS_REVIEW | L13: No hay suficiente información inequívoca para decidir la fórmula. | M13: 0.45 | P13: LOW | Q13: BLOCKED | R13: YES | S13: Semántica o dirección de evaluación ambigua. | T13: Sales & Commercial | U13: Contenedores | V13: Contenedores | W13: 1 | X13: Porcentaje | Y13: 0.2 | AA13: P0 - BLOCKING | AB13: Must choose the Evaluation Type; define the Scoring Method before this KPI can be scored safely. | AC13: Is higher better, lower better, exact target, range, or milestone/binary? How should Goal + Result be converted to Compliance %? | AD13: BLOCKED | AE13: YES
A14: CAT-013 | B14: 1.7 | C14: Lograr ventas de gasolinera de galones | D14: ATOMIC KPI | E14: Commercial Growth | F14: Gasolinera | G14: ABSOLUTE_VALUE | H14: galones | I14: 100000 | J14: GREATER_IS_BETTER | K14: PROPORTIONAL | L14: Mayor resultado = mejor; usar Result/Goal si el Goal es comparable. | M14: 112588 | N14: 112.588 | O14: 100 | P14: HIGH | Q14: PROPOSED | R14: YES | S14: Clasificación propuesta con señales consistentes; requiere aprobación formal. | T14: Sales & Commercial | U14: Gasolinera | V14: Abner U b, Gasolinera | W14: 2 | X14: Galones | Y14: 100000 | AA14: P2 - APPROVAL | AB14: No formula change is currently suggested; obtain formal business approval and normalize any naming/unit variants. | AC14: Confirm KPI meaning, Goal, Unit, Evaluation Type and Scoring Method as proposed. | AD14: APPROVED | AE14: NO - formula can be tested
A15: CAT-014 | B15: 1.8 | C15: Aumentar ventas en TREXA | D15: ATOMIC KPI | E15: Commercial Growth | F15: Contenedores / Ventas | G15: CHANGE_PERCENT | H15: USD | I15: 0.2 | J15: GREATER_IS_BETTER | K15: PROPORTIONAL | L15: Mayor resultado = mejor; usar Result/Goal si el Goal es comparable. | M15: 1.03 | N15: 515 | O15: 100 | P15: MEDIUM | Q15: PROPOSED | R15: YES | S15: Confirmar que Result es porcentaje de cambio logrado y no valor absoluto. | T15: Sales & Commercial | U15: Administracion | V15: Nancy Garcia b (4), TREXA | W15: 2 | X15: Dólares | Y15: 0.2 | AA15: P1 - BUSINESS CONFIRMATION | AB15: Confirm Result Semantics and Goal interpretation; the current Greater/Lower proposal is plausible but not safe enough to approve automatically. | AC15: Confirmar que Result es porcentaje de cambio logrado y no valor absoluto. | AD15: APPROVED | AE15: YES for production
A16: CAT-015 | B16: 1.9 | C16: Aumento en ventas de GPS a terceros (nuevos clientes) | D16: ATOMIC KPI | E16: Commercial Growth | F16: Contenedores / Ventas | G16: ABSOLUTE_VALUE | H16: unidades/mes | I16: 10 | J16: GREATER_IS_BETTER | K16: PROPORTIONAL | L16: Mayor resultado = mejor; usar Result/Goal si el Goal es comparable. | M16: 0 | N16: 0 | O16: 0 | P16: HIGH | Q16: PROPOSED | R16: YES | S16: Clasificación propuesta con señales consistentes; requiere aprobación formal. | T16: Sales & Commercial | U16: Contenedores, Sistemas Y Procesos | V16: Keila, Roy Reyes | W16: 2 | X16: Unidad instaladas / mensuales | Y16: 10 | AA16: P2 - APPROVAL | AB16: No formula change is currently suggested; obtain formal business approval and normalize any naming/unit variants. | AC16: Confirm KPI meaning, Goal, Unit, Evaluation Type and Scoring Method as proposed. | AD16: APPROVED | AE16: NO - formula can be tested
A17: CAT-016 | B17: 10 | C17: CONMOXA | D17: SCORECARD_AGGREGATE | E17: Needs Business Review | F17: Contenedores | G17: NEEDS_REVIEW | H17: RESULTADO SCORECARD | I17: 1 | J17: NEEDS_REVIEW | K17: NEEDS_REVIEW | L17: No hay suficiente información inequívoca para decidir la fórmula. | M17: 0.4255 | P17: LOW | Q17: EXCLUDE / REVIEW | R17: YES | S17: No es un KPI atómico confiable para scoring. | T17: Other | U17: Contenedores | V17: Luis Madrid, Roy Reyes | W17: 2 | X17: RESULTADO SCORECARD | Y17: 1 | AA17: P3 - EXCLUDE/STRUCTURE | AB17: Do not score this row as an atomic KPI. Keep it only as a parent/group/Scorecard aggregate if the business still needs it. | AC17: Confirm that this row is an aggregate/header and should not generate an independent KPI result. | AD17: EXCLUDE / REVIEW | AE17: NO - exclude from atomic scoring
A18: CAT-017 | B18: 2 | C18: Aumentar margen neto | D18: PARENT / AGGREGATE | E18: Financial Performance | F18: Administración / Finanzas | G18: RATIO_OR_PERCENT | H18: % | I18: 0.1 | J18: GREATER_IS_BETTER | K18: PROPORTIONAL | L18: Mayor resultado = mejor; usar Result/Goal si el Goal es comparable. | P18: LOW | Q18: EXCLUDE / REVIEW | R18: YES | S18: No es un KPI atómico confiable para scoring. | T18: Margins | V18: Hoja1 | W18: 1 | X18: Porcentaje | Y18: 0.1 | AA18: P3 - EXCLUDE/STRUCTURE | AB18: Do not score this row as an atomic KPI. Keep it only as a parent/group/Scorecard aggregate if the business still needs it. | AC18: Confirm that this row is an aggregate/header and should not generate an independent KPI result. | AD18: EXCLUDE / REVIEW | AE18: NO - exclude from atomic scoring
A19: CAT-018 | B19: 2 | C19: Aumentar margen neto vrs año anterior | D19: ATOMIC KPI | E19: Financial Performance | F19: Administración / Finanzas | G19: RATIO_OR_PERCENT | H19: % | I19: 0.1 | J19: GREATER_IS_BETTER | K19: PROPORTIONAL | L19: Mayor resultado = mejor; usar Result/Goal si el Goal es comparable. | M19: 0.1 | N19: 100 | O19: 100 | P19: HIGH | Q19: PROPOSED | R19: YES | S19: Clasificación propuesta con señales consistentes; requiere aprobación formal. | T19: Margins | V19: Hoja3 | W19: 2 | Y19: 0.1 | AA19: P2 - APPROVAL | AB19: No formula change is currently suggested; obtain formal business approval and normalize any naming/unit variants. | AC19: Confirm KPI meaning, Goal, Unit, Evaluation Type and Scoring Method as proposed. | AD19: APPROVED | AE19: NO - formula can be tested
A20: CAT-019 | B20: 2.1 | C20: Reducir gasto administrativo x% | D20: ATOMIC KPI | E20: Cost Efficiency | F20: Administración / Finanzas | G20: CHANGE_PERCENT | H20: % | I20: 0.1 | J20: GREATER_IS_BETTER | K20: PROPORTIONAL | L20: Result parece representar % de reducción lograda; confirmar semántica antes de aprobar. | M20: 0.32 | N20: 320 | O20: 100 | P20: MEDIUM | Q20: PROPOSED | R20: YES | S20: Confirmar que Result es porcentaje de cambio logrado y no valor absoluto. | T20: Costs & Efficiency | U20: Administracion | V20: Cecilia, Compras, Julio - Alejandro, Nancy Garcia b (4), Tesoreria | W20: 5 | X20: % | Y20: 0.1 | AA20: P1 - BUSINESS CONFIRMATION | AB20: Confirm Result Semantics and Goal interpretation; the current Greater/Lower proposal is plausible but not safe enough to approve automatically. | AC20: Confirmar que Result es porcentaje de cambio logrado y no valor absoluto. | AD20: APPROVED | AE20: YES for production
A21: CAT-020 | B21: 2.11 | C21: Gasto administrativo San Lorenzo | D21: ATOMIC KPI | E21: Cost Efficiency | F21: Administración / Finanzas | G21: UNIT_COST_OR_COST_RATE | H21: REVIEW | I21: 0.1 | J21: NEEDS_REVIEW | K21: NEEDS_REVIEW | L21: No hay suficiente información inequívoca para decidir la fórmula. | M21: 0 | P21: LOW | Q21: BLOCKED | R21: YES | S21: Semántica o dirección de evaluación ambigua. | T21: Costs & Efficiency | U21: Predio San Lorenzo | V21: Cubillo, San Lorenzo b | W21: 2 | X21: 0 | Y21: 0.1 | AA21: P0 - BLOCKING | AB21: Must normalize the Measurement Unit; choose the Evaluation Type; define the Scoring Method before this KPI can be scored safely. | AC21: What exact unit should be stored and displayed for Result? Is higher better, lower better, exact target, range, or milestone/binary? How should Goal + Result be converted to Compliance %? | AD21: BLOCKED | AE21: YES
A22: CAT-021 | B22: 2.12 | C22: Costo por mes por GPS (Costo de plataforma + Tigo/claro + otros costos) | D22: ATOMIC KPI | E22: Cost Efficiency | F22: Sistemas y Procesos | G22: UNIT_COST_OR_COST_RATE | H22: USD | I22: 8 | J22: NEEDS_REVIEW | K22: NEEDS_REVIEW | L22: No hay suficiente información inequívoca para decidir la fórmula. | M22: 4.71 | P22: LOW | Q22: BLOCKED | R22: YES | S22: Semántica o dirección de evaluación ambigua. | T22: Costs & Efficiency | U22: Sistemas Y Procesos | V22: Keila | W22: 1 | X22: $ | Y22: 8 | AA22: P0 - BLOCKING | AB22: Must choose the Evaluation Type; define the Scoring Method before this KPI can be scored safely. | AC22: Is higher better, lower better, exact target, range, or milestone/binary? How should Goal + Result be converted to Compliance %? | AD22: BLOCKED | AE22: YES
A23: CAT-022 | B23: 2.13 | C23: Reducir Costo de M&R por contenedor Puerto Cortes | D23: ATOMIC KPI | E23: Cost Efficiency | F23: Predio Puerto Cortés / Taller | G23: UNIT_COST_OR_COST_RATE | H23: USD/contenedor | I23: 0.1 | J23: LOWER_IS_BETTER | K23: PROPORTIONAL | L23: Menor valor real = mejor; usar Goal/Result si Goal>0. | M23: 0 | N23: 100 | O23: 100 | P23: HIGH | Q23: PROPOSED | R23: YES | S23: Clasificación propuesta con señales consistentes; requiere aprobación formal. | T23: Costs & Efficiency | U23: Predio Puerto Cortes | V23: Lorenzo Varela, Puerto Cortes | W23: 2 | X23: $/contenedor | Y23: 0.1 | Z23: Result=0 tratado como mejor que meta para ejemplo; revisar negocio. | AA23: P2 - APPROVAL | AB23: No formula change is currently suggested; obtain formal business approval and normalize any naming/unit variants. | AC23: Confirm KPI meaning, Goal, Unit, Evaluation Type and Scoring Method as proposed. | AD23: APPROVED | AE23: NO - formula can be tested
A24: CAT-023 | B24: 2.14 | C24: Reducir costo máquinas (incluye mulita y containers handler) Puerto Cortes | D24: ATOMIC KPI | E24: Cost Efficiency | F24: Predio Puerto Cortés / Taller | G24: UNIT_COST_OR_COST_RATE | H24: USD/contenedor | I24: 0.1 | J24: LOWER_IS_BETTER | K24: PROPORTIONAL | L24: Menor valor real = mejor; usar Goal/Result si Goal>0. | M24: 0 | N24: 100 | O24: 100 | P24: HIGH | Q24: PROPOSED | R24: YES | S24: Clasificación propuesta con señales consistentes; requiere aprobación formal. | T24: Costs & Efficiency | U24: Predio Puerto Cortes | V24: Lorenzo Varela, Puerto Cortes | W24: 2 | X24: $/contenedor | Y24: 0.1 | Z24: Result=0 tratado como mejor que meta para ejemplo; revisar negocio. | AA24: P2 - APPROVAL | AB24: No formula change is currently suggested; obtain formal business approval and normalize any naming/unit variants. | AC24: Confirm KPI meaning, Goal, Unit, Evaluation Type and Scoring Method as proposed. | AD24: APPROVED | AE24: NO - formula can be tested
A25: CAT-024 | B25: 2.15 | C25: Aumentar margen de M&R por contenedor San Lorenzo | D25: ATOMIC KPI | E25: Needs Business Review | F25: Predio San Lorenzo / Taller | G25: RATIO_OR_PERCENT | H25: % | I25: 0 | J25: GREATER_IS_BETTER | K25: PROPORTIONAL | L25: Mayor resultado = mejor; usar Result/Goal si el Goal es comparable. | M25: 0 | P25: LOW | Q25: BLOCKED | R25: YES | S25: Goal=0 no es compatible con scoring proporcional. | T25: Margins | U25: Predio San Lorenzo | V25: Cubillo, San Lorenzo b | W25: 2 | X25: 0 | Y25: 0 | AA25: P0 - BLOCKING | AB25: Resolve the documented ambiguity before using this KPI in production scoring. | AC25: Goal=0 no es compatible con scoring proporcional. | AD25: BLOCKED | AE25: YES
A26: CAT-025 | B26: 2.16 | C26: Reducir costo máquinas (incluye mulita y containers handler) San Lorenzo | D26: ATOMIC KPI | E26: Cost Efficiency | F26: Predio San Lorenzo / Taller | G26: UNIT_COST_OR_COST_RATE | H26: REVIEW | I26: 0 | J26: LOWER_IS_BETTER | K26: PROPORTIONAL | L26: Menor valor real = mejor; usar Goal/Result si Goal>0. | M26: 0 | P26: MEDIUM | Q26: PROPOSED | R26: YES | S26: Unidad de medida ausente/inconsistente; confirmar. | T26: Costs & Efficiency | U26: Predio San Lorenzo | V26: Cubillo, San Lorenzo b | W26: 2 | X26: 0 | Y26: 0 | AA26: P0 - BLOCKING | AB26: Must normalize the Measurement Unit before this KPI can be scored safely. | AC26: What exact unit should be stored and displayed for Result? | AD26: BLOCKED | AE26: YES
A27: CAT-026 | B27: 2.17 | C27: Reducir costo por km/cabezal TRANEXPA | D27: ATOMIC KPI | E27: Cost Efficiency | F27: Transporte | G27: UNIT_COST_OR_COST_RATE | H27: REVIEW | I27: 0 | J27: LOWER_IS_BETTER | K27: PROPORTIONAL | L27: Menor valor real = mejor; usar Goal/Result si Goal>0. | M27: 0.14 | P27: MEDIUM | Q27: PROPOSED | R27: YES | S27: Unidad de medida ausente/inconsistente; confirmar. | T27: Costs & Efficiency | U27: Transporte | V27: TRANEXPA | W27: 1 | X27: 0 | Y27: 0 | AA27: P0 - BLOCKING | AB27: Must normalize the Measurement Unit before this KPI can be scored safely. | AC27: What exact unit should be stored and displayed for Result? | AD27: BLOCKED | AE27: YES
A28: CAT-027 | B28: 2.18 | C28: Reducir M&R gensets $ /genset activo 10% | D28: ATOMIC KPI | E28: Needs Business Review | F28: Predio Puerto Cortes / Predio San Lorenzo | G28: NEEDS_REVIEW | H28: USD | I28: 0.1 | J28: LOWER_IS_BETTER | K28: PROPORTIONAL | L28: Menor valor real = mejor; usar Goal/Result si Goal>0. | M28: 4.66 | N28: 2.1459227 | O28: 2.1459227 | P28: LOW | Q28: BLOCKED | R28: YES | S28: Semántica o dirección de evaluación ambigua. | T28: Other | U28: Predio Puerto Cortes, Predio San Lorenzo | V28: Cubillo, Lorenzo Varela, Puerto Cortes, San Lorenzo b | W28: 4 | X28: dolares | Y28: 0.1 | AA28: P0 - BLOCKING | AB28: Must clarify what the Result actually represents before this KPI can be scored safely. | AC28: What does Result represent: absolute value, percentage change, compliance %, count, rate, duration, cost, ratio, or another value? | AD28: BLOCKED | AE28: YES
A29: CAT-028 | B29: 2.19 | C29: Gasto administrativo gasolinera 3%/ventas | D29: ATOMIC KPI | E29: Cost Efficiency | F29: Administración / Finanzas | G29: UNIT_COST_OR_COST_RATE | H29: USD | I29: 0.03 | J29: NEEDS_REVIEW | K29: NEEDS_REVIEW | L29: No hay suficiente información inequívoca para decidir la fórmula. | M29: 0.07 | P29: LOW | Q29: BLOCKED | R29: YES | S29: Semántica o dirección de evaluación ambigua. | T29: Costs & Efficiency | U29: Gasolinera | V29: Abner U b, Gasolinera | W29: 2 | X29: dolares | Y29: 0.03 | AA29: P0 - BLOCKING | AB29: Must choose the Evaluation Type; define the Scoring Method before this KPI can be scored safely. | AC29: Is higher better, lower better, exact target, range, or milestone/binary? How should Goal + Result be converted to Compliance %? | AD29: BLOCKED | AE29: YES
A30: CAT-029 | B30: 2.2 | C30: Reducir costo de M&R de chasis propios | D30: ATOMIC KPI | E30: Cost Efficiency | F30: Administracion / Predio Puerto Cortes / Predio San Lorenzo | G30: UNIT_COST_OR_COST_RATE | H30: USD/km | I30: 0.05 | J30: LOWER_IS_BETTER | K30: PROPORTIONAL | L30: Menor valor real = mejor; usar Goal/Result si Goal>0. | M30: 0.09 | N30: 55.555556 | O30: 55.555556 | P30: HIGH | Q30: PROPOSED | R30: YES | S30: Clasificación propuesta con señales consistentes; requiere aprobación formal. | T30: Costs & Efficiency | U30: Administracion, Predio Puerto Cortes, Predio San Lorenzo | V30: Compras, Cubillo, Lorenzo Varela, Puerto Cortes, San Lorenzo b | W30: 5 | X30: $/km | Y30: 0.05 | AA30: P2 - APPROVAL | AB30: No formula change is currently suggested; obtain formal business approval and normalize any naming/unit variants. | AC30: Confirm KPI meaning, Goal, Unit, Evaluation Type and Scoring Method as proposed. | AD30: APPROVED | AE30: NO - formula can be tested
A31: CAT-030 | B31: 2.20 | C31: Margen operativo de tienda | D31: ATOMIC KPI | E31: Financial Performance | F31: Administración / Finanzas | G31: RATIO_OR_PERCENT | H31: % | I31: 0.1 | J31: GREATER_IS_BETTER | K31: PROPORTIONAL | L31: Clasificación propuesta por semántica del resultado; requiere revisión del negocio. | M31: 0 | N31: 0 | O31: 0 | P31: HIGH | Q31: PROPOSED | R31: YES | S31: Clasificación propuesta con señales consistentes; requiere aprobación formal. | T31: Margins | U31: Gasolinera | V31: Abner U b, Gasolinera | W31: 2 | X31: 0 | Y31: 0.1 | AA31: P2 - APPROVAL | AB31: No formula change is currently suggested; obtain formal business approval and normalize any naming/unit variants. | AC31: Confirm KPI meaning, Goal, Unit, Evaluation Type and Scoring Method as proposed. | AD31: APPROVED | AE31: NO - formula can be tested
A32: CAT-031 | B32: 2.21 | C32: Aumentar % neto del servicio de transporte | D32: ATOMIC KPI | E32: Needs Business Review | F32: Servicio Al Cliente / Sistemas Y Procesos | G32: NEEDS_REVIEW | H32: % | I32: 0.1 | J32: GREATER_IS_BETTER | K32: PROPORTIONAL | L32: Mayor resultado = mejor; usar Result/Goal si el Goal es comparable. | M32: 0.1 | N32: 100 | O32: 100 | P32: LOW | Q32: BLOCKED | R32: YES | S32: Semántica o dirección de evaluación ambigua. | T32: Other | U32: Servicio Al Cliente, Sistemas Y Procesos | V32: Jacky, Servicio al cliente b, Yadira | W32: 3 | X32: 0 | Y32: 0.1 | AA32: P0 - BLOCKING | AB32: Must clarify what the Result actually represents before this KPI can be scored safely. | AC32: What does Result represent: absolute value, percentage change, compliance %, count, rate, duration, cost, ratio, or another value? | AD32: BLOCKED | AE32: YES
A33: CAT-032 | B33: 2.21 | C33: Margen operativo de la gasolinera | D33: ATOMIC KPI | E33: Financial Performance | F33: Administración / Finanzas | G33: RATIO_OR_PERCENT | H33: USD | I33: 0.1 | J33: GREATER_IS_BETTER | K33: PROPORTIONAL | L33: Clasificación propuesta por semántica del resultado; requiere revisión del negocio. | M33: 0.06 | N33: 60 | O33: 60 | P33: HIGH | Q33: PROPOSED | R33: YES | S33: Clasificación propuesta con señales consistentes; requiere aprobación formal. | T33: Margins | U33: Gasolinera | V33: Abner U b, Gasolinera | W33: 2 | X33: dolares | Y33: 0.1 | AA33: P2 - APPROVAL | AB33: No formula change is currently suggested; obtain formal business approval and normalize any naming/unit variants. | AC33: Confirm KPI meaning, Goal, Unit, Evaluation Type and Scoring Method as proposed. | AD33: APPROVED | AE33: NO - formula can be tested
A34: CAT-033 | B34: 2.22 | C34: Aumentar margen neto alquiler de contenedores secos (solo o en combo) TREXA | D34: ATOMIC KPI | E34: Financial Performance | F34: Administración / Finanzas | G34: RATIO_OR_PERCENT | H34: % | I34: 0.1 | J34: GREATER_IS_BETTER | K34: PROPORTIONAL | L34: Mayor resultado = mejor; usar Result/Goal si el Goal es comparable. | M34: 0.1 | N34: 100 | O34: 100 | P34: HIGH | Q34: PROPOSED | R34: YES | S34: Clasificación propuesta con señales consistentes; requiere aprobación formal. | T34: Margins | U34: Administracion | V34: TREXA | W34: 1 | X34: 0 | Y34: 0.1 | AA34: P2 - APPROVAL | AB34: No formula change is currently suggested; obtain formal business approval and normalize any naming/unit variants. | AC34: Confirm KPI meaning, Goal, Unit, Evaluation Type and Scoring Method as proposed. | AD34: APPROVED | AE34: NO - formula can be tested
A35: CAT-034 | B35: 2.3 | C35: Reducir Costo por km cabezales propios. | D35: ATOMIC KPI | E35: Cost Efficiency | F35: Transporte | G35: UNIT_COST_OR_COST_RATE | H35: USD | I35: 0.05 | J35: LOWER_IS_BETTER | K35: PROPORTIONAL | L35: Menor valor real = mejor; usar Goal/Result si Goal>0. | M35: 0.6 | N35: 8.3333333 | O35: 8.3333333 | P35: HIGH | Q35: PROPOSED | R35: YES | S35: Clasificación propuesta con señales consistentes; requiere aprobación formal. | T35: Costs & Efficiency | U35: Administracion, Transporte | V35: Cecilia, Compras, Nancy Garcia b (4), TRANEXPA | W35: 5 | X35: $ | Y35: 0.05 | AA35: P2 - APPROVAL | AB35: No formula change is currently suggested; obtain formal business approval and normalize any naming/unit variants. | AC35: Confirm KPI meaning, Goal, Unit, Evaluation Type and Scoring Method as proposed. | AD35: APPROVED | AE35: NO - formula can be tested
A36: CAT-035 | B36: 2.5 | C36: Aumentar Margen neto en venta de contenedores (modificados y secos) | D36: ATOMIC KPI | E36: Financial Performance | F36: Administración / Finanzas | G36: RATIO_OR_PERCENT | H36: % | I36: 0.1 | J36: GREATER_IS_BETTER | K36: PROPORTIONAL | L36: Mayor resultado = mejor; usar Result/Goal si el Goal es comparable. | M36: 0 | N36: 0 | O36: 0 | P36: HIGH | Q36: PROPOSED | R36: YES | S36: Clasificación propuesta con señales consistentes; requiere aprobación formal. | T36: Margins | U36: Contenedores | V36: Contenedores | W36: 1 | X36: % | Y36: 0.1 | AA36: P2 - APPROVAL | AB36: No formula change is currently suggested; obtain formal business approval and normalize any naming/unit variants. | AC36: Confirm KPI meaning, Goal, Unit, Evaluation Type and Scoring Method as proposed. | AD36: APPROVED | AE36: NO - formula can be tested
A37: CAT-036 | B37: 2.6 | C37: Aumento en 20% en margen de contribución bruta venta de contenedores | D37: ATOMIC KPI | E37: Financial Performance | F37: Administración / Finanzas | G37: RATIO_OR_PERCENT | H37: USD | I37: 0.2 | J37: GREATER_IS_BETTER | K37: PROPORTIONAL | L37: Mayor resultado = mejor; usar Result/Goal si el Goal es comparable. | M37: 0 | N37: 0 | O37: 0 | P37: HIGH | Q37: PROPOSED | R37: YES | S37: Clasificación propuesta con señales consistentes; requiere aprobación formal. | T37: Margins | U37: Contenedores | V37: Contenedores | W37: 1 | X37: $ | Y37: 0.2 | AA37: P2 - APPROVAL | AB37: No formula change is currently suggested; obtain formal business approval and normalize any naming/unit variants. | AC37: Confirm KPI meaning, Goal, Unit, Evaluation Type and Scoring Method as proposed. | AD37: APPROVED | AE37: NO - formula can be tested
A38: CAT-037 | B38: 2.7 | C38: Aumento en 20% en margen de contribución bruta alquiler de bodegas | D38: ATOMIC KPI | E38: Financial Performance | F38: Administración / Finanzas | G38: RATIO_OR_PERCENT | H38: USD | I38: 0.2 | J38: GREATER_IS_BETTER | K38: PROPORTIONAL | L38: Mayor resultado = mejor; usar Result/Goal si el Goal es comparable. | M38: 0 | N38: 0 | O38: 0 | P38: HIGH | Q38: PROPOSED | R38: YES | S38: Clasificación propuesta con señales consistentes; requiere aprobación formal. | T38: Margins | U38: Contenedores | V38: Contenedores | W38: 1 | X38: $ | Y38: 0.2 | AA38: P2 - APPROVAL | AB38: No formula change is currently suggested; obtain formal business approval and normalize any naming/unit variants. | AC38: Confirm KPI meaning, Goal, Unit, Evaluation Type and Scoring Method as proposed. | AD38: APPROVED | AE38: NO - formula can be tested
A39: CAT-038 | B39: 2.8 | C39: Aumento en 20% en margen de contribución bruta alquiler de reefers. | D39: ATOMIC KPI | E39: Financial Performance | F39: Administración / Finanzas | G39: RATIO_OR_PERCENT | H39: USD | I39: 0.2 | J39: GREATER_IS_BETTER | K39: PROPORTIONAL | L39: Mayor resultado = mejor; usar Result/Goal si el Goal es comparable. | M39: 0 | N39: 0 | O39: 0 | P39: HIGH | Q39: PROPOSED | R39: YES | S39: Clasificación propuesta con señales consistentes; requiere aprobación formal. | T39: Margins | U39: Contenedores | V39: Contenedores | W39: 1 | X39: $ | Y39: 0.2 | AA39: P2 - APPROVAL | AB39: No formula change is currently suggested; obtain formal business approval and normalize any naming/unit variants. | AC39: Confirm KPI meaning, Goal, Unit, Evaluation Type and Scoring Method as proposed. | AD39: APPROVED | AE39: NO - formula can be tested
A40: CAT-039 | B40: 2.9 | C40: Reducir Costo administrativo Puerto Cortés con relacion al año anterior | D40: ATOMIC KPI | E40: Cost Efficiency | F40: Predio Puerto Cortés | G40: UNIT_COST_OR_COST_RATE | H40: REVIEW | I40: 0.05 | J40: LOWER_IS_BETTER | K40: PROPORTIONAL | L40: Menor valor real = mejor; usar Goal/Result si Goal>0. | M40: 0 | N40: 100 | O40: 100 | P40: MEDIUM | Q40: PROPOSED | R40: YES | S40: Unidad de medida ausente/inconsistente; confirmar. | T40: Costs & Efficiency | U40: Predio Puerto Cortes | V40: Lorenzo Varela, Puerto Cortes | W40: 2 | X40: 0 | Y40: 0.05 | Z40: Result=0 tratado como mejor que meta para ejemplo; revisar negocio. | AA40: P0 - BLOCKING | AB40: Must normalize the Measurement Unit before this KPI can be scored safely. | AC40: What exact unit should be stored and displayed for Result? | AD40: BLOCKED | AE40: YES
A41: CAT-040 | B41: 3 | C41: Cero incidentes mayores de seguridad y sostenibilidad | D41: ATOMIC KPI | E41: Safety & Risk | F41: Operaciones / Seguridad | G41: COUNT_OR_RATE | H41: conteo | I41: 1 | J41: LOWER_IS_BETTER | K41: ZERO_TARGET_BANDS | L41: Goal=0: 0 eventos = 100%; 1+ requiere bandas aprobadas por negocio. | M41: 1 | P41: LOW | Q41: BLOCKED | R41: YES | S41: La dirección es clara, pero la penalización/bandas debe aprobarse. El texto exige cero, pero el Goal fuente es 1; confirmar si Goal debe ser 0 o si el resultado es binario. | T41: Safety & Compliance | U41: Predio Puerto Cortes, Predio San Lorenzo, Servicio Al Cliente, SistemasYProcesos, Sistemas Y Procesos, Transporte | V41: Cubillo, David Molina, Hoja1, Hoja3, Jacky, Keila, Lorenzo Varela, Mario, Puerto Cortes, San Lorenzo b, Servicio al cliente b, TRANEXPA, Yadira | W41: 16 | X41: 0 | # Incidente | Y41: 1 | Z41: Requiere bandas Zero Target aprobadas. | AA41: P0 - BLOCKING | AB41: Define KPI-specific Zero Target bands. Do not use a generic division formula when Goal = 0. | AC41: What Compliance should Result = 0, 1, 2, 3+ produce? Are any occurrences immediately critical? | AD41: BLOCKED | AE41: YES
A42: CAT-041 | B42: 3.5 | C42: Multas ambientales y fiscales. | D42: ATOMIC KPI | E42: Needs Business Review | F42: Administracion / Gasolinera | G42: COUNT_OR_RATE | H42: conteo | I42: 0 | J42: LOWER_IS_BETTER | K42: ZERO_TARGET_BANDS | L42: Goal=0: 0 eventos = 100%; 1+ requiere bandas aprobadas por negocio. | M42: 0 | N42: 100 | O42: 100 | P42: MEDIUM | Q42: PROPOSED | R42: YES | S42: La dirección es clara, pero la penalización/bandas debe aprobarse. | T42: Safety & Compliance | U42: Administracion, Gasolinera | V42: Abner U b, Gasolinera, Julio - Alejandro, Nancy Garcia b (4), Tesoreria | W42: 5 | X42: 0 | Y42: 0 | AA42: P0 - BLOCKING | AB42: Define KPI-specific Zero Target bands. Do not use a generic division formula when Goal = 0. | AC42: What Compliance should Result = 0, 1, 2, 3+ produce? Are any occurrences immediately critical? | AD42: BLOCKED | AE42: YES
A43: CAT-042 | B43: 3.6 | C43: Cierres contables a mas tardar el 6 de cada mes | D43: ATOMIC KPI | E43: Process & Service Quality | F43: Administración / Finanzas | G43: DEADLINE_OR_DURATION | H43: día/cierre | I43: 6 | J43: LOWER_IS_BETTER | K43: THRESHOLD | L43: Evaluar contra límite máximo/deadline; no usar regla de tres sin validar la regla empresarial. | M43: 6 | P43: MEDIUM | Q43: PROPOSED | R43: YES | S43: La dirección es clara, pero la penalización/bandas debe aprobarse. | T43: Process Timeliness | U43: Administracion | V43: Cecilia, Compras, Julio - Alejandro, Nancy Garcia b (4), Tesoreria | W43: 5 | X43: # de cierres a tiempo | Y43: 6 | AA43: P1 - RULE DEFINITION | AB43: Confirm threshold boundaries, inclusivity and the penalty/compliance behavior outside the accepted threshold. | AC43: What exact threshold(s) apply, are boundaries inclusive, and should values outside be proportional or step-based? | AD43: PROPOSED | AE43: YES - until rule confirmed
A44: CAT-043 | B44: 3.6.1 | C44: Cierre TREXA | D44: ATOMIC KPI | E44: Process & Service Quality | F44: Administracion | G44: DEADLINE_OR_DURATION | H44: día/cierre | I44: 1 | J44: NEEDS_REVIEW | K44: NEEDS_REVIEW | L44: No hay suficiente información inequívoca para decidir la fórmula. | M44: 1 | P44: LOW | Q44: BLOCKED | R44: YES | S44: Semántica o dirección de evaluación ambigua. | T44: Process Timeliness | U44: Administracion | V44: TREXA | W44: 1 | X44: # de cierres a tiempo | Y44: 1 | AA44: P0 - BLOCKING | AB44: Must choose the Evaluation Type; define the Scoring Method before this KPI can be scored safely. | AC44: Is higher better, lower better, exact target, range, or milestone/binary? How should Goal + Result be converted to Compliance %? | AD44: BLOCKED | AE44: YES
A45: CAT-044 | B45: 3.7 | C45: Cero accidente mayores Y/O robos TRANEXPA | D45: ATOMIC KPI | E45: Safety & Risk | F45: Transporte | G45: COUNT_OR_RATE | H45: conteo | I45: 0 | J45: LOWER_IS_BETTER | K45: ZERO_TARGET_BANDS | L45: Goal=0: 0 eventos = 100%; 1+ requiere bandas aprobadas por negocio. | M45: 0 | N45: 100 | O45: 100 | P45: MEDIUM | Q45: PROPOSED | R45: YES | S45: La dirección es clara, pero la penalización/bandas debe aprobarse. | T45: Safety & Compliance | U45: Transporte | V45: TRANEXPA | W45: 1 | X45: 0 | Y45: 0 | AA45: P0 - BLOCKING | AB45: Define KPI-specific Zero Target bands. Do not use a generic division formula when Goal = 0. | AC45: What Compliance should Result = 0, 1, 2, 3+ produce? Are any occurrences immediately critical? | AD45: BLOCKED | AE45: YES
A46: CAT-045 | B46: 3.8 | C46: Aumentar satisfaccion al cliente | D46: ATOMIC KPI | E46: Customer Experience | F46: Servicio al Cliente | G46: COMPLIANCE_PERCENT | H46: % | I46: 0.1 | J46: GREATER_IS_BETTER | K46: PROPORTIONAL | L46: Mayor resultado = mejor; usar Result/Goal si el Goal es comparable. | M46: 1 | N46: 1000 | O46: 100 | P46: HIGH | Q46: PROPOSED | R46: YES | S46: Clasificación propuesta con señales consistentes; requiere aprobación formal. | T46: Sales & Commercial | U46: Servicio Al Cliente | V46: Jacky, Servicio al cliente b | W46: 2 | X46: 0 | Y46: 0.1 | AA46: P2 - APPROVAL | AB46: No formula change is currently suggested; obtain formal business approval and normalize any naming/unit variants. | AC46: Confirm KPI meaning, Goal, Unit, Evaluation Type and Scoring Method as proposed. | AD46: APPROVED | AE46: NO - formula can be tested
A47: CAT-046 | B47: 3.9 | C47: On time delivery without sevice incidents | D47: ATOMIC KPI | E47: Process & Service Quality | F47: Servicio al Cliente | G47: COMPLIANCE_PERCENT | H47: % | I47: 0.995 | J47: GREATER_IS_BETTER | K47: PROPORTIONAL | L47: Mayor resultado = mejor; usar Result/Goal si el Goal es comparable. | M47: 1 | N47: 100.50251 | O47: 100 | P47: HIGH | Q47: PROPOSED | R47: YES | S47: Clasificación propuesta con señales consistentes; requiere aprobación formal. | T47: Customer Service | U47: Servicio Al Cliente | V47: Jacky, Servicio al cliente b | W47: 2 | X47: 0 | Y47: 0.995 | AA47: P2 - APPROVAL | AB47: No formula change is currently suggested; obtain formal business approval and normalize any naming/unit variants. | AC47: Confirm KPI meaning, Goal, Unit, Evaluation Type and Scoring Method as proposed. | AD47: APPROVED | AE47: NO - formula can be tested
A48: CAT-047 | B48: 4 | C48: Aumentar clima laboral | D48: ATOMIC KPI | E48: People & Culture | F48: Talento Humano | G48: COMPLIANCE_PERCENT | H48: % | I48: 0.1 | J48: GREATER_IS_BETTER | K48: PROPORTIONAL | L48: Mayor resultado = mejor; usar Result/Goal si el Goal es comparable. | M48: 0.1 | N48: 100 | O48: 100 | P48: HIGH | Q48: PROPOSED | R48: YES | S48: Clasificación propuesta con señales consistentes; requiere aprobación formal. | T48: People | U48: Administracion, Sistemas Y Procesos | V48: Hoja1, Hoja3, Mario, Nancy Garcia b (4) | W48: 5 | X48: 0 | Porcentaje | Y48: 0.1 | AA48: P2 - APPROVAL | AB48: No formula change is currently suggested; obtain formal business approval and normalize any naming/unit variants. | AC48: Confirm KPI meaning, Goal, Unit, Evaluation Type and Scoring Method as proposed. | AD48: APPROVED | AE48: NO - formula can be tested
A49: CAT-048 | B49: 5 | C49: Productividad | D49: PARENT / AGGREGATE | E49: Operational Productivity | F49: Transporte | G49: RATE | H49: REVIEW | I49: 3700 | J49: GREATER_IS_BETTER | K49: PROPORTIONAL | L49: Mayor resultado = mejor; usar Result/Goal si el Goal es comparable. | M49: 3932 | P49: LOW | Q49: EXCLUDE / REVIEW | R49: YES | S49: No es un KPI atómico confiable para scoring. | T49: Fleet Productivity | U49: SistemasYProcesos, Sistemas Y Procesos | V49: David Molina, Desarrollo, Hoja1, Hoja3, Yadira | W49: 8 | X49: 0 | Y49: 3700 | 3670 | AA49: P3 - EXCLUDE/STRUCTURE | AB49: Do not score this row as an atomic KPI. Keep it only as a parent/group/Scorecard aggregate if the business still needs it. | AC49: Confirm that this row is an aggregate/header and should not generate an independent KPI result. | AD49: EXCLUDE / REVIEW | AE49: NO - exclude from atomic scoring
A50: CAT-049 | B50: 5.1 | C50: Productividad kms/cabezal/mes. | D50: ATOMIC KPI | E50: Operational Productivity | F50: Transporte | G50: RATE | H50: km/cabezal/mes | I50: 3700 | J50: GREATER_IS_BETTER | K50: PROPORTIONAL | L50: Mayor resultado = mejor; usar Result/Goal si el Goal es comparable. | M50: 3932 | N50: 106.27027 | O50: 100 | P50: HIGH | Q50: PROPOSED | R50: YES | S50: Clasificación propuesta con señales consistentes; requiere aprobación formal. | T50: Fleet Productivity | U50: Servicio Al Cliente | V50: Jacky, Servicio al cliente b | W50: 2 | X50: 0 | Y50: 3700 | AA50: P2 - APPROVAL | AB50: No formula change is currently suggested; obtain formal business approval and normalize any naming/unit variants. | AC50: Confirm KPI meaning, Goal, Unit, Evaluation Type and Scoring Method as proposed. | AD50: APPROVED | AE50: NO - formula can be tested
A51: CAT-050 | B51: 5.10 | C51: Aumentar kms TRANEXPA | D51: ATOMIC KPI | E51: Operational Productivity | F51: Transporte | G51: ABSOLUTE_OR_RATE | H51: kms | I51: 0.2 | J51: GREATER_IS_BETTER | K51: PROPORTIONAL | L51: Mayor resultado = mejor; usar Result/Goal si el Goal es comparable. | M51: 0 | N51: 0 | O51: 0 | P51: HIGH | Q51: PROPOSED | R51: YES | S51: Clasificación propuesta con señales consistentes; requiere aprobación formal. | T51: Fleet Productivity | U51: Transporte | V51: TRANEXPA | W51: 1 | X51: kms | Y51: 0.2 | AA51: P2 - APPROVAL | AB51: No formula change is currently suggested; obtain formal business approval and normalize any naming/unit variants. | AC51: Confirm KPI meaning, Goal, Unit, Evaluation Type and Scoring Method as proposed. | AD51: APPROVED | AE51: NO - formula can be tested
A52: CAT-051 | B52: 5.11 | C52: # de fallas operativas adjudicables al predio (Incluye rescates, rechazos) Puerto Cortes | D52: ATOMIC KPI | E52: Needs Business Review | F52: Predio Puerto Cortés | G52: COUNT_OR_RATE | H52: fallas | I52: 1 | J52: LOWER_IS_BETTER | K52: THRESHOLD_OR_PROPORTIONAL | L52: Menor conteo/tasa suele ser mejor; confirmar si existe límite o bandas. | M52: 0 | P52: MEDIUM | Q52: PROPOSED | R52: YES | S52: La dirección es clara, pero la penalización/bandas debe aprobarse. | T52: Other | U52: Contenedores, Predio Puerto Cortes | V52: Lorenzo Varela, Puerto Cortes, Roy Reyes | W52: 3 | X52: # de fallas | Y52: 1 | AA52: P1 - RULE DEFINITION | AB52: Confirm threshold boundaries, inclusivity and the penalty/compliance behavior outside the accepted threshold. | AC52: What exact threshold(s) apply, are boundaries inclusive, and should values outside be proportional or step-based? | AD52: PROPOSED | AE52: YES - until rule confirmed
A53: CAT-052 | B53: 5.12 | C53: Aumentar # de viajes de EXA | D53: ATOMIC KPI | E53: Operational Productivity | F53: Transporte | G53: NEEDS_REVIEW | H53: # de viajes | I53: 0.2 | J53: GREATER_IS_BETTER | K53: PROPORTIONAL | L53: Mayor resultado = mejor; usar Result/Goal si el Goal es comparable. | M53: 0 | N53: 0 | O53: 0 | P53: LOW | Q53: BLOCKED | R53: YES | S53: Semántica o dirección de evaluación ambigua. | T53: Fleet Productivity | U53: Servicio Al Cliente | V53: Jacky, Servicio al cliente b | W53: 2 | X53: # de viajes | Y53: 0.2 | AA53: P0 - BLOCKING | AB53: Must clarify what the Result actually represents before this KPI can be scored safely. | AC53: What does Result represent: absolute value, percentage change, compliance %, count, rate, duration, cost, ratio, or another value? | AD53: BLOCKED | AE53: YES
A54: CAT-053 | B54: 5.13 | C54: Aumenar promedio de kms/viaje | D54: ATOMIC KPI | E54: Operational Productivity | F54: Transporte | G54: ABSOLUTE_OR_RATE | H54: kms/viaje | I54: 0.1 | J54: GREATER_IS_BETTER | K54: PROPORTIONAL | L54: Clasificación propuesta por semántica del resultado; requiere revisión del negocio. | M54: 0.25182482 | N54: 251.82482 | O54: 100 | P54: HIGH | Q54: PROPOSED | R54: YES | S54: Clasificación propuesta con señales consistentes; requiere aprobación formal. | T54: Fleet Productivity | U54: Servicio Al Cliente | V54: Jacky, Servicio al cliente b | W54: 2 | X54: kms/viaje | Y54: 0.1 | AA54: P2 - APPROVAL | AB54: No formula change is currently suggested; obtain formal business approval and normalize any naming/unit variants. | AC54: Confirm KPI meaning, Goal, Unit, Evaluation Type and Scoring Method as proposed. | AD54: APPROVED | AE54: NO - formula can be tested
A55: CAT-054 | B55: 5.15 | C55: # de fallas operativas adjudicables al predio (Incluye rescates, rechazos) San Lorenzo | D55: ATOMIC KPI | E55: Needs Business Review | F55: Predio San Lorenzo | G55: COUNT_OR_RATE | H55: conteo | I55: 0 | J55: LOWER_IS_BETTER | K55: ZERO_TARGET_BANDS | L55: Goal=0: 0 eventos = 100%; 1+ requiere bandas aprobadas por negocio. | M55: 0 | N55: 100 | O55: 100 | P55: MEDIUM | Q55: PROPOSED | R55: YES | S55: La dirección es clara, pero la penalización/bandas debe aprobarse. | T55: Other | U55: Predio San Lorenzo | V55: Cubillo, San Lorenzo b | W55: 2 | X55: 0 | Y55: 0 | AA55: P0 - BLOCKING | AB55: Define KPI-specific Zero Target bands. Do not use a generic division formula when Goal = 0. | AC55: What Compliance should Result = 0, 1, 2, 3+ produce? Are any occurrences immediately critical? | AD55: BLOCKED | AE55: YES
A56: CAT-055 | B56: 5.16 | C56: # de notas de credito mensuales | D56: ATOMIC KPI | E56: Needs Business Review | F56: Administracion | G56: NEEDS_REVIEW | H56: notas de crédito | I56: 0 | J56: NEEDS_REVIEW | K56: NEEDS_REVIEW | L56: No hay suficiente información inequívoca para decidir la fórmula. | M56: 0 | P56: LOW | Q56: BLOCKED | R56: YES | S56: Semántica o dirección de evaluación ambigua. | T56: Other | U56: Administracion | V56: Julio - Alejandro | W56: 1 | X56: # notas de credito | Y56: 0 | AA56: P0 - BLOCKING | AB56: Must clarify what the Result actually represents; choose the Evaluation Type; define the Scoring Method before this KPI can be scored safely. | AC56: What does Result represent: absolute value, percentage change, compliance %, count, rate, duration, cost, ratio, or another value? Is higher better, lower better, exact target, range, or milestone/binary? How should Goal + Result be converted to Compliance %? | AD56: BLOCKED | AE56: YES
A57: CAT-056 | B57: 5.2 | C57: Productividad cabezales Flota Nueva | D57: ATOMIC KPI | E57: Operational Productivity | F57: Transporte | G57: RATE | H57: km/cabezal/mes | I57: 4500 | J57: GREATER_IS_BETTER | K57: PROPORTIONAL | L57: Mayor resultado = mejor; usar Result/Goal si el Goal es comparable. | M57: 4782 | N57: 106.26667 | O57: 100 | P57: HIGH | Q57: PROPOSED | R57: YES | S57: Clasificación propuesta con señales consistentes; requiere aprobación formal. | T57: Fleet Productivity | U57: Administracion, Servicio Al Cliente | V57: Cecilia, Compras, Jacky, Nancy Garcia b (4), Servicio al cliente b | W57: 5 | X57: 0 | Y57: 4500 | AA57: P2 - APPROVAL | AB57: No formula change is currently suggested; obtain formal business approval and normalize any naming/unit variants. | AC57: Confirm KPI meaning, Goal, Unit, Evaluation Type and Scoring Method as proposed. | AD57: APPROVED | AE57: NO - formula can be tested
A58: CAT-057 | B58: 5.3 | C58: Productividad cabezales TRANEXPA | D58: ATOMIC KPI | E58: Operational Productivity | F58: Transporte | G58: RATE | H58: km/cabezal/mes | I58: 4000 | J58: GREATER_IS_BETTER | K58: PROPORTIONAL | L58: Mayor resultado = mejor; usar Result/Goal si el Goal es comparable. | M58: 4268 | N58: 106.7 | O58: 100 | P58: HIGH | Q58: PROPOSED | R58: YES | S58: Clasificación propuesta con señales consistentes; requiere aprobación formal. | T58: Fleet Productivity | U58: Servicio Al Cliente, Transporte | V58: Jacky, Servicio al cliente b, TRANEXPA | W58: 3 | X58: 0 | Y58: 4000 | AA58: P2 - APPROVAL | AB58: No formula change is currently suggested; obtain formal business approval and normalize any naming/unit variants. | AC58: Confirm KPI meaning, Goal, Unit, Evaluation Type and Scoring Method as proposed. | AD58: APPROVED | AE58: NO - formula can be tested
A59: CAT-058 | B59: 5.4 | C59: Productividad cabezales IPH | D59: ATOMIC KPI | E59: Operational Productivity | F59: Transporte | G59: RATE | H59: km/cabezal/mes | I59: 3800 | J59: GREATER_IS_BETTER | K59: PROPORTIONAL | L59: Mayor resultado = mejor; usar Result/Goal si el Goal es comparable. | M59: 3501 | N59: 92.131579 | O59: 92.131579 | P59: HIGH | Q59: PROPOSED | R59: YES | S59: Clasificación propuesta con señales consistentes; requiere aprobación formal. | T59: Fleet Productivity | U59: Servicio Al Cliente | V59: Jacky, Servicio al cliente b | W59: 2 | X59: 0 | Y59: 3800 | AA59: P2 - APPROVAL | AB59: No formula change is currently suggested; obtain formal business approval and normalize any naming/unit variants. | AC59: Confirm KPI meaning, Goal, Unit, Evaluation Type and Scoring Method as proposed. | AD59: APPROVED | AE59: NO - formula can be tested
A60: CAT-059 | B60: 5.5.1 | C60: Productividad cabezales Tranexpa Particulares. | D60: ATOMIC KPI | E60: Operational Productivity | F60: Transporte | G60: RATE | H60: km/cabezal/mes | I60: 3500 | J60: GREATER_IS_BETTER | K60: PROPORTIONAL | L60: Mayor resultado = mejor; usar Result/Goal si el Goal es comparable. | M60: 2144 | N60: 61.257143 | O60: 61.257143 | P60: HIGH | Q60: PROPOSED | R60: YES | S60: Clasificación propuesta con señales consistentes; requiere aprobación formal. | T60: Fleet Productivity | U60: Servicio Al Cliente | V60: Jacky, Servicio al cliente b | W60: 2 | X60: 0 | Y60: 3500 | AA60: P2 - APPROVAL | AB60: No formula change is currently suggested; obtain formal business approval and normalize any naming/unit variants. | AC60: Confirm KPI meaning, Goal, Unit, Evaluation Type and Scoring Method as proposed. | AD60: APPROVED | AE60: NO - formula can be tested
A61: CAT-060 | B61: 5.5.2 | C61: Productividad cabezales Ponce | D61: ATOMIC KPI | E61: Operational Productivity | F61: Transporte | G61: RATE | H61: km/cabezal/mes | I61: 3500 | J61: GREATER_IS_BETTER | K61: PROPORTIONAL | L61: Mayor resultado = mejor; usar Result/Goal si el Goal es comparable. | M61: 2560 | N61: 73.142857 | O61: 73.142857 | P61: HIGH | Q61: PROPOSED | R61: YES | S61: Clasificación propuesta con señales consistentes; requiere aprobación formal. | T61: Fleet Productivity | U61: Servicio Al Cliente | V61: Jacky, Servicio al cliente b | W61: 2 | X61: 0 | Y61: 3500 | AA61: P2 - APPROVAL | AB61: No formula change is currently suggested; obtain formal business approval and normalize any naming/unit variants. | AC61: Confirm KPI meaning, Goal, Unit, Evaluation Type and Scoring Method as proposed. | AD61: APPROVED | AE61: NO - formula can be tested
A62: CAT-061 | B62: 5.5.3 | C62: Productividad cabezales Moreno | D62: ATOMIC KPI | E62: Operational Productivity | F62: Transporte | G62: RATE | H62: km/cabezal/mes | I62: 3500 | J62: GREATER_IS_BETTER | K62: PROPORTIONAL | L62: Mayor resultado = mejor; usar Result/Goal si el Goal es comparable. | M62: 2923 | N62: 83.514286 | O62: 83.514286 | P62: HIGH | Q62: PROPOSED | R62: YES | S62: Clasificación propuesta con señales consistentes; requiere aprobación formal. | T62: Fleet Productivity | U62: Servicio Al Cliente | V62: Jacky, Servicio al cliente b | W62: 2 | X62: 0 | Y62: 3500 | AA62: P2 - APPROVAL | AB62: No formula change is currently suggested; obtain formal business approval and normalize any naming/unit variants. | AC62: Confirm KPI meaning, Goal, Unit, Evaluation Type and Scoring Method as proposed. | AD62: APPROVED | AE62: NO - formula can be tested
A63: CAT-062 | B63: 5.5.4 | C63: Productividad cabezales Obregon | D63: ATOMIC KPI | E63: Operational Productivity | F63: Transporte | G63: RATE | H63: km/cabezal/mes | I63: 3500 | J63: GREATER_IS_BETTER | K63: PROPORTIONAL | L63: Mayor resultado = mejor; usar Result/Goal si el Goal es comparable. | M63: 3165 | N63: 90.428571 | O63: 90.428571 | P63: HIGH | Q63: PROPOSED | R63: YES | S63: Clasificación propuesta con señales consistentes; requiere aprobación formal. | T63: Fleet Productivity | U63: Servicio Al Cliente | V63: Jacky, Servicio al cliente b | W63: 2 | X63: 0 | Y63: 3500 | AA63: P2 - APPROVAL | AB63: No formula change is currently suggested; obtain formal business approval and normalize any naming/unit variants. | AC63: Confirm KPI meaning, Goal, Unit, Evaluation Type and Scoring Method as proposed. | AD63: APPROVED | AE63: NO - formula can be tested
A64: CAT-063 | B64: 5.5.5 | C64: Productividad cabezales San Lorenzo | D64: ATOMIC KPI | E64: Operational Productivity | F64: Predio San Lorenzo | G64: RATE | H64: km/cabezal/mes | I64: 3500 | J64: GREATER_IS_BETTER | K64: PROPORTIONAL | L64: Mayor resultado = mejor; usar Result/Goal si el Goal es comparable. | M64: 2234 | N64: 63.828571 | O64: 63.828571 | P64: HIGH | Q64: PROPOSED | R64: YES | S64: Clasificación propuesta con señales consistentes; requiere aprobación formal. | T64: Fleet Productivity | U64: Servicio Al Cliente | V64: Jacky, Servicio al cliente b | W64: 2 | X64: 0 | Y64: 3500 | AA64: P2 - APPROVAL | AB64: No formula change is currently suggested; obtain formal business approval and normalize any naming/unit variants. | AC64: Confirm KPI meaning, Goal, Unit, Evaluation Type and Scoring Method as proposed. | AD64: APPROVED | AE64: NO - formula can be tested
A65: CAT-064 | B65: 5.5.6 | C65: Productividad cabezales Sinai | D65: ATOMIC KPI | E65: Operational Productivity | F65: Transporte | G65: RATE | H65: km/cabezal/mes | I65: 3500 | J65: GREATER_IS_BETTER | K65: PROPORTIONAL | L65: Mayor resultado = mejor; usar Result/Goal si el Goal es comparable. | M65: 1551 | N65: 44.314286 | O65: 44.314286 | P65: HIGH | Q65: PROPOSED | R65: YES | S65: Clasificación propuesta con señales consistentes; requiere aprobación formal. | T65: Fleet Productivity | U65: Servicio Al Cliente | V65: Jacky, Servicio al cliente b | W65: 2 | X65: 0 | Y65: 3500 | AA65: P2 - APPROVAL | AB65: No formula change is currently suggested; obtain formal business approval and normalize any naming/unit variants. | AC65: Confirm KPI meaning, Goal, Unit, Evaluation Type and Scoring Method as proposed. | AD65: APPROVED | AE65: NO - formula can be tested
A66: CAT-065 | B66: 5.6 | C66: Aprovechamiento GPS | D66: ATOMIC KPI | E66: Asset Utilization | F66: Sistemas y Procesos | G66: COMPLIANCE_PERCENT | H66: REVIEW | I66: 0.9 | J66: GREATER_IS_BETTER | K66: PROPORTIONAL | L66: Mayor resultado = mejor; usar Result/Goal si el Goal es comparable. | M66: 0.82 | N66: 91.111111 | O66: 91.111111 | P66: MEDIUM | Q66: PROPOSED | R66: YES | S66: Unidad de medida ausente/inconsistente; confirmar. | T66: Asset Utilization | U66: SistemasYProcesos, Sistemas Y Procesos | V66: David Molina, Keila | W66: 4 | X66: 0 | Y66: 0.9 | AA66: P0 - BLOCKING | AB66: Must normalize the Measurement Unit before this KPI can be scored safely. | AC66: What exact unit should be stored and displayed for Result? | AD66: BLOCKED | AE66: YES
A67: CAT-066 | B67: 5.7 | C67: Dias de facturacion | D67: ATOMIC KPI | E67: Process & Service Quality | F67: Sistemas Y Procesos | G67: DEADLINE_OR_DURATION | H67: días | I67: 4 | J67: LOWER_IS_BETTER | K67: THRESHOLD | L67: Evaluar contra límite máximo/deadline; no usar regla de tres sin validar la regla empresarial. | M67: 6 | P67: MEDIUM | Q67: PROPOSED | R67: YES | S67: La dirección es clara, pero la penalización/bandas debe aprobarse. | T67: Process Timeliness | U67: Sistemas Y Procesos | V67: Yadira | W67: 1 | X67: 0 | Y67: 4 | AA67: P1 - RULE DEFINITION | AB67: Confirm threshold boundaries, inclusivity and the penalty/compliance behavior outside the accepted threshold. | AC67: What exact threshold(s) apply, are boundaries inclusive, and should values outside be proportional or step-based? | AD67: PROPOSED | AE67: YES - until rule confirmed
A68: CAT-067 | B68: 5.8 | C68: Aumentar kms EXA | D68: ATOMIC KPI | E68: Operational Productivity | F68: Transporte | G68: ABSOLUTE_OR_RATE | H68: kms | I68: 506974.68 | J68: GREATER_IS_BETTER | K68: PROPORTIONAL | L68: Mayor resultado = mejor; usar Result/Goal si el Goal es comparable. | M68: 485973.6 | N68: 95.857568 | O68: 95.857568 | P68: HIGH | Q68: PROPOSED | R68: YES | S68: Clasificación propuesta con señales consistentes; requiere aprobación formal. | T68: Fleet Productivity | U68: Servicio Al Cliente | V68: Jacky, Servicio al cliente b | W68: 2 | X68: kms | Y68: 506974.68 | AA68: P2 - APPROVAL | AB68: No formula change is currently suggested; obtain formal business approval and normalize any naming/unit variants. | AC68: Confirm KPI meaning, Goal, Unit, Evaluation Type and Scoring Method as proposed. | AD68: APPROVED | AE68: NO - formula can be tested
A69: CAT-068 | B69: 6 | C69: Aumentar el ROA | D69: ATOMIC KPI | E69: Financial Performance | F69: Administración / Finanzas | G69: RATIO_OR_PERCENT | H69: % | I69: 0.05 | J69: GREATER_IS_BETTER | K69: PROPORTIONAL | L69: Mayor resultado = mejor; usar Result/Goal si el Goal es comparable. | M69: 1 | N69: 2000 | O69: 100 | P69: HIGH | Q69: PROPOSED | R69: YES | S69: Clasificación propuesta con señales consistentes; requiere aprobación formal. | T69: Financial Ratios | U69: Administracion | V69: Cecilia, Compras, Hoja1, Hoja3, Julio - Alejandro, Nancy Garcia b (4), Tesoreria | W69: 8 | X69: 0 | Porcentaje | Y69: 0.05 | AA69: P2 - APPROVAL | AB69: No formula change is currently suggested; obtain formal business approval and normalize any naming/unit variants. | AC69: Confirm KPI meaning, Goal, Unit, Evaluation Type and Scoring Method as proposed. | AD69: APPROVED | AE69: NO - formula can be tested
A70: CAT-069 | B70: 6.1 | C70: Aumentar Rotación de inventario. | D70: ATOMIC KPI | E70: Financial Performance | F70: Compras / Inventario | G70: RATIO_OR_PERCENT | H70: % | I70: 0.05 | J70: GREATER_IS_BETTER | K70: PROPORTIONAL | L70: Mayor resultado = mejor; usar Result/Goal si el Goal es comparable. | M70: 0 | N70: 0 | O70: 0 | P70: HIGH | Q70: PROPOSED | R70: YES | S70: Clasificación propuesta con señales consistentes; requiere aprobación formal. | T70: Sales & Commercial | U70: Administracion | V70: Cecilia, Compras, Nancy Garcia b (4), Tesoreria | W70: 4 | X70: 0 | Y70: 0.05 | AA70: P2 - APPROVAL | AB70: No formula change is currently suggested; obtain formal business approval and normalize any naming/unit variants. | AC70: Confirm KPI meaning, Goal, Unit, Evaluation Type and Scoring Method as proposed. | AD70: APPROVED | AE70: NO - formula can be tested
A71: CAT-070 | B71: 6.2 | C71: Disminuir a 5% el desuso de los chasis (equipos con mas de 30 dias en las yardas) | D71: ATOMIC KPI | E71: Asset Utilization | F71: Administracion | G71: NEEDS_REVIEW | H71: % | I71: 0.05 | J71: LOWER_IS_BETTER | K71: PROPORTIONAL | L71: Menor valor real = mejor; usar Goal/Result si Goal>0. | M71: 0.05 | N71: 100 | O71: 100 | P71: LOW | Q71: BLOCKED | R71: YES | S71: Semántica o dirección de evaluación ambigua. | T71: Asset Utilization | U71: Administracion | V71: Julio - Alejandro, Nancy Garcia b (4) | W71: 2 | X71: % | Y71: 0.05 | AA71: P0 - BLOCKING | AB71: Must clarify what the Result actually represents before this KPI can be scored safely. | AC71: What does Result represent: absolute value, percentage change, compliance %, count, rate, duration, cost, ratio, or another value? | AD71: BLOCKED | AE71: YES
A72: CAT-071 | B72: 6.2.1 | C72: Disminuir a 5% el desuso de los equipos Puerto Cortés (equipos con mas de 30 dias en yarda) | D72: ATOMIC KPI | E72: Asset Utilization | F72: Predio Puerto Cortés | G72: NEEDS_REVIEW | H72: Equipos | I72: 30 | J72: LOWER_IS_BETTER | K72: PROPORTIONAL | L72: Menor valor real = mejor; usar Goal/Result si Goal>0. | M72: 45 | N72: 66.666667 | O72: 66.666667 | P72: LOW | Q72: BLOCKED | R72: YES | S72: Semántica o dirección de evaluación ambigua. El texto expresa una meta porcentual, pero la unidad/Goal fuente parecen conteo o valor absoluto. | T72: Asset Utilization | U72: Predio Puerto Cortes | V72: Lorenzo Varela, Puerto Cortes | W72: 2 | X72: Equipos | Y72: 30 | AA72: P0 - BLOCKING | AB72: Must clarify what the Result actually represents before this KPI can be scored safely. | AC72: What does Result represent: absolute value, percentage change, compliance %, count, rate, duration, cost, ratio, or another value? | AD72: BLOCKED | AE72: YES
A73: CAT-072 | B73: 6.2.2 | C73: Disminuir a 1% el desuso de los equipos San Lorenzo (equipos con mas de 30 dias en yarda) | D73: ATOMIC KPI | E73: Asset Utilization | F73: Predio San Lorenzo | G73: NEEDS_REVIEW | H73: Equipos | I73: 6 | J73: LOWER_IS_BETTER | K73: PROPORTIONAL | L73: Menor valor real = mejor; usar Goal/Result si Goal>0. | M73: 7 | N73: 85.714286 | O73: 85.714286 | P73: LOW | Q73: BLOCKED | R73: YES | S73: Semántica o dirección de evaluación ambigua. El texto expresa una meta porcentual, pero la unidad/Goal fuente parecen conteo o valor absoluto. | T73: Asset Utilization | U73: Predio San Lorenzo | V73: Cubillo, San Lorenzo b | W73: 2 | X73: Equipos | Y73: 6 | AA73: P0 - BLOCKING | AB73: Must clarify what the Result actually represents before this KPI can be scored safely. | AC73: What does Result represent: absolute value, percentage change, compliance %, count, rate, duration, cost, ratio, or another value? | AD73: BLOCKED | AE73: YES
A74: CAT-073 | B74: 6.4 | C74: No exceder a 5 equipos en desuso generadores | D74: ATOMIC KPI | E74: Asset Utilization | F74: Predio Puerto Cortes / Predio San Lorenzo | G74: COUNT_OR_RATE | H74: generadores | I74: 1 | J74: LOWER_IS_BETTER | K74: THRESHOLD | L74: Evaluar contra límite máximo/deadline; no usar regla de tres sin validar la regla empresarial. | M74: 44 | P74: MEDIUM | Q74: PROPOSED | R74: YES | S74: La dirección es clara, pero la penalización/bandas debe aprobarse. | T74: Asset Utilization | U74: Predio Puerto Cortes, Predio San Lorenzo | V74: Cubillo, Lorenzo Varela, Puerto Cortes, San Lorenzo b | W74: 4 | X74: generadores | Y74: 1 | AA74: P1 - RULE DEFINITION | AB74: Confirm threshold boundaries, inclusivity and the penalty/compliance behavior outside the accepted threshold. | AC74: What exact threshold(s) apply, are boundaries inclusive, and should values outside be proportional or step-based? | AD74: PROPOSED | AE74: YES - until rule confirmed
A75: CAT-074 | B75: 6.5 | C75: Disminuir a 0-1 el desuso de cabezales propios | D75: ATOMIC KPI | E75: Asset Utilization | F75: Transporte | G75: COUNT_OR_RATE | H75: cabezales | I75: 1 | J75: LOWER_IS_BETTER | K75: THRESHOLD | L75: Cumple si el conteo está dentro del máximo permitido (0–1); definir tratamiento exacto por encima del límite. | M75: 1 | N75: 100 | O75: 100 | P75: MEDIUM | Q75: PROPOSED | R75: YES | S75: Clasificación propuesta con señales consistentes; requiere aprobación formal. | T75: Asset Utilization | U75: Administracion, Transporte | V75: Cecilia, Compras, Nancy Garcia b (4), TRANEXPA | W75: 4 | X75: cabezal | Y75: 1 | AA75: P1 - RULE DEFINITION | AB75: Confirm threshold boundaries, inclusivity and the penalty/compliance behavior outside the accepted threshold. | AC75: What exact threshold(s) apply, are boundaries inclusive, and should values outside be proportional or step-based? | AD75: PROPOSED | AE75: YES - until rule confirmed
A76: CAT-075 | B76: 7 | C76: Disminuir el D/E | D76: ATOMIC KPI | E76: Financial Performance | F76: Administración / Finanzas | G76: RATIO_OR_PERCENT | H76: % | I76: 0.05 | J76: LOWER_IS_BETTER | K76: PROPORTIONAL | L76: Menor valor real = mejor; usar Goal/Result si Goal>0. | M76: 0.05 | N76: 100 | O76: 100 | P76: HIGH | Q76: PROPOSED | R76: YES | S76: Clasificación propuesta con señales consistentes; requiere aprobación formal. | T76: Financial Ratios | U76: Administracion | V76: Cecilia, Compras, Hoja1, Hoja3, Julio - Alejandro, Nancy Garcia b (4), Tesoreria | W76: 8 | X76: 0 | Porcentaje | Y76: 0.05 | AA76: P2 - APPROVAL | AB76: No formula change is currently suggested; obtain formal business approval and normalize any naming/unit variants. | AC76: Confirm KPI meaning, Goal, Unit, Evaluation Type and Scoring Method as proposed. | AD76: APPROVED | AE76: NO - formula can be tested
A77: CAT-076 | B77: 7.1 | C77: Rotación de cuentas por cobrar. | D77: ATOMIC KPI | E77: Financial Performance | F77: Administración / Finanzas | G77: RATIO_OR_PERCENT | H77: % | I77: 0.1 | J77: GREATER_IS_BETTER | K77: PROPORTIONAL | L77: Mayor resultado = mejor; usar Result/Goal si el Goal es comparable. | M77: 0 | N77: 0 | O77: 0 | P77: HIGH | Q77: PROPOSED | R77: YES | S77: Clasificación propuesta con señales consistentes; requiere aprobación formal. | T77: Financial Ratios | U77: Administracion | V77: Julio - Alejandro, Nancy Garcia b (4), Tesoreria | W77: 3 | X77: 0 | Y77: 0.1 | AA77: P2 - APPROVAL | AB77: No formula change is currently suggested; obtain formal business approval and normalize any naming/unit variants. | AC77: Confirm KPI meaning, Goal, Unit, Evaluation Type and Scoring Method as proposed. | AD77: APPROVED | AE77: NO - formula can be tested
A78: CAT-077 | B78: 7.2 | C78: 95% de clientes activos dentro del periodo de recuperacion | D78: ATOMIC KPI | E78: Financial Health | F78: Administracion | G78: DERIVED_COMPLIANCE_PERCENT | H78: % | I78: 0.2 | J78: GREATER_IS_BETTER | K78: PROPORTIONAL | L78: Clasificación propuesta por semántica del resultado; requiere revisión del negocio. | M78: 0 | N78: 0 | O78: 0 | P78: HIGH | Q78: PROPOSED | R78: YES | S78: Clasificación propuesta con señales consistentes; requiere aprobación formal. | T78: Sales & Commercial | U78: Administracion | V78: Nancy Garcia b (4) | W78: 1 | X78: 0 | Y78: 0.2 | AA78: P1 - RULE DEFINITION | AB78: Document the raw-data calculation that produces the percentage Result before applying scoring. | AC78: What is the denominator/population, what records are excluded, what is the raw formula, and how are boundary values treated? | AD78: PROPOSED | AE78: YES - derived formula must be defined
A79: CAT-078 | B79: 8 | C79: Innovaciones estratégicas de sistemas de Impacto recurrente | D79: PARENT / AGGREGATE | E79: Innovation & Digitalization | F79: Sistemas y Procesos | G79: BINARY_OR_MILESTONE | H79: estado / hito | I79: 1 | J79: BINARY / MILESTONE | K79: BINARY_OR_MILESTONE | L79: Definir estados/hitos y porcentaje de cumplimiento por hito. | M79: 1 | P79: LOW | Q79: EXCLUDE / REVIEW | R79: YES | S79: No es un KPI atómico confiable para scoring. | T79: Digital Initiatives | U79: SistemasYProcesos, Sistemas Y Procesos | V79: David Molina, Desarrollo, Hoja1, Hoja3 | W79: 6 | X79: 0 | SW Implementado | Y79: 1 | AA79: P3 - EXCLUDE/STRUCTURE | AB79: Do not score this row as an atomic KPI. Keep it only as a parent/group/Scorecard aggregate if the business still needs it. | AC79: Confirm that this row is an aggregate/header and should not generate an independent KPI result. | AD79: EXCLUDE / REVIEW | AE79: NO - exclude from atomic scoring
A80: CAT-079 | B80: 8.1 | C80: Integracion EMS - Hapag-Lloyd | D80: FEATURE / MILESTONE | E80: Innovation & Digitalization | F80: Sistemas y Procesos | G80: BINARY_OR_MILESTONE | H80: estado / hito | J80: BINARY / MILESTONE | K80: BINARY_OR_MILESTONE | L80: Definir estados/hitos y porcentaje de cumplimiento por hito. | P80: LOW | Q80: BLOCKED | R80: YES | S80: Falta definir formalmente estados/hitos y scoring Binary/Milestone. | T80: Digital Initiatives | V80: Hoja1 | W80: 1 | AA80: P1 - RULE DEFINITION | AB80: Decide whether this is BINARY or MILESTONE-based, then define the allowed states/milestones and their Compliance mapping. | AC80: Is success only Completed/Not Completed, or are intermediate milestones valid? What Compliance % maps to each state? | AD80: BLOCKED | AE80: YES
A81: CAT-080 | B81: 8.10 | C81: Depot - EMS | D81: FEATURE / MILESTONE | E81: Innovation & Digitalization | F81: Sistemas y Procesos | G81: BINARY_OR_MILESTONE | H81: REVIEW | J81: BINARY / MILESTONE | K81: BINARY_OR_MILESTONE | L81: Definir estados/hitos y porcentaje de cumplimiento por hito. | P81: LOW | Q81: BLOCKED | R81: YES | S81: Falta definir formalmente estados/hitos y scoring Binary/Milestone. | T81: Digital Initiatives | V81: Hoja1 | W81: 1 | AA81: P1 - RULE DEFINITION | AB81: Decide whether this is BINARY or MILESTONE-based, then define the allowed states/milestones and their Compliance mapping. | AC81: Is success only Completed/Not Completed, or are intermediate milestones valid? What Compliance % maps to each state? | AD81: BLOCKED | AE81: YES
A82: CAT-081 | B82: 8.11 | C82: Multireport | D82: FEATURE / MILESTONE | E82: Innovation & Digitalization | F82: Sistemas y Procesos | G82: BINARY_OR_MILESTONE | H82: estado / hito | J82: BINARY / MILESTONE | K82: BINARY_OR_MILESTONE | L82: Definir estados/hitos y porcentaje de cumplimiento por hito. | P82: LOW | Q82: BLOCKED | R82: YES | S82: Falta definir formalmente estados/hitos y scoring Binary/Milestone. | T82: Digital Initiatives | V82: Hoja1 | W82: 1 | AA82: P1 - RULE DEFINITION | AB82: Decide whether this is BINARY or MILESTONE-based, then define the allowed states/milestones and their Compliance mapping. | AC82: Is success only Completed/Not Completed, or are intermediate milestones valid? What Compliance % maps to each state? | AD82: BLOCKED | AE82: YES
A83: CAT-082 | B83: 8.2 | C83: Integracion EMS - GPS | D83: FEATURE / MILESTONE | E83: Innovation & Digitalization | F83: Sistemas y Procesos | G83: BINARY_OR_MILESTONE | H83: estado / hito | J83: BINARY / MILESTONE | K83: BINARY_OR_MILESTONE | L83: Definir estados/hitos y porcentaje de cumplimiento por hito. | P83: LOW | Q83: BLOCKED | R83: YES | S83: Falta definir formalmente estados/hitos y scoring Binary/Milestone. | T83: Digital Initiatives | V83: Hoja1 | W83: 1 | AA83: P1 - RULE DEFINITION | AB83: Decide whether this is BINARY or MILESTONE-based, then define the allowed states/milestones and their Compliance mapping. | AC83: Is success only Completed/Not Completed, or are intermediate milestones valid? What Compliance % maps to each state? | AD83: BLOCKED | AE83: YES
A84: CAT-083 | B84: 8.3 | C84: Integracion EMS - SAP | D84: FEATURE / MILESTONE | E84: Innovation & Digitalization | F84: Sistemas y Procesos | G84: BINARY_OR_MILESTONE | H84: estado / hito | J84: BINARY / MILESTONE | K84: BINARY_OR_MILESTONE | L84: Definir estados/hitos y porcentaje de cumplimiento por hito. | P84: LOW | Q84: BLOCKED | R84: YES | S84: Falta definir formalmente estados/hitos y scoring Binary/Milestone. | T84: Digital Initiatives | V84: Hoja1 | W84: 1 | AA84: P1 - RULE DEFINITION | AB84: Decide whether this is BINARY or MILESTONE-based, then define the allowed states/milestones and their Compliance mapping. | AC84: Is success only Completed/Not Completed, or are intermediate milestones valid? What Compliance % maps to each state? | AD84: BLOCKED | AE84: YES
A85: CAT-084 | B85: 8.4 | C85: Integracion EMS - Gasolinera | D85: FEATURE / MILESTONE | E85: Innovation & Digitalization | F85: Sistemas y Procesos | G85: BINARY_OR_MILESTONE | H85: estado / hito | J85: BINARY / MILESTONE | K85: BINARY_OR_MILESTONE | L85: Definir estados/hitos y porcentaje de cumplimiento por hito. | P85: LOW | Q85: BLOCKED | R85: YES | S85: Falta definir formalmente estados/hitos y scoring Binary/Milestone. | T85: Digital Initiatives | V85: Hoja1 | W85: 1 | AA85: P1 - RULE DEFINITION | AB85: Decide whether this is BINARY or MILESTONE-based, then define the allowed states/milestones and their Compliance mapping. | AC85: Is success only Completed/Not Completed, or are intermediate milestones valid? What Compliance % maps to each state? | AD85: BLOCKED | AE85: YES
A86: CAT-085 | B86: 8.5 | C86: Planilla de motorista | D86: FEATURE / MILESTONE | E86: Innovation & Digitalization | F86: Needs Business Review | G86: BINARY_OR_MILESTONE | H86: REVIEW | J86: BINARY / MILESTONE | K86: BINARY_OR_MILESTONE | L86: Definir estados/hitos y porcentaje de cumplimiento por hito. | P86: LOW | Q86: BLOCKED | R86: YES | S86: Falta definir formalmente estados/hitos y scoring Binary/Milestone. | T86: Digital Initiatives | V86: Hoja1 | W86: 1 | AA86: P1 - RULE DEFINITION | AB86: Decide whether this is BINARY or MILESTONE-based, then define the allowed states/milestones and their Compliance mapping. | AC86: Is success only Completed/Not Completed, or are intermediate milestones valid? What Compliance % maps to each state? | AD86: BLOCKED | AE86: YES
A87: CAT-086 | B87: 8.6 | C87: Reset Module | D87: FEATURE / MILESTONE | E87: Innovation & Digitalization | F87: Sistemas y Procesos | G87: BINARY_OR_MILESTONE | H87: estado / hito | J87: BINARY / MILESTONE | K87: BINARY_OR_MILESTONE | L87: Definir estados/hitos y porcentaje de cumplimiento por hito. | P87: LOW | Q87: BLOCKED | R87: YES | S87: Falta definir formalmente estados/hitos y scoring Binary/Milestone. | T87: Digital Initiatives | V87: Hoja1 | W87: 1 | AA87: P1 - RULE DEFINITION | AB87: Decide whether this is BINARY or MILESTONE-based, then define the allowed states/milestones and their Compliance mapping. | AC87: Is success only Completed/Not Completed, or are intermediate milestones valid? What Compliance % maps to each state? | AD87: BLOCKED | AE87: YES
A88: CAT-087 | B88: 8.7 | C88: Add on SAP | D88: FEATURE / MILESTONE | E88: Innovation & Digitalization | F88: Sistemas y Procesos | G88: BINARY_OR_MILESTONE | H88: estado / hito | J88: BINARY / MILESTONE | K88: BINARY_OR_MILESTONE | L88: Definir estados/hitos y porcentaje de cumplimiento por hito. | P88: LOW | Q88: BLOCKED | R88: YES | S88: Falta definir formalmente estados/hitos y scoring Binary/Milestone. | T88: Digital Initiatives | V88: Hoja1 | W88: 1 | AA88: P1 - RULE DEFINITION | AB88: Decide whether this is BINARY or MILESTONE-based, then define the allowed states/milestones and their Compliance mapping. | AC88: Is success only Completed/Not Completed, or are intermediate milestones valid? What Compliance % maps to each state? | AD88: BLOCKED | AE88: YES
A89: CAT-088 | B89: 8.8 | C89: Multilanguage | D89: FEATURE / MILESTONE | E89: Innovation & Digitalization | F89: Sistemas y Procesos | G89: BINARY_OR_MILESTONE | H89: estado / hito | J89: BINARY / MILESTONE | K89: BINARY_OR_MILESTONE | L89: Definir estados/hitos y porcentaje de cumplimiento por hito. | P89: LOW | Q89: BLOCKED | R89: YES | S89: Falta definir formalmente estados/hitos y scoring Binary/Milestone. | T89: Digital Initiatives | V89: Hoja1 | W89: 1 | AA89: P1 - RULE DEFINITION | AB89: Decide whether this is BINARY or MILESTONE-based, then define the allowed states/milestones and their Compliance mapping. | AC89: Is success only Completed/Not Completed, or are intermediate milestones valid? What Compliance % maps to each state? | AD89: BLOCKED | AE89: YES
A90: CAT-089 | B90: 8.9 | C90: Multicompany | D90: FEATURE / MILESTONE | E90: Innovation & Digitalization | F90: Sistemas y Procesos | G90: BINARY_OR_MILESTONE | H90: estado / hito | J90: BINARY / MILESTONE | K90: BINARY_OR_MILESTONE | L90: Definir estados/hitos y porcentaje de cumplimiento por hito. | P90: LOW | Q90: BLOCKED | R90: YES | S90: Falta definir formalmente estados/hitos y scoring Binary/Milestone. | T90: Digital Initiatives | V90: Hoja1 | W90: 1 | AA90: P1 - RULE DEFINITION | AB90: Decide whether this is BINARY or MILESTONE-based, then define the allowed states/milestones and their Compliance mapping. | AC90: Is success only Completed/Not Completed, or are intermediate milestones valid? What Compliance % maps to each state? | AD90: BLOCKED | AE90: YES

Sheet Review Queue
A1: Catalog ID | B1: Legacy Code | C1: KPI Name / Original | D1: Row Type | E1: Category (Proposed) | F1: Primary Owner (Proposed) | G1: Result Semantics | H1: Measurement Unit (Proposed) | I1: Goal Example | J1: Evaluation Type (Proposed) | K1: Scoring Method (Proposed) | L1: Catalog Status | M1: Classification Confidence | N1: Review Reason | O1: Source Sheet(s) | P1: Action Priority | Q1: What Must Change / Confirm | R1: Business Question / Decision
A2: CAT-001 | B2: 1 | C2: Aumentar ventas en el año 2023 del Grupo EXA (EXA, CONMOXA, AXA, TREXA, SAN JORGE) en 10% en USD vs año 2022. | D2: ATOMIC KPI | E2: Commercial Growth | F2: Contenedores / Ventas | G2: CHANGE_PERCENT | H2: % | I2: 0.1 | J2: GREATER_IS_BETTER | K2: PROPORTIONAL | L2: PROPOSED | M2: MEDIUM | N2: Confirmar que Result es porcentaje de cambio logrado y no valor absoluto. | O2: Hoja3 | P2: P1 - BUSINESS CONFIRMATION | Q2: Confirm Result Semantics and Goal interpretation; the current Greater/Lower proposal is plausible but not safe enough to approve automatically. | R2: Confirmar que Result es porcentaje de cambio logrado y no valor absoluto.
A3: CAT-002 | B3: 1 | C3: Aumentar ventas en: | D3: PARENT / AGGREGATE | E3: Commercial Growth | F3: Contenedores / Ventas | G3: CHANGE_PERCENT | H3: USD | I3: 0.2 | J3: GREATER_IS_BETTER | K3: PROPORTIONAL | L3: EXCLUDE / REVIEW | M3: LOW | N3: No es un KPI atómico confiable para scoring. | O3: Hoja1 | P3: P3 - EXCLUDE/STRUCTURE | Q3: Do not score this row as an atomic KPI. Keep it only as a parent/group/Scorecard aggregate if the business still needs it. | R3: Confirm that this row is an aggregate/header and should not generate an independent KPI result.
A4: CAT-004 | B4: 1.11 | C4: Tienda de conveniencia (Primeros 4 meses 15k usd y 25k usd) | D4: ATOMIC KPI | E4: Commercial Growth | F4: Gasolinera | G4: NEEDS_REVIEW | H4: USD | I4: 25000 | J4: NEEDS_REVIEW | K4: NEEDS_REVIEW | L4: BLOCKED | M4: LOW | N4: Semántica o dirección de evaluación ambigua. | O4: Abner U b, Gasolinera | P4: P0 - BLOCKING | Q4: Must clarify what the Result actually represents; choose the Evaluation Type; define the Scoring Method before this KPI can be scored safely. | R4: What does Result represent: absolute value, percentage change, compliance %, count, rate, duration, cost, ratio, or another value? Is higher better, lower better, exact target, range, or milestone/binary? How should Goal + Result be converted to Compliance %?
A5: CAT-005 | B5: 1.13 | C5: Aumentar servicio de almacenamiento y M&R San Lorenzo | D5: ATOMIC KPI | E5: Needs Business Review | F5: Predio San Lorenzo / Taller | G5: NEEDS_REVIEW | H5: REVIEW | I5: 0.2 | J5: GREATER_IS_BETTER | K5: PROPORTIONAL | L5: BLOCKED | M5: LOW | N5: Semántica o dirección de evaluación ambigua. | O5: Cubillo, San Lorenzo b | P5: P0 - BLOCKING | Q5: Must clarify what the Result actually represents; normalize the Measurement Unit before this KPI can be scored safely. | R5: What does Result represent: absolute value, percentage change, compliance %, count, rate, duration, cost, ratio, or another value? What exact unit should be stored and displayed for Result?
A6: CAT-006 | B6: 1.14 | C6: Incrementar gate out de contenedores Puerto Cortés | D6: ATOMIC KPI | E6: Commercial Growth | F6: Predio Puerto Cortés | G6: CHANGE_PERCENT | H6: gate-outs | I6: 0.2 | J6: GREATER_IS_BETTER | K6: PROPORTIONAL | L6: PROPOSED | M6: MEDIUM | N6: Confirmar que Result es porcentaje de cambio logrado y no valor absoluto. | O6: Lorenzo Varela, Puerto Cortes | P6: P1 - BUSINESS CONFIRMATION | Q6: Confirm Result Semantics and Goal interpretation; the current Greater/Lower proposal is plausible but not safe enough to approve automatically. | R6: Confirmar que Result es porcentaje de cambio logrado y no valor absoluto.
A7: CAT-007 | B7: 1.17 | C7: Aumentar el numero de cliente semestralmente | D7: ATOMIC KPI | E7: Commercial Growth | F7: Administracion | G7: CHANGE_PERCENT | H7: clientes | I7: 1 | J7: GREATER_IS_BETTER | K7: PROPORTIONAL | L7: PROPOSED | M7: MEDIUM | N7: Confirmar que Result es porcentaje de cambio logrado y no valor absoluto. | O7: TREXA | P7: P1 - BUSINESS CONFIRMATION | Q7: Confirm Result Semantics and Goal interpretation; the current Greater/Lower proposal is plausible but not safe enough to approve automatically. | R7: Confirmar que Result es porcentaje de cambio logrado y no valor absoluto.
A8: CAT-008 | B8: 1.2 | C8: Lograr meta de contenedores | D8: ATOMIC KPI | E8: Needs Business Review | F8: Contenedores / Ventas | G8: NEEDS_REVIEW | H8: REVIEW | I8: 15 | J8: GREATER_IS_BETTER | K8: PROPORTIONAL | L8: BLOCKED | M8: LOW | N8: Semántica o dirección de evaluación ambigua. | O8: Contenedores | P8: P0 - BLOCKING | Q8: Must clarify what the Result actually represents; normalize the Measurement Unit before this KPI can be scored safely. | R8: What does Result represent: absolute value, percentage change, compliance %, count, rate, duration, cost, ratio, or another value? What exact unit should be stored and displayed for Result?
A9: CAT-011 | B9: 1.5 | C9: Aumentar Rentas bienes y raices | D9: ATOMIC KPI | E9: Commercial Growth | F9: Contenedores / Ventas | G9: CHANGE_PERCENT | H9: % | I9: 0.2 | J9: GREATER_IS_BETTER | K9: PROPORTIONAL | L9: PROPOSED | M9: MEDIUM | N9: Confirmar que Result es porcentaje de cambio logrado y no valor absoluto. | O9: Luis Madrid | P9: P1 - BUSINESS CONFIRMATION | Q9: Confirm Result Semantics and Goal interpretation; the current Greater/Lower proposal is plausible but not safe enough to approve automatically. | R9: Confirmar que Result es porcentaje de cambio logrado y no valor absoluto.
A10: CAT-012 | B10: 1.6 | C10: Alquileres de contenedores secos (solo o en combos CONMOXA) | D10: ATOMIC KPI | E10: Commercial Growth | F10: Contenedores / Ventas | G10: CHANGE_PERCENT | H10: % | I10: 0.2 | J10: NEEDS_REVIEW | K10: NEEDS_REVIEW | L10: BLOCKED | M10: LOW | N10: Semántica o dirección de evaluación ambigua. | O10: Contenedores | P10: P0 - BLOCKING | Q10: Must choose the Evaluation Type; define the Scoring Method before this KPI can be scored safely. | R10: Is higher better, lower better, exact target, range, or milestone/binary? How should Goal + Result be converted to Compliance %?
A11: CAT-014 | B11: 1.8 | C11: Aumentar ventas en TREXA | D11: ATOMIC KPI | E11: Commercial Growth | F11: Contenedores / Ventas | G11: CHANGE_PERCENT | H11: USD | I11: 0.2 | J11: GREATER_IS_BETTER | K11: PROPORTIONAL | L11: PROPOSED | M11: MEDIUM | N11: Confirmar que Result es porcentaje de cambio logrado y no valor absoluto. | O11: Nancy Garcia b (4), TREXA | P11: P1 - BUSINESS CONFIRMATION | Q11: Confirm Result Semantics and Goal interpretation; the current Greater/Lower proposal is plausible but not safe enough to approve automatically. | R11: Confirmar que Result es porcentaje de cambio logrado y no valor absoluto.
A12: CAT-016 | B12: 10 | C12: CONMOXA | D12: SCORECARD_AGGREGATE | E12: Needs Business Review | F12: Contenedores | G12: NEEDS_REVIEW | H12: RESULTADO SCORECARD | I12: 1 | J12: NEEDS_REVIEW | K12: NEEDS_REVIEW | L12: EXCLUDE / REVIEW | M12: LOW | N12: No es un KPI atómico confiable para scoring. | O12: Luis Madrid, Roy Reyes | P12: P3 - EXCLUDE/STRUCTURE | Q12: Do not score this row as an atomic KPI. Keep it only as a parent/group/Scorecard aggregate if the business still needs it. | R12: Confirm that this row is an aggregate/header and should not generate an independent KPI result.
A13: CAT-017 | B13: 2 | C13: Aumentar margen neto | D13: PARENT / AGGREGATE | E13: Financial Performance | F13: Administración / Finanzas | G13: RATIO_OR_PERCENT | H13: % | I13: 0.1 | J13: GREATER_IS_BETTER | K13: PROPORTIONAL | L13: EXCLUDE / REVIEW | M13: LOW | N13: No es un KPI atómico confiable para scoring. | O13: Hoja1 | P13: P3 - EXCLUDE/STRUCTURE | Q13: Do not score this row as an atomic KPI. Keep it only as a parent/group/Scorecard aggregate if the business still needs it. | R13: Confirm that this row is an aggregate/header and should not generate an independent KPI result.
... A41: CAT-078 | B41: 8 | C41: Innovaciones estratégicas de sistemas de Impacto recurrente | D41: PARENT / AGGREGATE | E41: Innovation & Digitalization | F41: Sistemas y Procesos | G41: BINARY_OR_MILESTONE | H41: estado / hito | I41: 1 | J41: BINARY / MILESTONE | K41: BINARY_OR_MILESTONE | L41: EXCLUDE / REVIEW | M41: LOW | N41: No es un KPI atómico confiable para scoring. | O41: David Molina, Desarrollo, Hoja1, Hoja3 | P41: P3 - EXCLUDE/STRUCTURE | Q41: Do not score this row as an atomic KPI. Keep it only as a parent/group/Scorecard aggregate if the business still needs it. | R41: Confirm that this row is an aggregate/header and should not generate an independent KPI result.
A42: CAT-079 | B42: 8.1 | C42: Integracion EMS - Hapag-Lloyd | D42: FEATURE / MILESTONE | E42: Innovation & Digitalization | F42: Sistemas y Procesos | G42: BINARY_OR_MILESTONE | H42: estado / hito | J42: BINARY / MILESTONE | K42: BINARY_OR_MILESTONE | L42: BLOCKED | M42: LOW | N42: Falta definir formalmente estados/hitos y scoring Binary/Milestone. | O42: Hoja1 | P42: P1 - RULE DEFINITION | Q42: Decide whether this is BINARY or MILESTONE-based, then define the allowed states/milestones and their Compliance mapping. | R42: Is success only Completed/Not Completed, or are intermediate milestones valid? What Compliance % maps to each state?
A43: CAT-080 | B43: 8.10 | C43: Depot - EMS | D43: FEATURE / MILESTONE | E43: Innovation & Digitalization | F43: Sistemas y Procesos | G43: BINARY_OR_MILESTONE | H43: REVIEW | J43: BINARY / MILESTONE | K43: BINARY_OR_MILESTONE | L43: BLOCKED | M43: LOW | N43: Falta definir formalmente estados/hitos y scoring Binary/Milestone. | O43: Hoja1 | P43: P1 - RULE DEFINITION | Q43: Decide whether this is BINARY or MILESTONE-based, then define the allowed states/milestones and their Compliance mapping. | R43: Is success only Completed/Not Completed, or are intermediate milestones valid? What Compliance % maps to each state?
A44: CAT-081 | B44: 8.11 | C44: Multireport | D44: FEATURE / MILESTONE | E44: Innovation & Digitalization | F44: Sistemas y Procesos | G44: BINARY_OR_MILESTONE | H44: estado / hito | J44: BINARY / MILESTONE | K44: BINARY_OR_MILESTONE | L44: BLOCKED | M44: LOW | N44: Falta definir formalmente estados/hitos y scoring Binary/Milestone. | O44: Hoja1 | P44: P1 - RULE DEFINITION | Q44: Decide whether this is BINARY or MILESTONE-based, then define the allowed states/milestones and their Compliance mapping. | R44: Is success only Completed/Not Completed, or are intermediate milestones valid? What Compliance % maps to each state?
A45: CAT-082 | B45: 8.2 | C45: Integracion EMS - GPS | D45: FEATURE / MILESTONE | E45: Innovation & Digitalization | F45: Sistemas y Procesos | G45: BINARY_OR_MILESTONE | H45: estado / hito | J45: BINARY / MILESTONE | K45: BINARY_OR_MILESTONE | L45: BLOCKED | M45: LOW | N45: Falta definir formalmente estados/hitos y scoring Binary/Milestone. | O45: Hoja1 | P45: P1 - RULE DEFINITION | Q45: Decide whether this is BINARY or MILESTONE-based, then define the allowed states/milestones and their Compliance mapping. | R45: Is success only Completed/Not Completed, or are intermediate milestones valid? What Compliance % maps to each state?
A46: CAT-083 | B46: 8.3 | C46: Integracion EMS - SAP | D46: FEATURE / MILESTONE | E46: Innovation & Digitalization | F46: Sistemas y Procesos | G46: BINARY_OR_MILESTONE | H46: estado / hito | J46: BINARY / MILESTONE | K46: BINARY_OR_MILESTONE | L46: BLOCKED | M46: LOW | N46: Falta definir formalmente estados/hitos y scoring Binary/Milestone. | O46: Hoja1 | P46: P1 - RULE DEFINITION | Q46: Decide whether this is BINARY or MILESTONE-based, then define the allowed states/milestones and their Compliance mapping. | R46: Is success only Completed/Not Completed, or are intermediate milestones valid? What Compliance % maps to each state?
A47: CAT-084 | B47: 8.4 | C47: Integracion EMS - Gasolinera | D47: FEATURE / MILESTONE | E47: Innovation & Digitalization | F47: Sistemas y Procesos | G47: BINARY_OR_MILESTONE | H47: estado / hito | J47: BINARY / MILESTONE | K47: BINARY_OR_MILESTONE | L47: BLOCKED | M47: LOW | N47: Falta definir formalmente estados/hitos y scoring Binary/Milestone. | O47: Hoja1 | P47: P1 - RULE DEFINITION | Q47: Decide whether this is BINARY or MILESTONE-based, then define the allowed states/milestones and their Compliance mapping. | R47: Is success only Completed/Not Completed, or are intermediate milestones valid? What Compliance % maps to each state?
A48: CAT-085 | B48: 8.5 | C48: Planilla de motorista | D48: FEATURE / MILESTONE | E48: Innovation & Digitalization | F48: Needs Business Review | G48: BINARY_OR_MILESTONE | H48: REVIEW | J48: BINARY / MILESTONE | K48: BINARY_OR_MILESTONE | L48: BLOCKED | M48: LOW | N48: Falta definir formalmente estados/hitos y scoring Binary/Milestone. | O48: Hoja1 | P48: P1 - RULE DEFINITION | Q48: Decide whether this is BINARY or MILESTONE-based, then define the allowed states/milestones and their Compliance mapping. | R48: Is success only Completed/Not Completed, or are intermediate milestones valid? What Compliance % maps to each state?
A49: CAT-086 | B49: 8.6 | C49: Reset Module | D49: FEATURE / MILESTONE | E49: Innovation & Digitalization | F49: Sistemas y Procesos | G49: BINARY_OR_MILESTONE | H49: estado / hito | J49: BINARY / MILESTONE | K49: BINARY_OR_MILESTONE | L49: BLOCKED | M49: LOW | N49: Falta definir formalmente estados/hitos y scoring Binary/Milestone. | O49: Hoja1 | P49: P1 - RULE DEFINITION | Q49: Decide whether this is BINARY or MILESTONE-based, then define the allowed states/milestones and their Compliance mapping. | R49: Is success only Completed/Not Completed, or are intermediate milestones valid? What Compliance % maps to each state?
A50: CAT-087 | B50: 8.7 | C50: Add on SAP | D50: FEATURE / MILESTONE | E50: Innovation & Digitalization | F50: Sistemas y Procesos | G50: BINARY_OR_MILESTONE | H50: estado / hito | J50: BINARY / MILESTONE | K50: BINARY_OR_MILESTONE | L50: BLOCKED | M50: LOW | N50: Falta definir formalmente estados/hitos y scoring Binary/Milestone. | O50: Hoja1 | P50: P1 - RULE DEFINITION | Q50: Decide whether this is BINARY or MILESTONE-based, then define the allowed states/milestones and their Compliance mapping. | R50: Is success only Completed/Not Completed, or are intermediate milestones valid? What Compliance % maps to each state?
A51: CAT-088 | B51: 8.8 | C51: Multilanguage | D51: FEATURE / MILESTONE | E51: Innovation & Digitalization | F51: Sistemas y Procesos | G51: BINARY_OR_MILESTONE | H51: estado / hito | J51: BINARY / MILESTONE | K51: BINARY_OR_MILESTONE | L51: BLOCKED | M51: LOW | N51: Falta definir formalmente estados/hitos y scoring Binary/Milestone. | O51: Hoja1 | P51: P1 - RULE DEFINITION | Q51: Decide whether this is BINARY or MILESTONE-based, then define the allowed states/milestones and their Compliance mapping. | R51: Is success only Completed/Not Completed, or are intermediate milestones valid? What Compliance % maps to each state?
A52: CAT-089 | B52: 8.9 | C52: Multicompany | D52: FEATURE / MILESTONE | E52: Innovation & Digitalization | F52: Sistemas y Procesos | G52: BINARY_OR_MILESTONE | H52: estado / hito | J52: BINARY / MILESTONE | K52: BINARY_OR_MILESTONE | L52: BLOCKED | M52: LOW | N52: Falta definir formalmente estados/hitos y scoring Binary/Milestone. | O52: Hoja1 | P52: P1 - RULE DEFINITION | Q52: Decide whether this is BINARY or MILESTONE-based, then define the allowed states/milestones and their Compliance mapping. | R52: Is success only Completed/Not Completed, or are intermediate milestones valid? What Compliance % maps to each state?

Sheet Source Occurrences
A1: Catalog ID | B1: Source Sheet | C1: Source Row | D1: Source Department | E1: Source Collaborator | F1: Original KPI Description | G1: Original Unit | H1: Original Goal | I1: Original Result | J1: Original Weight
A2: CAT-008 | B2: Contenedores | C2: 6 | D2: Contenedores | F2: 1.2 Lograr meta de contenedores | G2: 0 | H2: 15 | I2: 1 | J2: 0.3
A3: CAT-012 | B3: Contenedores | C3: 8 | D3: Contenedores | F3: 1.6 Alquileres de contenedores secos (solo o en combos CONMOXA) | G3: Porcentaje | H3: 0.2 | I3: 0.45 | J3: 0.05
A4: CAT-010 | B4: Contenedores | C4: 9 | D4: Contenedores | F4: 1.4 Lograr meta de ventas en alquileres de contenedores reefer (solo o en combo) | G4: Dólares | H4: 16000 | I4: 0 | J4: 0.05
A5: CAT-009 | B5: Contenedores | C5: 10 | D5: Contenedores | F5: 1.3 Lograr meta de ventas contenedores secos y modificados(dolares) | G5: Dólares | H5: 40000 | I5: 1800 | J5: 0.05
A6: CAT-035 | B6: Contenedores | C6: 11 | D6: Contenedores | F6: 2.5 Aumentar Margen neto en venta de contenedores (modificados y secos) | G6: % | H6: 0.1 | I6: 0 | J6: 0.05
A7: CAT-036 | B7: Contenedores | C7: 12 | D7: Contenedores | F7: 2.6 Aumento en 20% en margen de contribución bruta venta de contenedores | G7: $ | H7: 0.2 | I7: 0 | J7: 0.05
A8: CAT-003 | B8: Contenedores | C8: 13 | D8: Contenedores | F8: 1.10 Aumentar ventas en articulos Sejue/get504 | G8: Articulos | H8: 10 | I8: 19 | J8: 0.25
A9: CAT-003 | B9: Luis Madrid | C9: 8 | D9: Contenedores | E9: Luis Madrid | F9: 1.10 Aumentar ventas en articulos Sejue/get504 | G9: Articulos | H9: 10 | I9: 19 | J9: 0.1
A10: CAT-038 | B10: Contenedores | C10: 14 | D10: Contenedores | F10: 2.8 Aumento en 20% en margen de contribución bruta alquiler de reefers. | G10: $ | H10: 0.2 | I10: 0 | J10: 0.05
A11: CAT-037 | B11: Contenedores | C11: 15 | D11: Contenedores | F11: 2.7 Aumento en 20% en margen de contribución bruta alquiler de bodegas | G11: $ | H11: 0.2 | I11: 0 | J11: 0.05
A12: CAT-047 | B12: Nancy Garcia b (4) | C12: 7 | D12: Administracion | E12: Nancy Garcia | F12: 4. Aumentar clima laboral | G12: 0 | H12: 0.1 | I12: 0.1 | J12: 0.03
A13: CAT-047 | B13: Mario | C13: 7 | D13: Sistemas_Y_Procesos | E13: Mario Murillo | F13: 4. Aumentar clima laboral | G13: 0 | H13: 0.1 | I13: 0.1 | J13: 0.15
A14: CAT-047 | B14: Hoja3 | C14: 5 | F14: 4. Aumentar clima laboral | H14: 0.1 | I14: 0.1 | J14: 0.1
A15: CAT-047 | B15: Hoja3 | C15: 24 | F15: 4. Aumentar clima laboral | J15: 0.1
A16: CAT-047 | B16: Hoja1 | C16: 7 | F16: 4. Aumentar clima laboral | G16: Porcentaje | H16: 0.1 | J16: 0.1
A17: CAT-019 | B17: Nancy Garcia b (4) | C17: 8 | D17: Administracion | E17: Nancy Garcia | F17: 2.1 Reducir gasto administrativo x% | G17: % | H17: 0.1 | I17: 0.32 | J17: 0.03
A18: CAT-019 | B18: Julio - Alejandro | C18: 7 | D18: Administracion | F18: 2.1 Reducir gasto administrativo x% | G18: % | H18: 0.1 | I18: 0.32 | J18: 0.1
A19: CAT-019 | B19: Cecilia | C19: 7 | D19: Administracion | F19: 2.1 Reducir gasto administrativo x% | G19: % | H19: 0.1 | I19: 0.32 | J19: 0.05
A20: CAT-019 | B20: Compras | C20: 7 | D20: Administracion | F20: 2.1 Reducir gasto administrativo x% | G20: % | H20: 0.1 | I20: 0.32 | J20: 0.1
A21: CAT-019 | B21: Tesoreria | C21: 7 | D21: Administracion | F21: 2.1 Reducir gasto administrativo x% | G21: % | H21: 0.1 | I21: 0.32 | J21: 0.1
A22: CAT-041 | B22: Nancy Garcia b (4) | C22: 9 | D22: Administracion | E22: Nancy Garcia | F22: 3.5 Multas ambientales y fiscales. | G22: 0 | H22: 0 | I22: 0 | J22: 0.03
A23: CAT-041 | B23: Julio - Alejandro | C23: 8 | D23: Administracion | F23: 3.5 Multas ambientales y fiscales. | G23: 0 | H23: 0 | I23: 0 | J23: 0.05
A24: CAT-041 | B24: Tesoreria | C24: 8 | D24: Administracion | F24: 3.5 Multas ambientales y fiscales. | G24: 0 | H24: 0 | I24: 0 | J24: 0.05
A25: CAT-041 | B25: Gasolinera | C25: 9 | D25: Gasolinera | E25: Abner Urbina | F25: 3.5 Multas ambientales y fiscales. | G25: 0 | H25: 0 | I25: 0 | J25: 0.05
A26: CAT-041 | B26: Abner U b | C26: 9 | D26: Gasolinera | E26: Abner Urbina | F26: 3.5 Multas ambientales y fiscales. | G26: 0 | H26: 0 | I26: 0 | J26: 0.1
A27: CAT-069 | B27: Nancy Garcia b (4) | C27: 10 | D27: Administracion | E27: Nancy Garcia | F27: 6.1 Aumentar Rotación de inventario. | G27: 0 | H27: 0.05 | I27: 0 | J27: 0.03
A28: CAT-069 | B28: Cecilia | C28: 8 | D28: Administracion | F28: 6.1 Aumentar Rotación de inventario. | G28: 0 | H28: 0.05 | I28: 0 | J28: 0.05
A29: CAT-069 | B29: Compras | C29: 8 | D29: Administracion | F29: 6.1 Aumentar Rotación de inventario. | G29: 0 | H29: 0.05 | I29: 0 | J29: 0.2
A30: CAT-069 | B30: Tesoreria | C30: 9 | D30: Administracion | F30: 6.1 Aumentar Rotación de inventario. | G30: 0 | H30: 0.05 | I30: 0 | J30: 0.05
A31: CAT-076 | B31: Nancy Garcia b (4) | C31: 11 | D31: Administracion | E31: Nancy Garcia | F31: 7.1 Rotación de cuentas por cobrar. | G31: 0 | H31: 0.1 | I31: 0 | J31: 0.03
A32: CAT-076 | B32: Julio - Alejandro | C32: 13 | D32: Administracion | F32: 7.1 Rotación de cuentas por cobrar. | G32: 0 | H32: 0.1 | I32: 0 | J32: 0.1
A33: CAT-076 | B33: Tesoreria | C33: 10 | D33: Administracion | F33: 7.1 Rotación de cuentas por cobrar. | G33: 0 | H33: 0.1 | I33: 0 | J33: 0.15
A34: CAT-077 | B34: Nancy Garcia b (4) | C34: 12 | D34: Administracion | E34: Nancy Garcia | F34: 7.2 95% de clientes activos dentro del periodo de recuperacion | G34: 0 | H34: 0.2 | I34: 0 | J34: 0.03
A35: CAT-034 | B35: Nancy Garcia b (4) | C35: 13 | D35: Administracion | E35: Nancy Garcia | F35: 2.3 Reducir Costo por km cabezales propios. | G35: $ | H35: 0.05 | I35: 0.6 | J35: 0.03
A36: CAT-034 | B36: Nancy Garcia b (4) | C36: 21 | D36: Administracion | E36: Nancy Garcia | F36: 2.3 Reducir Costo por km cabezales propios. | G36: $ | H36: 0.05 | I36: 0.6 | J36: 0.03
A37: CAT-034 | B37: TRANEXPA | C37: 13 | D37: Transporte | F37: 2.3 Reducir Costo por km cabezales propios. | G37: $ | H37: 0.05 | I37: 0.6 | J37: 0.1
A38: CAT-034 | B38: Cecilia | C38: 9 | D38: Administracion | F38: 2.3 Reducir Costo por km cabezales propios. | G38: $ | H38: 0.05 | I38: 0.6 | J38: 0.2
A39: CAT-034 | B39: Compras | C39: 9 | D39: Administracion | F39: 2.3 Reducir Costo por km cabezales propios. | G39: $ | H39: 0.05 | I39: 0.6 | J39: 0.1
A40: CAT-056 | B40: Nancy Garcia b (4) | C40: 14 | D40: Administracion | E40: Nancy Garcia | F40: 5.2 Productividad cabezales Flota Nueva | G40: 0 | H40: 4500 | I40: 4782 | J40: 0.03
A41: CAT-056 | B41: Cecilia | C41: 10 | D41: Administracion | F41: 5.2 Productividad cabezales Flota Nueva | G41: 0 | H41: 4500 | I41: 4782 | J41: 0.2
A42: CAT-056 | B42: Compras | C42: 10 | D42: Administracion | F42: 5.2 Productividad cabezales Flota Nueva | G42: 0 | H42: 4500 | I42: 4782 | J42: 0.05
A43: CAT-056 | B43: Jacky | C43: 11 | D43: Servicio_Al_Cliente | E43: Jacky Mena | F43: 5.2 Productividad cabezales Flota Nueva | G43: 0 | H43: 4500 | I43: 4782 | J43: 0.04
A44: CAT-056 | B44: Servicio al cliente b | C44: 11 | D44: Servicio_Al_Cliente | F44: 5.2 Productividad cabezales Flota Nueva | G44: 0 | H44: 4500 | I44: 4782 | J44: 0.05
A45: CAT-070 | B45: Nancy Garcia b (4) | C45: 15 | D45: Administracion | E45: Nancy Garcia | F45: 6.2 Disminuir a 5% el desuso de los chasis (equipos con mas de 30 dias en las yardas) | G45: % | H45: 0.05 | I45: 0.05 | J45: 0.03
A46: CAT-070 | B46: Julio - Alejandro | C46: 12 | D46: Administracion | F46: 6.2 Disminuir a 5% el desuso de los chasis (equipos con mas de 30 dias en las yardas) | G46: % | H46: 0.05 | I46: 0.05 | J46: 0.1
A47: CAT-074 | B47: Nancy Garcia b (4) | C47: 16 | D47: Administracion | E47: Nancy Garcia | F47: 6.5 Disminuir a 0-1 el desuso de cabezales propios | G47: cabezal | H47: 1 | I47: 1 | J47: 0.03
A48: CAT-074 | B48: TRANEXPA | C48: 12 | D48: Transporte | F48: 6.5 Disminuir a 0-1 el desuso de cabezales propios | G48: cabezal | H48: 1 | I48: 1 | J48: 0.05
A49: CAT-074 | B49: Cecilia | C49: 11 | D49: Administracion | F49: 6.5 Disminuir a 0-1 el desuso de cabezales propios | G49: cabezal | H49: 1 | I49: 1 | J49: 0.1
A50: CAT-074 | B50: Compras | C50: 11 | D50: Administracion | F50: 6.5 Disminuir a 0-1 el desuso de cabezales propios | G50: cabezal | H50: 1 | I50: 1 | J50: 0.05
A51: CAT-075 | B51: Nancy Garcia b (4) | C51: 17 | D51: Administracion | E51: Nancy Garcia | F51: 7. Disminuir el D/E | G51: 0 | H51: 0.05 | I51: 0.05 | J51: 0.08
A52: CAT-075 | B52: Julio - Alejandro | C52: 9 | D52: Administracion | F52: 7. Disminuir el D/E | G52: 0 | H52: 0.05 | I52: 0.05 | J52: 0.05
A53: CAT-075 | B53: Cecilia | C53: 12 | D53: Administracion | F53: 7. Disminuir el D/E | G53: 0 | H53: 0.05 | I53: 0.05 | J53: 0.05
A54: CAT-075 | B54: Compras | C54: 12 | D54: Administracion | F54: 7. Disminuir el D/E | G54: 0 | H54: 0.05 | I54: 0.05 | J54: 0.025
A55: CAT-075 | B55: Tesoreria | C55: 11 | D55: Administracion | F55: 7. Disminuir el D/E | G55: 0 | H55: 0.05 | I55: 0.05 | J55: 0.1
A56: CAT-075 | B56: Hoja3 | C56: 8 | F56: 7. Disminuir el D/E | H56: 0.05 | I56: 0.05 | J56: 0.05
A57: CAT-075 | B57: Hoja3 | C57: 27 | F57: 7. Disminuir el D/E | J57: 0.05
A58: CAT-075 | B58: Hoja1 | C58: 10 | F58: 7. Disminuir el D/E | G58: Porcentaje | H58: 0.05 | J58: 0.05
A59: CAT-068 | B59: Nancy Garcia b (4) | C59: 18 | D59: Administracion | E59: Nancy Garcia | F59: 6. Aumentar el ROA | G59: 0 | H59: 0.05 | I59: 1 | J59: 0.08
A60: CAT-068 | B60: Julio - Alejandro | C60: 10 | D60: Administracion | F60: 6. Aumentar el ROA | G60: 0 | H60: 0.05 | I60: 1 | J60: 0.1
A61: CAT-068 | B61: Cecilia | C61: 13 | D61: Administracion | F61: 6. Aumentar el ROA | G61: 0 | H61: 0.05 | I61: 1 | J61: 0.05
A62: CAT-068 | B62: Compras | C62: 14 | D62: Administracion | F62: 6. Aumentar el ROA | G62: 0 | H62: 0.05 | I62: 1 | J62: 0.025
A63: CAT-068 | B63: Tesoreria | C63: 12 | D63: Administracion | F63: 6. Aumentar el ROA | G63: 0 | H63: 0.05 | I63: 1 | J63: 0.1
A64: CAT-068 | B64: Hoja3 | C64: 7 | F64: 6. Aumentar el ROA | H64: 0.05 | I64: 1 | J64: 0.05
A65: CAT-068 | B65: Hoja3 | C65: 26 | F65: 6. Aumentar el ROA | J65: 0.05
A66: CAT-068 | B66: Hoja1 | C66: 9 | F66: 6. Aumentar el ROA | G66: Porcentaje | H66: 0.05 | J66: 0.05
A67: CAT-042 | B67: Nancy Garcia b (4) | C67: 19 | D67: Administracion | E67: Nancy Garcia | F67: 3.6 Cierres contables a mas tardar el 6 de cada mes | G67: # de cierres a tiempo | H67: 6 | I67: 6 | J67: 0.1
A68: CAT-042 | B68: Julio - Alejandro | C68: 11 | D68: Administracion | F68: 3.6 Cierres contables a mas tardar el 6 de cada mes | G68: # de cierres a tiempo | H68: 6 | I68: 6 | J68: 0.1
A69: CAT-042 | B69: Cecilia | C69: 14 | D69: Administracion | F69: 3.6 Cierres contables a mas tardar el 6 de cada mes | G69: # de cierres a tiempo | H69: 6 | I69: 6 | J69: 0.05
A70: CAT-042 | B70: Compras | C70: 15 | D70: Administracion | F70: 3.6 Cierres contables a mas tardar el 6 de cada mes | G70: # de cierres a tiempo | H70: 6 | I70: 6 | J70: 0.1
A71: CAT-042 | B71: Tesoreria | C71: 13 | D71: Administracion | F71: 3.6 Cierres contables a mas tardar el 6 de cada mes | G71: # de cierres a tiempo | H71: 6 | I71: 6 | J71: 0.15
A72: CAT-014 | B72: Nancy Garcia b (4) | C72: 20 | D72: Administracion | E72: Nancy Garcia | F72: 1.8 Aumentar ventas en TREXA | G72: Dólares | H72: 0.2 | I72: 1.03 | J72: 0.03
A73: CAT-014 | B73: TREXA | C73: 10 | D73: Administracion | F73: 1.8 Aumentar ventas en TREXA | G73: Dólares | H73: 0.2 | I73: 1.03 | J73: 0.25
A74: CAT-040 | B74: David Molina | C74: 7 | D74: SistemasYProcesos | E74: David Molina | F74: 3. Cero incidentes mayores de seguridad y sostenibilidad | G74: 0 | H74: 1 | I74: 1 | J74: 0.05
A75: CAT-040 | B75: David Molina | C75: 17 | D75: SistemasYProcesos | E75: David Molina | F75: 3. Cero incidentes mayores de seguridad y sostenibilidad | G75: 0 | H75: 1 | I75: 1 | J75: 0.05
A76: CAT-040 | B76: David Molina | C76: 29 | D76: SistemasYProcesos | E76: David Molina | F76: 3. Cero incidentes mayores de seguridad y sostenibilidad | G76: 0 | H76: 1 | I76: 1 | J76: 0.05
A77: CAT-040 | B77: Yadira | C77: 7 | D77: Sistemas_Y_Procesos | E77: Yadira Reyes | F77: 3. Cero incidentes mayores de seguridad y sostenibilidad | G77: 0 | H77: 1 | I77: 1 | J77: 0.05
A78: CAT-040 | B78: Keila | C78: 7 | D78: Sistemas_Y_Procesos | E78: Keila Rodriguez | F78: 3. Cero incidentes mayores de seguridad y sostenibilidad | G78: 0 | H78: 1 | I78: 1 | J78: 0.05
A79: CAT-040 | B79: Mario | C79: 8 | D79: Sistemas_Y_Procesos | E79: Mario Murillo | F79: 3. Cero incidentes mayores de seguridad y sostenibilidad | G79: 0 | H79: 1 | I79: 1 | J79: 0.6
A80: CAT-040 | B80: TRANEXPA | C80: 8 | D80: Transporte | F80: 3. Cero incidentes mayores de seguridad y sostenibilidad | G80: 0 | H80: 1 | I80: 1 | J80: 0.1
A81: CAT-040 | B81: Lorenzo Varela | C81: 12 | D81: Predio_Puerto_Cortes | E81: Lorenzo Varela | F81: 3. Cero incidentes mayores de seguridad y sostenibilidad | G81: 0 | H81: 1 | I81: 1 | J81: 0.05
A82: CAT-040 | B82: Puerto Cortes | C82: 12 | D82: Predio_Puerto_Cortes | E82: Lorenzo Varela | F82: 3. Cero incidentes mayores de seguridad y sostenibilidad | G82: 0 | H82: 1 | I82: 1 | J82: 0.08
A83: CAT-040 | B83: Cubillo | C83: 13 | D83: Predio_San_Lorenzo | E83: Juan Cubillo | F83: 3. Cero incidentes mayores de seguridad y sostenibilidad | G83: 0 | H83: 1 | I83: 1 | J83: 0.05
A84: CAT-040 | B84: San Lorenzo b | C84: 13 | D84: Predio_San_Lorenzo | E84: Juan Cubillo | F84: 3. Cero incidentes mayores de seguridad y sostenibilidad | G84: 0 | H84: 1 | I84: 1 | J84: 0.08
A85: CAT-040 | B85: Jacky | C85: 9 | D85: Servicio_Al_Cliente | E85: Jacky Mena | F85: 3. Cero incidentes mayores de seguridad y sostenibilidad | G85: 0 | H85: 1 | I85: 1 | J85: 0.1
A86: CAT-040 | B86: Servicio al cliente b | C86: 9 | D86: Servicio_Al_Cliente | F86: 3. Cero incidentes mayores de seguridad y sostenibilidad | G86: 0 | H86: 1 | I86: 1 | J86: 0.1
A87: CAT-040 | B87: Hoja3 | C87: 4 | F87: 3. Cero incidentes mayores de seguridad y sostenibilidad | H87: 1 | I87: 1 | J87: 0.05
A88: CAT-040 | B88: Hoja3 | C88: 23 | F88: 3. Cero incidentes mayores de seguridad y sostenibilidad | J88: 0.05
A89: CAT-040 | B89: Hoja1 | C89: 6 | F89: 3. Cero incidentes mayores de seguridad y sostenibilidad | G89: # Incidente | H89: 1 | J89: 0.05
A90: CAT-078 | B90: David Molina | C90: 8 | D90: SistemasYProcesos | E90: David Molina | F90: 8. Innovaciones estratégicas de sistemas de Impacto recurrente | G90: 0 | H90: 1 | I90: 1 | J90: 0.25
A91: CAT-078 | B91: David Molina | C91: 18 | D91: SistemasYProcesos | E91: David Molina | F91: 8. Innovaciones estratégicas de sistemas de Impacto recurrente | G91: 0 | H91: 1 | I91: 1 | J91: 0.25
A92: CAT-078 | B92: David Molina | C92: 30 | D92: SistemasYProcesos | E92: David Molina | F92: 8. Innovaciones estratégicas de sistemas de Impacto recurrente | G92: 0 | H92: 1 | I92: 1 | J92: 0.25
A93: CAT-078 | B93: Desarrollo | C93: 7 | D93: Sistemas_Y_Procesos | F93: 8. Innovaciones estratégicas de sistemas de Impacto recurrente | G93: 0 | H93: 1 | I93: 1 | J93: 0.6
A94: CAT-078 | B94: Hoja3 | C94: 9 | F94: 8. Innovaciones estratégicas de sistemas de Impacto recurrente | H94: 1 | I94: 1 | J94: 0.05
A95: CAT-078 | B95: Hoja1 | C95: 11 | F95: 8. Innovaciones estratégicas de sistemas de Impacto recurrente | G95: SW Implementado | H95: 1 | J95: 0.05
A96: CAT-065 | B96: David Molina | C96: 9 | D96: SistemasYProcesos | E96: David Molina | F96: 5.6 Aprovechamiento GPS | G96: 0 | H96: 0.9 | I96: 0.82 | J96: 0.05
A97: CAT-065 | B97: David Molina | C97: 19 | D97: SistemasYProcesos | E97: David Molina | F97: 5.6 Aprovechamiento GPS | G97: 0 | H97: 0.9 | I97: 0.82 | J97: 0.05
A98: CAT-065 | B98: David Molina | C98: 31 | D98: SistemasYProcesos | E98: David Molina | F98: 5.6 Aprovechamiento GPS | G98: 0 | H98: 0.9 | I98: 0.82 | J98: 0.05
A99: CAT-065 | B99: Keila | C99: 9 | D99: Sistemas_Y_Procesos | E99: Keila Rodriguez | F99: 5.6 Aprovechamiento GPS | G99: 0 | H99: 0.9 | I99: 0.82 | J99: 0.5
A100: CAT-048 | B100: David Molina | C100: 10 | D100: SistemasYProcesos | E100: David Molina | F100: 5. Productividad | G100: 0 | H100: 3700 | I100: 3932 | J100: 0.1
...

Sheet Allowed Values
A1: Row Type | B1: Evaluation Type | C1: Scoring Method | D1: Confidence | E1: Catalog Status | F1: Business Review | G1: Category
A2: ATOMIC KPI | B2: GREATER_IS_BETTER | C2: PROPORTIONAL | D2: HIGH | E2: PROPOSED | F2: YES | G2: Commercial Growth
A3: FEATURE / MILESTONE | B3: LOWER_IS_BETTER | C3: ZERO_TARGET_BANDS | D3: MEDIUM | E3: BLOCKED | F3: NO | G3: Financial Performance
A4: PARENT / AGGREGATE | B4: EQUAL_IS_BETTER | C4: THRESHOLD | D4: LOW | E4: EXCLUDE / REVIEW | G4: Financial Health
A5: SCORECARD_AGGREGATE | B5: RANGE | C5: THRESHOLD_OR_PROPORTIONAL | E5: APPROVED | G5: Cost Efficiency
B6: BINARY / MILESTONE | C6: TOLERANCE_OR_THRESHOLD | E6: REJECTED / NEEDS_REDEFINITION | G6: Operational Productivity
B7: EQUAL_OR_LOWER_REVIEW | C7: BINARY_OR_MILESTONE | G7: Operational Reliability
B8: NEEDS_REVIEW | C8: RANGE_BASED | G8: Asset Utilization
C9: NEEDS_REVIEW | G9: Customer Experience
G10: Process & Service Quality
G11: Safety & Risk
G12: People & Culture
G13: Innovation & Digitalization
G14: Needs Business Review

Sheet Changes Needed
A1: KPI Evaluation Catalog — What We Need to Change
A2: This sheet separates blocking business decisions from simple approvals. The catalog remains PROPOSED until the business confirms the rule.
A4: Catalog rows | B4: 89 | C4: Atomic KPIs | D4: 73 | E4: Blocked rows | F4: 28 | G4: High-confidence proposed | H4: 38
A5: Need semantic review | B5: 11 | C5: Unit needs review | D5: 10 | E5: Zero-target rules | F5: 4 | G5: Feature/Milestone | H5: 11
A8: Priority | B8: Change Area | C8: Affected Rows | D8: What We Need to Change | E8: Decision / Question to Business | F8: Why It Matters | G8: Blocks Production Scoring? | H8: Recommended Owner
A9: P0 | B9: Blocked KPI definitions | C9: 28 | D9: Resolve ambiguous Result Semantics, units, Evaluation Type and/or Scoring Method before production use. | E9: For each BLOCKED KPI, define exactly what Result means and how Goal + Result becomes Compliance. | F9: A wrong interpretation can invert the score or produce mathematically invalid results. | G9: YES | H9: Business owner + Processes
A10: P0 | B10: Zero Target KPIs | C10: 4 | D10: Define bands per KPI instead of using a universal formula. | E10: What Compliance corresponds to 0, 1, 2, 3+ occurrences? Are any events immediately critical? | F10: Goal = 0 cannot use Goal/Result and different incident KPIs have different severity. | G10: YES | H10: Safety/Risk owner + Processes
A11: P0 | B11: Measurement units marked REVIEW | C11: 10 | D11: Normalize the unit stored/displayed for Result. | E11: Is Result USD, %, count, rate, days, km/head/month, etc.? | F11: Unit ambiguity makes validation, Excel import and scoring unreliable. | G11: YES | H11: KPI owner
A12: P1 | B12: Feature / Milestone rows | C12: 11 | D12: Separate BINARY from MILESTONE behavior and define allowed states. | E12: Is it Completed/Not Completed only, or are intermediate milestones allowed? Map each state to Compliance. | F12: Project-style KPIs cannot safely use proportional numeric scoring. | G12: YES | H12: Project owner + Processes
A13: P1 | B13: Threshold-based KPIs | C13: 5 | D13: Confirm exact threshold boundaries, inclusivity and behavior outside the accepted threshold. | E13: Does meeting the threshold give 100%? How is a miss penalized? Are boundaries inclusive? | F13: Ambiguous thresholds lead to inconsistent scoring at boundary values. | G13: YES | H13: Business owner
A14: P1 | B14: Derived percentage KPIs | C14: 1 | D14: Document the raw-data formula that produces Result before scoring. | E14: Define population/denominator, exclusions, boundary behavior and source data. | F14: Scoring may be simple Greater/Proportional, but the Result itself must be reproducible. | G14: YES | H14: Operational owner + Data/Systems
A15: P1 | B15: Medium-confidence proposed KPIs | C15: 18 | D15: Confirm Result Semantics and Goal interpretation before approval. | E15: Does Result represent the raw value, achieved change %, compliance %, rate, count, etc.? | F15: Keywords such as 'Reducir' can be misleading if Result is '% reduction achieved'. | G15: YES for production | H15: Business owner
A16: P2 | B16: High-confidence proposed KPIs | C16: 38 | D16: Formal business approval; normalize naming and unit variants where needed. | E16: Confirm the proposed Category, Owner, Result Semantics, Goal, Evaluation Type and Scoring Method. | F16: These are technically plausible but still not official business rules. | G16: NO - approval only | H16: Business owner
A17: P3 | B17: Parent / Scorecard aggregate rows | C17: 5 | D17: Exclude from atomic KPI scoring; retain only as grouping or aggregate output when useful. | E17: Confirm the row is not expected to receive its own Result/Goal independently. | F17: Scoring aggregate rows again would double-count performance. | G17: NO | H17: Processes / System design
A18: P1 | B18: Repeated KPI families | C18: Review by family | D18: Decide which repeated rows are one KPI Definition with multiple Configurations/scopes rather than separate Definitions. | E18: For repeated productivity/cost/sales patterns, which fields are truly the same definition and which only differ by scope/goal? | F18: Reduces duplicated definitions and makes the catalog reusable. | G18: NO - structural quality | H18: Processes + KPI owner
A19: P1 | B19: Goal representation / percentages | C19: Review % rows | D19: Normalize whether percentages are stored as 0.10 or 10 and document the canonical API/DB representation. | E19: Will 10% be stored as 0.10 or 10.00? Apply one convention across Goal, Result and thresholds. | F19: Prevents 100x scoring/import errors. | G19: YES | H19: Development + Processes
A20: P1 | B20: Approval metadata | C20: All rows | D20: Add approved_by, approved_at and business note when a KPI is promoted to APPROVED. | E20: Who approved the rule and when? | F20: Provides auditability and a trustworthy future RAG/test dataset. | G20: NO | H20: Processes / Governance
A23: Recommended order: P0 blockers → P1 rule definitions/business confirmations → P2 formal approvals → P3 structural cleanup.
